Workbook

Sheet Litoral
A2: Código | B2: Descripción | C2: EAN | D2: Kg. x Caja | E2: Cant. X Caja | F2: Precio de Lista | G2: Dcto | H2: Precio oferta | I2: Precio Neto estuche en factura | J2: IVA | K2: Px Unitario IVA Inc | L2: M-up Dx | M2: Px Unitario Minorista | N2: M-up Minorista | O2: Px Unitario Público | Q2: NOV | S2: OFERTAS Y ACCIONES | AF2: SEP | AG2: %
J3: 0.21 | L3: 0.35 | N3: 0.45
A4: 100021632 | B4: HAMBURGUESAS 30x160g CLASICA x2 SWIFT | C4: 7790360026606 | D4: 4.8 | E4: 30 | F4: =+VLOOKUP(A4,$AK$4:$AL$110,2,FALSE) -> 40261.782 | H4: =+F4*(1-G4) -> 40261.782 | I4: =+H4/E4 -> 1342.0594 | J4: =+I4*J$3 -> 281.83247 | K4: =+I4+J4 -> 1623.8919 | L4: =+K4*L$3 -> 568.36216 | M4: =+K4+L4 -> 2192.254 | N4: =+M4*N$3 -> 986.51431 | O4: =+M4+N4 -> 3178.7683 | P4: =H4/Q4-1 -> 0.05 | Q4: 38344.554 | S4: 5,67% de dcto adicional vía Flex. Para oferta $2.900 (Mup 33% dx , 42.5% min). VER CUPOS | AF4: 29534.055 | AG4: =+(H4-AF4)/AF4 -> 0.36323243 | AK4: 100021632 | AL4: 40261.782 | AN4: =+Q4/H4 -> 0.95238095
A5: 100021652 | B5: HAMBURGUESA 18X4X80G CLASICA SWIFT | C5: 7790360026576 | D5: 5.76 | E5: 18 | F5: =+VLOOKUP(A5,$AK$4:$AL$110,2,FALSE) -> 50775.845 | H5: =+F5*(1-G5) -> 50775.845 | I5: =+H5/E5 -> 2820.8803 | J5: =+I5*J$3 -> 592.38486 | K5: =+I5+J5 -> 3413.2651 | L5: =+K5*L$3 -> 1194.6428 | M5: =+K5+L5 -> 4607.9079 | N5: =+M5*N$3 -> 2073.5586 | O5: =+M5+N5 -> 6681.4665 | P5: =H5/Q5-1 -> 0.1 | Q5: 46159.859 | AF5: 38042.377 | AG5: =+(H5-AF5)/AF5 -> 0.334718 | AK5: 100021652 | AL5: 50775.845 | AN5: =+Q5/H5 -> 0.90909091
A6: 100021631 | B6: HAMBURGUESA 8X12X80G CLASICA SWIFT | C6: 7790360026590 | D6: 7.68 | E6: 8 | F6: =+VLOOKUP(A6,$AK$4:$AL$110,2,FALSE) -> 64362.044 | H6: =+F6*(1-G6) -> 64362.044 | I6: =+H6/E6 -> 8045.2555 | J6: =+I6*J$3 -> 1689.5037 | K6: =+I6+J6 -> 9734.7592 | L6: =+K6*L$3 -> 3407.1657 | M6: =+K6+L6 -> 13141.925 | N6: =+M6*N$3 -> 5913.8662 | O6: =+M6+N6 -> 19055.791 | P6: =H6/Q6-1 -> 0.1 | Q6: 58510.949 | AF6: 63884.504 | AG6: =+(H6-AF6)/AF6 -> 0.0074750646 | AK6: 100021631 | AL6: 64362.044 | AN6: =+Q6/H6 -> 0.90909091
A7: 100021630 | B7: HAMBURGUESA 6X20X80G CLASICA SWIFT | C7: 7790360026583 | D7: 9.6 | E7: 6 | F7: =+VLOOKUP(A7,$AK$4:$AL$110,2,FALSE) -> 78890.37 | H7: =+F7*(1-G7) -> 78890.37 | I7: =+H7/E7 -> 13148.395 | J7: =+I7*J$3 -> 2761.1629 | K7: =+I7+J7 -> 15909.558 | L7: =+K7*L$3 -> 5568.3453 | M7: =+K7+L7 -> 21477.903 | N7: =+M7*N$3 -> 9665.0564 | O7: =+M7+N7 -> 31142.96 | P7: =H7/Q7-1 -> 0.1 | Q7: 71718.518 | AF7: 79885.735 | AG7: =+(H7-AF7)/AF7 -> -0.012459863 | AK7: 100021630 | AL7: 78890.37 | AN7: =+Q7/H7 -> 0.90909091
A8: 100021653 | B8: MEDALLON 18X4X80G PARRILLERO SWIFT | C8: 7790360026682 | D8: 5.76 | E8: 18 | F8: =+VLOOKUP(A8,$AK$4:$AL$110,2,FALSE) -> 50614.812 | H8: =+F8*(1-G8) -> 50614.812 | I8: =+H8/E8 -> 2811.934 | J8: =+I8*J$3 -> 590.50614 | K8: =+I8+J8 -> 3402.4401 | L8: =+K8*L$3 -> 1190.854 | M8: =+K8+L8 -> 4593.2942 | N8: =+M8*N$3 -> 2066.9824 | O8: =+M8+N8 -> 6660.2765 | P8: =H8/Q8-1 -> 0 | Q8: 50614.812 | AF8: 50298.202 | AG8: =+(H8-AF8)/AF8 -> 0.0062946466 | AK8: 100021653 | AL8: 50614.812 | AN8: =+Q8/H8 -> 1
A9: 100516169 | B9: MEDALLONES 18X4X80G SWIFT RECETA ESPECIAL | C9: 7790360967961 | D9: 5.76 | E9: 18 | F9: =+VLOOKUP(A9,$AK$4:$AL$110,2,FALSE) -> 46670.247 | H9: =+F9*(1-G9) -> 46670.247 | I9: =+H9/E9 -> 2592.7915 | J9: =+I9*J$3 -> 544.48622 | K9: =+I9+J9 -> 3137.2777 | L9: =+K9*L$3 -> 1098.0472 | M9: =+K9+L9 -> 4235.3249 | N9: =+M9*N$3 -> 1905.8962 | O9: =+M9+N9 -> 6141.2212 | P9: =H9/Q9-1 -> 0 | Q9: 46670.247 | AF9: 41155.421 | AG9: =+(H9-AF9)/AF9 -> 0.134 | AK9: 100516169 | AL9: 46670.247 | AN9: =+Q9/H9 -> 1
A10: 100520337 | B10: MEDALLON BURGER SWIFT MEGA 30 x 160 g | C10: 7790360977960 | D10: 4.8 | E10: 30 | F10: =+VLOOKUP(A10,$AK$4:$AL$110,2,FALSE) -> 28467.876 | H10: =+F10*(1-G10) -> 28467.876 | I10: =+H10/E10 -> 948.9292 | J10: =+I10*J$3 -> 199.27513 | K10: =+I10+J10 -> 1148.2043 | L10: =+K10*L$3 -> 401.87151 | M10: =+K10+L10 -> 1550.0758 | N10: =+M10*N$3 -> 697.53413 | O10: =+M10+N10 -> 2247.61 | P10: =H10/Q10-1 -> 0.05 | Q10: 27112.263 | AF10: 25103.947 | AG10: =+(H10-AF10)/AF10 -> 0.134 | AK10: 100520337 | AL10: 28467.876 | AN10: =+Q10/H10 -> 0.95238095
A11: 100021503 | B11: Medallón CAJITA 12x4 69 grs | C11: 7790360966841 | D11: 3.312 | E11: 12 | F11: =+VLOOKUP(A11,$AK$4:$AL$110,2,FALSE) -> 21735.959 | H11: =+F11*(1-G11) -> 21735.959 | I11: =+H11/E11 -> 1811.3299 | J11: =+I11*J$3 -> 380.37928 | K11: =+I11+J11 -> 2191.7092 | L11: =+K11*L$3 -> 767.09821 | M11: =+K11+L11 -> 2958.8074 | N11: =+M11*N$3 -> 1331.4633 | O11: =+M11+N11 -> 4290.2707 | P11: =H11/Q11-1 -> 0.14541289 | Q11: 18976.527 | AF11: 15081.22 | AG11: =+(H11-AF11)/AF11 -> 0.44126 | AK11: 100021503 | AL11: 21735.959 | AN11: =+Q11/H11 -> 0.87304762
A12: 100516201 | B12: HAMBURGUESA 8X12X69G BURGER SWIFT | C12: 7790360968548 | D12: 6.624 | E12: 8 | F12: =+VLOOKUP(A12,$AK$4:$AL$110,2,FALSE) -> 47491.011 | H12: =+F12*(1-G12) -> 47491.011 | I12: =+H12/E12 -> 5936.3763 | J12: =+I12*J$3 -> 1246.639 | K12: =+I12+J12 -> 7183.0154 | L12: =+K12*L$3 -> 2514.0554 | M12: =+K12+L12 -> 9697.0707 | N12: =+M12*N$3 -> 4363.6818 | O12: =+M12+N12 -> 14060.753 | P12: =H12/Q12-1 -> 0.05 | Q12: 45229.534 | AF12: 37985.667 | AG12: =+(H12-AF12)/AF12 -> 0.250235 | AK12: 100516201 | AL12: 47491.011 | AN12: =+Q12/H12 -> 0.95238095
A13: 100021643 | B13: MEDALLON 42X112G DOBLE BURGER SWIFT | C13: 7790360966797 | D13: 4.704 | E13: 42 | F13: =+VLOOKUP(A13,$AK$4:$AL$110,2,FALSE) -> 29124.796 | G13: 0.095238095 | H13: =+F13*(1-G13) -> 26351.006 | I13: =+H13/E13 -> 627.40491 | J13: =+I13*J$3 -> 131.75503 | K13: =+I13+J13 -> 759.15994 | L13: =+K13*L$3 -> 265.70598 | M13: =+K13+L13 -> 1024.8659 | N13: =+M13*N$3 -> 461.18966 | O13: =+M13+N13 -> 1486.0556 | P13: =H13/Q13-1 -> -0.05 | Q13: 27737.901 | S13: COMPRA 19 ESTUCHES + 2 DE REGALO | AF13: 23295.457 | AG13: =+(H13-AF13)/AF13 -> 0.131165 | AK13: 100021643 | AL13: 29124.796 | AN13: =+Q13/H13 -> 1.0526316
A14: 100516325 | B14: MEDALLON DOBLE BURGER 2X2 | C14: 7790360967763 | D14: 4.704 | E14: 21 | F14: =+VLOOKUP(A14,$AK$4:$AL$110,2,FALSE) -> 32755.097 | H14: =+F14*(1-G14) -> 32755.097 | I14: =+H14/E14 -> 1559.7665 | J14: =+I14*J$3 -> 327.55097 | K14: =+I14+J14 -> 1887.3175 | L14: =+K14*L$3 -> 660.56112 | M14: =+K14+L14 -> 2547.8786 | N14: =+M14*N$3 -> 1146.5454 | O14: =+M14+N14 -> 3694.424 | P14: =H14/Q14-1 -> 0.05 | Q14: 31195.33 | AF14: 27509.109 | AG14: =+(H14-AF14)/AF14 -> 0.1907 | AK14: 100516325 | AL14: 32755.097 | AN14: =+Q14/H14 -> 0.95238095
A15: 100021676 | B15: HAMBURGUESA 30X250g CLASICA "XL" SWIFT | C15: 7790360967411 | D15: 7.5 | E15: 30 | F15: =+VLOOKUP(A15,$AK$4:$AL$110,2,FALSE) -> 60777.549 | H15: =+F15*(1-G15) -> 60777.549 | I15: =+H15/E15 -> 2025.9183 | J15: =+I15*J$3 -> 425.44284 | K15: =+I15+J15 -> 2451.3612 | L15: =+K15*L$3 -> 857.9764 | M15: =+K15+L15 -> 3309.3376 | N15: =+M15*N$3 -> 1489.2019 | O15: =+M15+N15 -> 4798.5395 | P15: =H15/Q15-1 -> 0.071466838 | Q15: 56723.687 | AF15: 53595.722 | AG15: =+(H15-AF15)/AF15 -> 0.134 | AK15: 100021676 | AL15: 60777.549 | AN15: =+Q15/H15 -> 0.9333
A16: 100516008 | B16: HAMBURGUESA 24X2X120g CASERA SWIFT | C16: 7790360967701 | D16: 5.76 | E16: 24 | F16: =+VLOOKUP(A16,$AK$4:$AL$110,2,FALSE) -> 50957.087 | G16: 0.05 | H16: =+F16*(1-G16) -> 48409.232 | I16: =+H16/E16 -> 2017.0514 | J16: =+I16*J$3 -> 423.58078 | K16: =+I16+J16 -> 2440.6321 | L16: =+K16*L$3 -> 854.22125 | M16: =+K16+L16 -> 3294.8534 | N16: =+M16*0.4265 -> 1405.255 | O16: =+M16+N16 -> 4700.1084 | P16: =H16/Q16-1 -> 0.04498955 | Q16: 46325.088 | S16: Oferta a $4.700 | AF16: 47578.979 | AG16: =+(H16-AF16)/AF16 -> 0.01745 | AK16: 100516008 | AL16: 50957.087 | AN16: =+Q16/H16 -> 0.95694737
A17: 100520834 | B17: HAMBURGUESA X-TREMA 36 x 185 grs | C17: 7790360980618 | D17: 6.66 | E17: 36 | F17: =+VLOOKUP(A17,$AK$4:$AL$110,2,FALSE) -> 63095.588 | H17: =+F17*(1-G17) -> 63095.588 | I17: =+H17/E17 -> 1752.6552 | J17: =+I17*J$3 -> 368.0576 | K17: =+I17+J17 -> 2120.7128 | L17: =+K17*L$3 -> 742.24949 | M17: =+K17+L17 -> 2862.9623 | N17: =+M17*N$3 -> 1288.333 | O17: =+M17+N17 -> 4151.2954 | P17: =H17/Q17-1 -> 0 | Q17: 63095.588 | AF17: 55639.849 | AG17: =+(H17-AF17)/AF17 -> 0.134 | AK17: 100520834 | AL17: 63095.588 | AN17: =+Q17/H17 -> 1
A18: 100021680 | B18: HAMBURGUESAS 18X2X120g CLL BRA/ARG | C18: 7790360967688 | D18: 4.32 | E18: 18 | F18: =+VLOOKUP(A18,$AK$4:$AL$110,2,FALSE) -> #N/A | H18: =+F18*(1-G18) -> #N/A | I18: =+H18/E18 -> #N/A | J18: =+I18*J$3 -> #N/A | K18: =+I18+J18 -> #N/A | L18: =+K18*L$3 -> #N/A | M18: =+K18+L18 -> #N/A | N18: =+M18*N$3 -> #N/A | O18: =+M18+N18 -> #N/A | P18: =H18/Q18-1 -> #N/A | Q18: 50536.767 | AF18: 44565.05 | AG18: =+(H18-AF18)/AF18 -> #N/A | AK18: 100021644 | AL18: 21089.839 | AN18: =+Q18/H18 -> #N/A
A19: 100021644 | B19: MEDALLON 42X112G LA BLANCA | C19: 7790360008541 | D19: 4.704 | E19: 42 | F19: =+VLOOKUP(A19,$AK$4:$AL$110,2,FALSE) -> 21089.839 | H19: =+F19*(1-G19) -> 21089.839 | I19: =+H19/E19 -> 502.13904 | J19: =+I19*J$3 -> 105.4492 | K19: =+I19+J19 -> 607.58823 | L19: =+K19*0.3 -> 182.27647 | M19: =+K19+L19 -> 789.8647 | N19: =+M19*N$3 -> 355.43912 | O19: =+M19+N19 -> 1145.3038 | P19: =H19/Q19-1 -> 0.1 | Q19: 19172.581 | AF19: 14434.467 | AG19: =+(H19-AF19)/AF19 -> 0.461075 | AK19: 100021677 | AL19: 16737.231 | AN19: =+Q19/H19 -> 0.90909091
A20: 100021677 | B20: MEDALLON 12x4X69G LA BLANCA | C20: 7790360967404 | D20: 3.312 | E20: 12 | F20: =+VLOOKUP(A20,$AK$4:$AL$110,2,FALSE) -> 16737.231 | H20: =+F20*(1-G20) -> 16737.231 | I20: =+H20/E20 -> 1394.7692 | J20: =+I20*J$3 -> 292.90154 | K20: =+I20+J20 -> 1687.6708 | L20: =+K20*0.3 -> 506.30123 | M20: =+K20+L20 -> 2193.972 | N20: =+M20*N$3 -> 987.28741 | O20: =+M20+N20 -> 3181.2594 | P20: =H20/Q20-1 -> 0.1 | Q20: 15215.664 | AF20: 13173.735 | AG20: =+(H20-AF20)/AF20 -> 0.2705 | AK20: 100021638 | AL20: 47532.849 | AN20: =+Q20/H20 -> 0.90909091
A21: 100021638 | B21: MEDALLONES 60X80g "SWIFT BURGER" PARRILLERAS FAMILY | C21: 7790360026699 | D21: 4.8 | E21: 60 | F21: =+VLOOKUP(A21,$AK$4:$AL$110,2,FALSE) -> 47532.849 | H21: =+F21*(1-G21) -> 47532.849 | I21: =+H21/E21 -> 792.21415 | J21: =+I21*J$3 -> 166.36497 | K21: =+I21+J21 -> 958.57912 | L21: =+K21*L$3 -> 335.50269 | M21: =+K21+L21 -> 1294.0818 | N21: =+M21*N$3 -> 582.33681 | O21: =+M21+N21 -> 1876.4186 | P21: =H21/Q21-1 -> 0 | Q21: 47532.849 | AF21: 41916.092 | AG21: =+(H21-AF21)/AF21 -> 0.134 | AK21: 100021575 | AL21: 38984.492 | AN21: =+Q21/H21 -> 1
A22: 100021575 | B22: MEDALLONES 60X69g "SWIFT BURGER"PARRILLERAS FAMILY | C22: 7790360007032 | D22: 4.14 | E22: 60 | F22: =+VLOOKUP(A22,$AK$4:$AL$110,2,FALSE) -> 38984.492 | H22: =+F22*(1-G22) -> 38984.492 | I22: =+H22/E22 -> 649.74153 | J22: =+I22*J$3 -> 136.44572 | K22: =+I22+J22 -> 786.18725 | L22: =+K22*L$3 -> 275.16554 | M22: =+K22+L22 -> 1061.3528 | N22: =+M22*N$3 -> 477.60875 | O22: =+M22+N22 -> 1538.9615 | P22: =H22/Q22-1 -> 0 | Q22: 38984.492 | AF22: 34377.859 | AG22: =+(H22-AF22)/AF22 -> 0.134 | AK22: 100021514 | AL22: 35475.666 | AN22: =+Q22/H22 -> 1
A23: 100021514 | B23: MEDALLON 60X69G CARNE VACUNA | C23: 7790360006943 | D23: 4.14 | E23: 60 | F23: =+VLOOKUP(A23,$AK$4:$AL$110,2,FALSE) -> 35475.666 | H23: =+F23*(1-G23) -> 35475.666 | I23: =+H23/E23 -> 591.26111 | J23: =+I23*J$3 -> 124.16483 | K23: =+I23+J23 -> 715.42594 | L23: =+K23*L$3 -> 250.39908 | M23: =+K23+L23 -> 965.82502 | N23: =+M23*N$3 -> 434.62126 | O23: =+M23+N23 -> 1400.4463 | P23: =H23/Q23-1 -> 0 | Q23: 35475.666 | AF23: 31283.656 | AG23: =+(H23-AF23)/AF23 -> 0.134 | AK23: 100516208 | AL23: 41131.229 | AN23: =+Q23/H23 -> 1
A24: 100516208 | B24: MEDALLON 60x80g PARRILLERO MC SWIFT | C24: 7790360968203 | D24: =60*0.08 -> 4.8 | E24: 60 | F24: =+VLOOKUP(A24,$AK$4:$AL$110,2,FALSE) -> 41131.229 | H24: =+F24*(1-G24) -> 41131.229 | I24: =+H24/E24 -> 685.52049 | J24: =+I24*J$3 -> 143.9593 | K24: =+I24+J24 -> 829.47979 | L24: =+K24*L$3 -> 290.31793 | M24: =+K24+L24 -> 1119.7977 | N24: =+M24*N$3 -> 503.90897 | O24: =+M24+N24 -> 1623.7067 | P24: =H24/Q24-1 -> 0 | Q24: 41131.229 | AF24: 36270.925 | AG24: =+(H24-AF24)/AF24 -> 0.134 | AK24: 100518346 | AL24: 58788.442 | AN24: =+Q24/H24 -> 1
A25: 100518346 | B25: MEDALLON 60X109G CARNE VACUNA PARRILLERO SWIFT | C25: 7790360975478 | D25: =60*0.109 -> 6.54 | E25: 60 | F25: =+VLOOKUP(A25,$AK$4:$AL$110,2,FALSE) -> 58788.442 | H25: =+F25*(1-G25) -> 58788.442 | I25: =+H25/E25 -> 979.80737 | J25: =I25*J3 -> 205.75955 | K25: =J25+I25 -> 1185.5669 | L25: =K25*L3 -> 414.94842 | M25: =L25+K25 -> 1600.5153 | N25: =M25*N3 -> 720.2319 | O25: =N25+M25 -> 2320.7472 | P25: =H25/Q25-1 -> 0 | Q25: 58788.442 | AF25: 51841.66 | AG25: =+(H25-AF25)/AF25 -> 0.134 | AK25: 100516259 | AL25: 136018.21 | AN25: =+Q25/H25 -> 1
A26: 100516259 | B26: MEDALLON GIGANTE 48x113.5g | C26: 7790360968340 | D26: 18.16 | E26: 48 | F26: =+VLOOKUP(A26,$AK$4:$AL$110,2,FALSE) -> 136018.21 | H26: =+F26*(1-G26) -> 136018.21 | I26: =+H26/E26 -> 2833.7127 | J26: =+I26*J$3 -> 595.07967 | K26: =+I26+J26 -> 3428.7924 | L26: =+K26*L$3 -> 1200.0773 | M26: =+K26+L26 -> 4628.8697 | N26: =+M26*N$3 -> 2082.9914 | O26: =+M26+N26 -> 6711.8611 | P26: =H26/Q26-1 -> 0 | Q26: 136018.21 | AF26: 119945.51 | AG26: =+(H26-AF26)/AF26 -> 0.134 | AK26: 100518095 | AL26: 67770.616 | AN26: =+Q26/H26 -> 1
A27: 100518095 | B27: HAMBURGUESA 36 X 185 GRS | C27: 7790360974785 | D27: 6.66 | E27: 36 | F27: =+VLOOKUP(A27,$AK$4:$AL$110,2,FALSE) -> 67770.616 | H27: =+F27*(1-G27) -> 67770.616 | I27: =+H27/E27 -> 1882.5171 | J27: =+I27*J$3 -> 395.32859 | K27: =+I27+J27 -> 2277.8457 | L27: =+K27*L$3 -> 797.24599 | M27: =+K27+L27 -> 3075.0917 | N27: =+M27*N$3 -> 1383.7913 | O27: =+M27+N27 -> 4458.883 | P27: =H27/Q27-1 -> 0 | Q27: 67770.616 | AF27: 59762.448 | AG27: =+(H27-AF27)/AF27 -> 0.134 | AK27: 100518223 | AL27: 52763.191 | AN27: =+Q27/H27 -> 1
A28: 100518223 | B28: HAMBURGUESA 30x2x106 GRS | C28: 7790360975065 | D28: =60*0.106 -> 6.36 | E28: 30 | F28: =+VLOOKUP(A28,$AK$4:$AL$110,2,FALSE) -> 52763.191 | H28: =+F28*(1-G28) -> 52763.191 | I28: =+H28/E28 -> 1758.773 | J28: =+I28*J$3 -> 369.34234 | K28: =+I28+J28 -> 2128.1154 | L28: =+K28*L$3 -> 744.84038 | M28: =+K28+L28 -> 2872.9557 | N28: =+M28*N$3 -> 1292.8301 | O28: =+M28+N28 -> 4165.7858 | P28: =H28/Q28-1 -> 0 | Q28: 52763.191 | AF28: 46528.387 | AG28: =+(H28-AF28)/AF28 -> 0.134 | AN28: =+Q28/H28 -> 1
F29: =+VLOOKUP(A29,$AK$4:$AL$110,2,FALSE) -> #N/A | H29: =+F29*(1-G29) -> #N/A | I29: =+H29/E29 -> #N/A | P29: =H29/Q29-1 -> #N/A | Q29: #N/A | Y29: OCT | Z29: PATY VIENA | AA29: VIENISSIMA | AB29: PALADINI | AF29: #N/A | AG29: =+(H29-AF29)/AF29 -> #N/A | AK29: 100522204 | AL29: 23406.479 | AN29: =+Q29/H29 -> #N/A
A30: 100022085 | B30: SALCHICHAS 24X6 SWIFT | C30: 7790360000132 | D30: 5.4 | E30: 24 | F30: =+VLOOKUP(A30,$AK$4:$AL$110,2,FALSE) -> #N/A | G30: =0.0833333333333333*100% -> 0.083333333 | H30: =+F30*(1-G30) -> #N/A | I30: =+H30/E30 -> #N/A | J30: =+I30*J$3 -> #N/A | K30: =+I30+J30 -> #N/A | L30: =+K30*L$3 -> #N/A | M30: =+K30+L30 -> #N/A | N30: =+M30*0.438 -> #N/A | O30: =+M30+N30 -> #N/A | P30: =H30/Q30-1 -> #N/A | Q30: 20434.227 | S30: Compra 11 estuches + 1 de regalo ----> OFERTA $2.100 público | Y30: 1900 | Z30: 2080 | AA30: 2435 | AB30: 2328 | AF30: 18238.814 | AG30: =+(H30-AF30)/AF30 -> #N/A | AK30: 100522205 | AL30: 22236.155 | AN30: =+Q30/H30 -> #N/A
A31: 100522204 | B31: SALCHICHAS 24X6 SWIFT | C31: 7790360983947 | D31: 5.4 | E31: 24 | F31: =+VLOOKUP(A31,$AK$4:$AL$110,2,FALSE) -> 23406.479 | G31: 0.083333333 | H31: =+F31*(1-G31) -> 21455.939 | I31: =+H31/E31 -> 893.99745 | J31: =+I31*J$3 -> 187.73946 | K31: =+I31+J31 -> 1081.7369 | L31: =+K31*L$3 -> 378.60792 | M31: =+K31+L31 -> 1460.3448 | N31: =+M31*0.438 -> 639.63103 | O31: =+M31+N31 -> 2099.9759 | P31: =H31/Q31-1 -> 0.05 | Q31: 20434.227 | S31: Compra 11 estuches + 1 de regalo ----> OFERTA $2.100 público | AK31: 100516849 | AL31: 18023.644
A32: 100022072 | B32: SALCHICHAS 12X12 SWIFT | C32: 7790360024541 | D32: 5.4 | E32: 12 | F32: =+VLOOKUP(A32,$AK$4:$AL$110,2,FALSE) -> #N/A | G32: =0.0833333333333333*100% -> 0.083333333 | H32: =+F32*(1-G32) -> #N/A | I32: =+H32/E32 -> #N/A | J32: =+I32*J$3 -> #N/A | K32: =+I32+J32 -> #N/A | L32: =+K32*0.3388 -> #N/A | M32: =+K32+L32 -> #N/A | N32: =+M32*N$3 -> #N/A | O32: =+M32+N32 -> #N/A | P32: =H32/Q32-1 -> #N/A | Q32: 19412.516 | S32: Conveniencia vs 22085: Oferta $3.990 | Y32: 3600 | Z32: 4090 | AA32: 4495 | AB32: 4400 | AF32: 17225.547 | AG32: =+(H32-AF32)/AF32 -> #N/A | AK32: 100522206 | AL32: 58843.879 | AN32: =+Q32/H32 -> #N/A
A33: 100522205 | B33: SALCHICHAS 12X12 SWIFT | C33: 7790360983954 | D33: 5.4 | E33: 12 | F33: =+VLOOKUP(A33,$AK$4:$AL$110,2,FALSE) -> 22236.155 | G33: =0.0833333333333333*100% -> 0.083333333 | H33: =+F33*(1-G33) -> 20383.142 | I33: =+H33/E33 -> 1698.5951 | J33: =+I33*J$3 -> 356.70498 | K33: =+I33+J33 -> 2055.3001 | L33: =+K33*0.3388 -> 696.33568 | M33: =+K33+L33 -> 2751.6358 | N33: =+M33*N$3 -> 1238.2361 | O33: =+M33+N33 -> 3989.8719 | P33: =H33/Q33-1 -> 0.05 | Q33: 19412.516 | S33: Conveniencia vs 22085: Oferta $3.990 | AK33: 100022058 | AL33: 15783.589
A34: 100516849 | B34: SALCHICHAS SIN PIEL 24X6 "SWIFT KIDS" X 190 g | C34: 7790360970053 | D34: 4.56 | E34: 24 | F34: =+VLOOKUP(A34,$AK$4:$AL$110,2,FALSE) -> 18023.644 | H34: =+F34*(1-G34) -> 18023.644 | I34: =+H34/E34 -> 750.98516 | J34: =+I34*J$3 -> 157.70688 | K34: =+I34+J34 -> 908.69205 | L34: =+K34*0.339 -> 308.0466 | M34: =+K34+L34 -> 1216.7386 | N34: =+M34*0.4 -> 486.69546 | O34: =+M34+N34 -> 1703.4341 | P34: =H34/Q34-1 -> 0.05 | Q34: 17165.375 | S34: Oferta incluida en lista: $1.700 | Y34: 1650 | Z34: 1888 | AA34: PATY FUN | AF34: 15705.646 | AG34: =+(H34-AF34)/AF34 -> 0.14759012 | AK34: 100518151 | AL34: 67038.027 | AN34: =+Q34/H34 -> 0.95238095
A35: 100022039 | B35: SALCHICHAS LARGAS 10 x 12 SWIFT INSTITUCIONAL | C35: 7790360007063 | D35: 8.7 | E35: 10 | F35: =+VLOOKUP(A35,$AK$4:$AL$110,2,FALSE) -> #N/A | H35: =+F35*(1-G35) -> #N/A | I35: =+H35/E35 -> #N/A | J35: =+I35*J$3 -> #N/A | K35: =+I35+J35 -> #N/A | L35: =+K35*L$3 -> #N/A | M35: =+K35+L35 -> #N/A | N35: =+M35*N$3 -> #N/A | O35: =+M35+N35 -> #N/A | P35: =H35/Q35-1 -> #N/A | Q35: 56041.789 | Z35: ICB | AA35: 66 | AB35: PANCHIN | AC35: fela | AF35: 44083.414 | AG35: =+(H35-AF35)/AF35 -> #N/A | AN35: =+Q35/H35 -> #N/A
A36: 100522206 | B36: SALCHICHAS LARGAS 10 x 12 SWIFT INSTITUCIONAL | C36: 7790360983961 | D36: 8.7 | E36: 10 | F36: 56041.789 | H36: =+F36*(1-G36) -> 56041.789 | I36: =+H36/E36 -> 5604.1789 | J36: =+I36*J$3 -> 1176.8776 | K36: =+I36+J36 -> 6781.0565 | L36: =+K36*L$3 -> 2373.3698 | M36: =+K36+L36 -> 9154.4263 | N36: =+M36*N$3 -> 4119.4918 | O36: =+M36+N36 -> 13273.918 | P36: =H36/Q36-1 -> 0 | Q36: 56041.789 | AK36: 100021000 | AL36: 12962.274
A37: 100022058 | B37: SALCHICHAS SIN PIEL "LA BLANCA" 24X6X190 Grs; | C37: 7790360026002 | D37: 4.56 | E37: 24 | F37: =+VLOOKUP(A37,$AK$4:$AL$110,2,FALSE) -> 15783.589 | H37: =+F37*(1-G37) -> 15783.589 | I37: =+H37/E37 -> 657.64956 | J37: =+I37*J$3 -> 138.10641 | K37: =+I37+J37 -> 795.75597 | L37: =+K37*0.3 -> 238.72679 | M37: =+K37+L37 -> 1034.4828 | N37: =+M37*N$3 -> 465.51724 | O37: =+M37+N37 -> 1500 | P37: =H37/Q37-1 -> 0 | Q37: 15783.589 | Y37: 1130 | Z37: 1190 | AA37: 1000 | AB37: 1198 | AC37: 1500 | AD37: MISMO PX MES ANT | AF37: 11449.922 | AG37: =+(H37-AF37)/AF37 -> 0.37848877 | AK37: 100021001 | AL37: 12962.274 | AN37: =+Q37/H37 -> 1
A38: 100518151 | B38: SALCHICHAS LARGAS 10 x 12 x 870g | C38: 7790360974990 | D38: 8.7 | E38: 10 | F38: =+VLOOKUP(A38,$AK$4:$AL$110,2,FALSE) -> 67038.027 | H38: =+F38*(1-G38) -> 67038.027 | I38: =+H38/E38 -> 6703.8027 | J38: =+I38*J$3 -> 1407.7986 | K38: =+I38+J38 -> 8111.6012 | L38: =+K38*0.3 -> 2433.4804 | M38: =+K38+L38 -> 10545.082 | N38: =+M38*N$3 -> 4745.2867 | O38: =+M38+N38 -> 15290.368 | P38: =H38/Q38-1 -> 0.05 | Q38: 63845.74 | AF38: 50222.132 | AG38: =+(H38-AF38)/AF38 -> 0.33483035 | AK38: 100522277 | AL38: 12962.274 | AN38: =+Q38/H38 -> 0.95238095
F39: =+VLOOKUP(A39,$AK$4:$AL$110,2,FALSE) -> #N/A | H39: =+F39*(1-G39) -> #N/A | I39: =+H39/E39 -> #N/A | J39: 0.21 | L39: 0.22 | N39: 0.35 | P39: =H39/Q39-1 -> #N/A | Q39: #N/A | Y39: =+Y37*24 -> 27120 | AF39: #N/A | AG39: =+(H39-AF39)/AF39 -> #N/A | AK39: 100522333 | AL39: 12962.274 | AN39: =+Q39/H39 -> #N/A
A40: 100021000 | B40: PATE DE FOIE 24X90G SWIFT | C40: 7790360720382 | D40: 2.16 | E40: 24 | F40: =+VLOOKUP(A40,$AK$4:$AL$110,2,FALSE) -> 12962.274 | H40: =+F40*(1-G40) -> 12962.274 | I40: =+H40/E40 -> 540.09474 | J40: =+I40*J$3 -> 113.41989 | K40: =+I40+J40 -> 653.51463 | L40: =+K40*L$39 -> 143.77322 | M40: =+K40+L40 -> 797.28785 | N40: =+M40*N$39 -> 279.05075 | O40: =+M40+N40 -> 1076.3386 | P40: =H40/Q40-1 -> 0.05 | Q40: 12345.023 | Y40: =+Y39/1.21/1.35/1.45 -> 11449.922 | Z40: PX 22058 | AF40: 10353.088 | AG40: =+(H40-AF40)/AF40 -> 0.25202 | AK40: 100021045 | AL40: 12962.274 | AN40: =+Q40/H40 -> 0.95238095
A41: 100021001 | B41: PICADILLO DE CARNE 24X90G SWIFT | C41: 7790360720115 | D41: 2.16 | E41: 24 | F41: =+VLOOKUP(A41,$AK$4:$AL$110,2,FALSE) -> 12962.274 | H41: =+F41*(1-G41) -> 12962.274 | I41: =+H41/E41 -> 540.09474 | J41: =+I41*J$3 -> 113.41989 | K41: =+I41+J41 -> 653.51463 | L41: =+K41*L$39 -> 143.77322 | M41: =+K41+L41 -> 797.28785 | N41: =+M41*N$39 -> 279.05075 | O41: =+M41+N41 -> 1076.3386 | P41: =H41/Q41-1 -> 0.05 | Q41: 12345.023 | Y41: =+F37-Y40 -> 4333.667 | AF41: 10353.088 | AG41: =+(H41-AF41)/AF41 -> 0.25202 | AK41: 100021004 | AL41: 12962.274 | AN41: =+Q41/H41 -> 0.95238095
A42: 100522277 | B42: Picadillo de Carne Picante Chile Chipotle 24x90 g | D42: 2.16 | E42: 24 | F42: =+VLOOKUP(A42,$AK$4:$AL$110,2,FALSE) -> 12962.274 | H42: =+F42*(1-G42) -> 12962.274 | I42: =+H42/E42 -> 540.09474 | J42: =+I42*J$3 -> 113.41989 | K42: =+I42+J42 -> 653.51463 | L42: =+K42*L$39 -> 143.77322 | M42: =+K42+L42 -> 797.28785 | N42: =+M42*N$39 -> 279.05075 | O42: =+M42+N42 -> 1076.3386 | P42: =H42/Q42-1 -> 0.05 | Q42: 12345.023 | AK42: 100021006 | AL42: 12962.274 | AN42: =+Q42/H42 -> 0.95238095
A43: 100522333 | B43: Pate de Foie Jalapeño 24x90 Swift | D43: 2.16 | E43: 24 | F43: =+VLOOKUP(A43,$AK$4:$AL$110,2,FALSE) -> 12962.274 | H43: =+F43*(1-G43) -> 12962.274 | I43: =+H43/E43 -> 540.09474 | J43: =+I43*J$3 -> 113.41989 | K43: =+I43+J43 -> 653.51463 | L43: =+K43*L$39 -> 143.77322 | M43: =+K43+L43 -> 797.28785 | N43: =+M43*N$39 -> 279.05075 | O43: =+M43+N43 -> 1076.3386 | P43: =H43/Q43-1 -> 0.05 | Q43: 12345.023 | AK43: 100021007 | AL43: 15499.255 | AN43: =+Q43/H43 -> 0.95238095
A44: 100021045 | B44: PICADILLO DE CARNE PICANTE 24X90G SWIFT | C44: 7790360966582 | D44: 2.16 | E44: 24 | F44: =+VLOOKUP(A44,$AK$4:$AL$110,2,FALSE) -> 12962.274 | H44: =+F44*(1-G44) -> 12962.274 | I44: =+H44/E44 -> 540.09474 | J44: =+I44*J$3 -> 113.41989 | K44: =+I44+J44 -> 653.51463 | L44: =+K44*L$39 -> 143.77322 | M44: =+K44+L44 -> 797.28785 | N44: =+M44*N$39 -> 279.05075 | O44: =+M44+N44 -> 1076.3386 | P44: =H44/Q44-1 -> 0.05 | Q44: 12345.023 | Y44: =+Y41/F37 -> 0.2745679 | AF44: 10088.4 | AG44: =+(H44-AF44)/AF44 -> 0.28486913 | AK44: 100021013 | AL44: 15499.255 | AN44: =+Q44/H44 -> 0.95238095
A45: 100021004 | B45: PATE DE FOIE A LA CREMA 24X88G SWIFT | C45: 7790360964526 | D45: 2.112 | E45: 24 | F45: =+VLOOKUP(A45,$AK$4:$AL$110,2,FALSE) -> 12962.274 | H45: =+F45*(1-G45) -> 12962.274 | I45: =+H45/E45 -> 540.09474 | J45: =+I45*J$3 -> 113.41989 | K45: =+I45+J45 -> 653.51463 | L45: =+K45*L$39 -> 143.77322 | M45: =+K45+L45 -> 797.28785 | N45: =+M45*N$39 -> 279.05075 | O45: =+M45+N45 -> 1076.3386 | P45: =H45/Q45-1 -> 0.05 | Q45: 12345.023 | AF45: 10088.4 | AG45: =+(H45-AF45)/AF45 -> 0.28486913 | AK45: 100021014 | AL45: 15499.255 | AN45: =+Q45/H45 -> 0.95238095
A46: 100021006 | B46: JAMON DEL DIABLO 24X88G SWIFT | C46: 7790360964557 | D46: 2.112 | E46: 24 | F46: =+VLOOKUP(A46,$AK$4:$AL$110,2,FALSE) -> 12962.274 | H46: =+F46*(1-G46) -> 12962.274 | I46: =+H46/E46 -> 540.09474 | J46: =+I46*J$3 -> 113.41989 | K46: =+I46+J46 -> 653.51463 | L46: =+K46*L$39 -> 143.77322 | M46: =+K46+L46 -> 797.28785 | N46: =+M46*N$39 -> 279.05075 | O46: =+M46+N46 -> 1076.3386 | P46: =H46/Q46-1 -> 0.05 | Q46: 12345.023 | Y46: =+Y34*24 -> 39600 | AF46: 10088.4 | AG46: =+(H46-AF46)/AF46 -> 0.28486913 | AK46: 100021054 | AL46: 15499.255 | AN46: =+Q46/H46 -> 0.95238095
A47: 100021007 | B47: PATE DE FOIE DE POLLO 24X85G SWIFT | C47: 7790360964540 | D47: 2.04 | E47: 24 | F47: =+VLOOKUP(A47,$AK$4:$AL$110,2,FALSE) -> 15499.255 | H47: =+F47*(1-G47) -> 15499.255 | I47: =+H47/E47 -> 645.80229 | J47: =+I47*J$3 -> 135.61848 | K47: =+I47+J47 -> 781.42077 | L47: =+K47*L$39 -> 171.91257 | M47: =+K47+L47 -> 953.33333 | N47: =+M47*N$39 -> 333.66667 | O47: =+M47+N47 -> 1287 | P47: =H47/Q47-1 -> 0.099827334 | Q47: 14092.444 | Y47: =+Y46/1.21/1.35/1.45 -> 16718.913 | AF47: 11917.5 | AG47: =+(H47-AF47)/AF47 -> 0.30054582 | AK47: 100021055 | AL47: 15499.255 | AN47: =+Q47/H47 -> 0.90923363
A48: 100021013 | B48: PATE DE FOIE TIPO PROVENZAL 24X85G SWIFT GOURMET | C48: 7790360965714 | D48: 2.04 | E48: 24 | F48: =+VLOOKUP(A48,$AK$4:$AL$110,2,FALSE) -> 15499.255 | H48: =+F48*(1-G48) -> 15499.255 | I48: =+H48/E48 -> 645.80229 | J48: =+I48*J$3 -> 135.61848 | K48: =+I48+J48 -> 781.42077 | L48: =+K48*L$39 -> 171.91257 | M48: =+K48+L48 -> 953.33333 | N48: =+M48*N$39 -> 333.66667 | O48: =+M48+N48 -> 1287 | P48: =H48/Q48-1 -> 0.099827334 | Q48: 14092.444 | Y48: =+F34-Y47 -> 1304.7306 | AF48: 11917.5 | AG48: =+(H48-AF48)/AF48 -> 0.30054582 | AK48: 100021015 | AL48: 15499.255 | AN48: =+Q48/H48 -> 0.90923363
A49: 100021014 | B49: PATE DE FOIE C/PIMIENTA VERDE 24X85G SWIFT GOURMET | C49: 7790360965721 | D49: 2.04 | E49: 24 | F49: =+VLOOKUP(A49,$AK$4:$AL$110,2,FALSE) -> 15499.255 | H49: =+F49*(1-G49) -> 15499.255 | I49: =+H49/E49 -> 645.80229 | J49: =+I49*J$3 -> 135.61848 | K49: =+I49+J49 -> 781.42077 | L49: =+K49*L$39 -> 171.91257 | M49: =+K49+L49 -> 953.33333 | N49: =+M49*N$39 -> 333.66667 | O49: =+M49+N49 -> 1287 | P49: =H49/Q49-1 -> 0.099827334 | Q49: 14092.444 | Y49: =+Y48/F34 -> 0.072389946 | AF49: 11917.5 | AG49: =+(H49-AF49)/AF49 -> 0.30054582 | AK49: 100021008 | AL49: 10971.007 | AN49: =+Q49/H49 -> 0.90923363
A50: 100021054 | B50: PATE JAMON AHUMADO 24X85G | C50: 7790360965707 | D50: 2.04 | E50: 24 | F50: =+VLOOKUP(A50,$AK$4:$AL$110,2,FALSE) -> 15499.255 | H50: =+F50*(1-G50) -> 15499.255 | I50: =+H50/E50 -> 645.80229 | J50: =+I50*J$3 -> 135.61848 | K50: =+I50+J50 -> 781.42077 | L50: =+K50*L$39 -> 171.91257 | M50: =+K50+L50 -> 953.33333 | N50: =+M50*N$39 -> 333.66667 | O50: =+M50+N50 -> 1287 | P50: =H50/Q50-1 -> 0.099827334 | Q50: 14092.444 | AF50: 11917.5 | AG50: =+(H50-AF50)/AF50 -> 0.30054582 | AK50: 100021009 | AL50: 10971.007 | AN50: =+Q50/H50 -> 0.90923363
A51: 100021055 | B51: PATE HONGOS 24X85G | C51: 7790360965189 | D51: 2.04 | E51: 24 | F51: =+VLOOKUP(A51,$AK$4:$AL$110,2,FALSE) -> 15499.255 | H51: =+F51*(1-G51) -> 15499.255 | I51: =+H51/E51 -> 645.80229 | J51: =+I51*J$3 -> 135.61848 | K51: =+I51+J51 -> 781.42077 | L51: =+K51*L$39 -> 171.91257 | M51: =+K51+L51 -> 953.33333 | N51: =+M51*N$39 -> 333.66667 | O51: =+M51+N51 -> 1287 | P51: =H51/Q51-1 -> 0.099827334 | Q51: 14092.444 | AF51: 11917.5 | AG51: =+(H51-AF51)/AF51 -> 0.30054582 | AK51: 100021010 | AL51: 10971.007 | AN51: =+Q51/H51 -> 0.90923363
A52: 100021015 | B52: PATE DE SALMON 24X85G SWIFT GOURMET | C52: 7790360965202 | D52: 2.04 | E52: 24 | F52: =+VLOOKUP(A52,$AK$4:$AL$110,2,FALSE) -> 15499.255 | H52: =+F52*(1-G52) -> 15499.255 | I52: =+H52/E52 -> 645.80229 | J52: =+I52*J$3 -> 135.61848 | K52: =+I52+J52 -> 781.42077 | L52: =+K52*L$39 -> 171.91257 | M52: =+K52+L52 -> 953.33333 | N52: =+M52*N$39 -> 333.66667 | O52: =+M52+N52 -> 1287 | P52: =H52/Q52-1 -> 0.099827334 | Q52: 14092.444 | AF52: 11917.5 | AG52: =+(H52-AF52)/AF52 -> 0.30054582 | AK52: 100021011 | AL52: 10971.007 | AN52: =+Q52/H52 -> 0.90923363
A53: 100021008 | B53: PICADILLO DE CARNE 24X90G LA BLANCA | C53: 7790360720122 | D53: 2.16 | E53: 24 | F53: =+VLOOKUP(A53,$AK$4:$AL$110,2,FALSE) -> 10971.007 | H53: =+F53*(1-G53) -> 10971.007 | I53: =+H53/E53 -> 457.12529 | J53: =+I53*J$3 -> 95.996311 | K53: =+I53+J53 -> 553.1216 | L53: =+K53*L$39 -> 121.68675 | M53: =+K53+L53 -> 674.80835 | N53: =+M53*N$39 -> 236.18292 | O53: =+M53+N53 -> 910.99127 | P53: =H53/Q53-1 -> 0.05 | Q53: 10448.578 | AF53: 9046.3879 | AG53: =+(H53-AF53)/AF53 -> 0.21275 | AN53: =+Q53/H53 -> 0.95238095
A54: 100021009 | B54: PATE DE FOIE 24X90G LA BLANCA | C54: 7790360965127 | D54: 2.16 | E54: 24 | F54: =+VLOOKUP(A54,$AK$4:$AL$110,2,FALSE) -> 10971.007 | H54: =+F54*(1-G54) -> 10971.007 | I54: =+H54/E54 -> 457.12529 | J54: =+I54*J$3 -> 95.996311 | K54: =+I54+J54 -> 553.1216 | L54: =+K54*L$39 -> 121.68675 | M54: =+K54+L54 -> 674.80835 | N54: =+M54*N$39 -> 236.18292 | O54: =+M54+N54 -> 910.99127 | P54: =H54/Q54-1 -> 0.05 | Q54: 10448.578 | AF54: 9046.3879 | AG54: =+(H54-AF54)/AF54 -> 0.21275 | AK54: 100516217 | AL54: 25816.615 | AN54: =+Q54/H54 -> 0.95238095
A55: 100021010 | B55: PICADILLO DE CARNE 24X90G SAFRA | C55: 7790920008707 | D55: 2.16 | E55: 24 | F55: =+VLOOKUP(A55,$AK$4:$AL$110,2,FALSE) -> 10971.007 | H55: =+F55*(1-G55) -> 10971.007 | I55: =+H55/E55 -> 457.12529 | J55: =+I55*J$3 -> 95.996311 | K55: =+I55+J55 -> 553.1216 | L55: =+K55*L$39 -> 121.68675 | M55: =+K55+L55 -> 674.80835 | N55: =+M55*N$39 -> 236.18292 | O55: =+M55+N55 -> 910.99127 | P55: =H55/Q55-1 -> 0.05 | Q55: 10448.578 | AF55: 9046.3879 | AG55: =+(H55-AF55)/AF55 -> 0.21275 | AK55: 100516214 | AL55: 33331.909 | AN55: =+Q55/H55 -> 0.95238095
A56: 100021011 | B56: PATE DE FOIE 24X90G SAFRA | C56: 7790920008714 | D56: 2.16 | E56: 24 | F56: =+VLOOKUP(A56,$AK$4:$AL$110,2,FALSE) -> 10971.007 | H56: =+F56*(1-G56) -> 10971.007 | I56: =+H56/E56 -> 457.12529 | J56: =+I56*J$3 -> 95.996311 | K56: =+I56+J56 -> 553.1216 | L56: =+K56*L$39 -> 121.68675 | M56: =+K56+L56 -> 674.80835 | N56: =+M56*N$39 -> 236.18292 | O56: =+M56+N56 -> 910.99127 | P56: =H56/Q56-1 -> 0.05 | Q56: 10448.578 | AF56: 9046.3879 | AG56: =+(H56-AF56)/AF56 -> 0.21275 | AK56: 100516215 | AL56: 33331.909 | AN56: =+Q56/H56 -> 0.95238095
F57: =+VLOOKUP(A57,$AK$4:$AL$110,2,FALSE) -> #N/A | H57: =+F57*(1-G57) -> #N/A | I57: =+H57/E57 -> #N/A | P57: =H57/Q57-1 -> #N/A | Q57: #N/A | AF57: #N/A | AG57: =+(H57-AF57)/AF57 -> #N/A | AK57: 100516216 | AL57: 33331.909 | AN57: =+Q57/H57 -> #N/A
A58: 100516217 | B58: MILANESAS DE SOJA CLASICAS PREFRITA | C58: 7790360967824 | D58: 5.8 | E58: 20 | F58: =+VLOOKUP(A58,$AK$4:$AL$110,2,FALSE) -> 25816.615 | H58: =+F58*(1-G58) -> 25816.615 | I58: =+H58/E58 -> 1290.8307 | J58: =+I58*J$3 -> 271.07446 | K58: =+I58+J58 -> 1561.9052 | L58: =+K58*L$3 -> 546.66682 | M58: =+K58+L58 -> 2108.572 | N58: =+M58*0.423 -> 891.92597 | O58: =+M58+N58 -> 3000.498 | P58: =H58/Q58-1 -> 0.03 | Q58: 25064.675 | S58: Oferta neteada en lista $2.999 | AF58: 22937.728 | AG58: =+(H58-AF58)/AF58 -> 0.12550881 | AN58: =+Q58/H58 -> 0.97087379
A59: 100516214 | B59: MILANESAS DE SOJA RELLENAS CON JAMON Y QUESO | C59: 7790360967794 | D59: 7 | E59: 20 | F59: =+VLOOKUP(A59,$AK$4:$AL$110,2,FALSE) -> 33331.909 | H59: =+F59*(1-G59) -> 33331.909 | I59: =+H59/E59 -> 1666.5955 | J59: =+I59*J$3 -> 349.98504 | K59: =+I59+J59 -> 2016.5805 | L59: =+K59*L$3 -> 705.80317 | M59: =+K59+L59 -> 2722.3837 | N59: =+M59*N$3 -> 1225.0727 | O59: =+M59+N59 -> 3947.4563 | P59: =H59/Q59-1 -> -1.1428248e-07 | Q59: 33331.913 | S59: Oferta neteada en lista $3.950 | AF59: 31418.525 | AG59: =+(H59-AF59)/AF59 -> 0.060899879 | AK59: 100021704 | AL59: 37686.636 | AN59: =+Q59/H59 -> 1.0000001
A60: 100516215 | B60: MILANESAS DE SOJA RELLENAS CON ESPINACA Y QUESO | C60: 7790360967800 | D60: 7 | E60: 20 | F60: =+VLOOKUP(A60,$AK$4:$AL$110,2,FALSE) -> 33331.909 | H60: =+F60*(1-G60) -> 33331.909 | I60: =+H60/E60 -> 1666.5955 | J60: =+I60*J$3 -> 349.98504 | K60: =+I60+J60 -> 2016.5805 | L60: =+K60*L$3 -> 705.80317 | M60: =+K60+L60 -> 2722.3837 | N60: =+M60*N$3 -> 1225.0727 | O60: =+M60+N60 -> 3947.4563 | P60: =H60/Q60-1 -> -1.1428248e-07 | Q60: 33331.913 | S60: Oferta neteada en lista $3.950 | AF60: 31418.525 | AG60: =+(H60-AF60)/AF60 -> 0.060899879 | AK60: 100021705 | AL60: 34258.029 | AN60: =+Q60/H60 -> 1.0000001
A61: 100516216 | B61: MILANESAS DE SOJA RELLENAS CON TOMATE Y QUESO | C61: 7790360967817 | D61: 7 | E61: 20 | F61: =+VLOOKUP(A61,$AK$4:$AL$110,2,FALSE) -> 33331.909 | H61: =+F61*(1-G61) -> 33331.909 | I61: =+H61/E61 -> 1666.5955 | J61: =+I61*J$3 -> 349.98504 | K61: =+I61+J61 -> 2016.5805 | L61: =+K61*L$3 -> 705.80317 | M61: =+K61+L61 -> 2722.3837 | N61: =+M61*N$3 -> 1225.0727 | O61: =+M61+N61 -> 3947.4563 | P61: =H61/Q61-1 -> -1.1428248e-07 | Q61: 33331.913 | S61: Oferta neteada en lista $3.950 | AF61: 31418.525 | AG61: =+(H61-AF61)/AF61 -> 0.060899879 | AK61: 100021709 | AL61: 54972.17 | AN61: =+Q61/H61 -> 1.0000001
F62: =+VLOOKUP(A62,$AK$4:$AL$110,2,FALSE) -> #N/A | H62: =+F62*(1-G62) -> #N/A | I62: =+H62/E62 -> #N/A | P62: =H62/Q62-1 -> #N/A | Q62: #N/A | AF62: #N/A | AG62: =+(H62-AF62)/AF62 -> #N/A | AK62: 100521357 | AL62: 44177.826 | AN62: =+Q62/H62 -> #N/A
A63: 100021704 | B63: BOCADITOS DE CARNE "SWIFT" - 12x380g | C63: 7790360023902 | D63: =12*0.38 -> 4.56 | E63: 12 | F63: =+VLOOKUP(A63,$AK$4:$AL$110,2,FALSE) -> 37686.636 | H63: =+F63*(1-G63) -> 37686.636 | I63: =+H63/E63 -> 3140.553 | J63: =+I63*J$3 -> 659.51613 | K63: =+I63+J63 -> 3800.0691 | L63: =+K63*L$3 -> 1330.0242 | M63: =+K63+L63 -> 5130.0933 | N63: =+M63*N$3 -> 2308.542 | O63: =+M63+N63 -> 7438.6353 | P63: =H63/Q63-1 -> 0 | Q63: 37686.636 | AF63: 35892.034 | AG63: =+(H63-AF63)/AF63 -> 0.05 | AK63: 100521358 | AL63: 66266.739 | AN63: =+Q63/H63 -> 1
A64: 100021705 | B64: BOCADITOS DE POLLO "SWIFT" - 12x380g | C64: 7790360024336 | D64: =12*0.38 -> 4.56 | E64: 12 | F64: =+VLOOKUP(A64,$AK$4:$AL$110,2,FALSE) -> 34258.029 | H64: =+F64*(1-G64) -> 34258.029 | I64: =+H64/E64 -> 2854.8357 | J64: =+I64*J$3 -> 599.51551 | K64: =+I64+J64 -> 3454.3513 | L64: =+K64*L$3 -> 1209.0229 | M64: =+K64+L64 -> 4663.3742 | N64: =+M64*N$3 -> 2098.5184 | O64: =+M64+N64 -> 6761.8926 | P64: =H64/Q64-1 -> 0 | Q64: 34258.029 | AF64: 32626.694 | AG64: =+(H64-AF64)/AF64 -> 0.05 | AK64: 100522130 | AL64: 36420.087 | AN64: =+Q64/H64 -> 1
A65: 100021709 | B65: BOCADITOS DE POLLO "SWIFT" - 10x760g | C65: 7790360024701 | D65: 7.6 | E65: 10 | F65: =+VLOOKUP(A65,$AK$4:$AL$110,2,FALSE) -> 54972.17 | H65: =+F65*(1-G65) -> 54972.17 | I65: =+H65/E65 -> 5497.217 | J65: =+I65*J$3 -> 1154.4156 | K65: =+I65+J65 -> 6651.6325 | L65: =+K65*L$3 -> 2328.0714 | M65: =+K65+L65 -> 8979.7039 | N65: =+M65*N$3 -> 4040.8668 | O65: =+M65+N65 -> 13020.571 | P65: =H65/Q65-1 -> 0 | Q65: 54972.17 | AF65: 43626.961 | AG65: =+(H65-AF65)/AF65 -> 0.2600504 | AK65: 100021725 | AL65: 28414.154 | AN65: =+Q65/H65 -> 1
A66: 100521357 | B66: CRUNCHIES DE POLLO "SWIFT" - 12x380g | C66: 7790360982018 | D66: 4.56 | E66: 12 | F66: =+VLOOKUP(A66,$AK$4:$AL$110,2,FALSE) -> 44177.826 | G66: 0.33 | H66: =+F66*(1-G66) -> 29599.143 | I66: =+H66/E66 -> 2466.5953 | J66: =+I66*J$3 -> 517.98501 | K66: =+I66+J66 -> 2984.5803 | L66: =+K66*L$3 -> 1044.6031 | M66: =+K66+L66 -> 4029.1834 | N66: =+M66*N$3 -> 1813.1325 | O66: =+M66+N66 -> 5842.3159 | P66: =H66/Q66-1 -> 0 | Q66: 29599.143 | S66: OFERTA INCORPORACION Compra 4 bolsa + 2 de regalo: 33% de dcto vía NC por cumplimiento mínimo de volumen. Si va en un solo pedido, pueder ir a px en factura. Objetivo informado en avance (por cliente, por sku) | AF66: 42074.12 | AG66: =+(H66-AF66)/AF66 -> -0.2965 | AK66: 100517055 | AL66: 28376.008 | AN66: =+Q66/H66 -> 1
A67: 100521358 | B67: CRUNCHIES DE POLLO "SWIFT" - 10x760g | C67: 7790360982025 | D67: 7.6 | E67: 10 | F67: =+VLOOKUP(A67,$AK$4:$AL$110,2,FALSE) -> 66266.739 | G67: 0.33 | H67: =+F67*(1-G67) -> 44398.715 | I67: =+H67/E67 -> 4439.8715 | J67: =+I67*J$3 -> 932.37302 | K67: =+I67+J67 -> 5372.2445 | L67: =+K67*L$3 -> 1880.2856 | M67: =+K67+L67 -> 7252.5301 | N67: =+M67*N$3 -> 3263.6386 | O67: =+M67+N67 -> 10516.169 | P67: =H67/Q67-1 -> -0.33 | Q67: 66266.739 | S67: Oferta incorporación 3x2 | Y67: OCT | Z67: LUCHETTI | AA67: PATITAS | AF67: 63111.18 | AG67: =+(H67-AF67)/AF67 -> -0.2965 | AK67: 100517186 | AL67: 71701.329 | AN67: =+Q67/H67 -> 1.4925373
A68: 100522130 | B68: BOCADITOS DE POLLO "SWIFT KIDS" - 12x400g | C68: 7790360982445 | D68: 4.8 | E68: 12 | F68: =+VLOOKUP(A68,$AK$4:$AL$110,2,FALSE) -> 36420.087 | H68: =+F68*(1-G68) -> 36420.087 | I68: =+H68/E68 -> 3035.0073 | J68: =+I68*J$3 -> 637.35152 | K68: =+I68+J68 -> 3672.3588 | L68: =+K68*L$3 -> 1285.3256 | M68: =+K68+L68 -> 4957.6844 | N68: =+M68*N$3 -> 2230.958 | O68: =+M68+N68 -> 7188.6423 | P68: =H68/Q68-1 -> 0.05 | Q68: 34685.797 | Y68: 5250 | Z68: 5560 | AA68: 7192 | AF68: 25331.687 | AG68: =+(H68-AF68)/AF68 -> 0.43772846 | AK68: 100521663 | AL68: 37997.53 | AN68: =+Q68/H68 -> 0.95238095
A69: 100021725 | B69: BOCADITOS DE POLLO GASTRONOMICOS "LA BLANCA" - x6kg | C69: 7790360027009 | D69: 6 | E69: 4 | F69: =+VLOOKUP(A69,$AK$4:$AL$110,2,FALSE) -> 28414.154 | H69: =+F69*(1-G69) -> 28414.154 | I69: =+H69/E69 -> 7103.5386 | J69: =+I69*J$3 -> 1491.7431 | K69: =+I69+J69 -> 8595.2817 | L69: =+K69*L$3 -> 3008.3486 | M69: =+K69+L69 -> 11603.63 | N69: =+M69*N$3 -> 5221.6336 | O69: =+M69+N69 -> 16825.264 | P69: =H69/Q69-1 -> 0 | Q69: 28414.154 | AF69: 27061.099 | AG69: =+(H69-AF69)/AF69 -> 0.05 | AK69: 100021728 | AL69: 35669.865 | AN69: =+Q69/H69 -> 1
A70: 100517055 | B70: PALITO DE POLLO "SWIFT" 12 X 260 Grs. | C70: 7790360971135 | D70: 3.12 | E70: 12 | F70: =+VLOOKUP(A70,$AK$4:$AL$110,2,FALSE) -> 28376.008 | H70: =+F70*(1-G70) -> 28376.008 | I70: =+H70/E70 -> 2364.6673 | J70: =+I70*J$3 -> 496.58014 | K70: =+I70+J70 -> 2861.2475 | L70: =+K70*L$3 -> 1001.4366 | M70: =+K70+L70 -> 3862.6841 | N70: =+M70*N$3 -> 1738.2079 | O70: =+M70+N70 -> 5600.892 | P70: =H70/Q70-1 -> 0 | Q70: 28376.008 | AF70: 27024.77 | AG70: =+(H70-AF70)/AF70 -> 0.05 | AK70: 100517679 | AL70: 35830.538 | AN70: =+Q70/H70 -> 1
A71: 100517186 | B71: PALITO DE POLLO "SWIFT" 8 X 1 Kg.. | C71: 7790360971395 | D71: 8 | E71: 8 | F71: =+VLOOKUP(A71,$AK$4:$AL$110,2,FALSE) -> 71701.329 | H71: =+F71*(1-G71) -> 71701.329 | I71: =+H71/E71 -> 8962.6661 | J71: =+I71*J$3 -> 1882.1599 | K71: =+I71+J71 -> 10844.826 | L71: =+K71*L$3 -> 3795.6891 | M71: =+K71+L71 -> 14640.515 | N71: =+M71*N$3 -> 6588.2318 | O71: =+M71+N71 -> 21228.747 | P71: =H71/Q71-1 -> 0 | Q71: 71701.329 | AF71: 68286.98 | AG71: =+(H71-AF71)/AF71 -> 0.05 | AN71: =+Q71/H71 -> 1
A72: 100521663 | B72: MILANESITAS DE CARNE "SWIFT" - 12x400g | C72: 7790360982537 | D72: 4.8 | E72: 12 | F72: 37997.53 | G72: 0.33 | H72: =+F72*(1-G72) -> 25458.345 | I72: =+H72/E72 -> 2121.5288 | J72: =+I72*J$3 -> 445.52104 | K72: =+I72+J72 -> 2567.0498 | L72: =+K72*0.343 -> 880.49808 | M72: =+K72+L72 -> 3447.5479 | N72: =+M72*N$3 -> 1551.3965 | O72: =+M72+N72 -> 4998.9444 | P72: =H72/Q72-1 -> 0 | Q72: 25458.345 | S72: OFERTA INCORPORACION Compra 4 bolsa + 2 de regalo: 33% de dcto vía NC por cumplimiento mínimo de volumen. Si va en un solo pedido, pueder ir a px en factura. Objetivo informado en avance (por cliente, por sku) | AF72: 42746.88 | AK72: 100516219 | AL72: 16599.454 | AN72: =+Q72/H72 -> 1
A73: 100021728 | B73: MEDALLONES DE POLLO "SWIFT" - 12x4x80g | C73: 7790360967558 | D73: 3.84 | E73: 12 | F73: =+VLOOKUP(A73,$AK$4:$AL$110,2,FALSE) -> 35669.865 | H73: =+F73*(1-G73) -> 35669.865 | I73: =+H73/E73 -> 2972.4887 | J73: =+I73*J$3 -> 624.22263 | K73: =+I73+J73 -> 3596.7114 | L73: =+K73*L$3 -> 1258.849 | M73: =+K73+L73 -> 4855.5603 | N73: =+M73*N$3 -> 2185.0021 | O73: =+M73+N73 -> 7040.5625 | P73: =H73/Q73-1 -> 0 | Q73: 35669.865 | AF73: 33971.3 | AG73: =+(H73-AF73)/AF73 -> 0.05 | AK73: 100516220 | AL73: 17830.838 | AN73: =+Q73/H73 -> 1
A74: 100517679 | B74: MEDALLONES DE POLLO GASTRONÓMICO 8x12x80 Grs. | C74: 7790360973498 | D74: 7.68 | E74: 8 | F74: =+VLOOKUP(A74,$AK$4:$AL$110,2,FALSE) -> 35830.538 | H74: =+F74*(1-G74) -> 35830.538 | I74: =+H74/E74 -> 4478.8173 | J74: =+I74*J$3 -> 940.55163 | K74: =+I74+J74 -> 5419.3689 | L74: =+K74*L$3 -> 1896.7791 | M74: =+K74+L74 -> 7316.1481 | N74: =+M74*N$3 -> 3292.2666 | O74: =+M74+N74 -> 10608.415 | P74: =H74/Q74-1 -> 0 | Q74: 35830.538 | AF74: 34124.322 | AG74: =+(H74-AF74)/AF74 -> 0.05 | AL74: 0 | AN74: =+Q74/H74 -> 1
F75: =+VLOOKUP(A75,$AK$4:$AL$110,2,FALSE) -> #N/A | H75: =+F75*(1-G75) -> #N/A | I75: =+H75/E75 -> #N/A | P75: =H75/Q75-1 -> #N/A | Q75: #N/A | AF75: #N/A | AG75: =+(H75-AF75)/AF75 -> #N/A | AK75: 100518158 | AL75: 68490.548 | AN75: =+Q75/H75 -> #N/A
A76: 100516219 | B76: PAPAS PREFRITAS SUPERCONGELADAS 25x400gr | C76: 7790360967770 | D76: 10 | E76: 25 | F76: =+VLOOKUP(A76,$AK$4:$AL$110,2,FALSE) -> 16599.454 | H76: =+F76*(1-G76) -> 16599.454 | I76: =+H76/E76 -> 663.97818 | J76: =+I76*J$3 -> 139.43542 | K76: =+I76+J76 -> 803.4136 | L76: =+K76*L$3 -> 281.19476 | M76: =+K76+L76 -> 1084.6084 | N76: =+M76*N$3 -> 488.07376 | O76: =+M76+N76 -> 1572.6821 | P76: =H76/Q76-1 -> 0 | Q76: 16599.454 | AF76: 16599.454 | AG76: =+(H76-AF76)/AF76 -> 0 | AK76: 100518160 | AL76: 68490.548 | AN76: =+Q76/H76 -> 1
A77: 100516220 | B77: PAPAS PREFRITAS SUPERCONGELADAS 6x2000gr | C77: 7790360967787 | D77: 12 | E77: 6 | F77: =+VLOOKUP(A77,$AK$4:$AL$110,2,FALSE) -> 17830.838 | H77: =+F77*(1-G77) -> 17830.838 | I77: =+H77/E77 -> 2971.8063 | J77: =+I77*J$3 -> 624.07933 | K77: =+I77+J77 -> 3595.8857 | L77: =+K77*L$3 -> 1258.56 | M77: =+K77+L77 -> 4854.4457 | N77: =+M77*N$3 -> 2184.5005 | O77: =+M77+N77 -> 7038.9462 | P77: =H77/Q77-1 -> 0 | Q77: 17830.838 | AF77: 17830.838 | AG77: =+(H77-AF77)/AF77 -> 0 | AK77: 100518463 | AL77: 33357.516 | AN77: =+Q77/H77 -> 1
F78: =+VLOOKUP(A78,$AK$4:$AL$110,2,FALSE) -> #N/A | H78: =+F78*(1-G78) -> #N/A | I78: =+H78/E78 -> #N/A | P78: =H78/Q78-1 -> #N/A | Q78: #N/A | AF78: #N/A | AG78: =+(H78-AF78)/AF78 -> #N/A | AN78: =+Q78/H78 -> #N/A
A79: 100518158 | B79: MILANESA DE CARNE VACUNA CONGELADA 24un x 500grs | C79: 7790360974280 | D79: 12 | E79: 24 | F79: =+VLOOKUP(A79,$AK$4:$AL$110,2,FALSE) -> 68490.548 | H79: =+F79*(1-G79) -> 68490.548 | I79: =+H79/E79 -> 2853.7728 | J79: =+I79*J$3 -> 599.2923 | K79: =+I79+J79 -> 3453.0651 | L79: =+K79*L$3 -> 1208.5728 | M79: =+K79+L79 -> 4661.6379 | N79: =+M79*N$3 -> 2097.7371 | O79: =+M79+N79 -> 6759.375 | P79: =H79/Q79-1 -> 0 | Q79: 68490.548 | AF79: 68490.548 | AG79: =+(H79-AF79)/AF79 -> 0 | AK79: 100518291 | AL79: 14228.63 | AN79: =+Q79/H79 -> 1
A80: 100518160 | B80: MILANESA DE CARNE VACUNA CONGELADA 12un x 1000grs | C80: 7790360974686 | D80: 12 | E80: 12 | F80: =+VLOOKUP(A80,$AK$4:$AL$110,2,FALSE) -> 68490.548 | H80: =+F80*(1-G80) -> 68490.548 | I80: =+H80/E80 -> 5707.5457 | J80: =+I80*J$3 -> 1198.5846 | K80: =+I80+J80 -> 6906.1303 | L80: =+K80*L$3 -> 2417.1456 | M80: =+K80+L80 -> 9323.2759 | N80: =+M80*N$3 -> 4195.4741 | O80: =+M80+N80 -> 13518.75 | P80: =H80/Q80-1 -> 0 | Q80: 68490.548 | AF80: 68490.548 | AG80: =+(H80-AF80)/AF80 -> 0 | AK80: 100518292 | AL80: 33574.49 | AN80: =+Q80/H80 -> 1
A81: 100518463 | B81: MILANESAS DE CARNE VACUNA CONG GRANEL 5 kg | C81: 7790360975188 | D81: 5 | E81: 1 | F81: =+VLOOKUP(A81,$AK$4:$AL$110,2,FALSE) -> 33357.516 | H81: =+F81*(1-G81) -> 33357.516 | I81: =+H81/E81 -> 33357.516 | J81: =+I81*J$3 -> 7005.0783 | K81: =+I81+J81 -> 40362.594 | L81: =+K81*L$3 -> 14126.908 | M81: =+K81+L81 -> 54489.502 | N81: =+M81*N$3 -> 24520.276 | O81: =+M81+N81 -> 79009.778 | P81: =H81/Q81-1 -> 0 | Q81: 33357.516 | AF81: 33357.516 | AG81: =+(H81-AF81)/AF81 -> 0 | AN81: =+Q81/H81 -> 1
F82: =+VLOOKUP(A82,$AK$4:$AL$110,2,FALSE) -> #N/A | H82: =+F82*(1-G82) -> #N/A | I82: =+H82/E82 -> #N/A | P82: =H82/Q82-1 -> #N/A | Q82: #N/A | AF82: #N/A | AG82: =+(H82-AF82)/AF82 -> #N/A | AK82: 100517915 | AL82: 145920.01 | AN82: =+Q82/H82 -> #N/A
A83: 100518291 | B83: GRASA VACUNA REFINADA SWIFT 10 X 500 | C83: 7790360975195 | D83: 5 | E83: 10 | F83: =+VLOOKUP(A83,$AK$4:$AL$110,2,FALSE) -> 14228.63 | H83: =+F83*(1-G83) -> 14228.63 | I83: =+H83/E83 -> 1422.863 | J83: =+I83*J$3 -> 298.80123 | K83: =+I83+J83 -> 1721.6642 | L83: =+K83*L$39 -> 378.76613 | M83: =+K83+L83 -> 2100.4304 | N83: =+M83*N$39 -> 735.15063 | O83: =+M83+N83 -> 2835.581 | P83: =H83/Q83-1 -> 0.05 | Q83: 13551.076 | S83: Oferta a px en factura neteada en lista, para $2.830 público | AF83: 13551.076 | AG83: =+(H83-AF83)/AF83 -> 0.05 | AK83: 100517914 | AL83: 159231.16 | AN83: =+Q83/H83 -> 0.95238095
A84: 100518292 | B84: GRASA VACUNA REFINADA SWIFT 12x1Kg | C84: 7790360975201 | D84: 12 | E84: 12 | F84: =+VLOOKUP(A84,$AK$4:$AL$110,2,FALSE) -> 33574.49 | H84: =+F84*(1-G84) -> 33574.49 | I84: =+H84/E84 -> 2797.8742 | J84: =+I84*J$3 -> 587.55357 | K84: =+I84+J84 -> 3385.4277 | L84: =+K84*L$39 -> 744.7941 | M84: =+K84+L84 -> 4130.2218 | N84: =+M84*N$39 -> 1445.5776 | O84: =+M84+N84 -> 5575.7995 | P84: =H84/Q84-1 -> 0.05 | Q84: 31975.705 | S84: Oferta a px en factura neteada en lista, para $5.570 público | AF84: 31975.705 | AG84: =+(H84-AF84)/AF84 -> 0.05 | AN84: =+Q84/H84 -> 0.95238095
F85: =+VLOOKUP(A85,$AK$4:$AL$110,2,FALSE) -> #N/A | H85: =+F85*(1-G85) -> #N/A | I85: =+H85/E85 -> #N/A | J85: 0.105 | L85: 0.3 | N85: 0.4 | P85: =H85/Q85-1 -> #N/A | Q85: #N/A | AF85: #N/A | AG85: =+(H85-AF85)/AF85 -> #N/A | AK85: 100010689 | AL85: 15000 | AN85: =+Q85/H85 -> #N/A
A86: 100517915 | B86: CARNE PICADA CONGELADA 36 UN X 500 g SWIFT | C86: 7790360974020 | D86: 18 | E86: 36 | F86: =+VLOOKUP(A86,$AK$4:$AL$110,2,FALSE) -> 145920.01 | H86: =+F86*(1-G86) -> 145920.01 | I86: =+H86/E86 -> 4053.3336 | J86: =+I86*J$85 -> 425.60003 | K86: =+I86+J86 -> 4478.9337 | L86: =+K86*L$85 -> 1343.6801 | M86: =+K86+L86 -> 5822.6138 | N86: =+M86*N$85 -> 2329.0455 | O86: =+M86+N86 -> 8151.6593 | P86: =H86/Q86-1 -> 0 | Q86: 145920.01 | AF86: 126062.63 | AG86: =+(H86-AF86)/AF86 -> 0.15752 | AK86: 100518335 | AL86: 10714.286 | AN86: =+Q86/H86 -> 1
A87: 100517914 | B87: CARNE PICADA CONGELADA 20 UN X 1 kg SWIFT | C87: 7790360974037 | D87: 20 | E87: 20 | F87: =+VLOOKUP(A87,$AK$4:$AL$110,2,FALSE) -> 159231.16 | H87: =+F87*(1-G87) -> 159231.16 | I87: =+H87/E87 -> 7961.5579 | J87: =+I87*J$85 -> 835.96358 | K87: =+I87+J87 -> 8797.5215 | L87: =+K87*L$85 -> 2639.2565 | M87: =+K87+L87 -> 11436.778 | N87: =+M87*N$85 -> 4574.7112 | O87: =+M87+N87 -> 16011.489 | P87: =H87/Q87-1 -> 0 | Q87: 159231.16 | AF87: 137562.34 | AG87: =+(H87-AF87)/AF87 -> 0.15752 | AK87: 100518332 | AL87: 12321.429 | AN87: =+Q87/H87 -> 1
F88: =+VLOOKUP(A88,$AK$4:$AL$110,2,FALSE) -> #N/A | H88: =+F88*(1-G88) -> #N/A | J88: 0.105 | L88: 0.3 | N88: 0.4 | P88: =H88/Q88-1 -> #N/A | Q88: #N/A | AF88: #N/A | AG88: =+(H88-AF88)/AF88 -> #N/A | AK88: 100518334 | AL88: 10928.571 | AN88: =+Q88/H88 -> #N/A
A89: 100010689 | B89: ENTRAÑA FINA ENF SWIFT | D89: 22 | E89: 1 | F89: =+VLOOKUP(A89,$AK$4:$AL$110,2,FALSE) -> 15000 | H89: =+F89*(1-G89) -> 15000 | I89: =+H89/E89 -> 15000 | J89: =+I89*J$88 -> 1575 | K89: =+I89+J89 -> 16575 | L89: =+K89*L$88 -> 4972.5 | M89: =+K89+L89 -> 21547.5 | N89: =+M89*N$88 -> 8619 | O89: =+M89+N89 -> 30166.5 | P89: =H89/Q89-1 -> 0.05 | Q89: 14285.714 | AF89: 14255.102 | AG89: =+(H89-AF89)/AF89 -> 0.052254832 | AK89: 100518227 | AL89: 12895.714 | AN89: =+Q89/H89 -> 0.95238095
A90: 100518335 | B90: ROAST BEEF EN PORCIONES ENF SWIFT (L) | D90: 22.5 | E90: 1 | F90: =+VLOOKUP(A90,$AK$4:$AL$110,2,FALSE) -> 10714.286 | H90: =+F90*(1-G90) -> 10714.286 | I90: =+H90/E90 -> 10714.286 | J90: =+I90*J$88 -> 1125 | K90: =+I90+J90 -> 11839.286 | L90: =+K90*L$88 -> 3551.7857 | M90: =+K90+L90 -> 15391.071 | N90: =+M90*N$88 -> 6156.4286 | O90: =+M90+N90 -> 21547.5 | P90: =H90/Q90-1 -> 0.05 | Q90: 10204.082 | AF90: 9029.5918 | AG90: =+(H90-AF90)/AF90 -> 0.18657475 | AN90: =+Q90/H90 -> 0.95238095
A91: 100518332 | B91: CARNAZA CUADRADA EN PORCIONES ENF SWIFT (L) | D91: 21.5 | E91: 1 | F91: =+VLOOKUP(A91,$AK$4:$AL$110,2,FALSE) -> 12321.429 | H91: =+F91*(1-G91) -> 12321.429 | I91: =+H91/E91 -> 12321.429 | J91: =+I91*J$88 -> 1293.75 | K91: =+I91+J91 -> 13615.179 | L91: =+K91*L$88 -> 4084.5536 | M91: =+K91+L91 -> 17699.732 | N91: =+M91*N$88 -> 7079.8929 | O91: =+M91+N91 -> 24779.625 | P91: =H91/Q91-1 -> 0.05 | Q91: 11734.694 | Y91: =+R100*72+R4*144 -> 0 | AF91: 9717.3469 | AG91: =+(H91-AF91)/AF91 -> 0.26798278 | AK91: 100520837 | AL91: 33805.839 | AN91: =+Q91/H91 -> 0.95238095
A92: 100518334 | B92: TAPA DE ASADO EN PORCIONES ENF SWIFT (L) | D92: 22.5 | E92: 1 | F92: =+VLOOKUP(A92,$AK$4:$AL$110,2,FALSE) -> 10928.571 | H92: =+F92*(1-G92) -> 10928.571 | I92: =+H92/E92 -> 10928.571 | J92: =+I92*J$88 -> 1147.5 | K92: =+I92+J92 -> 12076.071 | L92: =+K92*L$88 -> 3622.8214 | M92: =+K92+L92 -> 15698.893 | N92: =+M92*N$88 -> 6279.5571 | O92: =+M92+N92 -> 21978.45 | P92: =H92/Q92-1 -> 0.05 | Q92: 10408.163 | Y92: =+R96*24+R4*144 -> 0 | AF92: 7997.9592 | AG92: =+(H92-AF92)/AF92 -> 0.36642001 | AK92: 100522395 | AL92: 34481.949 | AN92: =+Q92/H92 -> 0.95238095
A93: 100518227 | B93: VACIO EN PORCIONES NOV ENFRIADO PARA VENTA LOCAL (L) | D93: 22.5 | E93: 1 | F93: =+VLOOKUP(A93,$AK$4:$AL$110,2,FALSE) -> 12895.714 | H93: =+F93*(1-G93) -> 12895.714 | I93: =+H93/E93 -> 12895.714 | J93: =+I93*J$88 -> 1354.05 | K93: =+I93+J93 -> 14249.764 | L93: =+K93*L$88 -> 4274.9293 | M93: =+K93+L93 -> 18524.694 | N93: =+M93*N$88 -> 7409.8774 | O93: =+M93+N93 -> 25934.571 | P93: =H93/Q93-1 -> 0.071 | Q93: 12040.816 | AF93: 7997.9592 | AG93: =+(H93-AF93)/AF93 -> 0.61237561 | AK93: 100522561 | AL93: 6824.5524 | AN93: =+Q93/H93 -> 0.93370682
A94: 100027726 | B94: BONDIOLA DE CERDO CONGELADA | D94: 22.5 | E94: 1 | F94: =+VLOOKUP(A94,$AK$4:$AL$110,2,FALSE) -> #N/A | H94: =+F94*(1-G94) -> #N/A | I94: =+H94/E94 -> #N/A | J94: =+I94*J$88 -> #N/A | K94: =+I94+J94 -> #N/A | L94: =+K94*L$88 -> #N/A | M94: =+K94+L94 -> #N/A | N94: =+M94*N$88 -> #N/A | O94: =+M94+N94 -> #N/A | P94: =H94/Q94-1 -> #N/A | Q94: 6195 | AN94: =+Q94/H94 -> #N/A
F95: =+VLOOKUP(A95,$AK$4:$AL$110,2,FALSE) -> #N/A | H95: =+F95*(1-G95) -> #N/A | J95: 0.21 | L95: 0.3 | N95: 0.4 | P95: =H95/Q95-1 -> #N/A | Q95: #N/A | AF95: #N/A | AG95: =+(H95-AF95)/AF95 -> #N/A | AK95: 100520902 | AL95: 30287.434 | AN95: =+Q95/H95 -> #N/A
A96: 100520837 | B96: CHORIZOS FRESCOS DE CERDO LIBRE DE GLUTEN | C96: 7790360980625 | D96: 4.8 | E96: 12 | F96: =+VLOOKUP(A96,$AK$4:$AL$110,2,FALSE) -> 33805.839 | H96: =+F96*(1-G96) -> 33805.839 | I96: =+H96/E96 -> 2817.1532 | J96: =+I96*J$95 -> 591.60218 | K96: =+I96+J96 -> 3408.7554 | L96: =+K96*L$95 -> 1022.6266 | M96: =+K96+L96 -> 4431.382 | N96: =+M96*N$95 -> 1772.5528 | O96: =+M96+N96 -> 6203.9348 | P96: =H96/Q96-1 -> 0.04 | Q96: 32505.614 | Y96: 0.1 | Z96: =+H96*(1-Y96) -> 30425.255 | AA96: =+Z96/E96 -> 2535.4379 | AB96: =+AA96*1.21*1.3*1.4 -> 5583.5413 | AC96: VER CUPOS | AD96: Con la compra de 1 caja de 21632 + 2 unidades de Chorizos --> 10% de dcto en ambos SKU | AF96: 30957.728 | AG96: =+(H96-AF96)/AF96 -> 0.092 | AK96: 100522698 | AL96: 38419.725 | AN96: =+Q96/H96 -> 0.96153846
A97: 100522395 | B97: CHORIZOS FRESCOS DE CERDO CONGELADOS LIBRE DE GLUTEN 12u x 400g | C97: 7790360980625 | D97: 4.8 | E97: 12 | F97: =+VLOOKUP(A97,$AK$4:$AL$110,2,FALSE) -> 34481.949 | G97: 0.33 | H97: =+F97*(1-G97) -> 23102.906 | I97: =+H97/E97 -> 1925.2421 | J97: =+I97*J$95 -> 404.30085 | K97: =+I97+J97 -> 2329.543 | L97: =+K97*L$95 -> 698.8629 | M97: =+K97+L97 -> 3028.4059 | N97: =+M97*N$95 -> 1211.3624 | O97: =+M97+N97 -> 4239.7682 | P97: =H97/Q97-1 -> -0.3032 | Q97: 33155.72 | S97: Dinámica 2+1. Compra 2, recibe 3 ----> oferta $4.240 (para distribuidores, vía NC, por cumplimiento de objetivo. Si compra en un solo pedido puede ir a px factura. Objetivo informado en avance por cliente, por sku)
A98: 100522561 | B98: CHORIZOS CONGELADOS DE CERDO LIBRE DE GLUTEN SWIFT GRANEL: 8 paq x 20 u (2kg por paq) | D98: 16 | E98: 8 | F98: =+VLOOKUP(A98,$AK$4:$AL$110,2,FALSE) -> 6824.5524 | G98: 0.33 | H98: =+F98*(1-G98) -> 4572.4501 | I98: =+H98*2 -> 9144.9002 | J98: =+I98*J$95 -> 1920.429 | K98: =+I98+J98 -> 11065.329 | L98: =+K98*L$95 -> 3319.5988 | M98: =+K98+L98 -> 14384.928 | N98: =+M98*N$95 -> 5753.9712 | O98: =+M98+N98 -> 20138.899 | P98: =H98/Q98-1 -> #N/A | Q98: #N/A | S98: Dinámica 2+1. Compra 2, recibe 3 ----> oferta $20.140 los 20 chori (2kg aprox) (para distribuidores, vía NC, por cumplimiento de objetivo. Si compra en un solo pedido puede ir a px factura. Objetivo informado en avance por cliente, por sku) | AK98: 100521457 | AL98: 34485.722
F99: =+VLOOKUP(A99,$AK$4:$AL$110,2,FALSE) -> #N/A | H99: =+F99*(1-G99) -> #N/A | J99: 0.21 | L99: 0.35 | N99: 0.45 | P99: =H99/Q99-1 -> #N/A | Q99: #N/A | AF99: #N/A | AG99: =+(H99-AF99)/AF99 -> #N/A | AK99: 100521455 | AL99: 34485.722 | AN99: =+Q99/H99 -> #N/A
A100: 100520902 | B100: PAPAS PRE COCIDAS SUPERCONGELADAS LIBRES DE GLUTEN 700G | C100: 7790360981042 | D100: 9.8 | E100: 14 | F100: =+VLOOKUP(A100,$AK$4:$AL$110,2,FALSE) -> 30287.434 | G100: 0.125 | H100: =+F100*(1-G100) -> 26501.504 | I100: =+H100/E100 -> 1892.9646 | J100: =+I100*J$99 -> 397.52257 | K100: =+I100+J100 -> 2290.4872 | L100: =+K100*L$99 -> 801.67051 | M100: =+K100+L100 -> 3092.1577 | N100: =+M100*N$99 -> 1391.471 | O100: =+M100+N100 -> 4483.6286 | P100: =H100/Q100-1 -> 0.03 | Q100: 25729.616 | S100: OFERTA compra 7 bolsas , recibe 8. | Y100: 0.1 | Z100: =+H100*(1-Y100) -> 23851.354 | AA100: =+Z100/E100 -> 1703.6681 | AB100: =+AA100*1.21*1.3*1.4 -> 3751.818 | AC100: VER CUPOS | AD100: Con la compra de 1 caja de 21632 + 7 unidades de PAPAS --> 10% de dcto en ambos SKU | AF100: 25729.616 | AG100: =+(H100-AF100)/AF100 -> 0.03 | AK100: 100521453 | AL100: 33300.276 | AN100: =+Q100/H100 -> 0.97087379
A101: 100522698 | B101: Papas Prefritas Supercongeladas libres de gluten 7u x 2 kg | C101: 7790360986511 | D101: 14 | E101: 7 | F101: 44823.005 | G101: =1/7 -> 0.14285714 | H101: =+F101*(1-G101) -> 38419.719 | I101: =+H101/E101 -> 5488.5312 | J101: =+I101*J$99 -> 1152.5916 | K101: =+I101+J101 -> 6641.1228 | L101: =+K101*L$99 -> 2324.393 | M101: =+K101+L101 -> 8965.5157 | N101: =+M101*N$99 -> 4034.4821 | O101: =+M101+N101 -> 12999.998 | Q101: #N/A | S101: 1 paq. Gratis x cj ---> OFERTA $13.000. DCTO VÍA NC POR OBJETIVO DE 1 PALLET. SI LO COMPRA EN UN PEDIDO PUEDE IR A PRECIO | AK101: 100521454 | AL101: 33300.276
...

Sheet NEA
Z1: ACCIÓN VIA NC: COMBO CLASICA 2 X 80 + CHORIZOS
A2: Código | B2: Descripción | C2: EAN | D2: Kg. x Caja | E2: Cant. X Caja | F2: Precio de Lista | H2: Precio de Factura | I2: Precio Neto estuche en factura | J2: IVA | K2: Px Unitario IVA Inc | L2: M-up Dx | M2: Px Unitario Minorista | N2: M-up Minorista | O2: Px Unitario Público | Q2: Enero | S2: OFERTAS Y ACCIONES | Z2: DCTO (%) | AA2: Px ACCIÓN CAJA ($) | AB2: Px Acción estuche ($) | AC2: Px oferta (%) | AD2: CUPO (Cajas) | AE2: CONDICIÓN | AI2: SEP | AJ2: VAR %
J3: 0.21 | L3: 0.33 | N3: 0.4 | AN3: 100021632 | AO3: 42178.607
A4: 100021632 | B4: HAMBURGUESAS 30x160g CLASICA x2 SWIFT | C4: 7790360026606 | D4: 4.8 | E4: 30 | F4: =+VLOOKUP(A4,$AN$3:$AO$109,2,FALSE) -> 42178.607 | G4: 0.07 | H4: =+F4*(1-G4) -> 39226.104 | I4: =+H4/E4 -> 1307.5368 | J4: =+I4*J$3 -> 274.58273 | K4: =+I4+J4 -> 1582.1195 | L4: =+K4*0.309 -> 488.87494 | M4: =+K4+L4 -> 2070.9945 | N4: =+M4*N$3 -> 828.39779 | O4: =+M4+N4 -> 2899.3923 | P4: =H4/Q4-1 -> -0.0235 | Q4: 40170.102 | S4: 7% dcto para oferta $2.900: +15% vs Friar ($2.600) -15% vs Paty ($3.500) | Y4: =+Z4*H4 -> 3922.6104 | Z4: 0.1 | AA4: =+H4*(1-Z4) -> 35303.494 | AB4: =+AA4/E4 -> 1176.7831 | AC4: =+AB4*1.21*1.3*1.4 -> 2591.5118 | AD4: VER CUPOS | AE4: Con la compra de 1 caja de 21632 + 2 unidades de Chorizos --> 10% de dcto en ambos SKU | AI4: 33427.033 | AJ4: =+(H4-AI4)/AI4 -> 0.17348446 | AN4: 100021652 | AO4: 52310.046
A5: 100021652 | B5: HAMBURGUESA 18X4X80G CLASICA SWIFT | C5: 7790360026576 | D5: 5.76 | E5: 18 | F5: =+VLOOKUP(A5,$AN$3:$AO$109,2,FALSE) -> 52310.046 | H5: =+F5*(1-G5) -> 52310.046 | I5: =+H5/E5 -> 2906.1137 | J5: =+I5*J$3 -> 610.28388 | K5: =+I5+J5 -> 3516.3976 | L5: =+K5*L$3 -> 1160.4112 | M5: =+K5+L5 -> 4676.8088 | N5: =+M5*N$3 -> 1870.7235 | O5: =+M5+N5 -> 6547.5323 | P5: =H5/Q5-1 -> 0 | Q5: 52310.046 | AI5: 43529.132 | AJ5: =+(H5-AI5)/AI5 -> 0.201725 | AN5: 100021631 | AO5: 61058.555
A6: 100021631 | B6: HAMBURGUESA 8X12X80G CLASICA SWIFT | C6: 7790360026590 | D6: 7.68 | E6: 8 | F6: =+VLOOKUP(A6,$AN$3:$AO$109,2,FALSE) -> 61058.555 | H6: =+F6*(1-G6) -> 61058.555 | I6: =+H6/E6 -> 7632.3193 | J6: =+I6*J$3 -> 1602.7871 | K6: =+I6+J6 -> 9235.1064 | L6: =+K6*L$3 -> 3047.5851 | M6: =+K6+L6 -> 12282.692 | N6: =+M6*N$3 -> 4913.0766 | O6: =+M6+N6 -> 17195.768 | P6: =H6/Q6-1 -> 0 | Q6: 61058.555 | Y6: =+O4*0.9 -> 2609.4531 | AI6: 69881.188 | AJ6: =+(H6-AI6)/AI6 -> -0.1262519 | AN6: 100021630 | AO6: 74716.389
A7: 100021630 | B7: HAMBURGUESA 6X20X80G CLASICA SWIFT | C7: 7790360026583 | D7: 9.6 | E7: 6 | F7: =+VLOOKUP(A7,$AN$3:$AO$109,2,FALSE) -> 74716.389 | H7: =+F7*(1-G7) -> 74716.389 | I7: =+H7/E7 -> 12452.732 | J7: =+I7*J$3 -> 2615.0736 | K7: =+I7+J7 -> 15067.805 | L7: =+K7*L$3 -> 4972.3757 | M7: =+K7+L7 -> 20040.181 | N7: =+M7*N$3 -> 8016.0724 | O7: =+M7+N7 -> 28056.253 | P7: =H7/Q7-1 -> 0 | Q7: 74716.389 | AI7: 87351.485 | AJ7: =+(H7-AI7)/AI7 -> -0.1446466 | AN7: 100021653 | AO7: 53024.534
A8: 100021653 | B8: MEDALLON 18X4X80G PARRILLERO SWIFT | C8: 7790360026682 | D8: 5.76 | E8: 18 | F8: =+VLOOKUP(A8,$AN$3:$AO$109,2,FALSE) -> 53024.534 | H8: =+F8*(1-G8) -> 53024.534 | I8: =+H8/E8 -> 2945.8075 | J8: =+I8*J$3 -> 618.61957 | K8: =+I8+J8 -> 3564.427 | L8: =+K8*L$3 -> 1176.2609 | M8: =+K8+L8 -> 4740.688 | N8: =+M8*N$3 -> 1896.2752 | O8: =+M8+N8 -> 6636.9631 | P8: =H8/Q8-1 -> 0 | Q8: 53024.534 | AI8: 52653.64 | AJ8: =+(H8-AI8)/AI8 -> 0.00704404 | AN8: 100516169 | AO8: 43213.192
A9: 100516169 | B9: MEDALLONES 18X4X80G SWIFT RECETA ESPECIAL | C9: 7790360967961 | D9: 5.76 | E9: 18 | F9: =+VLOOKUP(A9,$AN$3:$AO$109,2,FALSE) -> 43213.192 | H9: =+F9*(1-G9) -> 43213.192 | I9: =+H9/E9 -> 2400.7329 | J9: =+I9*J$3 -> 504.15391 | K9: =+I9+J9 -> 2904.8868 | L9: =+K9*L$3 -> 958.61264 | M9: =+K9+L9 -> 3863.4994 | N9: =+M9*N$3 -> 1545.3998 | O9: =+M9+N9 -> 5408.8992 | P9: =H9/Q9-1 -> 0 | Q9: 43213.192 | AI9: 41155.421 | AJ9: =+(H9-AI9)/AI9 -> 0.05 | AN9: 100520337 | AO9: 28412.978
A10: 100520337 | B10: MEDALLON BURGER SWIFT MEGA 30 x 160 g | C10: 7790360977960 | D10: 4.8 | E10: 30 | F10: =+VLOOKUP(A10,$AN$3:$AO$109,2,FALSE) -> 28412.978 | H10: =+F10*(1-G10) -> 28412.978 | I10: =+H10/E10 -> 947.09928 | J10: =+I10*J$3 -> 198.89085 | K10: =+I10+J10 -> 1145.9901 | L10: =+K10*0.309 -> 354.11095 | M10: =+K10+L10 -> 1500.1011 | N10: =+M10*N$3 -> 600.04043 | O10: =+M10+N10 -> 2100.1415 | P10: =H10/Q10-1 -> 0.12491965 | Q10: 25257.785 | S10: Oferta neteada en lista: $2.100 para activar estrategia Sandwich vs Friar 2x80 a $2600----> $2.100 con Mega y $2.900 con Clásica | AI10: 27059.979 | AJ10: =+(H10-AI10)/AI10 -> 0.05 | AN10: 100021503 | AO10: 22877.766
A11: 100021503 | B11: Medallón CAJITA 12x4 69 grs | C11: 7790360966841 | D11: 3.312 | E11: 12 | F11: =+VLOOKUP(A11,$AN$3:$AO$109,2,FALSE) -> 22877.766 | G11: 0.083333333 | H11: =+F11*(1-G11) -> 20971.285 | I11: =+H11/E11 -> 1747.6071 | J11: =+I11*J$3 -> 366.99749 | K11: =+I11+J11 -> 2114.6046 | L11: =+K11*L$3 -> 697.81951 | M11: =+K11+L11 -> 2812.4241 | N11: =+M11*N$3 -> 1124.9696 | O11: =+M11+N11 -> 3937.3937 | P11: =H11/Q11-1 -> 0.10044018 | Q11: 19057.179 | S11: Contra 10 estuches + 1 de regalo | AI11: 18946.39 | AJ11: =+(H11-AI11)/AI11 -> 0.106875 | AN11: 100516201 | AO11: 45177.91
A12: 100516201 | B12: HAMBURGUESA 8X12X69G BURGER SWIFT | C12: 7790360968548 | D12: 6.624 | E12: 8 | F12: =+VLOOKUP(A12,$AN$3:$AO$109,2,FALSE) -> 45177.91 | H12: =+F12*(1-G12) -> 45177.91 | I12: =+H12/E12 -> 5647.2388 | J12: =+I12*J$3 -> 1185.9201 | K12: =+I12+J12 -> 6833.1589 | L12: =+K12*L$3 -> 2254.9425 | M12: =+K12+L12 -> 9088.1014 | N12: =+M12*N$3 -> 3635.2406 | O12: =+M12+N12 -> 12723.342 | P12: =H12/Q12-1 -> 0 | Q12: 45177.91 | AI12: 43026.581 | AJ12: =+(H12-AI12)/AI12 -> 0.05 | AN12: 100021643 | AO12: 25320.574
A13: 100021643 | B13: MEDALLON 42X112G DOBLE BURGER SWIFT | C13: 7790360966797 | D13: 4.704 | E13: 42 | F13: =+VLOOKUP(A13,$AN$3:$AO$109,2,FALSE) -> 25320.574 | H13: =+F13*(1-G13) -> 25320.574 | I13: =+H13/E13 -> 602.87081 | J13: =+I13*J$3 -> 126.60287 | K13: =+I13+J13 -> 729.47368 | L13: =+K13*L$3 -> 240.72632 | M13: =+K13+L13 -> 970.2 | N13: =+M13*N$3 -> 388.08 | O13: =+M13+N13 -> 1358.28 | P13: =H13/Q13-1 -> 0 | Q13: 25320.574 | AI13: 19573.728 | AJ13: =+(H13-AI13)/AI13 -> 0.2936 | AN13: 100516325 | AO13: 27224.602
A14: 100516325 | B14: MEDALLON DOBLE BURGER 2X2 | C14: 7790360967763 | D14: 4.704 | E14: 21 | F14: =+VLOOKUP(A14,$AN$3:$AO$109,2,FALSE) -> 27224.602 | H14: =+F14*(1-G14) -> 27224.602 | I14: =+H14/E14 -> 1296.4096 | J14: =+I14*J$3 -> 272.24602 | K14: =+I14+J14 -> 1568.6556 | L14: =+K14*L$3 -> 517.65635 | M14: =+K14+L14 -> 2086.312 | N14: =+M14*N$3 -> 834.52479 | O14: =+M14+N14 -> 2920.8368 | P14: =H14/Q14-1 -> 0 | Q14: 27224.602 | AI14: 25928.192 | AJ14: =+(H14-AI14)/AI14 -> 0.05 | AN14: 100021676 | AO14: 64129.004
A15: 100021676 | B15: HAMBURGUESA 30X250g CLASICA "XL" SWIFT | C15: 7790360967411 | D15: 7.5 | E15: 30 | F15: =+VLOOKUP(A15,$AN$3:$AO$109,2,FALSE) -> 64129.004 | H15: =+F15*(1-G15) -> 64129.004 | I15: =+H15/E15 -> 2137.6335 | J15: =+I15*J$3 -> 448.90303 | K15: =+I15+J15 -> 2586.5365 | L15: =+K15*L$3 -> 853.55704 | M15: =+K15+L15 -> 3440.0935 | N15: =+M15*N$3 -> 1376.0374 | O15: =+M15+N15 -> 4816.131 | P15: =H15/Q15-1 -> 0 | Q15: 64129.004 | AI15: 53108.906 | AJ15: =+(H15-AI15)/AI15 -> 0.2075 | AN15: 100516008 | AO15: 62722.098
A16: 100516008 | B16: HAMBURGUESA 24X2X120g CASERA SWIFT | C16: 7790360967701 | D16: 5.76 | E16: 24 | F16: =+VLOOKUP(A16,$AN$3:$AO$109,2,FALSE) -> 62722.098 | G16: 0.0909 | H16: =+F16*(1-G16) -> 57020.659 | I16: =+H16/E16 -> 2375.8608 | J16: =+I16*J$3 -> 498.93077 | K16: =+I16+J16 -> 2874.7916 | L16: =+K16*L$3 -> 948.68121 | M16: =+K16+L16 -> 3823.4728 | N16: =+M16*N$3 -> 1529.3891 | O16: =+M16+N16 -> 5352.8619 | P16: =H16/Q16-1 -> 0 | Q16: 57020.659 | S16: OFERTA Compra 10 FLOW + 1 de regalo | AI16: 56890.791 | AJ16: =+(H16-AI16)/AI16 -> 0.00228275 | AN16: 100520834 | AO16: 61418.235
A17: 100520834 | B17: HAMBURGUESA X-TREMA 36 x 185 grs | C17: 7790360980618 | D17: 6.66 | E17: 36 | F17: =+VLOOKUP(A17,$AN$3:$AO$109,2,FALSE) -> 61418.235 | H17: =+F17*(1-G17) -> 61418.235 | I17: =+H17/E17 -> 1706.0621 | J17: =+I17*J$3 -> 358.27304 | K17: =+I17+J17 -> 2064.3351 | L17: =+K17*L$3 -> 681.23059 | M17: =+K17+L17 -> 2745.5657 | N17: =+M17*N$3 -> 1098.2263 | O17: =+M17+N17 -> 3843.792 | P17: =H17/Q17-1 -> 0 | Q17: 61418.235 | AI17: 55708.15 | AJ17: =+(H17-AI17)/AI17 -> 0.1025 | AN17: 100021644 | AO17: 21516.282
A18: 100021680 | B18: HAMBURGUESAS 18X2X120g CLL BRA/ARG | C18: 7790360967688 | D18: 4.32 | E18: 18 | F18: =+VLOOKUP(A18,$AN$3:$AO$109,2,FALSE) -> #N/A | H18: =+F18*(1-G18) -> #N/A | I18: =+H18/E18 -> #N/A | J18: =+I18*J$3 -> #N/A | K18: =+I18+J18 -> #N/A | L18: =+K18*L$3 -> #N/A | M18: =+K18+L18 -> #N/A | N18: =+M18*N$3 -> #N/A | O18: =+M18+N18 -> #N/A | P18: =H18/Q18-1 -> #N/A | Q18: 48105.264 | AI18: 45814.537 | AJ18: =+(H18-AI18)/AI18 -> #N/A | AN18: 100021677 | AO18: 16253.297
A19: 100021644 | B19: MEDALLON 42X112G LA BLANCA | C19: 7790360008541 | D19: 4.704 | E19: 42 | F19: =+VLOOKUP(A19,$AN$3:$AO$109,2,FALSE) -> 21516.282 | G19: 0.1 | H19: =+F19*(1-G19) -> 19364.654 | I19: =+H19/E19 -> 461.06319 | J19: =+I19*J$3 -> 96.823269 | K19: =+I19+J19 -> 557.88646 | L19: =+K19*0.3 -> 167.36594 | M19: =+K19+L19 -> 725.25239 | N19: =+M19*0.35 -> 253.83834 | O19: =+M19+N19 -> 979.09073 | P19: =H19/Q19-1 -> -0.0010570825 | Q19: 19385.146 | S19: Dcto a px en factura para oferta $980 vs $1.100 Friar | AI19: 14418.309 | AJ19: =+(H19-AI19)/AI19 -> 0.34305999 | AN19: 100021638 | AO19: 49008.427
A20: 100021677 | B20: MEDALLON 12x4X69G LA BLANCA | C20: 7790360967404 | D20: 3.312 | E20: 12 | F20: =+VLOOKUP(A20,$AN$3:$AO$109,2,FALSE) -> 16253.297 | H20: =+F20*(1-G20) -> 16253.297 | I20: =+H20/E20 -> 1354.4415 | J20: =+I20*J$3 -> 284.4327 | K20: =+I20+J20 -> 1638.8742 | L20: =+K20*0.3 -> 491.66225 | M20: =+K20+L20 -> 2130.5364 | N20: =+M20*N$3 -> 852.21456 | O20: =+M20+N20 -> 2982.751 | P20: =H20/Q20-1 -> 0.05 | Q20: 15479.331 | AI20: 13777.776 | AJ20: =+(H20-AI20)/AI20 -> 0.179675 | AN20: 100021575 | AO20: 39802.191
A21: 100021638 | B21: MEDALLONES 60X80g "SWIFT BURGER" PARRILLERAS FAMILY | C21: 7790360026699 | D21: 4.8 | E21: 60 | F21: =+VLOOKUP(A21,$AN$3:$AO$109,2,FALSE) -> 49008.427 | H21: =+F21*(1-G21) -> 49008.427 | I21: =+H21/E21 -> 816.80712 | J21: =+I21*J$3 -> 171.5295 | K21: =+I21+J21 -> 988.33661 | L21: =+K21*L$3 -> 326.15108 | M21: =+K21+L21 -> 1314.4877 | N21: =+M21*N$3 -> 525.79508 | O21: =+M21+N21 -> 1840.2828 | P21: =H21/Q21-1 -> 0 | Q21: 49008.427 | AI21: 44452.088 | AJ21: =+(H21-AI21)/AI21 -> 0.1025 | AN21: 100021514 | AO21: 36576.95
A22: 100021575 | B22: MEDALLONES 60X69g "SWIFT BURGER"PARRILLERAS FAMILY | C22: 7790360007032 | D22: 4.14 | E22: 60 | F22: =+VLOOKUP(A22,$AN$3:$AO$109,2,FALSE) -> 39802.191 | H22: =+F22*(1-G22) -> 39802.191 | I22: =+H22/E22 -> 663.36986 | J22: =+I22*J$3 -> 139.30767 | K22: =+I22+J22 -> 802.67753 | L22: =+K22*L$3 -> 264.88358 | M22: =+K22+L22 -> 1067.5611 | N22: =+M22*N$3 -> 427.02444 | O22: =+M22+N22 -> 1494.5856 | P22: =H22/Q22-1 -> 0 | Q22: 39802.191 | Z22: 7732.76 | AI22: 36101.761 | AJ22: =+(H22-AI22)/AI22 -> 0.1025 | AN22: 100516208 | AO22: 41975.344
A23: 100021514 | B23: MEDALLON 60X69G CARNE VACUNA | C23: 7790360006943 | D23: 4.14 | E23: 60 | F23: =+VLOOKUP(A23,$AN$3:$AO$109,2,FALSE) -> 36576.95 | H23: =+F23*(1-G23) -> 36576.95 | I23: =+H23/E23 -> 609.61583 | J23: =+I23*J$3 -> 128.01932 | K23: =+I23+J23 -> 737.63515 | L23: =+K23*L$3 -> 243.4196 | M23: =+K23+L23 -> 981.05475 | N23: =+M23*N$3 -> 392.4219 | O23: =+M23+N23 -> 1373.4766 | P23: =H23/Q23-1 -> 0 | Q23: 36576.95 | Z23: =+Z22*8640 -> 66811046 | AI23: 33176.372 | AJ23: =+(H23-AI23)/AI23 -> 0.1025 | AN23: 100518346 | AO23: 57727.078
A24: 100516208 | B24: MEDALLON 60x80g PARRILLERO MC SWIFT | C24: 7790360968203 | D24: =60*0.08 -> 4.8 | E24: 60 | F24: =+VLOOKUP(A24,$AN$3:$AO$109,2,FALSE) -> 41975.344 | H24: =+F24*(1-G24) -> 41975.344 | I24: =+H24/E24 -> 699.58907 | J24: =+I24*J$3 -> 146.91371 | K24: =+I24+J24 -> 846.50278 | L24: =+K24*L$3 -> 279.34592 | M24: =+K24+L24 -> 1125.8487 | N24: =+M24*N$3 -> 450.33948 | O24: =+M24+N24 -> 1576.1882 | P24: =H24/Q24-1 -> 0 | Q24: 41975.344 | Z24: =+Z23/2 -> 33405523 | AI24: 38072.875 | AJ24: =+(H24-AI24)/AI24 -> 0.1025 | AN24: 100516259 | AO24: 135947.63
A25: 100518346 | B25: MEDALLON 60X109G CARNE VACUNA PARRILLERO SWIFT | C25: 7790360975478 | D25: =60*0.109 -> 6.54 | E25: 60 | F25: =+VLOOKUP(A25,$AN$3:$AO$109,2,FALSE) -> 57727.078 | H25: =+F25*(1-G25) -> 57727.078 | I25: =+H25/E25 -> 962.11796 | J25: =I25*J3 -> 202.04477 | K25: =J25+I25 -> 1164.1627 | L25: =K25*L3 -> 384.1737 | M25: =L25+K25 -> 1548.3364 | N25: =M25*N3 -> 619.33457 | O25: =N25+M25 -> 2167.671 | P25: =H25/Q25-1 -> 0 | Q25: 57727.078 | AI25: 52360.161 | AJ25: =+(H25-AI25)/AI25 -> 0.1025 | AN25: 100518095 | AO25: 64509.932
A26: 100516259 | B26: MEDALLON GIGANTE 48x113.5g | C26: 7790360968340 | D26: 18.16 | E26: 48 | F26: =+VLOOKUP(A26,$AN$3:$AO$109,2,FALSE) -> 135947.63 | H26: =+F26*(1-G26) -> 135947.63 | I26: =+H26/E26 -> 2832.2423 | J26: =+I26*J$3 -> 594.77089 | K26: =+I26+J26 -> 3427.0132 | L26: =+K26*L$3 -> 1130.9144 | M26: =+K26+L26 -> 4557.9276 | N26: =+M26*N$3 -> 1823.171 | O26: =+M26+N26 -> 6381.0986 | P26: =H26/Q26-1 -> 0 | Q26: 135947.63 | AI26: 123308.51 | AJ26: =+(H26-AI26)/AI26 -> 0.1025 | AN26: 100518223 | AO26: 50224.567
A27: 100518095 | B27: HAMBURGUESA 36 X 185 GRS | C27: 7790360974785 | D27: 6.66 | E27: 36 | F27: =+VLOOKUP(A27,$AN$3:$AO$109,2,FALSE) -> 64509.932 | H27: =+F27*(1-G27) -> 64509.932 | I27: =+H27/E27 -> 1791.9426 | J27: =+I27*J$3 -> 376.30794 | K27: =+I27+J27 -> 2168.2505 | L27: =+K27*L$3 -> 715.52266 | M27: =+K27+L27 -> 2883.7732 | N27: =+M27*N$3 -> 1153.5093 | O27: =+M27+N27 -> 4037.2824 | P27: =H27/Q27-1 -> 0 | Q27: 64509.932 | AI27: 58512.41 | AJ27: =+(H27-AI27)/AI27 -> 0.1025
A28: 100518223 | B28: HAMBURGUESA 30x2x106 GRS | C28: 7790360975065 | D28: =60*0.106 -> 6.36 | E28: 30 | F28: =+VLOOKUP(A28,$AN$3:$AO$109,2,FALSE) -> 50224.567 | H28: =+F28*(1-G28) -> 50224.567 | I28: =+H28/E28 -> 1674.1522 | J28: =+I28*J$3 -> 351.57197 | K28: =+I28+J28 -> 2025.7242 | L28: =+K28*L$3 -> 668.48899 | M28: =+K28+L28 -> 2694.2132 | N28: =+M28*N$3 -> 1077.6853 | O28: =+M28+N28 -> 3771.8985 | P28: =H28/Q28-1 -> 0 | Q28: 50224.567 | AI28: 45555.163 | AJ28: =+(H28-AI28)/AI28 -> 0.1025 | AN28: 100522204 | AO28: 26630.922
F29: =+VLOOKUP(A29,$AN$3:$AO$109,2,FALSE) -> #N/A | H29: =+F29*(1-G29) -> #N/A | I29: =+H29/E29 -> #N/A | P29: =H29/Q29-1 -> #N/A | Q29: #N/A | Y29: SEPT | Z29: SEPT | AB29: PATY VIENA | AC29: VIENISSIMA | AD29: PALADINI | AE29: FRIAR | AI29: #N/A | AJ29: =+(H29-AI29)/AI29 -> #N/A | AN29: 100522205 | AO29: 25299.376
A30: 100022085 | B30: SALCHICHAS 24X6 SWIFT | C30: 7790360000132 | D30: 5.4 | E30: 24 | F30: =+VLOOKUP(A30,$AN$3:$AO$109,2,FALSE) -> #N/A | G30: 0.16666667 | H30: =+F30*(1-G30) -> #N/A | I30: =+H30/E30 -> #N/A | J30: =+I30*J$3 -> #N/A | K30: =+I30+J30 -> #N/A | L30: =+K30*0.3 -> #N/A | M30: =+K30+L30 -> #N/A | N30: =+M30*N$3 -> #N/A | O30: =+M30+N30 -> #N/A | P30: =H30/Q30-1 -> #N/A | Q30: 24411.679 | S30: compra 10 estuches + 2 de regalo ----> OFERTA $2.050 público | Y30: 1850 | Z30: =+Y30 -> 1850 | AB30: 2295 | AC30: 2518 | AD30: 2518 | AE30: 1328 | AI30: 19706.882 | AJ30: =+(H30-AI30)/AI30 -> #N/A | AN30: 100516849 | AO30: 20506.556
A31: 100522204 | B31: SALCHICHAS 24X6 SWIFT | C31: 7790360983947 | D31: 5.4 | E31: 24 | F31: =+VLOOKUP(A31,$AN$3:$AO$109,2,FALSE) -> 26630.922 | G31: 0.16666667 | H31: =+F31*(1-G31) -> 22192.435 | I31: =+H31/E31 -> 924.68479 | J31: =+I31*J$3 -> 194.18381 | K31: =+I31+J31 -> 1118.8686 | L31: =+K31*0.309 -> 345.7304 | M31: =+K31+L31 -> 1464.599 | N31: =+M31*N$3 -> 585.8396 | O31: =+M31+N31 -> 2050.4386 | P31: =H31/Q31-1 -> -0.090909091 | Q31: 24411.679 | S31: Oferta: compra 10 estuches + 2 de regalo ----> OFERTA $2.050 público | AN31: 100522206 | AO31: 60366.789
A32: 100022072 | B32: SALCHICHAS 12X12 SWIFT | C32: 7790360024541 | D32: 5.4 | E32: 12 | F32: =+VLOOKUP(A32,$AN$3:$AO$109,2,FALSE) -> #N/A | G32: 0.16666667 | H32: =+F32*(1-G32) -> #N/A | I32: =+H32/E32 -> #N/A | J32: =+I32*J$3 -> #N/A | K32: =+I32+J32 -> #N/A | L32: =+K32*0.328678 -> #N/A | M32: =+K32+L32 -> #N/A | N32: =+M32*N$3 -> #N/A | O32: =+M32+N32 -> #N/A | P32: =H32/Q32-1 -> #N/A | Q32: 23191.095 | S32: Conveniencia vs 22085: Oferta $3.899 | Y32: 3400 | Z32: =+Y32 -> 3400 | AB32: 4590 | AC32: 5045 | AI32: 18109.027 | AJ32: =+(H32-AI32)/AI32 -> #N/A | AN32: 100022058 | AO32: 15595.314
A33: 100522205 | B33: SALCHICHAS 12X12 SWIFT | C33: 7790360983954 | D33: 5.4 | E33: 12 | F33: =+VLOOKUP(A33,$AN$3:$AO$109,2,FALSE) -> 25299.376 | G33: 0.16666667 | H33: =+F33*(1-G33) -> 21082.813 | I33: =+H33/E33 -> 1756.9011 | J33: =+I33*J$3 -> 368.94923 | K33: =+I33+J33 -> 2125.8503 | L33: =+K33*0.31 -> 659.01361 | M33: =+K33+L33 -> 2784.8639 | N33: =+M33*N$3 -> 1113.9456 | O33: =+M33+N33 -> 3898.8095 | P33: =H33/Q33-1 -> -0.090909091 | Q33: 23191.095 | S33: Conveniencia vs 22085: Oferta $3.899 | AN33: 100518151 | AO33: 69421.808
A34: 100516849 | B34: SALCHICHAS SIN PIEL 24X6 "SWIFT KIDS" X 190 g | C34: 7790360970053 | D34: 4.56 | E34: 24 | F34: =+VLOOKUP(A34,$AN$3:$AO$109,2,FALSE) -> 20506.556 | H34: =+F34*(1-G34) -> 20506.556 | I34: =+H34/E34 -> 854.43982 | J34: =+I34*J$3 -> 179.43236 | K34: =+I34+J34 -> 1033.8722 | L34: =+K34*0.306 -> 316.36489 | M34: =+K34+L34 -> 1350.2371 | N34: =+M34*N$3 -> 540.09483 | O34: =+M34+N34 -> 1890.3319 | P34: =H34/Q34-1 -> 0 | Q34: 20506.556 | S34: Oferta incluida en lista: $1.890 | Y34: 1600 | Z34: 1650 | AA34: PATY FUN | AB34: 1745 | AI34: 17043.79 | AJ34: =+(H34-AI34)/AI34 -> 0.20316875
A35: 100022039 | B35: SALCHICHAS LARGAS 10 x 12 SWIFT INSTITUCIONAL | C35: 7790360007063 | D35: 8.7 | E35: 10 | F35: =+VLOOKUP(A35,$AN$3:$AO$109,2,FALSE) -> #N/A | H35: =+F35*(1-G35) -> #N/A | I35: =+H35/E35 -> #N/A | J35: =+I35*J$3 -> #N/A | K35: =+I35+J35 -> #N/A | L35: =+K35*L$3 -> #N/A | M35: =+K35+L35 -> #N/A | N35: =+M35*N$3 -> #N/A | O35: =+M35+N35 -> #N/A | P35: =H35/Q35-1 -> #N/A | Q35: 60366.789 | AB35: ICB | AC35: 66 | AD35: PANCHIN | AE35: NUTRITE | AI35: 46618.161 | AJ35: =+(H35-AI35)/AI35 -> #N/A | AN35: 100021000 | AO35: 12962.274
A36: 100522206 | B36: SALCHICHAS LARGAS 10 x 12 SWIFT INSTITUCIONAL | C36: 7790360983961 | D36: 8.7 | E36: 10 | F36: =+VLOOKUP(A36,$AN$3:$AO$109,2,FALSE) -> 60366.789 | H36: =+F36*(1-G36) -> 60366.789 | I36: =+H36/E36 -> 6036.6789 | J36: =+I36*J$3 -> 1267.7026 | K36: =+I36+J36 -> 7304.3815 | L36: =+K36*L$3 -> 2410.4459 | M36: =+K36+L36 -> 9714.8274 | N36: =+M36*N$3 -> 3885.931 | O36: =+M36+N36 -> 13600.758 | Q36: 60366.789 | AN36: 100021001 | AO36: 12962.274
A37: 100022058 | B37: SALCHICHAS SIN PIEL "LA BLANCA" 24X6X190 Grs; | C37: 7790360026002 | D37: 4.56 | E37: 24 | F37: =+VLOOKUP(A37,$AN$3:$AO$109,2,FALSE) -> 15595.314 | H37: =+F37*(1-G37) -> 15595.314 | I37: =+H37/E37 -> 649.80474 | J37: =+I37*J$3 -> 136.459 | K37: =+I37+J37 -> 786.26374 | L37: =+K37*0.3 -> 235.87912 | M37: =+K37+L37 -> 1022.1429 | N37: =+M37*N$3 -> 408.85714 | O37: =+M37+N37 -> 1431 | P37: =H37/Q37-1 -> 0.06 | Q37: 14712.56 | Y37: 1090 | Z37: 1090 | AA37: MANTENEMOS PX | AB37: 1044 | AC37: 887 | AD37: 1069 | AE37: 988 | AI37: 11611.082 | AJ37: =+(H37-AI37)/AI37 -> 0.34314044 | AN37: 100522277 | AO37: 12962.274
A38: 100518151 | B38: SALCHICHAS LARGAS 10 x 12 x 870g | C38: 7790360974990 | D38: 8.7 | E38: 10 | F38: =+VLOOKUP(A38,$AN$3:$AO$109,2,FALSE) -> 69421.808 | H38: =+F38*(1-G38) -> 69421.808 | I38: =+H38/E38 -> 6942.1808 | J38: =+I38*J$3 -> 1457.858 | K38: =+I38+J38 -> 8400.0387 | L38: =+K38*0.3 -> 2520.0116 | M38: =+K38+L38 -> 10920.05 | N38: =+M38*N$3 -> 4368.0201 | O38: =+M38+N38 -> 15288.071 | P38: =H38/Q38-1 -> 0 | Q38: 69421.808 | Z38: =+Z37*24 -> 26160 | AI38: 53610.885 | AJ38: =+(H38-AI38)/AI38 -> 0.29492 | AN38: 100522333 | AO38: 12962.274
F39: =+VLOOKUP(A39,$AN$3:$AO$109,2,FALSE) -> #N/A | H39: =+F39*(1-G39) -> #N/A | I39: =+H39/E39 -> #N/A | J39: 0.21 | L39: 0.22 | N39: 0.35 | P39: =H39/Q39-1 -> #N/A | Q39: #N/A | Z39: =+Z38/1.21/1.33/1.4 -> 11611.082 | AA39: =+Z32*12 -> 40800 | AI39: #N/A | AJ39: =+(H39-AI39)/AI39 -> #N/A | AN39: 100021045 | AO39: 12962.274
A40: 100021000 | B40: PATE DE FOIE 24X90G SWIFT | C40: 7790360720382 | D40: 2.16 | E40: 24 | F40: =+VLOOKUP(A40,$AN$3:$AO$109,2,FALSE) -> 12962.274 | H40: =+F40*(1-G40) -> 12962.274 | I40: =+H40/E40 -> 540.09474 | J40: =+I40*J$3 -> 113.41989 | K40: =+I40+J40 -> 653.51463 | L40: =+K40*L$39 -> 143.77322 | M40: =+K40+L40 -> 797.28785 | N40: =+M40*N$39 -> 279.05075 | O40: =+M40+N40 -> 1076.3386 | P40: =H40/Q40-1 -> 0.05 | Q40: 12345.023 | Z40: =+F37-Z39 -> 3984.2318 | AA40: =+AA39/1.21/1.33/1.4 -> 18109.027 | AI40: 10353.088 | AJ40: =+(H40-AI40)/AI40 -> 0.25202 | AN40: 100021004 | AO40: 12962.274
A41: 100021001 | B41: PICADILLO DE CARNE 24X90G SWIFT | C41: 7790360720115 | D41: 2.16 | E41: 24 | F41: =+VLOOKUP(A41,$AN$3:$AO$109,2,FALSE) -> 12962.274 | H41: =+F41*(1-G41) -> 12962.274 | I41: =+H41/E41 -> 540.09474 | J41: =+I41*J$3 -> 113.41989 | K41: =+I41+J41 -> 653.51463 | L41: =+K41*L$39 -> 143.77322 | M41: =+K41+L41 -> 797.28785 | N41: =+M41*N$39 -> 279.05075 | O41: =+M41+N41 -> 1076.3386 | P41: =H41/Q41-1 -> 0.05 | Q41: 12345.023 | Z41: =+Z40/F37 -> 0.25547622 | AA41: =+F32-AA40 -> #N/A | AI41: 10353.088 | AJ41: =+(H41-AI41)/AI41 -> 0.25202 | AN41: 100021006 | AO41: 12962.274
A42: 100522277 | B42: Picadillo de Carne Picante Chile Chipotle 24x90 g | D42: 2.16 | E42: 24 | F42: =+VLOOKUP(A42,$AN$3:$AO$109,2,FALSE) -> 12962.274 | H42: =+F42*(1-G42) -> 12962.274 | I42: =+H42/E42 -> 540.09474 | J42: =+I42*J$3 -> 113.41989 | K42: =+I42+J42 -> 653.51463 | L42: =+K42*L$39 -> 143.77322 | M42: =+K42+L42 -> 797.28785 | N42: =+M42*N$39 -> 279.05075 | O42: =+M42+N42 -> 1076.3386 | P42: =H42/Q42-1 -> 0.05 | Q42: 12345.023 | AN42: 100021007 | AO42: 15499.255
A43: 100522333 | B43: Pate de Foie Jalapeño 24x90 Swift | D43: 2.16 | E43: 24 | F43: =+VLOOKUP(A43,$AN$3:$AO$109,2,FALSE) -> 12962.274 | H43: =+F43*(1-G43) -> 12962.274 | I43: =+H43/E43 -> 540.09474 | J43: =+I43*J$3 -> 113.41989 | K43: =+I43+J43 -> 653.51463 | L43: =+K43*L$39 -> 143.77322 | M43: =+K43+L43 -> 797.28785 | N43: =+M43*N$39 -> 279.05075 | O43: =+M43+N43 -> 1076.3386 | P43: =H43/Q43-1 -> 0.05 | Q43: 12345.023 | AN43: 100021013 | AO43: 15499.255
A44: 100021045 | B44: PICADILLO DE CARNE PICANTE 24X90G SWIFT | C44: 7790360966582 | D44: 2.16 | E44: 24 | F44: =+VLOOKUP(A44,$AN$3:$AO$109,2,FALSE) -> 12962.274 | H44: =+F44*(1-G44) -> 12962.274 | I44: =+H44/E44 -> 540.09474 | J44: =+I44*J$3 -> 113.41989 | K44: =+I44+J44 -> 653.51463 | L44: =+K44*L$39 -> 143.77322 | M44: =+K44+L44 -> 797.28785 | N44: =+M44*N$39 -> 279.05075 | O44: =+M44+N44 -> 1076.3386 | P44: =H44/Q44-1 -> 0.05 | Q44: 12345.023 | AA44: =+AA41/F32 -> #N/A | AI44: 10088.4 | AJ44: =+(H44-AI44)/AI44 -> 0.28486913 | AN44: 100021014 | AO44: 15499.255
A45: 100021004 | B45: PATE DE FOIE A LA CREMA 24X88G SWIFT | C45: 7790360964526 | D45: 2.112 | E45: 24 | F45: =+VLOOKUP(A45,$AN$3:$AO$109,2,FALSE) -> 12962.274 | H45: =+F45*(1-G45) -> 12962.274 | I45: =+H45/E45 -> 540.09474 | J45: =+I45*J$3 -> 113.41989 | K45: =+I45+J45 -> 653.51463 | L45: =+K45*L$39 -> 143.77322 | M45: =+K45+L45 -> 797.28785 | N45: =+M45*N$39 -> 279.05075 | O45: =+M45+N45 -> 1076.3386 | P45: =H45/Q45-1 -> 0.05 | Q45: 12345.023 | AI45: 10088.4 | AJ45: =+(H45-AI45)/AI45 -> 0.28486913 | AN45: 100021054 | AO45: 15499.255
A46: 100021006 | B46: JAMON DEL DIABLO 24X88G SWIFT | C46: 7790360964557 | D46: 2.112 | E46: 24 | F46: =+VLOOKUP(A46,$AN$3:$AO$109,2,FALSE) -> 12962.274 | H46: =+F46*(1-G46) -> 12962.274 | I46: =+H46/E46 -> 540.09474 | J46: =+I46*J$3 -> 113.41989 | K46: =+I46+J46 -> 653.51463 | L46: =+K46*L$39 -> 143.77322 | M46: =+K46+L46 -> 797.28785 | N46: =+M46*N$39 -> 279.05075 | O46: =+M46+N46 -> 1076.3386 | P46: =H46/Q46-1 -> 0.05 | Q46: 12345.023 | AI46: 10088.4 | AJ46: =+(H46-AI46)/AI46 -> 0.28486913 | AN46: 100021055 | AO46: 15499.255
A47: 100021007 | B47: PATE DE FOIE DE POLLO 24X85G SWIFT | C47: 7790360964540 | D47: 2.04 | E47: 24 | F47: =+VLOOKUP(A47,$AN$3:$AO$109,2,FALSE) -> 15499.255 | H47: =+F47*(1-G47) -> 15499.255 | I47: =+H47/E47 -> 645.80229 | J47: =+I47*J$3 -> 135.61848 | K47: =+I47+J47 -> 781.42077 | L47: =+K47*L$39 -> 171.91257 | M47: =+K47+L47 -> 953.33333 | N47: =+M47*N$39 -> 333.66667 | O47: =+M47+N47 -> 1287 | P47: =H47/Q47-1 -> 0.099827334 | Q47: 14092.444 | AI47: 11917.5 | AJ47: =+(H47-AI47)/AI47 -> 0.30054582 | AN47: 100021015 | AO47: 15499.255
A48: 100021013 | B48: PATE DE FOIE TIPO PROVENZAL 24X85G SWIFT GOURMET | C48: 7790360965714 | D48: 2.04 | E48: 24 | F48: =+VLOOKUP(A48,$AN$3:$AO$109,2,FALSE) -> 15499.255 | H48: =+F48*(1-G48) -> 15499.255 | I48: =+H48/E48 -> 645.80229 | J48: =+I48*J$3 -> 135.61848 | K48: =+I48+J48 -> 781.42077 | L48: =+K48*L$39 -> 171.91257 | M48: =+K48+L48 -> 953.33333 | N48: =+M48*N$39 -> 333.66667 | O48: =+M48+N48 -> 1287 | P48: =H48/Q48-1 -> 0.099827334 | Q48: 14092.444 | Z48: 7200 | AI48: 11917.5 | AJ48: =+(H48-AI48)/AI48 -> 0.30054582 | AN48: 100021008 | AO48: 10971.007
A49: 100021014 | B49: PATE DE FOIE C/PIMIENTA VERDE 24X85G SWIFT GOURMET | C49: 7790360965721 | D49: 2.04 | E49: 24 | F49: =+VLOOKUP(A49,$AN$3:$AO$109,2,FALSE) -> 15499.255 | H49: =+F49*(1-G49) -> 15499.255 | I49: =+H49/E49 -> 645.80229 | J49: =+I49*J$3 -> 135.61848 | K49: =+I49+J49 -> 781.42077 | L49: =+K49*L$39 -> 171.91257 | M49: =+K49+L49 -> 953.33333 | N49: =+M49*N$39 -> 333.66667 | O49: =+M49+N49 -> 1287 | P49: =H49/Q49-1 -> 0.099827334 | Q49: 14092.444 | Z49: =+Z48*0.97 -> 6984 | AI49: 11917.5 | AJ49: =+(H49-AI49)/AI49 -> 0.30054582 | AN49: 100021009 | AO49: 10971.007
A50: 100021054 | B50: PATE JAMON AHUMADO 24X85G | C50: 7790360965707 | D50: 2.04 | E50: 24 | F50: =+VLOOKUP(A50,$AN$3:$AO$109,2,FALSE) -> 15499.255 | H50: =+F50*(1-G50) -> 15499.255 | I50: =+H50/E50 -> 645.80229 | J50: =+I50*J$3 -> 135.61848 | K50: =+I50+J50 -> 781.42077 | L50: =+K50*L$39 -> 171.91257 | M50: =+K50+L50 -> 953.33333 | N50: =+M50*N$39 -> 333.66667 | O50: =+M50+N50 -> 1287 | P50: =H50/Q50-1 -> 0.099827334 | Q50: 14092.444 | AI50: 11917.5 | AJ50: =+(H50-AI50)/AI50 -> 0.30054582 | AN50: 100021010 | AO50: 10971.007
A51: 100021055 | B51: PATE HONGOS 24X85G | C51: 7790360965189 | D51: 2.04 | E51: 24 | F51: =+VLOOKUP(A51,$AN$3:$AO$109,2,FALSE) -> 15499.255 | H51: =+F51*(1-G51) -> 15499.255 | I51: =+H51/E51 -> 645.80229 | J51: =+I51*J$3 -> 135.61848 | K51: =+I51+J51 -> 781.42077 | L51: =+K51*L$39 -> 171.91257 | M51: =+K51+L51 -> 953.33333 | N51: =+M51*N$39 -> 333.66667 | O51: =+M51+N51 -> 1287 | P51: =H51/Q51-1 -> 0.099827334 | Q51: 14092.444 | AI51: 11917.5 | AJ51: =+(H51-AI51)/AI51 -> 0.30054582 | AN51: 100021011 | AO51: 10971.007
A52: 100021015 | B52: PATE DE SALMON 24X85G SWIFT GOURMET | C52: 7790360965202 | D52: 2.04 | E52: 24 | F52: =+VLOOKUP(A52,$AN$3:$AO$109,2,FALSE) -> 15499.255 | H52: =+F52*(1-G52) -> 15499.255 | I52: =+H52/E52 -> 645.80229 | J52: =+I52*J$3 -> 135.61848 | K52: =+I52+J52 -> 781.42077 | L52: =+K52*L$39 -> 171.91257 | M52: =+K52+L52 -> 953.33333 | N52: =+M52*N$39 -> 333.66667 | O52: =+M52+N52 -> 1287 | P52: =H52/Q52-1 -> 0.099827334 | Q52: 14092.444 | AI52: 11917.5 | AJ52: =+(H52-AI52)/AI52 -> 0.30054582
A53: 100021008 | B53: PICADILLO DE CARNE 24X90G LA BLANCA | C53: 7790360720122 | D53: 2.16 | E53: 24 | F53: =+VLOOKUP(A53,$AN$3:$AO$109,2,FALSE) -> 10971.007 | H53: =+F53*(1-G53) -> 10971.007 | I53: =+H53/E53 -> 457.12529 | J53: =+I53*J$3 -> 95.996311 | K53: =+I53+J53 -> 553.1216 | L53: =+K53*0.2 -> 110.62432 | M53: =+K53+L53 -> 663.74592 | N53: =+M53*N$39 -> 232.31107 | O53: =+M53+N53 -> 896.05699 | P53: =H53/Q53-1 -> 0.05 | Q53: 10448.578 | Z53: 537 | AA53: changuito | AI53: 9046.3879 | AJ53: =+(H53-AI53)/AI53 -> 0.21275 | AN53: 100516217 | AO53: 26348.055
A54: 100021009 | B54: PATE DE FOIE 24X90G LA BLANCA | C54: 7790360965127 | D54: 2.16 | E54: 24 | F54: =+VLOOKUP(A54,$AN$3:$AO$109,2,FALSE) -> 10971.007 | H54: =+F54*(1-G54) -> 10971.007 | I54: =+H54/E54 -> 457.12529 | J54: =+I54*J$3 -> 95.996311 | K54: =+I54+J54 -> 553.1216 | L54: =+K54*0.2 -> 110.62432 | M54: =+K54+L54 -> 663.74592 | N54: =+M54*N$39 -> 232.31107 | O54: =+M54+N54 -> 896.05699 | P54: =H54/Q54-1 -> 0.05 | Q54: 10448.578 | Z54: 567 | AA54: la negra | AI54: 9046.3879 | AJ54: =+(H54-AI54)/AI54 -> 0.21275 | AN54: 100516214 | AO54: 35163.986
A55: 100021010 | B55: PICADILLO DE CARNE 24X90G SAFRA | C55: 7790920008707 | D55: 2.16 | E55: 24 | F55: =+VLOOKUP(A55,$AN$3:$AO$109,2,FALSE) -> 10971.007 | H55: =+F55*(1-G55) -> 10971.007 | I55: =+H55/E55 -> 457.12529 | J55: =+I55*J$3 -> 95.996311 | K55: =+I55+J55 -> 553.1216 | L55: =+K55*0.2 -> 110.62432 | M55: =+K55+L55 -> 663.74592 | N55: =+M55*N$39 -> 232.31107 | O55: =+M55+N55 -> 896.05699 | P55: =H55/Q55-1 -> 0.05 | Q55: 10448.578 | AI55: 9046.3879 | AJ55: =+(H55-AI55)/AI55 -> 0.21275 | AN55: 100516215 | AO55: 35163.986
A56: 100021011 | B56: PATE DE FOIE 24X90G SAFRA | C56: 7790920008714 | D56: 2.16 | E56: 24 | F56: =+VLOOKUP(A56,$AN$3:$AO$109,2,FALSE) -> 10971.007 | H56: =+F56*(1-G56) -> 10971.007 | I56: =+H56/E56 -> 457.12529 | J56: =+I56*J$3 -> 95.996311 | K56: =+I56+J56 -> 553.1216 | L56: =+K56*0.2 -> 110.62432 | M56: =+K56+L56 -> 663.74592 | N56: =+M56*N$39 -> 232.31107 | O56: =+M56+N56 -> 896.05699 | P56: =H56/Q56-1 -> 0.05 | Q56: 10448.578 | AI56: 9046.3879 | AJ56: =+(H56-AI56)/AI56 -> 0.21275 | AN56: 100516216 | AO56: 35163.986
F57: =+VLOOKUP(A57,$AN$3:$AO$109,2,FALSE) -> #N/A | H57: =+F57*(1-G57) -> #N/A | I57: =+H57/E57 -> #N/A | P57: =H57/Q57-1 -> #N/A | Q57: #N/A | AI57: #N/A | AJ57: =+(H57-AI57)/AI57 -> #N/A
A58: 100516217 | B58: MILANESAS DE SOJA CLASICAS PREFRITA | C58: 7790360967824 | D58: 5.8 | E58: 20 | F58: =+VLOOKUP(A58,$AN$3:$AO$109,2,FALSE) -> 26348.055 | H58: =+F58*(1-G58) -> 26348.055 | I58: =+H58/E58 -> 1317.4027 | J58: =+I58*J$3 -> 276.65458 | K58: =+I58+J58 -> 1594.0573 | L58: =+K58*0.3 -> 478.2172 | M58: =+K58+L58 -> 2072.2745 | N58: =+M58*N$3 -> 828.90981 | O58: =+M58+N58 -> 2901.1843 | P58: =H58/Q58-1 -> 0.03 | Q58: 25580.636 | S58: Oferta neteada en lista $2.900 | AA58: Obs | AB58: SKU | AC58: Px | AD58: Dcto | AE58: Px oferta | AF58: Px público | AG58: Volumen | AI58: 22964.003 | AJ58: =+(H58-AI58)/AI58 -> 0.14736335 | AN58: 100021704 | AO58: 32852.088
A59: 100516214 | B59: MILANESAS DE SOJA RELLENAS CON JAMON Y QUESO | C59: 7790360967794 | D59: 7 | E59: 20 | F59: =+VLOOKUP(A59,$AN$3:$AO$109,2,FALSE) -> 35163.986 | H59: =+F59*(1-G59) -> 35163.986 | I59: =+H59/E59 -> 1758.1993 | J59: =+I59*J$3 -> 369.22185 | K59: =+I59+J59 -> 2127.4212 | L59: =+K59*0.309 -> 657.37314 | M59: =+K59+L59 -> 2784.7943 | N59: =+M59*N$3 -> 1113.9177 | O59: =+M59+N59 -> 3898.712 | P59: =H59/Q59-1 -> 0 | Q59: 35163.986 | S59: Oferta neteada en lista $3.900 | AA59: Dcto a precio en factura | AB59: 21725 | AC59: =+F69 -> 28863.527 | AD59: =+(AC59-AE59)/AC59 -> 0.41795055 | AE59: 16800 | AF59: Para competir con Grangys | AG59: 4 pallets | AI59: 31567.076 | AJ59: =+(H59-AI59)/AI59 -> 0.113945 | AN59: 100021705 | AO59: 29873.001
A60: 100516215 | B60: MILANESAS DE SOJA RELLENAS CON ESPINACA Y QUESO | C60: 7790360967800 | D60: 7 | E60: 20 | F60: =+VLOOKUP(A60,$AN$3:$AO$109,2,FALSE) -> 35163.986 | H60: =+F60*(1-G60) -> 35163.986 | I60: =+H60/E60 -> 1758.1993 | J60: =+I60*J$3 -> 369.22185 | K60: =+I60+J60 -> 2127.4212 | L60: =+K60*0.309 -> 657.37314 | M60: =+K60+L60 -> 2784.7943 | N60: =+M60*N$3 -> 1113.9177 | O60: =+M60+N60 -> 3898.712 | P60: =H60/Q60-1 -> 0 | Q60: 35163.986 | S60: Oferta neteada en lista $3.900 | AA60: Dcto a precio en factura | AB60: 100517679 | AC60: 34124.322 | AD60: =+(AC60-AE60)/AC60 -> 0.36983364 | AE60: 21504 | AF60: Para competir con Grangys | AG60: 2 pallets | AI60: 31567.076 | AJ60: =+(H60-AI60)/AI60 -> 0.113945 | AN60: 100021709 | AO60: 56553.219
A61: 100516216 | B61: MILANESAS DE SOJA RELLENAS CON TOMATE Y QUESO | C61: 7790360967817 | D61: 7 | E61: 20 | F61: =+VLOOKUP(A61,$AN$3:$AO$109,2,FALSE) -> 35163.986 | H61: =+F61*(1-G61) -> 35163.986 | I61: =+H61/E61 -> 1758.1993 | J61: =+I61*J$3 -> 369.22185 | K61: =+I61+J61 -> 2127.4212 | L61: =+K61*0.309 -> 657.37314 | M61: =+K61+L61 -> 2784.7943 | N61: =+M61*N$3 -> 1113.9177 | O61: =+M61+N61 -> 3898.712 | P61: =H61/Q61-1 -> 0 | Q61: 35163.986 | S61: Oferta neteada en lista $3.900 | AA61: Dcto via NC | AB61: 21644 | AC61: 14418.309 | AD61: 0.03031 | AE61: 13981.29 | AF61: 750 | AG61: 4 pallets | AI61: 31567.076 | AJ61: =+(H61-AI61)/AI61 -> 0.113945 | AN61: 100521357 | AO61: 44177.826
F62: =+VLOOKUP(A62,$AN$3:$AO$109,2,FALSE) -> #N/A | H62: =+F62*(1-G62) -> #N/A | I62: =+H62/E62 -> #N/A | P62: =H62/Q62-1 -> #N/A | Q62: #N/A | AA62: Dcto via NC | AB62: 21643 | AC62: 19573.728 | AD62: 0.07436 | AE62: 18118.225 | AF62: 950 | AG62: 50 cajas | AI62: #N/A | AJ62: =+(H62-AI62)/AI62 -> #N/A | AN62: 100521358 | AO62: 66266.739
A63: 100021704 | B63: BOCADITOS DE CARNE "SWIFT" - 12x380g | C63: 7790360023902 | D63: =12*0.38 -> 4.56 | E63: 12 | F63: =+VLOOKUP(A63,$AN$3:$AO$109,2,FALSE) -> 32852.088 | H63: =+F63*(1-G63) -> 32852.088 | I63: =+H63/E63 -> 2737.674 | J63: =+I63*J$3 -> 574.91153 | K63: =+I63+J63 -> 3312.5855 | L63: =+K63*L$3 -> 1093.1532 | M63: =+K63+L63 -> 4405.7387 | N63: =+M63*N$3 -> 1762.2955 | O63: =+M63+N63 -> 6168.0342 | P63: =H63/Q63-1 -> 0 | Q63: 32852.088 | AI63: 31287.702 | AJ63: =+(H63-AI63)/AI63 -> 0.05 | AN63: 100522130 | AO63: 36420.087
A64: 100021705 | B64: BOCADITOS DE POLLO "SWIFT" - 12x380g | C64: 7790360024336 | D64: =12*0.38 -> 4.56 | E64: 12 | F64: =+VLOOKUP(A64,$AN$3:$AO$109,2,FALSE) -> 29873.001 | H64: =+F64*(1-G64) -> 29873.001 | I64: =+H64/E64 -> 2489.4168 | J64: =+I64*J$3 -> 522.77752 | K64: =+I64+J64 -> 3012.1943 | L64: =+K64*L$3 -> 994.02412 | M64: =+K64+L64 -> 4006.2184 | N64: =+M64*N$3 -> 1602.4874 | O64: =+M64+N64 -> 5608.7058 | P64: =H64/Q64-1 -> #N/A | Q64: #N/A | AI64: 28450.477 | AJ64: =+(H64-AI64)/AI64 -> 0.05 | AN64: 100021725 | AO64: 28863.527
A65: 100021709 | B65: BOCADITOS DE POLLO "SWIFT" - 10x760g | C65: 7790360024701 | D65: 7.6 | E65: 10 | F65: =+VLOOKUP(A65,$AN$3:$AO$109,2,FALSE) -> 56553.219 | H65: =+F65*(1-G65) -> 56553.219 | I65: =+H65/E65 -> 5655.3219 | J65: =+I65*J$3 -> 1187.6176 | K65: =+I65+J65 -> 6842.9395 | L65: =+K65*L$3 -> 2258.17 | M65: =+K65+L65 -> 9101.1095 | N65: =+M65*N$3 -> 3640.4438 | O65: =+M65+N65 -> 12741.553 | P65: =H65/Q65-1 -> 0 | Q65: 56553.219 | AI65: 44881.712 | AJ65: =+(H65-AI65)/AI65 -> 0.2600504 | AN65: 100517055 | AO65: 24684.359
A66: 100521357 | B66: CRUNCHIES DE POLLO "SWIFT" - 12x380g | C66: 7790360982018 | D66: 4.56 | E66: 12 | F66: =+VLOOKUP(A66,$AN$3:$AO$109,2,FALSE) -> 44177.826 | G66: 0.33 | H66: =+F66*(1-G66) -> 29599.143 | I66: =+H66/E66 -> 2466.5953 | J66: =+I66*J$3 -> 517.98501 | K66: =+I66+J66 -> 2984.5803 | L66: =+K66*L$3 -> 984.9115 | M66: =+K66+L66 -> 3969.4918 | N66: =+M66*N$3 -> 1587.7967 | O66: =+M66+N66 -> 5557.2885 | P66: =H66/Q66-1 -> 0 | Q66: 29599.143 | S66: OFERTA INCORPORACION Compra 4 bolsa + 2 de regalo: 33% de dcto vía NC por cumplimiento mínimo de volumen. Si va en un solo pedido, pueder ir a px en factura. Objetivo informado en avance (por cliente, por sku) | AD66: =6*60 -> 360 | AI66: 42074.12 | AN66: 100517186 | AO66: 62354.911
A67: 100521358 | B67: CRUNCHIES DE POLLO "SWIFT" - 10x760g | C67: 7790360982025 | D67: 7.6 | E67: 10 | F67: =+VLOOKUP(A67,$AN$3:$AO$109,2,FALSE) -> 66266.739 | G67: 0.33 | H67: =+F67*(1-G67) -> 44398.715 | I67: =+H67/E67 -> 4439.8715 | J67: =+I67*J$3 -> 932.37302 | K67: =+I67+J67 -> 5372.2445 | L67: =+K67*L$3 -> 1772.8407 | M67: =+K67+L67 -> 7145.0852 | N67: =+M67*N$3 -> 2858.0341 | O67: =+M67+N67 -> 10003.119 | P67: =H67/Q67-1 -> -0.33 | Q67: 66266.739 | S67: Oferta incorporación 3x2 | Y67: SEPT | Z67: OCT | AA67: LUCHETTI | AB67: PATITAS | AD67: =+AD66*6 -> 2160 | AI67: 63111.18 | AN67: 100521663 | AO67: 39946.383
A68: 100522130 | B68: BOCADITOS DE POLLO "SWIFT KIDS" - 12x400g | C68: 7790360982445 | D68: 4.8 | E68: 12 | F68: =+VLOOKUP(A68,$AN$3:$AO$109,2,FALSE) -> 36420.087 | H68: =+F68*(1-G68) -> 36420.087 | I68: =+H68/E68 -> 3035.0073 | J68: =+I68*J$3 -> 637.35152 | K68: =+I68+J68 -> 3672.3588 | L68: =+K68*L$3 -> 1211.8784 | M68: =+K68+L68 -> 4884.2372 | N68: =+M68*N$3 -> 1953.6949 | O68: =+M68+N68 -> 6837.9321 | P68: =H68/Q68-1 -> 0.05 | Q68: 34685.797 | Y68: 4000 | Z68: 4200 | AA68: 5344 | AB68: 6700 | AI68: 21304.738 | AJ68: =+(H68-AI68)/AI68 -> 0.70948301 | AN68: 100021728 | AO68: 37828.07
A69: 100021725 | B69: BOCADITOS DE POLLO GASTRONOMICOS "LA BLANCA" - x6kg | C69: 7790360027009 | D69: 6 | E69: 4 | F69: =+VLOOKUP(A69,$AN$3:$AO$109,2,FALSE) -> 28863.527 | H69: =+F69*(1-G69) -> 28863.527 | I69: =+H69/E69 -> 7215.8817 | J69: =+I69*J$3 -> 1515.3352 | K69: =+I69+J69 -> 8731.2168 | L69: =+K69*L$3 -> 2881.3016 | M69: =+K69+L69 -> 11612.518 | N69: =+M69*N$3 -> 4645.0074 | O69: =+M69+N69 -> 16257.526 | P69: =H69/Q69-1 -> 0 | Q69: 28863.527 | AI69: 27489.073 | AJ69: =+(H69-AI69)/AI69 -> 0.05 | AN69: 100517679 | AO69: 35830.538
A70: 100517055 | B70: PALITO DE POLLO "SWIFT" 12 X 260 Grs. | C70: 7790360971135 | D70: 3.12 | E70: 12 | F70: =+VLOOKUP(A70,$AN$3:$AO$109,2,FALSE) -> 24684.359 | H70: =+F70*(1-G70) -> 24684.359 | I70: =+H70/E70 -> 2057.0299 | J70: =+I70*J$3 -> 431.97628 | K70: =+I70+J70 -> 2489.0062 | L70: =+K70*L$3 -> 821.37204 | M70: =+K70+L70 -> 3310.3782 | N70: =+M70*N$3 -> 1324.1513 | O70: =+M70+N70 -> 4634.5295 | P70: =H70/Q70-1 -> 0 | Q70: 24684.359 | Z70: =+Z68*12 -> 50400 | AI70: 23508.913 | AJ70: =+(H70-AI70)/AI70 -> 0.05
A71: 100517186 | B71: PALITO DE POLLO "SWIFT" 8 X 1 Kg.. | C71: 7790360971395 | D71: 8 | E71: 8 | F71: =+VLOOKUP(A71,$AN$3:$AO$109,2,FALSE) -> 62354.911 | H71: =+F71*(1-G71) -> 62354.911 | I71: =+H71/E71 -> 7794.3639 | J71: =+I71*J$3 -> 1636.8164 | K71: =+I71+J71 -> 9431.1803 | L71: =+K71*L$3 -> 3112.2895 | M71: =+K71+L71 -> 12543.47 | N71: =+M71*N$3 -> 5017.3879 | O71: =+M71+N71 -> 17560.858 | P71: =H71/Q71-1 -> 0 | Q71: 62354.911 | Z71: =+Z70/1.21/1.33/1.4 -> 22369.975 | AI71: 59385.63 | AJ71: =+(H71-AI71)/AI71 -> 0.05 | AN71: 100516219 | AO71: 16599.454
A72: 100521663 | B72: MILANESITAS DE CARNE "SWIFT" - 12x400g | C72: 7790360982537 | D72: 4.8 | E72: 12 | F72: 39946.383 | G72: 0.33 | H72: =+F72*(1-G72) -> 26764.077 | I72: =+H72/E72 -> 2230.3397 | J72: =+I72*J$3 -> 468.37134 | K72: =+I72+J72 -> 2698.7111 | L72: =+K72*0.323 -> 871.68367 | M72: =+K72+L72 -> 3570.3947 | N72: =+M72*N$3 -> 1428.1579 | O72: =+M72+N72 -> 4998.5526 | P72: =H72/Q72-1 -> 0 | Q72: 26764.077 | S72: OFERTA INCORPORACION Compra 4 bolsa + 2 de regalo: 33% de dcto vía NC por cumplimiento mínimo de volumen. Si va en un solo pedido, pueder ir a px en factura. Objetivo informado en avance (por cliente, por sku) | Z72: =+F68-Z71 -> 14050.113 | AI72: 42746.88 | AN72: 100516220 | AO72: 17830.838
A73: 100021728 | B73: MEDALLONES DE POLLO "SWIFT" - 12x4x80g | C73: 7790360967558 | D73: 3.84 | E73: 12 | F73: =+VLOOKUP(A73,$AN$3:$AO$109,2,FALSE) -> 37828.07 | H73: =+F73*(1-G73) -> 37828.07 | I73: =+H73/E73 -> 3152.3392 | J73: =+I73*J$3 -> 661.99123 | K73: =+I73+J73 -> 3814.3304 | L73: =+K73*L$3 -> 1258.729 | M73: =+K73+L73 -> 5073.0595 | N73: =+M73*N$3 -> 2029.2238 | O73: =+M73+N73 -> 7102.2833 | P73: =H73/Q73-1 -> 0 | Q73: 37828.07 | Z73: =+Z72/F68 -> 0.38577921 | AI73: 36026.734 | AJ73: =+(H73-AI73)/AI73 -> 0.05
A74: 100517679 | B74: MEDALLONES DE POLLO GASTRONÓMICO 8x12x80 Grs. | C74: 7790360973498 | D74: 7.68 | E74: 8 | F74: =+VLOOKUP(A74,$AN$3:$AO$109,2,FALSE) -> 35830.538 | H74: =+F74*(1-G74) -> 35830.538 | I74: =+H74/E74 -> 4478.8173 | J74: =+I74*J$3 -> 940.55163 | K74: =+I74+J74 -> 5419.3689 | L74: =+K74*L$3 -> 1788.3918 | M74: =+K74+L74 -> 7207.7607 | N74: =+M74*N$3 -> 2883.1043 | O74: =+M74+N74 -> 10090.865 | P74: =H74/Q74-1 -> 0 | Q74: 35830.538 | AI74: 34124.322 | AJ74: =+(H74-AI74)/AI74 -> 0.05 | AN74: 100518158 | AO74: 72003.355
F75: =+VLOOKUP(A75,$AN$3:$AO$109,2,FALSE) -> #N/A | H75: =+F75*(1-G75) -> #N/A | I75: =+H75/E75 -> #N/A | P75: =H75/Q75-1 -> #N/A | Q75: #N/A | AI75: #N/A | AJ75: =+(H75-AI75)/AI75 -> #N/A | AN75: 100518160 | AO75: 72003.355
A76: 100516219 | B76: PAPAS PREFRITAS SUPERCONGELADAS 25x400gr | C76: 7790360967770 | D76: 10 | E76: 25 | F76: =+VLOOKUP(A76,$AN$3:$AO$109,2,FALSE) -> 16599.454 | H76: =+F76*(1-G76) -> 16599.454 | I76: =+H76/E76 -> 663.97818 | J76: =+I76*J$3 -> 139.43542 | K76: =+I76+J76 -> 803.4136 | L76: =+K76*L$3 -> 265.12649 | M76: =+K76+L76 -> 1068.5401 | N76: =+M76*N$3 -> 427.41603 | O76: =+M76+N76 -> 1495.9561 | P76: =H76/Q76-1 -> 0 | Q76: 16599.454 | AI76: 16599.454 | AJ76: =+(H76-AI76)/AI76 -> 0 | AN76: 100518463 | AO76: 33318.085
A77: 100516220 | B77: PAPAS PREFRITAS SUPERCONGELADAS 6x2000gr | C77: 7790360967787 | D77: 12 | E77: 6 | F77: =+VLOOKUP(A77,$AN$3:$AO$109,2,FALSE) -> 17830.838 | H77: =+F77*(1-G77) -> 17830.838 | I77: =+H77/E77 -> 2971.8063 | J77: =+I77*J$3 -> 624.07933 | K77: =+I77+J77 -> 3595.8857 | L77: =+K77*L$3 -> 1186.6423 | M77: =+K77+L77 -> 4782.5279 | N77: =+M77*N$3 -> 1913.0112 | O77: =+M77+N77 -> 6695.5391 | P77: =H77/Q77-1 -> 0 | Q77: 17830.838 | AI77: 17830.838 | AJ77: =+(H77-AI77)/AI77 -> 0
F78: =+VLOOKUP(A78,$AN$3:$AO$109,2,FALSE) -> #N/A | H78: =+F78*(1-G78) -> #N/A | I78: =+H78/E78 -> #N/A | P78: =H78/Q78-1 -> #N/A | Q78: #N/A | AI78: #N/A | AJ78: =+(H78-AI78)/AI78 -> #N/A | AN78: 100518291 | AO78: 14228.63
A79: 100518158 | B79: MILANESA DE CARNE VACUNA CONGELADA 24un x 500grs | C79: 7790360974280 | D79: 12 | E79: 24 | F79: =+VLOOKUP(A79,$AN$3:$AO$109,2,FALSE) -> 72003.355 | H79: =+F79*(1-G79) -> 72003.355 | I79: =+H79/E79 -> 3000.1398 | J79: =+I79*J$3 -> 630.02936 | K79: =+I79+J79 -> 3630.1692 | L79: =+K79*L$3 -> 1197.9558 | M79: =+K79+L79 -> 4828.125 | N79: =+M79*N$3 -> 1931.25 | O79: =+M79+N79 -> 6759.375 | P79: =H79/Q79-1 -> 0 | Q79: 72003.355 | AI79: 72003.355 | AJ79: =+(H79-AI79)/AI79 -> 0 | AN79: 100518292 | AO79: 33574.49
A80: 100518160 | B80: MILANESA DE CARNE VACUNA CONGELADA 12un x 1000grs | C80: 7790360974686 | D80: 12 | E80: 12 | F80: =+VLOOKUP(A80,$AN$3:$AO$109,2,FALSE) -> 72003.355 | H80: =+F80*(1-G80) -> 72003.355 | I80: =+H80/E80 -> 6000.2796 | J80: =+I80*J$3 -> 1260.0587 | K80: =+I80+J80 -> 7260.3383 | L80: =+K80*L$3 -> 2395.9117 | M80: =+K80+L80 -> 9656.25 | N80: =+M80*N$3 -> 3862.5 | O80: =+M80+N80 -> 13518.75 | P80: =H80/Q80-1 -> 0 | Q80: 72003.355 | AI80: 72003.355 | AJ80: =+(H80-AI80)/AI80 -> 0
A81: 100518463 | B81: MILANESAS DE CARNE VACUNA CONG GRANEL 5 kg | C81: 7790360975188 | D81: 5 | E81: 1 | F81: =+VLOOKUP(A81,$AN$3:$AO$109,2,FALSE) -> 33318.085 | H81: =+F81*(1-G81) -> 33318.085 | I81: =+H81/E81 -> 33318.085 | J81: =+I81*J$3 -> 6996.798 | K81: =+I81+J81 -> 40314.883 | L81: =+K81*L$3 -> 13303.912 | M81: =+K81+L81 -> 53618.795 | N81: =+M81*N$3 -> 21447.518 | O81: =+M81+N81 -> 75066.313 | P81: =H81/Q81-1 -> 0 | Q81: 33318.085 | AI81: 33318.085 | AJ81: =+(H81-AI81)/AI81 -> 0 | AN81: 100517915 | AO81: 145920.01
F82: =+VLOOKUP(A82,$AN$3:$AO$109,2,FALSE) -> #N/A | H82: =+F82*(1-G82) -> #N/A | I82: =+H82/E82 -> #N/A | P82: =H82/Q82-1 -> #N/A | Q82: #N/A | AI82: #N/A | AJ82: =+(H82-AI82)/AI82 -> #N/A | AN82: 100517914 | AO82: 159231.16
A83: 100518291 | B83: GRASA VACUNA REFINADA SWIFT 10 X 500 | C83: 7790360975195 | D83: 5 | E83: 10 | F83: =+VLOOKUP(A83,$AN$3:$AO$109,2,FALSE) -> 14228.63 | H83: =+F83*(1-G83) -> 14228.63 | I83: =+H83/E83 -> 1422.863 | J83: =+I83*J$3 -> 298.80123 | K83: =+I83+J83 -> 1721.6642 | L83: =+K83*L$39 -> 378.76613 | M83: =+K83+L83 -> 2100.4304 | N83: =+M83*N$39 -> 735.15063 | O83: =+M83+N83 -> 2835.581 | P83: =H83/Q83-1 -> 0.05 | Q83: 13551.076 | S83: Oferta a px en factura neteada en lista, para $2.830 público | Z83: 0.074262 | AA83: =+H83*(1-Z83) -> 13171.984 | AB83: =+AA83/10 -> 1317.1984 | AC83: =+AB83*1.21*1.22*1.35 -> 2625.0051 | AI83: 13551.076 | AJ83: =+(H83-AI83)/AI83 -> 0.05
A84: 100518292 | B84: GRASA VACUNA REFINADA SWIFT 12x1Kg | C84: 7790360975201 | D84: 12 | E84: 12 | F84: =+VLOOKUP(A84,$AN$3:$AO$109,2,FALSE) -> 33574.49 | H84: =+F84*(1-G84) -> 33574.49 | I84: =+H84/E84 -> 2797.8742 | J84: =+I84*J$3 -> 587.55357 | K84: =+I84+J84 -> 3385.4277 | L84: =+K84*L$39 -> 744.7941 | M84: =+K84+L84 -> 4130.2218 | N84: =+M84*N$39 -> 1445.5776 | O84: =+M84+N84 -> 5575.7995 | P84: =H84/Q84-1 -> 0.05 | Q84: 31975.705 | S84: Oferta a px en factura neteada en lista, para $5.570 público | AI84: 31975.705 | AJ84: =+(H84-AI84)/AI84 -> 0.05 | AN84: 100010689 | AO84: 15000
F85: =+VLOOKUP(A85,$AN$3:$AO$109,2,FALSE) -> #N/A | H85: =+F85*(1-G85) -> #N/A | I85: =+H85/E85 -> #N/A | J85: 0.105 | L85: 0.3 | N85: 0.4 | P85: =H85/Q85-1 -> #N/A | Q85: #N/A | AI85: #N/A | AJ85: =+(H85-AI85)/AI85 -> #N/A | AN85: 100518335 | AO85: 10714.286
A86: 100517915 | B86: CARNE PICADA CONGELADA 36 UN X 500 g SWIFT | C86: 7790360974020 | D86: 18 | E86: 36 | F86: =+VLOOKUP(A86,$AN$3:$AO$109,2,FALSE) -> 145920.01 | H86: =+F86*(1-G86) -> 145920.01 | I86: =+H86/E86 -> 4053.3336 | J86: =+I86*J$85 -> 425.60003 | K86: =+I86+J86 -> 4478.9337 | L86: =+K86*L$85 -> 1343.6801 | M86: =+K86+L86 -> 5822.6138 | N86: =+M86*N$85 -> 2329.0455 | O86: =+M86+N86 -> 8151.6593 | P86: =H86/Q86-1 -> 0 | Q86: 145920.01 | AI86: 126062.63 | AJ86: =+(H86-AI86)/AI86 -> 0.15752 | AN86: 100518332 | AO86: 12321.429
A87: 100517914 | B87: CARNE PICADA CONGELADA 20 UN X 1 kg SWIFT | C87: 7790360974037 | D87: 20 | E87: 20 | F87: =+VLOOKUP(A87,$AN$3:$AO$109,2,FALSE) -> 159231.16 | H87: =+F87*(1-G87) -> 159231.16 | I87: =+H87/E87 -> 7961.5579 | J87: =+I87*J$85 -> 835.96358 | K87: =+I87+J87 -> 8797.5215 | L87: =+K87*L$85 -> 2639.2565 | M87: =+K87+L87 -> 11436.778 | N87: =+M87*N$85 -> 4574.7112 | O87: =+M87+N87 -> 16011.489 | P87: =H87/Q87-1 -> 0 | Q87: 159231.16 | AI87: 137562.34 | AJ87: =+(H87-AI87)/AI87 -> 0.15752 | AN87: 100518334 | AO87: 10928.571
F88: =+VLOOKUP(A88,$AN$3:$AO$109,2,FALSE) -> #N/A | H88: =+F88*(1-G88) -> #N/A | J88: 0.105 | L88: 0.3 | N88: 0.4 | P88: =H88/Q88-1 -> #N/A | Q88: #N/A | AI88: #N/A | AJ88: =+(H88-AI88)/AI88 -> #N/A | AN88: 100518227 | AO88: 12895.714
A89: 100010689 | B89: ENTRAÑA FINA ENF SWIFT | D89: 22 | E89: 1 | F89: =+VLOOKUP(A89,$AN$3:$AO$109,2,FALSE) -> 15000 | H89: =+F89*(1-G89) -> 15000 | I89: =+H89/E89 -> 15000 | J89: =+I89*J$88 -> 1575 | K89: =+I89+J89 -> 16575 | L89: =+K89*L$88 -> 4972.5 | M89: =+K89+L89 -> 21547.5 | N89: =+M89*N$88 -> 8619 | O89: =+M89+N89 -> 30166.5 | P89: =H89/Q89-1 -> 0.05 | Q89: 14285.714 | AI89: 14255.102 | AJ89: =+(H89-AI89)/AI89 -> 0.052254832
A90: 100518335 | B90: ROAST BEEF EN PORCIONES ENF SWIFT (L) | D90: 22.5 | E90: 1 | F90: =+VLOOKUP(A90,$AN$3:$AO$109,2,FALSE) -> 10714.286 | H90: =+F90*(1-G90) -> 10714.286 | I90: =+H90/E90 -> 10714.286 | J90: =+I90*J$88 -> 1125 | K90: =+I90+J90 -> 11839.286 | L90: =+K90*L$88 -> 3551.7857 | M90: =+K90+L90 -> 15391.071 | N90: =+M90*N$88 -> 6156.4286 | O90: =+M90+N90 -> 21547.5 | P90: =H90/Q90-1 -> 0.05 | Q90: 10204.082 | Z90: =+Y4*144+Y100*AA90 -> 755666.74 | AA90: =144/2 -> 72 | AI90: 9029.5918 | AJ90: =+(H90-AI90)/AI90 -> 0.18657475 | AN90: 100520837 | AO90: 33805.839
A91: 100518332 | B91: CARNAZA CUADRADA EN PORCIONES ENF SWIFT (L) | D91: 21.5 | E91: 1 | F91: =+VLOOKUP(A91,$AN$3:$AO$109,2,FALSE) -> 12321.429 | H91: =+F91*(1-G91) -> 12321.429 | I91: =+H91/E91 -> 12321.429 | J91: =+I91*J$88 -> 1293.75 | K91: =+I91+J91 -> 13615.179 | L91: =+K91*L$88 -> 4084.5536 | M91: =+K91+L91 -> 17699.732 | N91: =+M91*N$88 -> 7079.8929 | O91: =+M91+N91 -> 24779.625 | P91: =H91/Q91-1 -> 0.05 | Q91: 11734.694 | Z91: =+Y4*144+Y96*AA91 -> 645989.92 | AA91: =144/6 -> 24 | AI91: 9717.3469 | AJ91: =+(H91-AI91)/AI91 -> 0.26798278 | AN91: 100522395 | AO91: 34481.949
A92: 100518334 | B92: TAPA DE ASADO EN PORCIONES ENF SWIFT (L) | D92: 22.5 | E92: 1 | F92: =+VLOOKUP(A92,$AN$3:$AO$109,2,FALSE) -> 10928.571 | H92: =+F92*(1-G92) -> 10928.571 | I92: =+H92/E92 -> 10928.571 | J92: =+I92*J$88 -> 1147.5 | K92: =+I92+J92 -> 12076.071 | L92: =+K92*L$88 -> 3622.8214 | M92: =+K92+L92 -> 15698.893 | N92: =+M92*N$88 -> 6279.5571 | O92: =+M92+N92 -> 21978.45 | P92: =H92/Q92-1 -> 0.05 | Q92: 10408.163 | AI92: 7997.9592 | AJ92: =+(H92-AI92)/AI92 -> 0.36642001 | AN92: 100522561 | AO92: 6824.5524
A93: 100518227 | B93: VACIO EN PORCIONES NOV ENFRIADO PARA VENTA LOCAL (L) | D93: 22.5 | E93: 1 | F93: =+VLOOKUP(A93,$AN$3:$AO$109,2,FALSE) -> 12895.714 | H93: =+F93*(1-G93) -> 12895.714 | I93: =+H93/E93 -> 12895.714 | J93: =+I93*J$88 -> 1354.05 | K93: =+I93+J93 -> 14249.764 | L93: =+K93*L$88 -> 4274.9293 | M93: =+K93+L93 -> 18524.694 | N93: =+M93*N$88 -> 7409.8774 | O93: =+M93+N93 -> 25934.571 | P93: =H93/Q93-1 -> 0.071 | Q93: 12040.816 | AI93: 7997.9592 | AJ93: =+(H93-AI93)/AI93 -> 0.61237561
A94: 100027726 | B94: BONDIOLA DE CERDO CONGELADA | D94: 22.5 | E94: 1 | F94: =+VLOOKUP(A94,$AN$3:$AO$109,2,FALSE) -> #N/A | H94: =+F94*(1-G94) -> #N/A | I94: =+H94/E94 -> #N/A | J94: =+I94*J$88 -> #N/A | K94: =+I94+J94 -> #N/A | L94: =+K94*L$88 -> #N/A | M94: =+K94+L94 -> #N/A | N94: =+M94*N$88 -> #N/A | O94: =+M94+N94 -> #N/A | P94: =H94/Q94-1 -> #N/A | Q94: 6195 | AN94: 100520902 | AO94: 30287.434
F95: =+VLOOKUP(A95,$AN$3:$AO$109,2,FALSE) -> #N/A | H95: =+F95*(1-G95) -> #N/A | J95: 0.21 | L95: 0.3 | N95: 0.4 | P95: =H95/Q95-1 -> #N/A | Q95: #N/A | AI95: #N/A | AJ95: =+(H95-AI95)/AI95 -> #N/A | AN95: 100522698 | AO95: 38836.761
A96: 100520837 | B96: CHORIZOS FRESCOS DE CERDO LIBRE DE GLUTEN | C96: 7790360980625 | D96: 4.8 | E96: 12 | F96: =+VLOOKUP(A96,$AN$3:$AO$109,2,FALSE) -> 33805.839 | H96: =+F96*(1-G96) -> 33805.839 | I96: =+H96/E96 -> 2817.1532 | J96: =+I96*J$95 -> 591.60218 | K96: =+I96+J96 -> 3408.7554 | L96: =+K96*L$95 -> 1022.6266 | M96: =+K96+L96 -> 4431.382 | N96: =+M96*N$95 -> 1772.5528 | O96: =+M96+N96 -> 6203.9348 | P96: =H96/Q96-1 -> 0.04 | Q96: 32505.614 | Y96: =+Z96*H96 -> 3380.5839 | Z96: 0.1 | AA96: =+H96*(1-Z96) -> 30425.255 | AB96: =+AA96/E96 -> 2535.4379 | AC96: =+AB96*1.21*1.3*1.4 -> 5583.5413 | AD96: VER CUPOS | AE96: Con la compra de 1 caja de 21632 + 2 unidades de Chorizos --> 10% de dcto en ambos SKU | AI96: 30957.728 | AJ96: =+(H96-AI96)/AI96 -> 0.092
A97: 100522395 | B97: CHORIZOS FRESCOS DE CERDO CONGELADOS LIBRE DE GLUTEN 12u x 400g | C97: 7790360980625 | D97: 4.8 | E97: 12 | F97: =+VLOOKUP(A97,$AN$3:$AO$109,2,FALSE) -> 34481.949 | G97: 0.33 | H97: =+F97*(1-G97) -> 23102.906 | I97: =+H97/E97 -> 1925.2421 | J97: =+I97*J$95 -> 404.30085 | K97: =+I97+J97 -> 2329.543 | L97: =+K97*L$95 -> 698.8629 | M97: =+K97+L97 -> 3028.4059 | N97: =+M97*N$95 -> 1211.3624 | O97: =+M97+N97 -> 4239.7682 | P97: =H97/Q97-1 -> -0.3032 | Q97: 33155.72 | S97: Dinámica 2+1. Compra 2, recibe 3 ----> oferta $4.240 (para distribuidores, vía NC, por cumplimiento de objetivo. Si compra en un solo pedido puede ir a px factura. Objetivo informado en avance por cliente, por sku) | AN97: 100521457 | AO97: 34485.722
A98: 100522561 | B98: CHORIZOS CONGELADOS DE CERDO LIBRE DE GLUTEN SWIFT GRANEL | D98: 16 | E98: 8 | F98: =+VLOOKUP(A98,$AN$3:$AO$109,2,FALSE) -> 6824.5524 | G98: 0.33 | H98: =+F98*(1-G98) -> 4572.4501 | I98: =+H98*2 -> 9144.9002 | J98: =+I98*J$95 -> 1920.429 | K98: =+I98+J98 -> 11065.329 | L98: =+K98*L$95 -> 3319.5988 | M98: =+K98+L98 -> 14384.928 | N98: =+M98*N$95 -> 5753.9712 | O98: =+M98+N98 -> 20138.899 | P98: =H98/Q98-1 -> #N/A | Q98: #N/A | S98: Dinámica 2+1. Compra 2, recibe 3 ----> oferta $20.140 los 20 chori (2kg aprox) (para distribuidores, vía NC, por cumplimiento de objetivo. Si compra en un solo pedido puede ir a px factura. Objetivo informado en avance por cliente, por sku) | AN98: 100521455 | AO98: 34485.722
F99: =+VLOOKUP(A99,$AN$3:$AO$109,2,FALSE) -> #N/A | H99: =+F99*(1-G99) -> #N/A | J99: 0.21 | L99: 0.33 | N99: 0.4 | P99: =H99/Q99-1 -> #N/A | Q99: #N/A | AI99: #N/A | AJ99: =+(H99-AI99)/AI99 -> #N/A | AN99: 100521453 | AO99: 33300.276
A100: 100520902 | B100: PAPAS PRE COCIDAS SUPERCONGELADAS LIBRES DE GLUTEN 700G | C100: 7790360981042 | D100: 9.8 | E100: 14 | F100: =+VLOOKUP(A100,$AN$3:$AO$109,2,FALSE) -> 30287.434 | G100: 0.125 | H100: =+F100*(1-G100) -> 26501.504 | I100: =+H100/E100 -> 1892.9646 | J100: =+I100*J$99 -> 397.52257 | K100: =+I100+J100 -> 2290.4872 | L100: =+K100*L$99 -> 755.86076 | M100: =+K100+L100 -> 3046.3479 | N100: =+M100*N$99 -> 1218.5392 | O100: =+M100+N100 -> 4264.8871 | P100: =H100/Q100-1 -> 0.03 | Q100: 25729.616 | S100: OFERTA compra 7 bolsas , recibe 8. | Y100: =+Z100*H100 -> 2650.1504 | Z100: 0.1 | AA100: =+H100*(1-Z100) -> 23851.354 | AB100: =+AA100/E100 -> 1703.6681 | AC100: =+AB100*1.21*1.3*1.4 -> 3751.818 | AD100: VER CUPOS | AE100: Con la compra de 1 caja de 21632 + 7 unidades de PAPAS --> 10% de dcto en ambos SKU | AI100: 25729.616 | AJ100: =+(H100-AI100)/AI100 -> 0.03 | AN100: 100521454 | AO100: 33300.276
...

Sheet NOA
H1: =10700*1.05 -> 11235 | Z1: ACCIÓN VIA NC: COMBO CLASICA 2 X 80 + CHORIZOS
A2: Código | B2: Descripción | C2: EAN | D2: Kg. x Caja | E2: Cant. X Caja | F2: Precio de Factura | G2: Dcto | H2: Precio de Factura | I2: Precio Neto estuche en factura | J2: IVA | K2: Px Unitario IVA Inc | L2: M-up Dx | M2: Px Unitario Minorista | N2: M-up Minorista | O2: Px Unitario Público | Q2: Enero | S2: OFERTAS Y ACCIONES | Z2: DCTO (%) | AA2: Px ACCIÓN CAJA ($) | AB2: Px Acción estuche ($) | AC2: Px oferta (%) | AD2: CUPO (Cajas) | AE2: CONDICIÓN | AG2: SEP | AH2: Var %
J3: 0.21 | L3: 0.33 | N3: 0.4
A4: 100021632 | B4: HAMBURGUESAS 30x160g CLASICA x2 SWIFT | C4: 7790360026606 | D4: 4.8 | E4: 30 | F4: =+VLOOKUP(A4,$AL$4:$AM$110,2,FALSE) -> 36223.374 | H4: =+F4*(1-G4) -> 36223.374 | I4: =+H4/E4 -> 1207.4458 | J4: =+I4*J$3 -> 253.56362 | K4: =+I4+J4 -> 1461.0094 | L4: =+K4*L$3 -> 482.1331 | M4: =+K4+L4 -> 1943.1425 | N4: =+M4*N$3 -> 777.257 | O4: =+M4+N4 -> 2720.3995 | P4: =H4/Q4-1 -> 0.05 | Q4: 34498.451 | Y4: =+Z4*H4 -> 3622.3374 | Z4: 0.1 | AA4: =+H4*(1-Z4) -> 32601.036 | AB4: =+AA4/E4 -> 1086.7012 | AC4: =+AB4*1.21*1.3*1.4 -> 2393.1334 | AD4: VER CUPOS | AE4: Con la compra de 1 caja de 21632 + 2 unidades de Chorizos --> 10% de dcto en ambos SKU | AG4: 28670.618 | AH4: =+(H4-AG4)/AG4 -> 0.26343193 | AL4: 100021632 | AM4: 36223.374
A5: 100021652 | B5: HAMBURGUESA 18X4X80G CLASICA SWIFT | C5: 7790360026576 | D5: 5.76 | E5: 18 | F5: =+VLOOKUP(A5,$AL$4:$AM$110,2,FALSE) -> 49208.688 | H5: =+F5*(1-G5) -> 49208.688 | I5: =+H5/E5 -> 2733.816 | J5: =+I5*J$3 -> 574.10136 | K5: =+I5+J5 -> 3307.9174 | L5: =+K5*L$3 -> 1091.6127 | M5: =+K5+L5 -> 4399.5301 | N5: =+M5*N$3 -> 1759.812 | O5: =+M5+N5 -> 6159.3421 | P5: =H5/Q5-1 -> 0 | Q5: 49208.688 | AG5: 41713.767 | AH5: =+(H5-AG5)/AG5 -> 0.179675 | AL5: 100021652 | AM5: 49208.688
A6: 100021631 | B6: HAMBURGUESA 8X12X80G CLASICA SWIFT | C6: 7790360026590 | D6: 7.68 | E6: 8 | F6: =+VLOOKUP(A6,$AL$4:$AM$110,2,FALSE) -> 60717.274 | H6: =+F6*(1-G6) -> 60717.274 | I6: =+H6/E6 -> 7589.6592 | J6: =+I6*J$3 -> 1593.8284 | K6: =+I6+J6 -> 9183.4877 | L6: =+K6*L$3 -> 3030.5509 | M6: =+K6+L6 -> 12214.039 | N6: =+M6*N$3 -> 4885.6154 | O6: =+M6+N6 -> 17099.654 | P6: =H6/Q6-1 -> 0 | Q6: 60717.274 | AG6: 61026.747 | AH6: =+(H6-AG6)/AG6 -> -0.0050711089 | AL6: 100021631 | AM6: 60717.274
A7: 100021630 | B7: HAMBURGUESA 6X20X80G CLASICA SWIFT | C7: 7790360026583 | D7: 9.6 | E7: 6 | F7: =+VLOOKUP(A7,$AL$4:$AM$110,2,FALSE) -> 75896.592 | H7: =+F7*(1-G7) -> 75896.592 | I7: =+H7/E7 -> 12649.432 | J7: =+I7*J$3 -> 2656.3807 | K7: =+I7+J7 -> 15305.813 | L7: =+K7*L$3 -> 5050.9182 | M7: =+K7+L7 -> 20356.731 | N7: =+M7*N$3 -> 8142.6924 | O7: =+M7+N7 -> 28499.423 | P7: =H7/Q7-1 -> 0 | Q7: 75896.592 | AG7: 76268.328 | AH7: =+(H7-AG7)/AG7 -> -0.0048740543 | AL7: 100021630 | AM7: 75896.592
A8: 100021653 | B8: MEDALLON 18X4X80G PARRILLERO SWIFT | C8: 7790360026682 | D8: 5.76 | E8: 18 | F8: =+VLOOKUP(A8,$AL$4:$AM$110,2,FALSE) -> 49208.688 | H8: =+F8*(1-G8) -> 49208.688 | I8: =+H8/E8 -> 2733.816 | J8: =+I8*J$3 -> 574.10136 | K8: =+I8+J8 -> 3307.9174 | L8: =+K8*L$3 -> 1091.6127 | M8: =+K8+L8 -> 4399.5301 | N8: =+M8*N$3 -> 1759.812 | O8: =+M8+N8 -> 6159.3421 | P8: =H8/Q8-1 -> 0 | Q8: 49208.688 | AG8: 49250.373 | AH8: =+(H8-AG8)/AG8 -> -0.0008463821 | AL8: 100021653 | AM8: 49208.688
A9: 100516169 | B9: MEDALLONES 18X4X80G SWIFT RECETA ESPECIAL | C9: 7790360967961 | D9: 5.76 | E9: 18 | F9: =+VLOOKUP(A9,$AL$4:$AM$110,2,FALSE) -> 45373.852 | H9: =+F9*(1-G9) -> 45373.852 | I9: =+H9/E9 -> 2520.7695 | J9: =+I9*J$3 -> 529.3616 | K9: =+I9+J9 -> 3050.1311 | L9: =+K9*L$3 -> 1006.5433 | M9: =+K9+L9 -> 4056.6744 | N9: =+M9*N$3 -> 1622.6698 | O9: =+M9+N9 -> 5679.3442 | P9: =H9/Q9-1 -> 0 | Q9: 45373.852 | AG9: 41155.421 | AH9: =+(H9-AG9)/AG9 -> 0.1025 | AL9: 100516169 | AM9: 45373.852
A10: 100520337 | B10: MEDALLON BURGER SWIFT MEGA 30 x 160 g | C10: 7790360977960 | D10: 4.8 | E10: 30 | F10: =+VLOOKUP(A10,$AL$4:$AM$110,2,FALSE) -> 28211.35 | H10: =+F10*(1-G10) -> 28211.35 | I10: =+H10/E10 -> 940.37834 | J10: =+I10*J$3 -> 197.47945 | K10: =+I10+J10 -> 1137.8578 | L10: =+K10*L$3 -> 375.49307 | M10: =+K10+L10 -> 1513.3509 | N10: =+M10*N$3 -> 605.34035 | O10: =+M10+N10 -> 2118.6912 | P10: =H10/Q10-1 -> 0.05 | Q10: 26867.953 | AG10: 24370.025 | AH10: =+(H10-AG10)/AG10 -> 0.157625 | AL10: 100520337 | AM10: 28211.35
A11: 100021503 | B11: Medallón CAJITA 12x4 69 grs | C11: 7790360966841 | D11: 3.312 | E11: 12 | F11: =+VLOOKUP(A11,$AL$4:$AM$110,2,FALSE) -> 19950.311 | G11: 0.090909091 | H11: =+F11*(1-G11) -> 18136.646 | I11: =+H11/E11 -> 1511.3872 | J11: =+I11*J$3 -> 317.3913 | K11: =+I11+J11 -> 1828.7785 | L11: =+K11*L$3 -> 603.49689 | M11: =+K11+L11 -> 2432.2754 | N11: =+M11*N$3 -> 972.91015 | O11: =+M11+N11 -> 3405.1855 | P11: =H11/Q11-1 -> 0.090821825 | Q11: 16626.589 | S11: Contra 10 estuches + 1 de regalo | AG11: 16911.701 | AH11: =+(H11-AG11)/AG11 -> 0.072431818 | AL11: 100021503 | AM11: 19950.311
A12: 100516201 | B12: HAMBURGUESA 8X12X69G BURGER SWIFT | C12: 7790360968548 | D12: 6.624 | E12: 8 | F12: =+VLOOKUP(A12,$AL$4:$AM$110,2,FALSE) -> 39562.393 | H12: =+F12*(1-G12) -> 39562.393 | I12: =+H12/E12 -> 4945.2992 | J12: =+I12*J$3 -> 1038.5128 | K12: =+I12+J12 -> 5983.812 | L12: =+K12*L$3 -> 1974.658 | M12: =+K12+L12 -> 7958.4699 | N12: =+M12*N$3 -> 3183.388 | O12: =+M12+N12 -> 11141.858 | P12: =H12/Q12-1 -> 0.05 | Q12: 37678.47 | AG12: 34175.483 | AH12: =+(H12-AG12)/AG12 -> 0.157625 | AL12: 100516201 | AM12: 39562.393
A13: 100021643 | B13: MEDALLON 42X112G DOBLE BURGER SWIFT | C13: 7790360966797 | D13: 4.704 | E13: 42 | F13: =+VLOOKUP(A13,$AL$4:$AM$110,2,FALSE) -> 27190.844 | H13: =+F13*(1-G13) -> 27190.844 | I13: =+H13/E13 -> 647.40104 | J13: =+I13*J$3 -> 135.95422 | K13: =+I13+J13 -> 783.35526 | L13: =+K13*L$3 -> 258.50724 | M13: =+K13+L13 -> 1041.8625 | N13: =+M13*N$3 -> 416.745 | O13: =+M13+N13 -> 1458.6075 | P13: =H13/Q13-1 -> 0 | Q13: 27190.844 | AG13: 25896.042 | AH13: =+(H13-AG13)/AG13 -> 0.05 | AL13: 100021643 | AM13: 27190.844
A14: 100516325 | B14: MEDALLON DOBLE BURGER 2X2 | C14: 7790360967763 | D14: 4.704 | E14: 21 | F14: =+VLOOKUP(A14,$AL$4:$AM$110,2,FALSE) -> 26444.818 | H14: =+F14*(1-G14) -> 26444.818 | I14: =+H14/E14 -> 1259.2771 | J14: =+I14*J$3 -> 264.44818 | K14: =+I14+J14 -> 1523.7253 | L14: =+K14*L$3 -> 502.82933 | M14: =+K14+L14 -> 2026.5546 | N14: =+M14*N$3 -> 810.62184 | O14: =+M14+N14 -> 2837.1764 | P14: =H14/Q14-1 -> 0 | Q14: 26444.818 | AG14: 23986.23 | AH14: =+(H14-AG14)/AG14 -> 0.1025 | AL14: 100516325 | AM14: 26444.818
A15: 100021676 | B15: HAMBURGUESA 30X250g CLASICA "XL" SWIFT | C15: 7790360967411 | D15: 7.5 | E15: 30 | F15: =+VLOOKUP(A15,$AL$4:$AM$110,2,FALSE) -> 58407.612 | G15: 0.088 | H15: =+F15*(1-G15) -> 53267.743 | I15: =+H15/E15 -> 1775.5914 | J15: =+I15*J$3 -> 372.8742 | K15: =+I15+J15 -> 2148.4656 | L15: =+K15*0.33 -> 708.99365 | M15: =+K15+L15 -> 2857.4593 | N15: =+M15*N$3 -> 1142.9837 | O15: =+M15+N15 -> 4000.443 | P15: =H15/Q15-1 -> -0.088 | Q15: 58407.612 | S15: Dcto por posicionamiento para oferta a $3.999 | AG15: 48161.297 | AH15: =+(H15-AG15)/AG15 -> 0.106028 | AL15: 100021676 | AM15: 58407.612
A16: 100516008 | B16: HAMBURGUESA 24X2X120g CASERA SWIFT | C16: 7790360967701 | D16: 5.76 | E16: 24 | F16: =+VLOOKUP(A16,$AL$4:$AM$110,2,FALSE) -> 57960.92 | G16: 0.083333333 | H16: =+F16*(1-G16) -> 53130.844 | I16: =+H16/E16 -> 2213.7851 | J16: =+I16*J$3 -> 464.89488 | K16: =+I16+J16 -> 2678.68 | L16: =+K16*L$3 -> 883.96441 | M16: =+K16+L16 -> 3562.6444 | N16: =+M16*N$3 -> 1425.0578 | O16: =+M16+N16 -> 4987.7022 | P16: =H16/Q16-1 -> 0.0083232501 | Q16: 52692.273 | S16: OFERTA Compra 10 FLOW + 1 de regalo | AG16: 52572.263 | AH16: =+(H16-AG16)/AG16 -> 0.010625 | AL16: 100516008 | AM16: 57960.92
A17: 100520834 | B17: HAMBURGUESA X-TREMA 36 x 185 grs | C17: 7790360980618 | D17: 6.66 | E17: 36 | F17: =+VLOOKUP(A17,$AL$4:$AM$110,2,FALSE) -> 67713.604 | H17: =+F17*(1-G17) -> 67713.604 | I17: =+H17/E17 -> 1880.9335 | J17: =+I17*J$3 -> 394.99603 | K17: =+I17+J17 -> 2275.9295 | L17: =+K17*L$3 -> 751.05673 | M17: =+K17+L17 -> 3026.9862 | N17: =+M17*N$3 -> 1210.7945 | O17: =+M17+N17 -> 4237.7807 | P17: =H17/Q17-1 -> 0 | Q17: 67713.604 | AG17: 58493.557 | AH17: =+(H17-AG17)/AG17 -> 0.157625 | AL17: 100520834 | AM17: 67713.604
A18: 100021680 | B18: HAMBURGUESAS 18X2X120g CLL BRA/ARG | C18: 7790360967688 | D18: 4.32 | E18: 18 | F18: =+VLOOKUP(A18,$AL$4:$AM$110,2,FALSE) -> #N/A | H18: =+F18*(1-G18) -> #N/A | I18: =+H18/E18 -> #N/A | J18: =+I18*J$3 -> #N/A | K18: =+I18+J18 -> #N/A | L18: =+K18*L$3 -> #N/A | M18: =+K18+L18 -> #N/A | N18: =+M18*N$3 -> #N/A | O18: =+M18+N18 -> #N/A | P18: =H18/Q18-1 -> #N/A | Q18: 51589.616 | AG18: 44565.05 | AH18: =+(H18-AG18)/AG18 -> #N/A | AL18: 100021644 | AM18: 20661.7
A19: 100021644 | B19: MEDALLON 42X112G LA BLANCA | C19: 7790360008541 | D19: 4.704 | E19: 42 | F19: =+VLOOKUP(A19,$AL$4:$AM$110,2,FALSE) -> 20661.7 | H19: =+F19*(1-G19) -> 20661.7 | I19: =+H19/E19 -> 491.94523 | J19: =+I19*J$3 -> 103.3085 | K19: =+I19+J19 -> 595.25373 | L19: =+K19*0.3 -> 178.57612 | M19: =+K19+L19 -> 773.82985 | N19: =+M19*N$3 -> 309.53194 | O19: =+M19+N19 -> 1083.3618 | P19: =H19/Q19-1 -> 0.05 | Q19: 19677.809 | AG19: 15520.307 | AH19: =+(H19-AG19)/AG19 -> 0.33126875 | AL19: 100021677 | AM19: 16816.177
A20: 100021677 | B20: MEDALLON 12x4X69G LA BLANCA | C20: 7790360967404 | D20: 3.312 | E20: 12 | F20: =+VLOOKUP(A20,$AL$4:$AM$110,2,FALSE) -> 16816.177 | H20: =+F20*(1-G20) -> 16816.177 | I20: =+H20/E20 -> 1401.3481 | J20: =+I20*J$3 -> 294.2831 | K20: =+I20+J20 -> 1695.6312 | L20: =+K20*0.3 -> 508.68937 | M20: =+K20+L20 -> 2204.3206 | N20: =+M20*N$3 -> 881.72823 | O20: =+M20+N20 -> 3086.0488 | P20: =H20/Q20-1 -> 0 | Q20: 16816.177 | AG20: 14526.446 | AH20: =+(H20-AG20)/AG20 -> 0.157625 | AL20: 100021638 | AM20: 48130.217
A21: 100021638 | B21: MEDALLONES 60X80g "SWIFT BURGER" PARRILLERAS FAMILY | C21: 7790360026699 | D21: 4.8 | E21: 60 | F21: =+VLOOKUP(A21,$AL$4:$AM$110,2,FALSE) -> 48130.217 | H21: =+F21*(1-G21) -> 48130.217 | I21: =+H21/E21 -> 802.17028 | J21: =+I21*J$3 -> 168.45576 | K21: =+I21+J21 -> 970.62604 | L21: =+K21*L$3 -> 320.30659 | M21: =+K21+L21 -> 1290.9326 | N21: =+M21*N$3 -> 516.37305 | O21: =+M21+N21 -> 1807.3057 | P21: =H21/Q21-1 -> 0 | Q21: 48130.217 | AG21: 41576.691 | AH21: =+(H21-AG21)/AG21 -> 0.157625 | AL21: 100021575 | AM21: 40652.511
A22: 100021575 | B22: MEDALLONES 60X69g "SWIFT BURGER"PARRILLERAS FAMILY | C22: 7790360007032 | D22: 4.14 | E22: 60 | F22: =+VLOOKUP(A22,$AL$4:$AM$110,2,FALSE) -> 40652.511 | H22: =+F22*(1-G22) -> 40652.511 | I22: =+H22/E22 -> 677.54185 | J22: =+I22*J$3 -> 142.28379 | K22: =+I22+J22 -> 819.82564 | L22: =+K22*L$3 -> 270.54246 | M22: =+K22+L22 -> 1090.3681 | N22: =+M22*N$3 -> 436.14724 | O22: =+M22+N22 -> 1526.5153 | P22: =H22/Q22-1 -> 0 | Q22: 40652.511 | AG22: 35117.167 | AH22: =+(H22-AG22)/AG22 -> 0.157625 | AL22: 100021514 | AM22: 37358.366
A23: 100021514 | B23: MEDALLON 60X69G CARNE VACUNA | C23: 7790360006943 | D23: 4.14 | E23: 60 | F23: =+VLOOKUP(A23,$AL$4:$AM$110,2,FALSE) -> 37358.366 | H23: =+F23*(1-G23) -> 37358.366 | I23: =+H23/E23 -> 622.63944 | J23: =+I23*J$3 -> 130.75428 | K23: =+I23+J23 -> 753.39372 | L23: =+K23*L$3 -> 248.61993 | M23: =+K23+L23 -> 1002.0136 | N23: =+M23*N$3 -> 400.80546 | O23: =+M23+N23 -> 1402.8191 | P23: =H23/Q23-1 -> 0 | Q23: 37358.366 | AG23: 32271.561 | AH23: =+(H23-AG23)/AG23 -> 0.157625 | AL23: 100516208 | AM23: 42872.09
A24: 100516208 | B24: MEDALLON 60x80g PARRILLERO MC SWIFT | C24: 7790360968203 | D24: =60*0.08 -> 4.8 | E24: 60 | F24: =+VLOOKUP(A24,$AL$4:$AM$110,2,FALSE) -> 42872.09 | H24: =+F24*(1-G24) -> 42872.09 | I24: =+H24/E24 -> 714.53484 | J24: =+I24*J$3 -> 150.05232 | K24: =+I24+J24 -> 864.58716 | L24: =+K24*L$3 -> 285.31376 | M24: =+K24+L24 -> 1149.9009 | N24: =+M24*N$3 -> 459.96037 | O24: =+M24+N24 -> 1609.8613 | P24: =H24/Q24-1 -> 0 | Q24: 42872.09 | AG24: 37034.524 | AH24: =+(H24-AG24)/AG24 -> 0.157625 | AL24: 100518346 | AM24: 61908.355
A25: 100518346 | B25: MEDALLON 60X109G CARNE VACUNA PARRILLERO SWIFT | C25: 7790360975478 | D25: =60*0.109 -> 6.54 | E25: 60 | F25: =+VLOOKUP(A25,$AL$4:$AM$110,2,FALSE) -> 61908.355 | H25: =+F25*(1-G25) -> 61908.355 | I25: =+H25/E25 -> 1031.8059 | J25: =I25*J3 -> 216.67924 | K25: =J25+I25 -> 1248.4852 | L25: =K25*L3 -> 412.0001 | M25: =L25+K25 -> 1660.4853 | N25: =M25*N3 -> 664.1941 | O25: =N25+M25 -> 2324.6794 | P25: =H25/Q25-1 -> 0 | Q25: 61908.355 | AG25: 53478.765 | AH25: =+(H25-AG25)/AG25 -> 0.157625 | AL25: 100516259 | AM25: 138851.97
A26: 100516259 | B26: MEDALLON GIGANTE 48x113.5g | C26: 7790360968340 | D26: 18.16 | E26: 48 | F26: =+VLOOKUP(A26,$AL$4:$AM$110,2,FALSE) -> 138851.97 | H26: =+F26*(1-G26) -> 138851.97 | I26: =+H26/E26 -> 2892.7493 | J26: =+I26*J$3 -> 607.47736 | K26: =+I26+J26 -> 3500.2267 | L26: =+K26*L$3 -> 1155.0748 | M26: =+K26+L26 -> 4655.3015 | N26: =+M26*N$3 -> 1862.1206 | O26: =+M26+N26 -> 6517.4221 | P26: =H26/Q26-1 -> 0 | Q26: 138851.97 | AG26: 119945.55 | AH26: =+(H26-AG26)/AG26 -> 0.157625 | AL26: 100518095 | AM26: 69182.504
A27: 100518095 | B27: HAMBURGUESA 36 X 185 GRS | C27: 7790360974785 | D27: 6.66 | E27: 36 | F27: =+VLOOKUP(A27,$AL$4:$AM$110,2,FALSE) -> 69182.504 | H27: =+F27*(1-G27) -> 69182.504 | I27: =+H27/E27 -> 1921.7362 | J27: =+I27*J$3 -> 403.5646 | K27: =+I27+J27 -> 2325.3008 | L27: =+K27*L$3 -> 767.34927 | M27: =+K27+L27 -> 3092.6501 | N27: =+M27*N$3 -> 1237.06 | O27: =+M27+N27 -> 4329.7101 | P27: =H27/Q27-1 -> 0 | Q27: 69182.504 | AG27: 59762.448 | AH27: =+(H27-AG27)/AG27 -> 0.157625 | AL27: 100518223 | AM27: 53862.424
A28: 100518223 | B28: HAMBURGUESA 30x2x106 GRS | C28: 7790360975065 | D28: =60*0.106 -> 6.36 | E28: 30 | F28: =+VLOOKUP(A28,$AL$4:$AM$110,2,FALSE) -> 53862.424 | H28: =+F28*(1-G28) -> 53862.424 | I28: =+H28/E28 -> 1795.4141 | J28: =+I28*J$3 -> 377.03697 | K28: =+I28+J28 -> 2172.4511 | L28: =+K28*L$3 -> 716.90886 | M28: =+K28+L28 -> 2889.36 | N28: =+M28*N$3 -> 1155.744 | O28: =+M28+N28 -> 4045.1039 | P28: =H28/Q28-1 -> 0 | Q28: 53862.424 | AG28: 46528.387 | AH28: =+(H28-AG28)/AG28 -> 0.157625
F29: =+VLOOKUP(A29,$AL$4:$AM$110,2,FALSE) -> #N/A | H29: =+F29*(1-G29) -> #N/A | I29: =+H29/E29 -> #N/A | P29: =H29/Q29-1 -> #N/A | Q29: #N/A | Y29: SEP | Z29: OCT | AB29: PATY VIENA | AC29: VIENISSIMA | AD29: PALADINI | AG29: #N/A | AH29: =+(H29-AG29)/AG29 -> #N/A | AL29: 100522204 | AM29: 26630.922
A30: 100022085 | B30: SALCHICHAS 24X6 SWIFT | C30: 7790360000132 | D30: 5.4 | E30: 24 | F30: =+VLOOKUP(A30,$AL$4:$AM$110,2,FALSE) -> #N/A | G30: 0.25 | H30: =+F30*(1-G30) -> #N/A | I30: =+H30/E30 -> #N/A | J30: =+I30*J$3 -> #N/A | K30: =+I30+J30 -> #N/A | L30: =+K30*L$3 -> #N/A | M30: =+K30+L30 -> #N/A | N30: =+M30*N$3 -> #N/A | O30: =+M30+N30 -> #N/A | P30: =H30/Q30-1 -> #N/A | Q30: 19973.192 | S30: Px LISTA: $2.500 + además compra 9 estuches + 2 de regalo ----> OFERTA $1.875 Público | Y30: 1700 | Z30: 1750 | AB30: 1890 | AC30: 2153 | AD30: 2208 | AG30: 18109.027 | AH30: =+(H30-AG30)/AG30 -> #N/A | AL30: 100522205 | AM30: 25299.376
A31: 100522204 | B31: SALCHICHAS 24X6 SWIFT | C31: 7790360983947 | D31: 5.4 | E31: 24 | F31: =+VLOOKUP(A31,$AL$4:$AM$110,2,FALSE) -> 26630.922 | G31: 0.25 | H31: =+F31*(1-G31) -> 19973.192 | I31: =+H31/E31 -> 832.21631 | J31: =+I31*J$3 -> 174.76543 | K31: =+I31+J31 -> 1006.9817 | L31: =+K31*L$3 -> 332.30397 | M31: =+K31+L31 -> 1339.2857 | N31: =+M31*N$3 -> 535.71429 | O31: =+M31+N31 -> 1875 | P31: =H31/Q31-1 -> 0 | Q31: 19973.192 | S31: Px LISTA: $2.500 + además compra 9 estuches + 2 de regalo ----> OFERTA $1.875 Público | AL31: 100516849 | AM31: 17895.98
A32: 100022072 | B32: SALCHICHAS 12X12 SWIFT | C32: 7790360024541 | D32: 5.4 | E32: 12 | F32: =+VLOOKUP(A32,$AL$4:$AM$110,2,FALSE) -> #N/A | G32: 0.2106 | H32: =+F32*(1-G32) -> #N/A | I32: =+H32/E32 -> #N/A | J32: =+I32*J$3 -> #N/A | K32: =+I32+J32 -> #N/A | L32: =+K32*0.30667 -> #N/A | M32: =+K32+L32 -> #N/A | N32: =+M32*N$3 -> #N/A | O32: =+M32+N32 -> #N/A | P32: =H32/Q32-1 -> #N/A | Q32: 18974.532 | S32: Conveniencia vs 22085: Oferta $3.500 | Y32: 3300 | Z32: 3350 | AG32: 17576.409 | AH32: =+(H32-AG32)/AG32 -> #N/A | AL32: 100522206 | AM32: 47623.273
A33: 100522205 | B33: SALCHICHAS 12X12 SWIFT | C33: 7790360983954 | D33: 5.4 | E33: 12 | F33: =+VLOOKUP(A33,$AL$4:$AM$110,2,FALSE) -> 25299.376 | G33: 0.2106 | H33: =+F33*(1-G33) -> 19971.327 | I33: =+H33/E33 -> 1664.2773 | J33: =+I33*J$3 -> 349.49823 | K33: =+I33+J33 -> 2013.7755 | L33: =+K33*0.31239 -> 629.08333 | M33: =+K33+L33 -> 2642.8588 | N33: =+M33*N$3 -> 1057.1435 | O33: =+M33+N33 -> 3700.0024 | P33: =H33/Q33-1 -> 0.052533333 | Q33: 18974.532 | S33: Conveniencia vs 22085: Oferta $3.700 | AL33: 100022058 | AM33: 15595.314
A34: 100516849 | B34: SALCHICHAS SIN PIEL 24X6 "SWIFT KIDS" X 190 g | C34: 7790360970053 | D34: 4.56 | E34: 24 | F34: =+VLOOKUP(A34,$AL$4:$AM$110,2,FALSE) -> 17895.98 | H34: =+F34*(1-G34) -> 17895.98 | I34: =+H34/E34 -> 745.66582 | J34: =+I34*J$3 -> 156.58982 | K34: =+I34+J34 -> 902.25564 | L34: =+K34*L$3 -> 297.74436 | M34: =+K34+L34 -> 1200 | N34: =+M34*N$3 -> 480 | O34: =+M34+N34 -> 1680 | P34: =H34/Q34-1 -> 0.12 | Q34: 15978.553 | S34: Oferta incluida en lista: $1.680 público | Y34: 1450 | Z34: 1500 | AA34: PATY FUN | AB34: 1534 | AG34: 15445.935 | AH34: =+(H34-AG34)/AG34 -> 0.15862069 | AL34: 100518151 | AM34: 58015.64
A35: 100022039 | B35: SALCHICHAS LARGAS 10 x 12 SWIFT INSTITUCIONAL | C35: 7790360007063 | D35: 8.7 | E35: 10 | F35: =+VLOOKUP(A35,$AL$4:$AM$110,2,FALSE) -> #N/A | H35: =+F35*(1-G35) -> #N/A | I35: =+H35/E35 -> #N/A | J35: =+I35*J$3 -> #N/A | K35: =+I35+J35 -> #N/A | L35: =+K35*L$3 -> #N/A | M35: =+K35+L35 -> #N/A | N35: =+M35*N$3 -> #N/A | O35: =+M35+N35 -> #N/A | P35: =H35/Q35-1 -> #N/A | Q35: 47623.273 | AB35: ICB | AC35: 66 | AD35: JET FOOD | AE35: PANCHIN | AG35: 40388.004 | AH35: =+(H35-AG35)/AG35 -> #N/A
A36: 100522206 | B36: SALCHICHAS LARGAS 10 x 12 SWIFT INSTITUCIONAL | C36: 7790360983961 | D36: 8.7 | E36: 10 | F36: =+VLOOKUP(A36,$AL$4:$AM$110,2,FALSE) -> 47623.273 | H36: =+F36*(1-G36) -> 47623.273 | I36: =+H36/E36 -> 4762.3273 | J36: =+I36*J$3 -> 1000.0887 | K36: =+I36+J36 -> 5762.416 | L36: =+K36*L$3 -> 1901.5973 | M36: =+K36+L36 -> 7664.0133 | N36: =+M36*N$3 -> 3065.6053 | O36: =+M36+N36 -> 10729.619 | Q36: 47623.273 | AL36: 100021000 | AM36: 12962.274
A37: 100022058 | B37: SALCHICHAS SIN PIEL "LA BLANCA" 24X6X190 Grs; | C37: 7790360026002 | D37: 4.56 | E37: 24 | F37: =+VLOOKUP(A37,$AL$4:$AM$110,2,FALSE) -> 15595.314 | H37: =+F37*(1-G37) -> 15595.314 | I37: =+H37/E37 -> 649.80474 | J37: =+I37*J$3 -> 136.459 | K37: =+I37+J37 -> 786.26374 | L37: =+K37*0.3 -> 235.87912 | M37: =+K37+L37 -> 1022.1429 | N37: =+M37*N$3 -> 408.85714 | O37: =+M37+N37 -> 1431 | P37: =H37/Q37-1 -> 0.06 | Q37: 14712.56 | Y37: 980 | Z37: =+Y37 -> 980 | AA37: MANTENMOS PX | AB37: 766 | AC37: 818 | AD37: 825 | AE37: 765 | AG37: 10439.321 | AH37: =+(H37-AG37)/AG37 -> 0.4939011 | AL37: 100021001 | AM37: 12962.274
A38: 100518151 | B38: SALCHICHAS LARGAS 10 x 12 x 870g | C38: 7790360974990 | D38: 8.7 | E38: 10 | F38: =+VLOOKUP(A38,$AL$4:$AM$110,2,FALSE) -> 58015.64 | H38: =+F38*(1-G38) -> 58015.64 | I38: =+H38/E38 -> 5801.564 | J38: =+I38*J$3 -> 1218.3284 | K38: =+I38+J38 -> 7019.8924 | L38: =+K38*0.3 -> 2105.9677 | M38: =+K38+L38 -> 9125.8601 | N38: =+M38*N$3 -> 3650.3441 | O38: =+M38+N38 -> 12776.204 | P38: =H38/Q38-1 -> 0 | Q38: 58015.64 | Y38: =+Y37*24 -> 23520 | AD38: 850 NUTRITE | AG38: 49201.488 | AH38: =+(H38-AG38)/AG38 -> 0.179144 | AL38: 100522277 | AM38: 12962.274
F39: =+VLOOKUP(A39,$AL$4:$AM$110,2,FALSE) -> #N/A | H39: =+F39*(1-G39) -> #N/A | I39: =+H39/E39 -> #N/A | J39: 0.21 | L39: 0.22 | N39: 0.35 | P39: =H39/Q39-1 -> #N/A | Q39: #N/A | Y39: =+Y38/1.21/1.33/1.4 -> 10439.321 | AA39: =+Z32*12 -> 40200 | AG39: #N/A | AH39: =+(H39-AG39)/AG39 -> #N/A | AL39: 100522333 | AM39: 12962.274
A40: 100021000 | B40: PATE DE FOIE 24X90G SWIFT | C40: 7790360720382 | D40: 2.16 | E40: 24 | F40: =+VLOOKUP(A40,$AL$4:$AM$110,2,FALSE) -> 12962.274 | H40: =+F40*(1-G40) -> 12962.274 | I40: =+H40/E40 -> 540.09474 | J40: =+I40*J$3 -> 113.41989 | K40: =+I40+J40 -> 653.51463 | L40: =+K40*L$39 -> 143.77322 | M40: =+K40+L40 -> 797.28785 | N40: =+M40*N$39 -> 279.05075 | O40: =+M40+N40 -> 1076.3386 | P40: =H40/Q40-1 -> 0.05 | Q40: 12345.023 | Y40: =+F37-Y39 -> 5155.9923 | AA40: =+AA39/1.21/1.33/1.4 -> 17842.718 | AG40: 10353.088 | AH40: =+(H40-AG40)/AG40 -> 0.25202 | AL40: 100021045 | AM40: 12962.274
A41: 100021001 | B41: PICADILLO DE CARNE 24X90G SWIFT | C41: 7790360720115 | D41: 2.16 | E41: 24 | F41: =+VLOOKUP(A41,$AL$4:$AM$110,2,FALSE) -> 12962.274 | H41: =+F41*(1-G41) -> 12962.274 | I41: =+H41/E41 -> 540.09474 | J41: =+I41*J$3 -> 113.41989 | K41: =+I41+J41 -> 653.51463 | L41: =+K41*L$39 -> 143.77322 | M41: =+K41+L41 -> 797.28785 | N41: =+M41*N$39 -> 279.05075 | O41: =+M41+N41 -> 1076.3386 | P41: =H41/Q41-1 -> 0.05 | Q41: 12345.023 | Y41: =+Y40/F37 -> 0.33061164 | AA41: =+F32-AA40 -> #N/A | AG41: 10353.088 | AH41: =+(H41-AG41)/AG41 -> 0.25202 | AL41: 100021004 | AM41: 12962.274
A42: 100522277 | B42: Picadillo de Carne Picante Chile Chipotle 24x90 g | D42: 2.16 | E42: 24 | F42: =+VLOOKUP(A42,$AL$4:$AM$110,2,FALSE) -> 12962.274 | H42: =+F42*(1-G42) -> 12962.274 | I42: =+H42/E42 -> 540.09474 | J42: =+I42*J$3 -> 113.41989 | K42: =+I42+J42 -> 653.51463 | L42: =+K42*L$39 -> 143.77322 | M42: =+K42+L42 -> 797.28785 | N42: =+M42*N$39 -> 279.05075 | O42: =+M42+N42 -> 1076.3386 | P42: =H42/Q42-1 -> 0.05 | Q42: 12345.023 | AL42: 100021006 | AM42: 12962.274
A43: 100522333 | B43: Pate de Foie Jalapeño 24x90 Swift | D43: 2.16 | E43: 24 | F43: =+VLOOKUP(A43,$AL$4:$AM$110,2,FALSE) -> 12962.274 | H43: =+F43*(1-G43) -> 12962.274 | I43: =+H43/E43 -> 540.09474 | J43: =+I43*J$3 -> 113.41989 | K43: =+I43+J43 -> 653.51463 | L43: =+K43*L$39 -> 143.77322 | M43: =+K43+L43 -> 797.28785 | N43: =+M43*N$39 -> 279.05075 | O43: =+M43+N43 -> 1076.3386 | P43: =H43/Q43-1 -> 0.05 | Q43: 12345.023 | AL43: 100021007 | AM43: 15499.255
A44: 100021045 | B44: PICADILLO DE CARNE PICANTE 24X90G SWIFT | C44: 7790360966582 | D44: 2.16 | E44: 24 | F44: =+VLOOKUP(A44,$AL$4:$AM$110,2,FALSE) -> 12962.274 | H44: =+F44*(1-G44) -> 12962.274 | I44: =+H44/E44 -> 540.09474 | J44: =+I44*J$3 -> 113.41989 | K44: =+I44+J44 -> 653.51463 | L44: =+K44*L$39 -> 143.77322 | M44: =+K44+L44 -> 797.28785 | N44: =+M44*N$39 -> 279.05075 | O44: =+M44+N44 -> 1076.3386 | P44: =H44/Q44-1 -> 0.05 | Q44: 12345.023 | AA44: =+AA41/F32 -> #N/A | AG44: 10088.4 | AH44: =+(H44-AG44)/AG44 -> 0.28486913 | AL44: 100021013 | AM44: 15499.255
A45: 100021004 | B45: PATE DE FOIE A LA CREMA 24X88G SWIFT | C45: 7790360964526 | D45: 2.112 | E45: 24 | F45: =+VLOOKUP(A45,$AL$4:$AM$110,2,FALSE) -> 12962.274 | H45: =+F45*(1-G45) -> 12962.274 | I45: =+H45/E45 -> 540.09474 | J45: =+I45*J$3 -> 113.41989 | K45: =+I45+J45 -> 653.51463 | L45: =+K45*L$39 -> 143.77322 | M45: =+K45+L45 -> 797.28785 | N45: =+M45*N$39 -> 279.05075 | O45: =+M45+N45 -> 1076.3386 | P45: =H45/Q45-1 -> 0.05 | Q45: 12345.023 | AG45: 10088.4 | AH45: =+(H45-AG45)/AG45 -> 0.28486913 | AL45: 100021014 | AM45: 15499.255
A46: 100021006 | B46: JAMON DEL DIABLO 24X88G SWIFT | C46: 7790360964557 | D46: 2.112 | E46: 24 | F46: =+VLOOKUP(A46,$AL$4:$AM$110,2,FALSE) -> 12962.274 | H46: =+F46*(1-G46) -> 12962.274 | I46: =+H46/E46 -> 540.09474 | J46: =+I46*J$3 -> 113.41989 | K46: =+I46+J46 -> 653.51463 | L46: =+K46*L$39 -> 143.77322 | M46: =+K46+L46 -> 797.28785 | N46: =+M46*N$39 -> 279.05075 | O46: =+M46+N46 -> 1076.3386 | P46: =H46/Q46-1 -> 0.05 | Q46: 12345.023 | AG46: 10088.4 | AH46: =+(H46-AG46)/AG46 -> 0.28486913 | AL46: 100021054 | AM46: 15499.255
A47: 100021007 | B47: PATE DE FOIE DE POLLO 24X85G SWIFT | C47: 7790360964540 | D47: 2.04 | E47: 24 | F47: =+VLOOKUP(A47,$AL$4:$AM$110,2,FALSE) -> 15499.255 | H47: =+F47*(1-G47) -> 15499.255 | I47: =+H47/E47 -> 645.80229 | J47: =+I47*J$3 -> 135.61848 | K47: =+I47+J47 -> 781.42077 | L47: =+K47*L$39 -> 171.91257 | M47: =+K47+L47 -> 953.33333 | N47: =+M47*N$39 -> 333.66667 | O47: =+M47+N47 -> 1287 | P47: =H47/Q47-1 -> 0.099827334 | Q47: 14092.444 | AG47: 11917.5 | AH47: =+(H47-AG47)/AG47 -> 0.30054582 | AL47: 100021055 | AM47: 15499.255
A48: 100021013 | B48: PATE DE FOIE TIPO PROVENZAL 24X85G SWIFT GOURMET | C48: 7790360965714 | D48: 2.04 | E48: 24 | F48: =+VLOOKUP(A48,$AL$4:$AM$110,2,FALSE) -> 15499.255 | H48: =+F48*(1-G48) -> 15499.255 | I48: =+H48/E48 -> 645.80229 | J48: =+I48*J$3 -> 135.61848 | K48: =+I48+J48 -> 781.42077 | L48: =+K48*L$39 -> 171.91257 | M48: =+K48+L48 -> 953.33333 | N48: =+M48*N$39 -> 333.66667 | O48: =+M48+N48 -> 1287 | P48: =H48/Q48-1 -> 0.099827334 | Q48: 14092.444 | AG48: 11917.5 | AH48: =+(H48-AG48)/AG48 -> 0.30054582 | AL48: 100021015 | AM48: 15499.255
A49: 100021014 | B49: PATE DE FOIE C/PIMIENTA VERDE 24X85G SWIFT GOURMET | C49: 7790360965721 | D49: 2.04 | E49: 24 | F49: =+VLOOKUP(A49,$AL$4:$AM$110,2,FALSE) -> 15499.255 | H49: =+F49*(1-G49) -> 15499.255 | I49: =+H49/E49 -> 645.80229 | J49: =+I49*J$3 -> 135.61848 | K49: =+I49+J49 -> 781.42077 | L49: =+K49*L$39 -> 171.91257 | M49: =+K49+L49 -> 953.33333 | N49: =+M49*N$39 -> 333.66667 | O49: =+M49+N49 -> 1287 | P49: =H49/Q49-1 -> 0.099827334 | Q49: 14092.444 | AG49: 11917.5 | AH49: =+(H49-AG49)/AG49 -> 0.30054582 | AL49: 100021008 | AM49: 10971.007
A50: 100021054 | B50: PATE JAMON AHUMADO 24X85G | C50: 7790360965707 | D50: 2.04 | E50: 24 | F50: =+VLOOKUP(A50,$AL$4:$AM$110,2,FALSE) -> 15499.255 | H50: =+F50*(1-G50) -> 15499.255 | I50: =+H50/E50 -> 645.80229 | J50: =+I50*J$3 -> 135.61848 | K50: =+I50+J50 -> 781.42077 | L50: =+K50*L$39 -> 171.91257 | M50: =+K50+L50 -> 953.33333 | N50: =+M50*N$39 -> 333.66667 | O50: =+M50+N50 -> 1287 | P50: =H50/Q50-1 -> 0.099827334 | Q50: 14092.444 | AG50: 11917.5 | AH50: =+(H50-AG50)/AG50 -> 0.30054582 | AL50: 100021009 | AM50: 10971.007
A51: 100021055 | B51: PATE HONGOS 24X85G | C51: 7790360965189 | D51: 2.04 | E51: 24 | F51: =+VLOOKUP(A51,$AL$4:$AM$110,2,FALSE) -> 15499.255 | H51: =+F51*(1-G51) -> 15499.255 | I51: =+H51/E51 -> 645.80229 | J51: =+I51*J$3 -> 135.61848 | K51: =+I51+J51 -> 781.42077 | L51: =+K51*L$39 -> 171.91257 | M51: =+K51+L51 -> 953.33333 | N51: =+M51*N$39 -> 333.66667 | O51: =+M51+N51 -> 1287 | P51: =H51/Q51-1 -> 0.099827334 | Q51: 14092.444 | AG51: 11917.5 | AH51: =+(H51-AG51)/AG51 -> 0.30054582 | AL51: 100021010 | AM51: 10971.007
A52: 100021015 | B52: PATE DE SALMON 24X85G SWIFT GOURMET | C52: 7790360965202 | D52: 2.04 | E52: 24 | F52: =+VLOOKUP(A52,$AL$4:$AM$110,2,FALSE) -> 15499.255 | H52: =+F52*(1-G52) -> 15499.255 | I52: =+H52/E52 -> 645.80229 | J52: =+I52*J$3 -> 135.61848 | K52: =+I52+J52 -> 781.42077 | L52: =+K52*L$39 -> 171.91257 | M52: =+K52+L52 -> 953.33333 | N52: =+M52*N$39 -> 333.66667 | O52: =+M52+N52 -> 1287 | P52: =H52/Q52-1 -> 0.099827334 | Q52: 14092.444 | AG52: 11917.5 | AH52: =+(H52-AG52)/AG52 -> 0.30054582 | AL52: 100021011 | AM52: 10971.007
A53: 100021008 | B53: PICADILLO DE CARNE 24X90G LA BLANCA | C53: 7790360720122 | D53: 2.16 | E53: 24 | F53: =+VLOOKUP(A53,$AL$4:$AM$110,2,FALSE) -> 10971.007 | H53: =+F53*(1-G53) -> 10971.007 | I53: =+H53/E53 -> 457.12529 | J53: =+I53*J$3 -> 95.996311 | K53: =+I53+J53 -> 553.1216 | L53: =+K53*0.2 -> 110.62432 | M53: =+K53+L53 -> 663.74592 | N53: =+M53*N$39 -> 232.31107 | O53: =+M53+N53 -> 896.05699 | P53: =H53/Q53-1 -> 0.05 | Q53: 10448.578 | AG53: 9046.3879 | AH53: =+(H53-AG53)/AG53 -> 0.21275
A54: 100021009 | B54: PATE DE FOIE 24X90G LA BLANCA | C54: 7790360965127 | D54: 2.16 | E54: 24 | F54: =+VLOOKUP(A54,$AL$4:$AM$110,2,FALSE) -> 10971.007 | H54: =+F54*(1-G54) -> 10971.007 | I54: =+H54/E54 -> 457.12529 | J54: =+I54*J$3 -> 95.996311 | K54: =+I54+J54 -> 553.1216 | L54: =+K54*0.2 -> 110.62432 | M54: =+K54+L54 -> 663.74592 | N54: =+M54*N$39 -> 232.31107 | O54: =+M54+N54 -> 896.05699 | P54: =H54/Q54-1 -> 0.05 | Q54: 10448.578 | AG54: 9046.3879 | AH54: =+(H54-AG54)/AG54 -> 0.21275 | AL54: 100516217 | AM54: 25505.374
A55: 100021010 | B55: PICADILLO DE CARNE 24X90G SAFRA | C55: 7790920008707 | D55: 2.16 | E55: 24 | F55: =+VLOOKUP(A55,$AL$4:$AM$110,2,FALSE) -> 10971.007 | H55: =+F55*(1-G55) -> 10971.007 | I55: =+H55/E55 -> 457.12529 | J55: =+I55*J$3 -> 95.996311 | K55: =+I55+J55 -> 553.1216 | L55: =+K55*L$39 -> 121.68675 | M55: =+K55+L55 -> 674.80835 | N55: =+M55*N$39 -> 236.18292 | O55: =+M55+N55 -> 910.99127 | P55: =H55/Q55-1 -> 0.05 | Q55: 10448.578 | AG55: 9046.3879 | AH55: =+(H55-AG55)/AG55 -> 0.21275 | AL55: 100516214 | AM55: 35312.916
A56: 100021011 | B56: PATE DE FOIE 24X90G SAFRA | C56: 7790920008714 | D56: 2.16 | E56: 24 | F56: =+VLOOKUP(A56,$AL$4:$AM$110,2,FALSE) -> 10971.007 | H56: =+F56*(1-G56) -> 10971.007 | I56: =+H56/E56 -> 457.12529 | J56: =+I56*J$3 -> 95.996311 | K56: =+I56+J56 -> 553.1216 | L56: =+K56*L$39 -> 121.68675 | M56: =+K56+L56 -> 674.80835 | N56: =+M56*N$39 -> 236.18292 | O56: =+M56+N56 -> 910.99127 | P56: =H56/Q56-1 -> 0.05 | Q56: 10448.578 | AG56: 9046.3879 | AH56: =+(H56-AG56)/AG56 -> 0.21275 | AL56: 100516215 | AM56: 35312.916
F57: =+VLOOKUP(A57,$AL$4:$AM$110,2,FALSE) -> #N/A | H57: =+F57*(1-G57) -> #N/A | I57: =+H57/E57 -> #N/A | P57: =H57/Q57-1 -> #N/A | Q57: #N/A | AG57: #N/A | AH57: =+(H57-AG57)/AG57 -> #N/A | AL57: 100516216 | AM57: 35312.916
A58: 100516217 | B58: MILANESAS DE SOJA CLASICAS PREFRITA | C58: 7790360967824 | D58: 5.8 | E58: 20 | F58: =+VLOOKUP(A58,$AL$4:$AM$110,2,FALSE) -> 25505.374 | H58: =+F58*(1-G58) -> 25505.374 | I58: =+H58/E58 -> 1275.2687 | J58: =+I58*J$3 -> 267.80643 | K58: =+I58+J58 -> 1543.0751 | L58: =+K58*0.3191 -> 492.39527 | M58: =+K58+L58 -> 2035.4704 | N58: =+M58*N$3 -> 814.18816 | O58: =+M58+N58 -> 2849.6586 | P58: =H58/Q58-1 -> 0.11111111 | Q58: 22954.837 | S58: Oferta neteada en lista $2.850 | AG58: 24041.261 | AH58: =+(H58-AG58)/AG58 -> 0.0609
A59: 100516214 | B59: MILANESAS DE SOJA RELLENAS CON JAMON Y QUESO | C59: 7790360967794 | D59: 7 | E59: 20 | F59: =+VLOOKUP(A59,$AL$4:$AM$110,2,FALSE) -> 35312.916 | H59: =+F59*(1-G59) -> 35312.916 | I59: =+H59/E59 -> 1765.6458 | J59: =+I59*J$3 -> 370.78562 | K59: =+I59+J59 -> 2136.4314 | L59: =+K59*0.304 -> 649.47515 | M59: =+K59+L59 -> 2785.9066 | N59: =+M59*N$3 -> 1114.3626 | O59: =+M59+N59 -> 3900.2692 | P59: =H59/Q59-1 -> -0.03 | Q59: 36405.068 | S59: Oferta neteada en lista $3.900 | AG59: 34315.268 | AH59: =+(H59-AG59)/AG59 -> 0.029073 | AL59: 100021704 | AM59: 36084.031
A60: 100516215 | B60: MILANESAS DE SOJA RELLENAS CON ESPINACA Y QUESO | C60: 7790360967800 | D60: 7 | E60: 20 | F60: =+VLOOKUP(A60,$AL$4:$AM$110,2,FALSE) -> 35312.916 | H60: =+F60*(1-G60) -> 35312.916 | I60: =+H60/E60 -> 1765.6458 | J60: =+I60*J$3 -> 370.78562 | K60: =+I60+J60 -> 2136.4314 | L60: =+K60*0.304 -> 649.47515 | M60: =+K60+L60 -> 2785.9066 | N60: =+M60*N$3 -> 1114.3626 | O60: =+M60+N60 -> 3900.2692 | P60: =H60/Q60-1 -> -0.03 | Q60: 36405.068 | S60: Oferta neteada en lista $3.900 | AG60: 34315.268 | AH60: =+(H60-AG60)/AG60 -> 0.029073 | AL60: 100021705 | AM60: 32473.212
A61: 100516216 | B61: MILANESAS DE SOJA RELLENAS CON TOMATE Y QUESO | C61: 7790360967817 | D61: 7 | E61: 20 | F61: =+VLOOKUP(A61,$AL$4:$AM$110,2,FALSE) -> 35312.916 | H61: =+F61*(1-G61) -> 35312.916 | I61: =+H61/E61 -> 1765.6458 | J61: =+I61*J$3 -> 370.78562 | K61: =+I61+J61 -> 2136.4314 | L61: =+K61*0.304 -> 649.47515 | M61: =+K61+L61 -> 2785.9066 | N61: =+M61*N$3 -> 1114.3626 | O61: =+M61+N61 -> 3900.2692 | P61: =H61/Q61-1 -> -0.03 | Q61: 36405.068 | S61: Oferta neteada en lista $3.900 | AG61: 34315.268 | AH61: =+(H61-AG61)/AG61 -> 0.029073 | AL61: 100021709 | AM61: 54740.252
F62: =+VLOOKUP(A62,$AL$4:$AM$110,2,FALSE) -> #N/A | H62: =+F62*(1-G62) -> #N/A | I62: =+H62/E62 -> #N/A | P62: =H62/Q62-1 -> #N/A | Q62: #N/A | AG62: #N/A | AH62: =+(H62-AG62)/AG62 -> #N/A | AL62: 100521357 | AM62: 44177.826
A63: 100021704 | B63: BOCADITOS DE CARNE "SWIFT" - 12x380g | C63: 7790360023902 | D63: =12*0.38 -> 4.56 | E63: 12 | F63: =+VLOOKUP(A63,$AL$4:$AM$110,2,FALSE) -> 36084.031 | H63: =+F63*(1-G63) -> 36084.031 | I63: =+H63/E63 -> 3007.0026 | J63: =+I63*J$3 -> 631.47055 | K63: =+I63+J63 -> 3638.4731 | L63: =+K63*L$3 -> 1200.6961 | M63: =+K63+L63 -> 4839.1693 | N63: =+M63*N$3 -> 1935.6677 | O63: =+M63+N63 -> 6774.837 | P63: =H63/Q63-1 -> 0 | Q63: 36084.031 | AG63: 34365.744 | AH63: =+(H63-AG63)/AG63 -> 0.05 | AL63: 100521358 | AM63: 66266.739
A64: 100021705 | B64: BOCADITOS DE POLLO "SWIFT" - 12x380g | C64: 7790360024336 | D64: =12*0.38 -> 4.56 | E64: 12 | F64: =+VLOOKUP(A64,$AL$4:$AM$110,2,FALSE) -> 32473.212 | H64: =+F64*(1-G64) -> 32473.212 | I64: =+H64/E64 -> 2706.101 | J64: =+I64*J$3 -> 568.28121 | K64: =+I64+J64 -> 3274.3822 | L64: =+K64*L$3 -> 1080.5461 | M64: =+K64+L64 -> 4354.9283 | N64: =+M64*N$3 -> 1741.9713 | O64: =+M64+N64 -> 6096.8996 | P64: =H64/Q64-1 -> #N/A | Q64: #N/A | AG64: 30926.868 | AH64: =+(H64-AG64)/AG64 -> 0.05 | AL64: 100522130 | AM64: 36420.087
A65: 100021709 | B65: BOCADITOS DE POLLO "SWIFT" - 10x760g | C65: 7790360024701 | D65: 7.6 | E65: 10 | F65: =+VLOOKUP(A65,$AL$4:$AM$110,2,FALSE) -> 54740.252 | H65: =+F65*(1-G65) -> 54740.252 | I65: =+H65/E65 -> 5474.0252 | J65: =+I65*J$3 -> 1149.5453 | K65: =+I65+J65 -> 6623.5705 | L65: =+K65*L$3 -> 2185.7783 | M65: =+K65+L65 -> 8809.3488 | N65: =+M65*N$3 -> 3523.7395 | O65: =+M65+N65 -> 12333.088 | P65: =H65/Q65-1 -> 0 | Q65: 54740.252 | Z65: SEPT | AG65: 43442.907 | AH65: =+(H65-AG65)/AG65 -> 0.2600504 | AL65: 100021725 | AM65: 27314.921
A66: 100521357 | B66: CRUNCHIES DE POLLO "SWIFT" - 12x380g | C66: 7790360982018 | D66: 4.56 | E66: 12 | F66: =+VLOOKUP(A66,$AL$4:$AM$110,2,FALSE) -> 44177.826 | G66: 0.33 | H66: =+F66*(1-G66) -> 29599.143 | I66: =+H66/E66 -> 2466.5953 | J66: =+I66*J$3 -> 517.98501 | K66: =+I66+J66 -> 2984.5803 | L66: =+K66*L$3 -> 984.9115 | M66: =+K66+L66 -> 3969.4918 | N66: =+M66*N$3 -> 1587.7967 | O66: =+M66+N66 -> 5557.2885 | P66: =H66/Q66-1 -> 0 | Q66: 29599.143 | S66: OFERTA INCORPORACION Compra 4 bolsa + 2 de regalo: 33% de dcto vía NC por cumplimiento mínimo de volumen. Si va en un solo pedido, pueder ir a px en factura. Objetivo informado en avance (por cliente, por sku) | AG66: 42074.12 | AL66: 100517055 | AM66: 27215.39
A67: 100521358 | B67: CRUNCHIES DE POLLO "SWIFT" - 10x760g | C67: 7790360982025 | D67: 7.6 | E67: 10 | F67: =+VLOOKUP(A67,$AL$4:$AM$110,2,FALSE) -> 66266.739 | G67: 0.33 | H67: =+F67*(1-G67) -> 44398.715 | I67: =+H67/E67 -> 4439.8715 | J67: =+I67*J$3 -> 932.37302 | K67: =+I67+J67 -> 5372.2445 | L67: =+K67*L$3 -> 1772.8407 | M67: =+K67+L67 -> 7145.0852 | N67: =+M67*N$3 -> 2858.0341 | O67: =+M67+N67 -> 10003.119 | P67: =H67/Q67-1 -> -0.33 | Q67: 66266.739 | S67: Oferta incorporación 3x2 | AA67: patitas | AB67: PALADINI | AG67: 63111.18 | AL67: 100517186 | AM67: 69116.127
A68: 100522130 | B68: BOCADITOS DE POLLO "SWIFT KIDS" - 12x400g | C68: 7790360982445 | D68: 4.8 | E68: 12 | F68: =+VLOOKUP(A68,$AL$4:$AM$110,2,FALSE) -> 36420.087 | H68: =+F68*(1-G68) -> 36420.087 | I68: =+H68/E68 -> 3035.0073 | J68: =+I68*J$3 -> 637.35152 | K68: =+I68+J68 -> 3672.3588 | L68: =+K68*L$3 -> 1211.8784 | M68: =+K68+L68 -> 4884.2372 | N68: =+M68*N$3 -> 1953.6949 | O68: =+M68+N68 -> 6837.9321 | P68: =H68/Q68-1 -> 0.05 | Q68: 34685.797 | Y68: 4000 | Z68: 4200 | AA68: 7900 | AB68: 4800 | AG68: 21304.738 | AL68: 100521663 | AM68: 39946.383
A69: 100021725 | B69: BOCADITOS DE POLLO GASTRONOMICOS "LA BLANCA" - x6kg | C69: 7790360027009 | D69: 6 | E69: 4 | F69: =+VLOOKUP(A69,$AL$4:$AM$110,2,FALSE) -> 27314.921 | H69: =+F69*(1-G69) -> 27314.921 | I69: =+H69/E69 -> 6828.7302 | J69: =+I69*J$3 -> 1434.0333 | K69: =+I69+J69 -> 8262.7635 | L69: =+K69*L$3 -> 2726.712 | M69: =+K69+L69 -> 10989.475 | N69: =+M69*N$3 -> 4395.7902 | O69: =+M69+N69 -> 15385.266 | P69: =H69/Q69-1 -> 0 | Q69: 27314.921 | AG69: 26014.21 | AH69: =+(H69-AG69)/AG69 -> 0.05 | AL69: 100021728 | AM69: 37847.095
A70: 100517055 | B70: PALITO DE POLLO "SWIFT" 12 X 260 Grs. | C70: 7790360971135 | D70: 3.12 | E70: 12 | F70: =+VLOOKUP(A70,$AL$4:$AM$110,2,FALSE) -> 27215.39 | H70: =+F70*(1-G70) -> 27215.39 | I70: =+H70/E70 -> 2267.9492 | J70: =+I70*J$3 -> 476.26933 | K70: =+I70+J70 -> 2744.2185 | L70: =+K70*L$3 -> 905.59211 | M70: =+K70+L70 -> 3649.8106 | N70: =+M70*N$3 -> 1459.9243 | O70: =+M70+N70 -> 5109.7349 | P70: =H70/Q70-1 -> 0 | Q70: 27215.39 | Z70: =+Z68*12 -> 50400 | AG70: 25919.419 | AH70: =+(H70-AG70)/AG70 -> 0.05 | AL70: 100517679 | AM70: 35830.538
A71: 100517186 | B71: PALITO DE POLLO "SWIFT" 8 X 1 Kg.. | C71: 7790360971395 | D71: 8 | E71: 8 | F71: =+VLOOKUP(A71,$AL$4:$AM$110,2,FALSE) -> 69116.127 | H71: =+F71*(1-G71) -> 69116.127 | I71: =+H71/E71 -> 8639.5159 | J71: =+I71*J$3 -> 1814.2983 | K71: =+I71+J71 -> 10453.814 | L71: =+K71*L$3 -> 3449.7587 | M71: =+K71+L71 -> 13903.573 | N71: =+M71*N$3 -> 5561.4292 | O71: =+M71+N71 -> 19465.002 | P71: =H71/Q71-1 -> 0 | Q71: 69116.127 | Z71: =+Z70/1.21/1.33/1.4 -> 22369.975 | AG71: 65824.883 | AH71: =+(H71-AG71)/AG71 -> 0.05
A72: 100521663 | B72: MILANESITAS DE CARNE "SWIFT" - 12x400g | C72: 7790360982537 | D72: 4.8 | E72: 12 | F72: 39946.383 | G72: 0.33 | H72: =+F72*(1-G72) -> 26764.077 | I72: =+H72/E72 -> 2230.3397 | J72: =+I72*J$3 -> 468.37134 | K72: =+I72+J72 -> 2698.7111 | L72: =+K72*0.323 -> 871.68367 | M72: =+K72+L72 -> 3570.3947 | N72: =+M72*N$3 -> 1428.1579 | O72: =+M72+N72 -> 4998.5526 | P72: =H72/Q72-1 -> 0 | Q72: 26764.077 | S72: OFERTA INCORPORACION Compra 4 bolsa + 2 de regalo: 33% de dcto vía NC por cumplimiento mínimo de volumen. Si va en un solo pedido, pueder ir a px en factura. Objetivo informado en avance (por cliente, por sku) | Z72: =+F68-Z71 -> 14050.113 | AG72: 42746.88 | AL72: 100516219 | AM72: 16599.454
A73: 100021728 | B73: MEDALLONES DE POLLO "SWIFT" - 12x4x80g | C73: 7790360967558 | D73: 3.84 | E73: 12 | F73: =+VLOOKUP(A73,$AL$4:$AM$110,2,FALSE) -> 37847.095 | H73: =+F73*(1-G73) -> 37847.095 | I73: =+H73/E73 -> 3153.9245 | J73: =+I73*J$3 -> 662.32415 | K73: =+I73+J73 -> 3816.2487 | L73: =+K73*L$3 -> 1259.3621 | M73: =+K73+L73 -> 5075.6108 | N73: =+M73*N$3 -> 2030.2443 | O73: =+M73+N73 -> 7105.8551 | P73: =H73/Q73-1 -> 0 | Q73: 37847.095 | Z73: =+Z72/F68 -> 0.38577921 | AG73: 36044.852 | AH73: =+(H73-AG73)/AG73 -> 0.05 | AL73: 100516220 | AM73: 17830.838
A74: 100517679 | B74: MEDALLONES DE POLLO GASTRONÓMICO 8x12x80 Grs. | C74: 7790360973498 | D74: 7.68 | E74: 8 | F74: =+VLOOKUP(A74,$AL$4:$AM$110,2,FALSE) -> 35830.538 | H74: =+F74*(1-G74) -> 35830.538 | I74: =+H74/E74 -> 4478.8173 | J74: =+I74*J$3 -> 940.55163 | K74: =+I74+J74 -> 5419.3689 | L74: =+K74*L$3 -> 1788.3918 | M74: =+K74+L74 -> 7207.7607 | N74: =+M74*N$3 -> 2883.1043 | O74: =+M74+N74 -> 10090.865 | P74: =H74/Q74-1 -> 0 | Q74: 35830.538 | AG74: 34124.322 | AH74: =+(H74-AG74)/AG74 -> 0.05 | AM74: 0
F75: =+VLOOKUP(A75,$AL$4:$AM$110,2,FALSE) -> #N/A | H75: =+F75*(1-G75) -> #N/A | I75: =+H75/E75 -> #N/A | P75: =H75/Q75-1 -> #N/A | Q75: #N/A | AG75: #N/A | AH75: =+(H75-AG75)/AG75 -> #N/A | AL75: 100518158 | AM75: 72003.355
A76: 100516219 | B76: PAPAS PREFRITAS SUPERCONGELADAS 25x400gr | C76: 7790360967770 | D76: 10 | E76: 25 | F76: =+VLOOKUP(A76,$AL$4:$AM$110,2,FALSE) -> 16599.454 | H76: =+F76*(1-G76) -> 16599.454 | I76: =+H76/E76 -> 663.97818 | J76: =+I76*J$3 -> 139.43542 | K76: =+I76+J76 -> 803.4136 | L76: =+K76*L$3 -> 265.12649 | M76: =+K76+L76 -> 1068.5401 | N76: =+M76*N$3 -> 427.41603 | O76: =+M76+N76 -> 1495.9561 | P76: =H76/Q76-1 -> 0 | Q76: 16599.454 | AG76: 16599.454 | AH76: =+(H76-AG76)/AG76 -> 0 | AL76: 100518160 | AM76: 72003.355
A77: 100516220 | B77: PAPAS PREFRITAS SUPERCONGELADAS 6x2000gr | C77: 7790360967787 | D77: 12 | E77: 6 | F77: =+VLOOKUP(A77,$AL$4:$AM$110,2,FALSE) -> 17830.838 | H77: =+F77*(1-G77) -> 17830.838 | I77: =+H77/E77 -> 2971.8063 | J77: =+I77*J$3 -> 624.07933 | K77: =+I77+J77 -> 3595.8857 | L77: =+K77*L$3 -> 1186.6423 | M77: =+K77+L77 -> 4782.5279 | N77: =+M77*N$3 -> 1913.0112 | O77: =+M77+N77 -> 6695.5391 | P77: =H77/Q77-1 -> 0 | Q77: 17830.838 | AG77: 17830.838 | AH77: =+(H77-AG77)/AG77 -> 0 | AL77: 100518463 | AM77: 33357.516
F78: =+VLOOKUP(A78,$AL$4:$AM$110,2,FALSE) -> #N/A | H78: =+F78*(1-G78) -> #N/A | I78: =+H78/E78 -> #N/A | P78: =H78/Q78-1 -> #N/A | Q78: #N/A | AG78: #N/A | AH78: =+(H78-AG78)/AG78 -> #N/A
A79: 100518158 | B79: MILANESA DE CARNE VACUNA CONGELADA 24un x 500grs | C79: 7790360974280 | D79: 12 | E79: 24 | F79: =+VLOOKUP(A79,$AL$4:$AM$110,2,FALSE) -> 72003.355 | H79: =+F79*(1-G79) -> 72003.355 | I79: =+H79/E79 -> 3000.1398 | J79: =+I79*J$3 -> 630.02936 | K79: =+I79+J79 -> 3630.1692 | L79: =+K79*L$3 -> 1197.9558 | M79: =+K79+L79 -> 4828.125 | N79: =+M79*N$3 -> 1931.25 | O79: =+M79+N79 -> 6759.375 | P79: =H79/Q79-1 -> 0 | Q79: 72003.355 | AG79: 72003.355 | AH79: =+(H79-AG79)/AG79 -> 0 | AL79: 100518291 | AM79: 13957.609
A80: 100518160 | B80: MILANESA DE CARNE VACUNA CONGELADA 12un x 1000grs | C80: 7790360974686 | D80: 12 | E80: 12 | F80: =+VLOOKUP(A80,$AL$4:$AM$110,2,FALSE) -> 72003.355 | H80: =+F80*(1-G80) -> 72003.355 | I80: =+H80/E80 -> 6000.2796 | J80: =+I80*J$3 -> 1260.0587 | K80: =+I80+J80 -> 7260.3383 | L80: =+K80*L$3 -> 2395.9117 | M80: =+K80+L80 -> 9656.25 | N80: =+M80*N$3 -> 3862.5 | O80: =+M80+N80 -> 13518.75 | P80: =H80/Q80-1 -> 0 | Q80: 72003.355 | AG80: 72003.355 | AH80: =+(H80-AG80)/AG80 -> 0 | AL80: 100518292 | AM80: 32934.976
A81: 100518463 | B81: MILANESAS DE CARNE VACUNA CONG GRANEL 5 kg | C81: 7790360975188 | D81: 5 | E81: 1 | F81: =+VLOOKUP(A81,$AL$4:$AM$110,2,FALSE) -> 33357.516 | H81: =+F81*(1-G81) -> 33357.516 | I81: =+H81/E81 -> 33357.516 | J81: =+I81*J$3 -> 7005.0783 | K81: =+I81+J81 -> 40362.594 | L81: =+K81*L$3 -> 13319.656 | M81: =+K81+L81 -> 53682.25 | N81: =+M81*N$3 -> 21472.9 | O81: =+M81+N81 -> 75155.15 | P81: =H81/Q81-1 -> 0 | Q81: 33357.516 | AG81: 33357.516 | AH81: =+(H81-AG81)/AG81 -> 0
F82: =+VLOOKUP(A82,$AL$4:$AM$110,2,FALSE) -> #N/A | H82: =+F82*(1-G82) -> #N/A | I82: =+H82/E82 -> #N/A | P82: =H82/Q82-1 -> #N/A | Q82: #N/A | AG82: #N/A | AH82: =+(H82-AG82)/AG82 -> #N/A | AL82: 100517915 | AM82: 145920.01
A83: 100518291 | B83: GRASA VACUNA REFINADA SWIFT 10 X 500 | C83: 7790360975195 | D83: 5 | E83: 10 | F83: =+VLOOKUP(A83,$AL$4:$AM$110,2,FALSE) -> 13957.609 | H83: =+F83*(1-G83) -> 13957.609 | I83: =+H83/E83 -> 1395.7609 | J83: =+I83*J$3 -> 293.10978 | K83: =+I83+J83 -> 1688.8706 | L83: =+K83*L$39 -> 371.55154 | M83: =+K83+L83 -> 2060.4222 | N83: =+M83*N$39 -> 721.14776 | O83: =+M83+N83 -> 2781.5699 | P83: =H83/Q83-1 -> 0.03 | Q83: 13551.076 | S83: Oferta a px en factura neteada en lista, para $2.780 público | AG83: 13551.076 | AH83: =+(H83-AG83)/AG83 -> 0.03 | AL83: 100517914 | AM83: 159231.16
A84: 100518292 | B84: GRASA VACUNA REFINADA SWIFT 12x1Kg | C84: 7790360975201 | D84: 12 | E84: 12 | F84: =+VLOOKUP(A84,$AL$4:$AM$110,2,FALSE) -> 32934.976 | H84: =+F84*(1-G84) -> 32934.976 | I84: =+H84/E84 -> 2744.5813 | J84: =+I84*J$3 -> 576.36208 | K84: =+I84+J84 -> 3320.9434 | L84: =+K84*L$39 -> 730.60755 | M84: =+K84+L84 -> 4051.5509 | N84: =+M84*N$39 -> 1418.0428 | O84: =+M84+N84 -> 5469.5938 | P84: =H84/Q84-1 -> 0.03 | Q84: 31975.705 | S84: Oferta a px en factura neteada en lista, para $5.470 público | AG84: 31975.705 | AH84: =+(H84-AG84)/AG84 -> 0.03
F85: =+VLOOKUP(A85,$AL$4:$AM$110,2,FALSE) -> #N/A | H85: =+F85*(1-G85) -> #N/A | I85: =+H85/E85 -> #N/A | J85: 0.105 | L85: 0.3 | N85: 0.4 | P85: =H85/Q85-1 -> #N/A | Q85: #N/A | AG85: #N/A | AH85: =+(H85-AG85)/AG85 -> #N/A | AL85: 100010689 | AM85: 15000
A86: 100517915 | B86: CARNE PICADA CONGELADA 36 UN X 500 g SWIFT | C86: 7790360974020 | D86: 18 | E86: 36 | F86: =+VLOOKUP(A86,$AL$4:$AM$110,2,FALSE) -> 145920.01 | H86: =+F86*(1-G86) -> 145920.01 | I86: =+H86/E86 -> 4053.3336 | J86: =+I86*J$85 -> 425.60003 | K86: =+I86+J86 -> 4478.9337 | L86: =+K86*L$85 -> 1343.6801 | M86: =+K86+L86 -> 5822.6138 | N86: =+M86*N$85 -> 2329.0455 | O86: =+M86+N86 -> 8151.6593 | P86: =H86/Q86-1 -> 0 | Q86: 145920.01 | AG86: 126062.63 | AH86: =+(H86-AG86)/AG86 -> 0.15752 | AL86: 100518335 | AM86: 10714.286
A87: 100517914 | B87: CARNE PICADA CONGELADA 20 UN X 1 kg SWIFT | C87: 7790360974037 | D87: 20 | E87: 20 | F87: =+VLOOKUP(A87,$AL$4:$AM$110,2,FALSE) -> 159231.16 | H87: =+F87*(1-G87) -> 159231.16 | I87: =+H87/E87 -> 7961.5579 | J87: =+I87*J$85 -> 835.96358 | K87: =+I87+J87 -> 8797.5215 | L87: =+K87*L$85 -> 2639.2565 | M87: =+K87+L87 -> 11436.778 | N87: =+M87*N$85 -> 4574.7112 | O87: =+M87+N87 -> 16011.489 | P87: =H87/Q87-1 -> 0 | Q87: 159231.16 | AG87: 137562.34 | AH87: =+(H87-AG87)/AG87 -> 0.15752 | AL87: 100518332 | AM87: 12321.429
F88: =+VLOOKUP(A88,$AL$4:$AM$110,2,FALSE) -> #N/A | H88: =+F88*(1-G88) -> #N/A | J88: 0.105 | L88: 0.3 | N88: 0.4 | P88: =H88/Q88-1 -> #N/A | Q88: #N/A | AG88: #N/A | AH88: =+(H88-AG88)/AG88 -> #N/A | AL88: 100518334 | AM88: 10928.571
A89: 100010689 | B89: ENTRAÑA FINA ENF SWIFT | D89: 22 | E89: 1 | F89: =+VLOOKUP(A89,$AL$4:$AM$110,2,FALSE) -> 15000 | H89: =+F89*(1-G89) -> 15000 | I89: =+H89/E89 -> 15000 | J89: =+I89*J$88 -> 1575 | K89: =+I89+J89 -> 16575 | L89: =+K89*L$88 -> 4972.5 | M89: =+K89+L89 -> 21547.5 | N89: =+M89*N$88 -> 8619 | O89: =+M89+N89 -> 30166.5 | P89: =H89/Q89-1 -> 0.05 | Q89: 14285.714 | AG89: 14255.102 | AH89: =+(H89-AG89)/AG89 -> 0.052254832 | AL89: 100518227 | AM89: 12895.714
A90: 100518335 | B90: ROAST BEEF EN PORCIONES ENF SWIFT (L) | D90: 22.5 | E90: 1 | F90: =+VLOOKUP(A90,$AL$4:$AM$110,2,FALSE) -> 10714.286 | H90: =+F90*(1-G90) -> 10714.286 | I90: =+H90/E90 -> 10714.286 | J90: =+I90*J$88 -> 1125 | K90: =+I90+J90 -> 11839.286 | L90: =+K90*L$88 -> 3551.7857 | M90: =+K90+L90 -> 15391.071 | N90: =+M90*N$88 -> 6156.4286 | O90: =+M90+N90 -> 21547.5 | P90: =H90/Q90-1 -> 0.05 | Q90: 10204.082 | AG90: 9029.5918 | AH90: =+(H90-AG90)/AG90 -> 0.18657475
A91: 100518332 | B91: CARNAZA CUADRADA EN PORCIONES ENF SWIFT (L) | D91: 21.5 | E91: 1 | F91: =+VLOOKUP(A91,$AL$4:$AM$110,2,FALSE) -> 12321.429 | H91: =+F91*(1-G91) -> 12321.429 | I91: =+H91/E91 -> 12321.429 | J91: =+I91*J$88 -> 1293.75 | K91: =+I91+J91 -> 13615.179 | L91: =+K91*L$88 -> 4084.5536 | M91: =+K91+L91 -> 17699.732 | N91: =+M91*N$88 -> 7079.8929 | O91: =+M91+N91 -> 24779.625 | P91: =H91/Q91-1 -> 0.05 | Q91: 11734.694 | AG91: 9717.3469 | AH91: =+(H91-AG91)/AG91 -> 0.26798278 | AL91: 100520837 | AM91: 33805.839
A92: 100518334 | B92: TAPA DE ASADO EN PORCIONES ENF SWIFT (L) | D92: 22.5 | E92: 1 | F92: =+VLOOKUP(A92,$AL$4:$AM$110,2,FALSE) -> 10928.571 | H92: =+F92*(1-G92) -> 10928.571 | I92: =+H92/E92 -> 10928.571 | J92: =+I92*J$88 -> 1147.5 | K92: =+I92+J92 -> 12076.071 | L92: =+K92*L$88 -> 3622.8214 | M92: =+K92+L92 -> 15698.893 | N92: =+M92*N$88 -> 6279.5571 | O92: =+M92+N92 -> 21978.45 | P92: =H92/Q92-1 -> 0.05 | Q92: 10408.163 | Z92: =+Y96*24+Y4*144 -> 602750.59 | AG92: 7997.9592 | AH92: =+(H92-AG92)/AG92 -> 0.36642001 | AL92: 100522395 | AM92: 34481.949
A93: 100518227 | B93: VACIO EN PORCIONES NOV ENFRIADO PARA VENTA LOCAL (L) | D93: 22.5 | E93: 1 | F93: =+VLOOKUP(A93,$AL$4:$AM$110,2,FALSE) -> 12895.714 | H93: =+F93*(1-G93) -> 12895.714 | I93: =+H93/E93 -> 12895.714 | J93: =+I93*J$88 -> 1354.05 | K93: =+I93+J93 -> 14249.764 | L93: =+K93*L$88 -> 4274.9293 | M93: =+K93+L93 -> 18524.694 | N93: =+M93*N$88 -> 7409.8774 | O93: =+M93+N93 -> 25934.571 | P93: =H93/Q93-1 -> 0.071 | Q93: 12040.816 | Z93: =+Y100*72+Y4*144 -> 712427.41 | AG93: 7997.9592 | AH93: =+(H93-AG93)/AG93 -> 0.61237561 | AL93: 100522561 | AM93: 6824.5524
A94: 100027726 | B94: BONDIOLA DE CERDO CONGELADA | D94: 22.5 | E94: 1 | F94: =+VLOOKUP(A94,$AL$4:$AM$110,2,FALSE) -> #N/A | H94: =+F94*(1-G94) -> #N/A | I94: =+H94/E94 -> #N/A | J94: =+I94*J$88 -> #N/A | K94: =+I94+J94 -> #N/A | L94: =+K94*L$88 -> #N/A | M94: =+K94+L94 -> #N/A | N94: =+M94*N$88 -> #N/A | O94: =+M94+N94 -> #N/A | P94: =H94/Q94-1 -> #N/A | Q94: 6195
F95: =+VLOOKUP(A95,$AL$4:$AM$110,2,FALSE) -> #N/A | H95: =+F95*(1-G95) -> #N/A | J95: 0.21 | L95: 0.3 | N95: 0.4 | P95: =H95/Q95-1 -> #N/A | Q95: #N/A | AG95: #N/A | AH95: =+(H95-AG95)/AG95 -> #N/A | AL95: 100520902 | AM95: 30287.434
A96: 100520837 | B96: CHORIZOS FRESCOS DE CERDO LIBRE DE GLUTEN | C96: 7790360980625 | D96: 4.8 | E96: 12 | F96: =+VLOOKUP(A96,$AL$4:$AM$110,2,FALSE) -> 33805.839 | H96: =+F96*(1-G96) -> 33805.839 | I96: =+H96/E96 -> 2817.1532 | J96: =+I96*J$95 -> 591.60218 | K96: =+I96+J96 -> 3408.7554 | L96: =+K96*L$95 -> 1022.6266 | M96: =+K96+L96 -> 4431.382 | N96: =+M96*N$95 -> 1772.5528 | O96: =+M96+N96 -> 6203.9348 | P96: =H96/Q96-1 -> 0.04 | Q96: 32505.614 | Y96: =+F96*0.1 -> 3380.5839 | Z96: 0.1 | AA96: =+H96*(1-Z96) -> 30425.255 | AB96: =+AA96/E96 -> 2535.4379 | AC96: =+AB96*1.21*1.3*1.4 -> 5583.5413 | AD96: VER CUPOS | AE96: Con la compra de 1 caja de 21632 + 2 unidades de Chorizos --> 10% de dcto en ambos SKU | AG96: 30957.728 | AH96: =+(H96-AG96)/AG96 -> 0.092 | AL96: 100522698 | AM96: 38836.761
A97: 100522395 | B97: CHORIZOS FRESCOS DE CERDO CONGELADOS LIBRE DE GLUTEN 12u x 400g | C97: 7790360980625 | D97: 4.8 | E97: 12 | F97: =+VLOOKUP(A97,$AL$4:$AM$110,2,FALSE) -> 34481.949 | G97: 0.33 | H97: =+F97*(1-G97) -> 23102.906 | I97: =+H97/E97 -> 1925.2421 | J97: =+I97*J$95 -> 404.30085 | K97: =+I97+J97 -> 2329.543 | L97: =+K97*L$95 -> 698.8629 | M97: =+K97+L97 -> 3028.4059 | N97: =+M97*N$95 -> 1211.3624 | O97: =+M97+N97 -> 4239.7682 | Q97: 33155.72 | S97: Dinámica 2+1. Compra 2, recibe 3 ----> oferta $4.240 (para distribuidores, vía NC, por cumplimiento de objetivo. Si compra en un solo pedido puede ir a px factura. Objetivo informado en avance por cliente, por sku)
A98: 100522561 | B98: CHORIZOS CONGELADOS DE CERDO LIBRE DE GLUTEN SWIFT GRANEL | D98: 16 | E98: 8 | F98: =+VLOOKUP(A98,$AL$4:$AM$110,2,FALSE) -> 6824.5524 | G98: 0.33 | H98: =+F98*(1-G98) -> 4572.4501 | I98: =+H98*2 -> 9144.9002 | J98: =+I98*J$95 -> 1920.429 | K98: =+I98+J98 -> 11065.329 | L98: =+K98*L$95 -> 3319.5988 | M98: =+K98+L98 -> 14384.928 | N98: =+M98*N$95 -> 5753.9712 | O98: =+M98+N98 -> 20138.899 | Q98: #N/A | S98: Dinámica 2+1. Compra 2, recibe 3 ----> oferta $20.140 los 20 chori (2kg aprox) (para distribuidores, vía NC, por cumplimiento de objetivo. Si compra en un solo pedido puede ir a px factura. Objetivo informado en avance por cliente, por sku) | AL98: 100521457 | AM98: 34485.722
F99: =+VLOOKUP(A99,$AL$4:$AM$110,2,FALSE) -> #N/A | H99: =+F99*(1-G99) -> #N/A | J99: 0.21 | L99: 0.33 | N99: 0.4 | P99: =H99/Q99-1 -> #N/A | Q99: #N/A | AG99: #N/A | AH99: =+(H99-AG99)/AG99 -> #N/A | AL99: 100521455 | AM99: 34485.722
A100: 100520902 | B100: PAPAS PRE COCIDAS SUPERCONGELADAS LIBRES DE GLUTEN 700G | C100: 7790360981042 | D100: 9.8 | E100: 14 | F100: =+VLOOKUP(A100,$AL$4:$AM$110,2,FALSE) -> 30287.434 | G100: 0.125 | H100: =+F100*(1-G100) -> 26501.504 | I100: =+H100/E100 -> 1892.9646 | J100: =+I100*J$99 -> 397.52257 | K100: =+I100+J100 -> 2290.4872 | L100: =+K100*L$99 -> 755.86076 | M100: =+K100+L100 -> 3046.3479 | N100: =+M100*N$99 -> 1218.5392 | O100: =+M100+N100 -> 4264.8871 | P100: =H100/Q100-1 -> 0.03 | Q100: 25729.616 | S100: OFERTA compra 7 bolsas , recibe 8. | Y100: =+H100*0.1 -> 2650.1504 | Z100: 0.1 | AA100: =+H100*(1-Z100) -> 23851.354 | AB100: =+AA100/E100 -> 1703.6681 | AC100: =+AB100*1.21*1.3*1.4 -> 3751.818 | AD100: VER CUPOS | AE100: Con la compra de 1 caja de 21632 + 7 unidades de PAPAS --> 10% de dcto en ambos SKU | AG100: 25729.616 | AH100: =+(H100-AG100)/AG100 -> 0.03 | AL100: 100521453 | AM100: 33300.276
...

Sheet Sub Litoral
B2: Código | C2: Descripción | D2: EAN | E2: Kg. x Caja | F2: Cant. X Caja | G2: Precio de Lista | H2: Dcto | I2: Precio de factura | J2: Precio Neto estuche en factura | K2: IVA | L2: Px Unitario IVA Inc | M2: M-up Dx | N2: Px Unitario Minorista | O2: M-up Minorista | P2: Px Unitario Público | R2: PX MAYO
K3: 0.21 | M3: 0.3 | O3: 0.4
B4: 100021632 | C4: HAMBURGUESAS 30x160g CLASICA x2 SWIFT | D4: 7790360026606 | E4: 4.8 | F4: 30 | G4: =+VLOOKUP(B4,$T$4:$U$106,2,FALSE) -> 44287.96 | I4: =+G4*(1-H4) -> 44287.96 | J4: =+I4/F4 -> 1476.2653 | K4: =+J4*K$3 -> 310.01572 | L4: =+J4+K4 -> 1786.2811 | M4: =+L4*M$3 -> 535.88432 | N4: =+L4+M4 -> 2322.1654 | O4: =+N4*O$3 -> 928.86615 | P4: =+N4+O4 -> 3251.0315 | R4: 42179.01 | S4: =+(I4-R4)/R4 -> 0.05 | T4: 100021632 | U4: 44287.96
B5: 100021652 | C5: HAMBURGUESA 18X4X80G CLASICA SWIFT | D5: 7790360026576 | E5: 5.76 | F5: 18 | G5: =+VLOOKUP(B5,$T$4:$U$106,2,FALSE) -> 55853.43 | I5: =+G5*(1-H5) -> 55853.43 | J5: =+I5/F5 -> 3102.9683 | K5: =+J5*K$3 -> 651.62334 | L5: =+J5+K5 -> 3754.5917 | M5: =+L5*M$3 -> 1126.3775 | N5: =+L5+M5 -> 4880.9691 | O5: =+N5*O$3 -> 1952.3877 | P5: =+N5+O5 -> 6833.3568 | R5: 50775.845 | S5: =+(I5-R5)/R5 -> 0.1 | T5: 100021652 | U5: 55853.43
B6: 100021631 | C6: HAMBURGUESA 8X12X80G CLASICA SWIFT | D6: 7790360026590 | E6: 7.68 | F6: 8 | G6: =+VLOOKUP(B6,$T$4:$U$106,2,FALSE) -> 70798.249 | I6: =+G6*(1-H6) -> 70798.249 | J6: =+I6/F6 -> 8849.7811 | K6: =+J6*K$3 -> 1858.454 | L6: =+J6+K6 -> 10708.235 | M6: =+L6*M$3 -> 3212.4705 | N6: =+L6+M6 -> 13920.706 | O6: =+N6*O$3 -> 5568.2823 | P6: =+N6+O6 -> 19488.988 | R6: 64362.044 | S6: =+(I6-R6)/R6 -> 0.1 | T6: 100021631 | U6: 70798.249
B7: 100021630 | C7: HAMBURGUESA 6X20X80G CLASICA SWIFT | D7: 7790360026583 | E7: 9.6 | F7: 6 | G7: =+VLOOKUP(B7,$T$4:$U$106,2,FALSE) -> 86779.407 | I7: =+G7*(1-H7) -> 86779.407 | J7: =+I7/F7 -> 14463.234 | K7: =+J7*K$3 -> 3037.2792 | L7: =+J7+K7 -> 17500.514 | M7: =+L7*M$3 -> 5250.1541 | N7: =+L7+M7 -> 22750.668 | O7: =+N7*O$3 -> 9100.2671 | P7: =+N7+O7 -> 31850.935 | R7: 78890.37 | S7: =+(I7-R7)/R7 -> 0.1 | T7: 100021630 | U7: 86779.407
B8: 100021653 | C8: MEDALLON 18X4X80G PARRILLERO SWIFT | D8: 7790360026682 | E8: 5.76 | F8: 18 | G8: =+VLOOKUP(B8,$T$4:$U$106,2,FALSE) -> 55676.293 | I8: =+G8*(1-H8) -> 55676.293 | J8: =+I8/F8 -> 3093.1274 | K8: =+J8*K$3 -> 649.55675 | L8: =+J8+K8 -> 3742.6841 | M8: =+L8*M$3 -> 1122.8052 | N8: =+L8+M8 -> 4865.4894 | O8: =+N8*O$3 -> 1946.1957 | P8: =+N8+O8 -> 6811.6851 | R8: 55676.293 | S8: =+(I8-R8)/R8 -> 0 | T8: 100021653 | U8: 55676.293
B9: 100516169 | C9: MEDALLONES 18X4X80G SWIFT RECETA ESPECIAL | D9: 7790360967961 | E9: 5.76 | F9: 18 | G9: =+VLOOKUP(B9,$T$4:$U$106,2,FALSE) -> 51337.272 | I9: =+G9*(1-H9) -> 51337.272 | J9: =+I9/F9 -> 2852.0707 | K9: =+J9*K$3 -> 598.93484 | L9: =+J9+K9 -> 3451.0055 | M9: =+L9*M$3 -> 1035.3017 | N9: =+L9+M9 -> 4486.3072 | O9: =+N9*O$3 -> 1794.5229 | P9: =+N9+O9 -> 6280.83 | R9: 51337.272 | S9: =+(I9-R9)/R9 -> 0 | T9: 100516169 | U9: 51337.272
B10: 100520337 | C10: MEDALLON BURGER SWIFT MEGA 30 x 160 g | D10: 7790360977960 | E10: 4.8 | F10: 30 | G10: =+VLOOKUP(B10,$T$4:$U$106,2,FALSE) -> 31314.663 | I10: =+G10*(1-H10) -> 31314.663 | J10: =+I10/F10 -> 1043.8221 | K10: =+J10*K$3 -> 219.20264 | L10: =+J10+K10 -> 1263.0248 | M10: =+L10*M$3 -> 378.90743 | N10: =+L10+M10 -> 1641.9322 | O10: =+N10*O$3 -> 656.77288 | P10: =+N10+O10 -> 2298.7051 | R10: 29823.489 | S10: =+(I10-R10)/R10 -> 0.05 | T10: 100516170 | U10: 0
B11: 100021503 | C11: Medallón CAJITA 12x4 69 grs | D11: 7790360966841 | E11: 3.312 | F11: 12 | G11: =+VLOOKUP(B11,$T$4:$U$106,2,FALSE) -> 23909.555 | I11: =+G11*(1-H11) -> 23909.555 | J11: =+I11/F11 -> 1992.4629 | K11: =+J11*K$3 -> 418.41721 | L11: =+J11+K11 -> 2410.8801 | M11: =+L11*M$3 -> 723.26403 | N11: =+L11+M11 -> 3134.1441 | O11: =+N11*O$3 -> 1253.6576 | P11: =+N11+O11 -> 4387.8018 | Q11: 0.0833 | R11: 20874.18 | S11: =+(I11-R11)/R11 -> 0.14541289 | T11: 100517438 | U11: 0
B12: 100516201 | C12: HAMBURGUESA 8X12X69G BURGER SWIFT | D12: 7790360968548 | E12: 6.624 | F12: 8 | G12: =+VLOOKUP(B12,$T$4:$U$106,2,FALSE) -> 52240.112 | I12: =+G12*(1-H12) -> 52240.112 | J12: =+I12/F12 -> 6530.014 | K12: =+J12*K$3 -> 1371.3029 | L12: =+J12+K12 -> 7901.3169 | M12: =+L12*M$3 -> 2370.3951 | N12: =+L12+M12 -> 10271.712 | O12: =+N12*O$3 -> 4108.6848 | P12: =+N12+O12 -> 14380.397 | R12: 49752.487 | S12: =+(I12-R12)/R12 -> 0.05 | T12: 100520337 | U12: 31314.663
B13: 100021643 | C13: MEDALLON 42X112G DOBLE BURGER SWIFT | D13: 7790360966797 | E13: 4.704 | F13: 42 | G13: =+VLOOKUP(B13,$T$4:$U$106,2,FALSE) -> 32037.276 | H13: 0.095238095 | I13: =+G13*(1-H13) -> 28986.107 | J13: =+I13/F13 -> 690.1454 | K13: =+J13*K$3 -> 144.93053 | L13: =+J13+K13 -> 835.07593 | M13: =+L13*M$3 -> 250.52278 | N13: =+L13+M13 -> 1085.5987 | O13: =+N13*O$3 -> 434.23948 | P13: =+N13+O13 -> 1519.8382 | R13: 30511.691 | S13: =+(I13-R13)/R13 -> -0.05 | T13: 100021503 | U13: 23909.555
B14: 100516325 | C14: MEDALLON DOBLE BURGER 2X2 | D14: 7790360967763 | E14: 4.704 | F14: 21 | G14: =+VLOOKUP(B14,$T$4:$U$106,2,FALSE) -> 36030.606 | I14: =+G14*(1-H14) -> 36030.606 | J14: =+I14/F14 -> 1715.7432 | K14: =+J14*K$3 -> 360.30606 | L14: =+J14+K14 -> 2076.0492 | M14: =+L14*M$3 -> 622.81477 | N14: =+L14+M14 -> 2698.864 | O14: =+N14*O$3 -> 1079.5456 | P14: =+N14+O14 -> 3778.4096 | R14: 34314.863 | S14: =+(I14-R14)/R14 -> 0.05 | T14: 100516201 | U14: 52240.112
B15: 100021676 | C15: HAMBURGUESA 30X250g CLASICA "XL" SWIFT | D15: 7790360967411 | E15: 7.5 | F15: 30 | G15: =+VLOOKUP(B15,$T$4:$U$106,2,FALSE) -> 66855.304 | I15: =+G15*(1-H15) -> 66855.304 | J15: =+I15/F15 -> 2228.5101 | K15: =+J15*K$3 -> 467.98713 | L15: =+J15+K15 -> 2696.4973 | M15: =+L15*M$3 -> 808.94918 | N15: =+L15+M15 -> 3505.4464 | O15: =+N15*O$3 -> 1402.1786 | P15: =+N15+O15 -> 4907.625 | Q15: 0.0667 | R15: 62396.055 | S15: =+(I15-R15)/R15 -> 0.071466838 | T15: 100021643 | U15: 32037.276
B16: 100516008 | C16: HAMBURGUESA 24X2X120g CASERA SWIFT | D16: 7790360967701 | E16: 5.76 | F16: 24 | G16: =+VLOOKUP(B16,$T$4:$U$106,2,FALSE) -> 56052.795 | H16: 0.05 | I16: =+G16*(1-H16) -> 53250.156 | J16: =+I16/F16 -> 2218.7565 | K16: =+J16*K$3 -> 465.93886 | L16: =+J16+K16 -> 2684.6953 | M16: =+L16*M$3 -> 805.4086 | N16: =+L16+M16 -> 3490.104 | O16: =+N16*O$3 -> 1396.0416 | P16: =+N16+O16 -> 4886.1455 | Q16: 0.0909 | R16: 50957.596 | S16: =+(I16-R16)/R16 -> 0.04498955 | T16: 100516325 | U16: 36030.606
B17: 100520834 | C17: HAMBURGUESA X-TREMA 36 x 185 grs | D17: 7790360980618 | E17: 6.66 | F17: 36 | G17: =+VLOOKUP(B17,$T$4:$U$106,2,FALSE) -> 69405.147 | I17: =+G17*(1-H17) -> 69405.147 | J17: =+I17/F17 -> 1927.9208 | K17: =+J17*K$3 -> 404.86336 | L17: =+J17+K17 -> 2332.7841 | M17: =+L17*M$3 -> 699.83523 | N17: =+L17+M17 -> 3032.6193 | O17: =+N17*O$3 -> 1213.0477 | P17: =+N17+O17 -> 4245.6671 | R17: 69405.147 | S17: =+(I17-R17)/R17 -> 0 | T17: 100021676 | U17: 66855.304
B18: 100021680 | C18: HAMBURGUESAS 18X2X120g CLL BRA/ARG | D18: 7790360967688 | E18: 4.32 | F18: 18 | G18: =+VLOOKUP(B18,$T$4:$U$106,2,FALSE) -> 55590.443 | I18: =+G18*(1-H18) -> 55590.443 | J18: =+I18/F18 -> 3088.358 | K18: =+J18*K$3 -> 648.55517 | L18: =+J18+K18 -> 3736.9131 | M18: =+L18*M$3 -> 1121.0739 | N18: =+L18+M18 -> 4857.9871 | O18: =+N18*O$3 -> 1943.1948 | P18: =+N18+O18 -> 6801.1819 | R18: 55590.443 | S18: =+(I18-R18)/R18 -> 0 | T18: 100021664 | U18: 0
B19: 100021644 | C19: MEDALLON 42X112G LA BLANCA | D19: 7790360008541 | E19: 4.704 | F19: 42 | G19: =+VLOOKUP(B19,$T$4:$U$106,2,FALSE) -> 23198.823 | I19: =+G19*(1-H19) -> 23198.823 | J19: =+I19/F19 -> 552.35294 | K19: =+J19*K$3 -> 115.99412 | L19: =+J19+K19 -> 668.34706 | M19: =+L19*0.33 -> 220.55453 | N19: =+L19+M19 -> 888.90158 | O19: =+N19*O$3 -> 355.56063 | P19: =+N19+O19 -> 1244.4622 | R19: 21089.839 | S19: =+(I19-R19)/R19 -> 0.1 | T19: 100516008 | U19: 56052.795
B20: 100021677 | C20: MEDALLON 12x4X69G LA BLANCA | D20: 7790360967404 | E20: 3.312 | F20: 12 | G20: =+VLOOKUP(B20,$T$4:$U$106,2,FALSE) -> 18410.954 | I20: =+G20*(1-H20) -> 18410.954 | J20: =+I20/F20 -> 1534.2462 | K20: =+J20*K$3 -> 322.19169 | L20: =+J20+K20 -> 1856.4379 | M20: =+L20*0.33 -> 612.62449 | N20: =+L20+M20 -> 2469.0624 | O20: =+N20*O$3 -> 987.62494 | P20: =+N20+O20 -> 3456.6873 | R20: 16737.231 | S20: =+(I20-R20)/R20 -> 0.1 | T20: 100520834 | U20: 69405.147
B21: 100021638 | C21: MEDALLONES 60X80g "SWIFT BURGER" PARRILLERAS FAMILY | D21: 7790360026699 | E21: 4.8 | F21: 60 | G21: =+VLOOKUP(B21,$T$4:$U$106,2,FALSE) -> 52286.134 | I21: =+G21*(1-H21) -> 52286.134 | J21: =+I21/F21 -> 871.43556 | K21: =+J21*K$3 -> 183.00147 | L21: =+J21+K21 -> 1054.437 | M21: =+L21*M$3 -> 316.33111 | N21: =+L21+M21 -> 1370.7681 | O21: =+N21*O$3 -> 548.30725 | P21: =+N21+O21 -> 1919.0754 | R21: 52286.134 | S21: =+(I21-R21)/R21 -> 0 | T21: 100021680 | U21: 55590.443
B22: 100021575 | C22: MEDALLONES 60X69g "SWIFT BURGER"PARRILLERAS FAMILY | D22: 7790360007032 | E22: 4.14 | F22: 60 | G22: =+VLOOKUP(B22,$T$4:$U$106,2,FALSE) -> 42882.941 | I22: =+G22*(1-H22) -> 42882.941 | J22: =+I22/F22 -> 714.71568 | K22: =+J22*K$3 -> 150.09029 | L22: =+J22+K22 -> 864.80597 | M22: =+L22*M$3 -> 259.44179 | N22: =+L22+M22 -> 1124.2478 | O22: =+N22*O$3 -> 449.69911 | P22: =+N22+O22 -> 1573.9469 | R22: 42882.941 | S22: =+(I22-R22)/R22 -> 0 | T22: 100021644 | U22: 23198.823
B23: 100021514 | C23: MEDALLON 60X69G CARNE VACUNA | D23: 7790360006943 | E23: 4.14 | F23: 60 | G23: =+VLOOKUP(B23,$T$4:$U$106,2,FALSE) -> 39023.233 | I23: =+G23*(1-H23) -> 39023.233 | J23: =+I23/F23 -> 650.38722 | K23: =+J23*K$3 -> 136.58132 | L23: =+J23+K23 -> 786.96853 | M23: =+L23*M$3 -> 236.09056 | N23: =+L23+M23 -> 1023.0591 | O23: =+N23*O$3 -> 409.22364 | P23: =+N23+O23 -> 1432.2827 | R23: 39023.233 | S23: =+(I23-R23)/R23 -> 0 | T23: 100021677 | U23: 18410.954
B24: 100516208 | C24: MEDALLON 60x80g PARRILLERO MC SWIFT | D24: 7790360968203 | E24: =60*0.08 -> 4.8 | F24: 60 | G24: =+VLOOKUP(B24,$T$4:$U$106,2,FALSE) -> 45244.352 | I24: =+G24*(1-H24) -> 45244.352 | J24: =+I24/F24 -> 754.07253 | K24: =+J24*K$3 -> 158.35523 | L24: =+J24+K24 -> 912.42777 | M24: =+L24*M$3 -> 273.72833 | N24: =+L24+M24 -> 1186.1561 | O24: =+N24*O$3 -> 474.46244 | P24: =+N24+O24 -> 1660.6185 | R24: 45244.352 | S24: =+(I24-R24)/R24 -> 0 | T24: 100021638 | U24: 52286.134
B25: 100518346 | C25: MEDALLON 60X109G CARNE VACUNA PARRILLERO SWIFT | E25: 6.54 | F25: 60 | G25: =+VLOOKUP(B25,$T$4:$U$106,2,FALSE) -> 64667.286 | I25: =+G25*(1-H25) -> 64667.286 | J25: =+I25/F25 -> 1077.7881 | K25: =+J25*K$3 -> 226.3355 | L25: =+J25+K25 -> 1304.1236 | M25: =+L25*M$3 -> 391.23708 | N25: =+L25+M25 -> 1695.3607 | O25: =+N25*O$3 -> 678.14427 | P25: =+N25+O25 -> 2373.505 | R25: 64667.286 | S25: =+(I25-R25)/R25 -> 0 | T25: 100021575 | U25: 42882.941
B26: 100516259 | C26: MEDALLON GIGANTE 48x113.5g | D26: 7790360968340 | E26: 18.16 | F26: 48 | G26: =+VLOOKUP(B26,$T$4:$U$106,2,FALSE) -> 149620.03 | I26: =+G26*(1-H26) -> 149620.03 | J26: =+I26/F26 -> 3117.084 | K26: =+J26*K$3 -> 654.58764 | L26: =+J26+K26 -> 3771.6716 | M26: =+L26*M$3 -> 1131.5015 | N26: =+L26+M26 -> 4903.1731 | O26: =+N26*O$3 -> 1961.2692 | P26: =+N26+O26 -> 6864.4424 | R26: 149620.03 | S26: =+(I26-R26)/R26 -> 0 | T26: 100021514 | U26: 39023.233
B27: 100518095 | C27: HAMBURGUESA 36 X 185 GRS | D27: 7790360974785 | E27: 6.66 | F27: 36 | G27: =+VLOOKUP(B27,$T$4:$U$106,2,FALSE) -> 74547.677 | I27: =+G27*(1-H27) -> 74547.677 | J27: =+I27/F27 -> 2070.7688 | K27: =+J27*K$3 -> 434.86145 | L27: =+J27+K27 -> 2505.6303 | M27: =+L27*M$3 -> 751.68908 | N27: =+L27+M27 -> 3257.3194 | O27: =+N27*O$3 -> 1302.9277 | P27: =+N27+O27 -> 4560.2471 | R27: 74547.677 | S27: =+(I27-R27)/R27 -> 0 | T27: 100516208 | U27: 45244.352
B28: 100518223 | C28: HAMBURGUESA 30x2x106 GRS | D28: 7790360975065 | E28: =60*0.106 -> 6.36 | F28: 30 | G28: =+VLOOKUP(B28,$T$4:$U$106,2,FALSE) -> 58039.51 | I28: =+G28*(1-H28) -> 58039.51 | J28: =+I28/F28 -> 1934.6503 | K28: =+J28*K$3 -> 406.27657 | L28: =+J28+K28 -> 2340.9269 | M28: =+L28*M$3 -> 702.27807 | N28: =+L28+M28 -> 3043.205 | O28: =+N28*O$3 -> 1217.282 | P28: =+N28+O28 -> 4260.487 | R28: 58039.51 | S28: =+(I28-R28)/R28 -> 0 | T28: 100518346 | U28: 64667.286
J29: =+I29/F29 -> #DIV/0! | K29: 0.21 | M29: 0.3 | O29: 0.4 | S29: =+(I29-R29)/R29 -> #DIV/0! | T29: 100516259 | U29: 149620.03
B30: 100022085 | C30: SALCHICHAS 24X6 SWIFT | D30: 7790360000132 | E30: 5.4 | F30: 24 | G30: =+Litoral!H30*1.1 -> #N/A | I30: =+G30*(1-H30) -> #N/A | J30: =+I30/F30 -> #N/A | K30: =+J30*K$3 -> #N/A | L30: =+J30+K30 -> #N/A | M30: =+L30*M$3 -> #N/A | N30: =+L30+M30 -> #N/A | O30: =+N30*O$3 -> #N/A | P30: =+N30+O30 -> #N/A | R30: #N/A | S30: =+(I30-R30)/R30 -> #N/A | T30: 100518095 | U30: 74547.677
B31: 100522204 | C31: SALCHICHAS 24X6 SWIFT | D31: 7790360983947 | E31: 5.4 | F31: 24 | G31: =+Litoral!H31*1.1 -> 23601.533 | H31: 0.083333333 | I31: =+G31*(1-H31) -> 21634.738 | J31: =+I31/F31 -> 901.44742 | K31: =+J31*K$3 -> 189.30396 | L31: =+J31+K31 -> 1090.7514 | M31: =+L31*M$3 -> 327.22542 | N31: =+L31+M31 -> 1417.9768 | O31: =+N31*O$3 -> 567.19072 | P31: =+N31+O31 -> 1985.1675 | R31: 23601.533 | T31: 100518223 | U31: 58039.51
B32: 100022072 | C32: SALCHICHAS 12X12 SWIFT | D32: 7790360024541 | E32: 5.4 | F32: 12 | G32: =+Litoral!H32*1.1 -> #N/A | I32: =+G32*(1-H32) -> #N/A | J32: =+I32/F32 -> #N/A | K32: =+J32*K$3 -> #N/A | L32: =+J32+K32 -> #N/A | M32: =+L32*M$3 -> #N/A | N32: =+L32+M32 -> #N/A | O32: =+N32*O$3 -> #N/A | P32: =+N32+O32 -> #N/A | R32: #N/A | S32: =+(I32-R32)/R32 -> #N/A
B33: 100522205 | C33: SALCHICHAS 12X12 SWIFT | D33: 7790360983954 | E33: 5.4 | F33: 12 | G33: =+Litoral!H33*1.1 -> 22421.456 | H33: 0.083333333 | I33: =+G33*(1-H33) -> 20553.001 | J33: =+I33/F33 -> 1712.7501 | K33: =+J33*K$3 -> 359.67752 | L33: =+J33+K33 -> 2072.4276 | M33: =+L33*M$3 -> 621.72829 | N33: =+L33+M33 -> 2694.1559 | O33: =+N33*O$3 -> 1077.6624 | P33: =+N33+O33 -> 3771.8183 | R33: 22421.456 | T33: 100022085 | U33: 25747.126
B34: 100516849 | C34: SALCHICHAS SIN PIEL 24X6 "SWIFT KIDS" X 190 g | D34: 7790360970053 | E34: 4.56 | F34: 24 | G34: =+Litoral!H34*1.1 -> 19826.008 | I34: =+G34*(1-H34) -> 19826.008 | J34: =+I34/F34 -> 826.08368 | K34: =+J34*K$3 -> 173.47757 | L34: =+J34+K34 -> 999.56125 | M34: =+L34*M$3 -> 299.86838 | N34: =+L34+M34 -> 1299.4296 | O34: =+N34*O$3 -> 519.77185 | P34: =+N34+O34 -> 1819.2015 | R34: 19826.008 | S34: =+(I34-R34)/R34 -> 0 | T34: 100522204 | U34: 25747.126
B35: 100022039 | C35: SALCHICHAS LARGAS 10 x 12 SWIFT INSTITUCIONAL | D35: 7790360007063 | E35: 8.7 | F35: 10 | G35: =+VLOOKUP(B35,$T$4:$U$106,2,FALSE) -> 64728.267 | I35: =+G35*(1-H35) -> 64728.267 | J35: =+I35/F35 -> 6472.8267 | K35: =+J35*K$3 -> 1359.2936 | L35: =+J35+K35 -> 7832.1203 | M35: =+L35*M$3 -> 2349.6361 | N35: =+L35+M35 -> 10181.756 | O35: =+N35*O$3 -> 4072.7025 | P35: =+N35+O35 -> 14254.459 | R35: 61645.968 | S35: =+(I35-R35)/R35 -> 0.05 | T35: 100022072 | U35: 24459.77
B36: 100522206 | C36: SALCHICHAS LARGAS 10 x 12 SWIFT INSTITUCIONAL | D36: 7790360983961 | E36: 8.7 | F36: 10 | G36: =+VLOOKUP(B36,$T$4:$U$106,2,FALSE) -> 64728.267 | I36: =+G36*(1-H36) -> 64728.267 | J36: =+I36/F36 -> 6472.8267 | K36: =+J36*K$3 -> 1359.2936 | L36: =+J36+K36 -> 7832.1203 | M36: =+L36*M$3 -> 2349.6361 | N36: =+L36+M36 -> 10181.756 | O36: =+N36*O$3 -> 4072.7025 | P36: =+N36+O36 -> 14254.459 | R36: 61645.968 | T36: 100522205 | U36: 24459.77
B37: 100022058 | C37: SALCHICHAS SIN PIEL "LA BLANCA" 24X6X190 Grs; | D37: 7790360026002 | E37: 4.56 | F37: 24 | G37: =+VLOOKUP(B37,$T$4:$U$106,2,FALSE) -> 17361.948 | I37: =+G37*(1-H37) -> 17361.948 | J37: =+I37/F37 -> 723.41452 | K37: =+J37*K$3 -> 151.91705 | L37: =+J37+K37 -> 875.33156 | M37: =+L37*0.33 -> 288.85942 | N37: =+L37+M37 -> 1164.191 | O37: =+N37*O$3 -> 465.67639 | P37: =+N37+O37 -> 1629.8674 | R37: 17361.948 | S37: =+(I37-R37)/R37 -> 0 | T37: 100516849 | U37: 19826.008 | X37: Ver posicionamiento por verba según necesidad de la zona
B38: 100518151 | C38: SALCHICHAS LARGAS 10 x 12 x 870g | D38: 7790360974990 | E38: 8.7 | F38: 10 | G38: =+VLOOKUP(B38,$T$4:$U$106,2,FALSE) -> 73741.829 | I38: =+G38*(1-H38) -> 73741.829 | J38: =+I38/F38 -> 7374.1829 | K38: =+J38*K$3 -> 1548.5784 | L38: =+J38+K38 -> 8922.7613 | M38: =+L38*0.33 -> 2944.5112 | N38: =+L38+M38 -> 11867.273 | O38: =+N38*O$3 -> 4746.909 | P38: =+N38+O38 -> 16614.182 | R38: 70230.314 | S38: =+(I38-R38)/R38 -> 0.05 | T38: 100022039 | U38: 64728.267
J39: =+I39/F39 -> #DIV/0! | K39: 0.21 | M39: 0.2 | O39: 0.35 | S39: =+(I39-R39)/R39 -> #DIV/0! | T39: 100522206 | U39: 64728.267
B40: 100021000 | C40: PATE DE FOIE 24X90G SWIFT | D40: 7790360720382 | E40: 2.16 | F40: 24 | G40: =+VLOOKUP(B40,$T$4:$U$106,2,FALSE) -> 14258.501 | I40: =+G40*(1-H40) -> 14258.501 | J40: =+I40/F40 -> 594.10421 | K40: =+J40*K$3 -> 124.76188 | L40: =+J40+K40 -> 718.8661 | M40: =+L40*M$39 -> 143.77322 | N40: =+L40+M40 -> 862.63932 | O40: =+N40*O$39 -> 301.92376 | P40: =+N40+O40 -> 1164.5631 | R40: 13579.525 | S40: =+(I40-R40)/R40 -> 0.05 | T40: 100022058 | U40: 17361.948
B41: 100021001 | C41: PICADILLO DE CARNE 24X90G SWIFT | D41: 7790360720115 | E41: 2.16 | F41: 24 | G41: =+VLOOKUP(B41,$T$4:$U$106,2,FALSE) -> 14258.501 | I41: =+G41*(1-H41) -> 14258.501 | J41: =+I41/F41 -> 594.10421 | K41: =+J41*K$3 -> 124.76188 | L41: =+J41+K41 -> 718.8661 | M41: =+L41*M$39 -> 143.77322 | N41: =+L41+M41 -> 862.63932 | O41: =+N41*O$39 -> 301.92376 | P41: =+N41+O41 -> 1164.5631 | R41: 13579.525 | S41: =+(I41-R41)/R41 -> 0.05 | T41: 100518151 | U41: 73741.829
B42: 100522277 | C42: Picadillo de Carne Picante Chile Chipotle 24x90 g | E42: 2.16 | F42: 24 | G42: =+VLOOKUP(B42,$T$4:$U$106,2,FALSE) -> 14258.501 | I42: =+G42*(1-H42) -> 14258.501 | J42: =+I42/F42 -> 594.10421 | K42: =+J42*K$3 -> 124.76188 | L42: =+J42+K42 -> 718.8661 | M42: =+L42*M$39 -> 143.77322 | N42: =+L42+M42 -> 862.63932 | O42: =+N42*O$39 -> 301.92376 | P42: =+N42+O42 -> 1164.5631 | R42: 13579.525
B43: 100522333 | C43: Pate de Foie Jalapeño 24x90 Swift | E43: 2.16 | F43: 24 | G43: =+VLOOKUP(B43,$T$4:$U$106,2,FALSE) -> 14258.501 | I43: =+G43*(1-H43) -> 14258.501 | J43: =+I43/F43 -> 594.10421 | K43: =+J43*K$3 -> 124.76188 | L43: =+J43+K43 -> 718.8661 | M43: =+L43*M$39 -> 143.77322 | N43: =+L43+M43 -> 862.63932 | O43: =+N43*O$39 -> 301.92376 | P43: =+N43+O43 -> 1164.5631 | R43: 13579.525 | T43: 100021000 | U43: 14258.501
B44: 100021045 | C44: PICADILLO DE CARNE PICANTE 24X90G SWIFT | D44: 7790360966582 | E44: 2.16 | F44: 24 | G44: =+VLOOKUP(B44,$T$4:$U$106,2,FALSE) -> 14258.501 | I44: =+G44*(1-H44) -> 14258.501 | J44: =+I44/F44 -> 594.10421 | K44: =+J44*K$3 -> 124.76188 | L44: =+J44+K44 -> 718.8661 | M44: =+L44*M$39 -> 143.77322 | N44: =+L44+M44 -> 862.63932 | O44: =+N44*O$39 -> 301.92376 | P44: =+N44+O44 -> 1164.5631 | R44: 13579.525 | S44: =+(I44-R44)/R44 -> 0.05 | T44: 100021001 | U44: 14258.501
B45: 100021004 | C45: PATE DE FOIE A LA CREMA 24X88G SWIFT | D45: 7790360964526 | E45: 2.112 | F45: 24 | G45: =+VLOOKUP(B45,$T$4:$U$106,2,FALSE) -> 14258.501 | I45: =+G45*(1-H45) -> 14258.501 | J45: =+I45/F45 -> 594.10421 | K45: =+J45*K$3 -> 124.76188 | L45: =+J45+K45 -> 718.8661 | M45: =+L45*M$39 -> 143.77322 | N45: =+L45+M45 -> 862.63932 | O45: =+N45*O$39 -> 301.92376 | P45: =+N45+O45 -> 1164.5631 | R45: 13579.525 | S45: =+(I45-R45)/R45 -> 0.05 | T45: 100522277 | U45: 14258.501
B46: 100021006 | C46: JAMON DEL DIABLO 24X88G SWIFT | D46: 7790360964557 | E46: 2.112 | F46: 24 | G46: =+VLOOKUP(B46,$T$4:$U$106,2,FALSE) -> 14258.501 | I46: =+G46*(1-H46) -> 14258.501 | J46: =+I46/F46 -> 594.10421 | K46: =+J46*K$3 -> 124.76188 | L46: =+J46+K46 -> 718.8661 | M46: =+L46*M$39 -> 143.77322 | N46: =+L46+M46 -> 862.63932 | O46: =+N46*O$39 -> 301.92376 | P46: =+N46+O46 -> 1164.5631 | R46: 13579.525 | S46: =+(I46-R46)/R46 -> 0.05 | T46: 100522333 | U46: 14258.501
B47: 100021007 | C47: PATE DE FOIE DE POLLO 24X85G SWIFT | D47: 7790360964540 | E47: 2.04 | F47: 24 | G47: =+VLOOKUP(B47,$T$4:$U$106,2,FALSE) -> 17049.18 | I47: =+G47*(1-H47) -> 17049.18 | J47: =+I47/F47 -> 710.38251 | K47: =+J47*K$3 -> 149.18033 | L47: =+J47+K47 -> 859.56284 | M47: =+L47*M$39 -> 171.91257 | N47: =+L47+M47 -> 1031.4754 | O47: =+N47*O$39 -> 361.01639 | P47: =+N47+O47 -> 1392.4918 | R47: 15501.688 | S47: =+(I47-R47)/R47 -> 0.099827334 | T47: 100021045 | U47: 14258.501
B48: 100021013 | C48: PATE DE FOIE TIPO PROVENZAL 24X85G SWIFT GOURMET | D48: 7790360965714 | E48: 2.04 | F48: 24 | G48: =+VLOOKUP(B48,$T$4:$U$106,2,FALSE) -> 17049.18 | I48: =+G48*(1-H48) -> 17049.18 | J48: =+I48/F48 -> 710.38251 | K48: =+J48*K$3 -> 149.18033 | L48: =+J48+K48 -> 859.56284 | M48: =+L48*M$39 -> 171.91257 | N48: =+L48+M48 -> 1031.4754 | O48: =+N48*O$39 -> 361.01639 | P48: =+N48+O48 -> 1392.4918 | R48: 15501.688 | S48: =+(I48-R48)/R48 -> 0.099827334 | T48: 100021004 | U48: 14258.501
B49: 100021014 | C49: PATE DE FOIE C/PIMIENTA VERDE 24X85G SWIFT GOURMET | D49: 7790360965721 | E49: 2.04 | F49: 24 | G49: =+VLOOKUP(B49,$T$4:$U$106,2,FALSE) -> 17049.18 | I49: =+G49*(1-H49) -> 17049.18 | J49: =+I49/F49 -> 710.38251 | K49: =+J49*K$3 -> 149.18033 | L49: =+J49+K49 -> 859.56284 | M49: =+L49*M$39 -> 171.91257 | N49: =+L49+M49 -> 1031.4754 | O49: =+N49*O$39 -> 361.01639 | P49: =+N49+O49 -> 1392.4918 | R49: 15501.688 | S49: =+(I49-R49)/R49 -> 0.099827334 | T49: 100021006 | U49: 14258.501
B50: 100021054 | C50: PATE JAMON AHUMADO 24X85G | D50: 7790360965707 | E50: 2.04 | F50: 24 | G50: =+VLOOKUP(B50,$T$4:$U$106,2,FALSE) -> 17049.18 | I50: =+G50*(1-H50) -> 17049.18 | J50: =+I50/F50 -> 710.38251 | K50: =+J50*K$3 -> 149.18033 | L50: =+J50+K50 -> 859.56284 | M50: =+L50*M$39 -> 171.91257 | N50: =+L50+M50 -> 1031.4754 | O50: =+N50*O$39 -> 361.01639 | P50: =+N50+O50 -> 1392.4918 | R50: 15501.688 | S50: =+(I50-R50)/R50 -> 0.099827334 | T50: 100021007 | U50: 17049.18
B51: 100021055 | C51: PATE HONGOS 24X85G | D51: 7790360965189 | E51: 2.04 | F51: 24 | G51: =+VLOOKUP(B51,$T$4:$U$106,2,FALSE) -> 17049.18 | I51: =+G51*(1-H51) -> 17049.18 | J51: =+I51/F51 -> 710.38251 | K51: =+J51*K$3 -> 149.18033 | L51: =+J51+K51 -> 859.56284 | M51: =+L51*M$39 -> 171.91257 | N51: =+L51+M51 -> 1031.4754 | O51: =+N51*O$39 -> 361.01639 | P51: =+N51+O51 -> 1392.4918 | R51: 15501.688 | S51: =+(I51-R51)/R51 -> 0.099827334 | T51: 100021013 | U51: 17049.18
B52: 100021015 | C52: PATE DE SALMON 24X85G SWIFT GOURMET | D52: 7790360965202 | E52: 2.04 | F52: 24 | G52: =+VLOOKUP(B52,$T$4:$U$106,2,FALSE) -> 17049.18 | I52: =+G52*(1-H52) -> 17049.18 | J52: =+I52/F52 -> 710.38251 | K52: =+J52*K$3 -> 149.18033 | L52: =+J52+K52 -> 859.56284 | M52: =+L52*M$39 -> 171.91257 | N52: =+L52+M52 -> 1031.4754 | O52: =+N52*O$39 -> 361.01639 | P52: =+N52+O52 -> 1392.4918 | R52: 15501.688 | S52: =+(I52-R52)/R52 -> 0.099827334 | T52: 100021014 | U52: 17049.18
B53: 100021008 | C53: PICADILLO DE CARNE 24X90G LA BLANCA | D53: 7790360720122 | E53: 2.16 | F53: 24 | G53: =+VLOOKUP(B53,$T$4:$U$106,2,FALSE) -> 12068.108 | I53: =+G53*(1-H53) -> 12068.108 | J53: =+I53/F53 -> 502.83782 | K53: =+J53*K$3 -> 105.59594 | L53: =+J53+K53 -> 608.43376 | M53: =+L53*M$39 -> 121.68675 | N53: =+L53+M53 -> 730.12051 | O53: =+N53*O$39 -> 255.54218 | P53: =+N53+O53 -> 985.66269 | R53: 11493.436 | S53: =+(I53-R53)/R53 -> 0.05 | T53: 100021054 | U53: 17049.18
B54: 100021009 | C54: PATE DE FOIE 24X90G LA BLANCA | D54: 7790360965127 | E54: 2.16 | F54: 24 | G54: =+VLOOKUP(B54,$T$4:$U$106,2,FALSE) -> 12068.108 | I54: =+G54*(1-H54) -> 12068.108 | J54: =+I54/F54 -> 502.83782 | K54: =+J54*K$3 -> 105.59594 | L54: =+J54+K54 -> 608.43376 | M54: =+L54*M$39 -> 121.68675 | N54: =+L54+M54 -> 730.12051 | O54: =+N54*O$39 -> 255.54218 | P54: =+N54+O54 -> 985.66269 | R54: 11493.436 | S54: =+(I54-R54)/R54 -> 0.05 | T54: 100021055 | U54: 17049.18
B55: 100021010 | C55: PICADILLO DE CARNE 24X90G SAFRA | D55: 7790920008707 | E55: 2.16 | F55: 24 | G55: =+VLOOKUP(B55,$T$4:$U$106,2,FALSE) -> 12068.108 | I55: =+G55*(1-H55) -> 12068.108 | J55: =+I55/F55 -> 502.83782 | K55: =+J55*K$3 -> 105.59594 | L55: =+J55+K55 -> 608.43376 | M55: =+L55*M$39 -> 121.68675 | N55: =+L55+M55 -> 730.12051 | O55: =+N55*O$39 -> 255.54218 | P55: =+N55+O55 -> 985.66269 | R55: 11493.436 | S55: =+(I55-R55)/R55 -> 0.05 | T55: 100021015 | U55: 17049.18
B56: 100021011 | C56: PATE DE FOIE 24X90G SAFRA | D56: 7790920008714 | E56: 2.16 | F56: 24 | G56: =+VLOOKUP(B56,$T$4:$U$106,2,FALSE) -> 12068.108 | I56: =+G56*(1-H56) -> 12068.108 | J56: =+I56/F56 -> 502.83782 | K56: =+J56*K$3 -> 105.59594 | L56: =+J56+K56 -> 608.43376 | M56: =+L56*M$39 -> 121.68675 | N56: =+L56+M56 -> 730.12051 | O56: =+N56*O$39 -> 255.54218 | P56: =+N56+O56 -> 985.66269 | R56: 11493.436 | S56: =+(I56-R56)/R56 -> 0.05 | T56: 100021008 | U56: 12068.108
J57: =+I57/F57 -> #DIV/0! | K57: 0.21 | M57: 0.3 | O57: 0.4 | S57: =+(I57-R57)/R57 -> #DIV/0! | T57: 100021009 | U57: 12068.108
B58: 100516217 | C58: MILANESAS DE SOJA CLASICAS PREFRITA | D58: 7790360967824 | E58: 5.8 | F58: 20 | G58: =+VLOOKUP(B58,$T$4:$U$106,2,FALSE) -> 28398.276 | I58: =+G58*(1-H58) -> 28398.276 | J58: =+I58/F58 -> 1419.9138 | K58: =+J58*K$3 -> 298.1819 | L58: =+J58+K58 -> 1718.0957 | M58: =+L58*M$3 -> 515.42872 | N58: =+L58+M58 -> 2233.5244 | O58: =+N58*O$3 -> 893.40978 | P58: =+N58+O58 -> 3126.9342 | R58: 27571.142 | S58: =+(I58-R58)/R58 -> 0.03 | T58: 100021010 | U58: 12068.108
B59: 100516214 | C59: MILANESAS DE SOJA RELLENAS CON JAMON Y QUESO | D59: 7790360967794 | E59: 7 | F59: 20 | G59: =+VLOOKUP(B59,$T$4:$U$106,2,FALSE) -> 36665.1 | I59: =+G59*(1-H59) -> 36665.1 | J59: =+I59/F59 -> 1833.255 | K59: =+J59*K$3 -> 384.98355 | L59: =+J59+K59 -> 2218.2385 | M59: =+L59*M$3 -> 665.47156 | N59: =+L59+M59 -> 2883.7101 | O59: =+N59*O$3 -> 1153.484 | P59: =+N59+O59 -> 4037.1941 | Q59: 0.05 | R59: 36665.104 | S59: =+(I59-R59)/R59 -> -1.1428248e-07 | T59: 100021011 | U59: 12068.108
B60: 100516215 | C60: MILANESAS DE SOJA RELLENAS CON ESPINACA Y QUESO | D60: 7790360967800 | E60: 7 | F60: 20 | G60: =+VLOOKUP(B60,$T$4:$U$106,2,FALSE) -> 36665.1 | I60: =+G60*(1-H60) -> 36665.1 | J60: =+I60/F60 -> 1833.255 | K60: =+J60*K$3 -> 384.98355 | L60: =+J60+K60 -> 2218.2385 | M60: =+L60*M$3 -> 665.47156 | N60: =+L60+M60 -> 2883.7101 | O60: =+N60*O$3 -> 1153.484 | P60: =+N60+O60 -> 4037.1941 | Q60: 0.05 | R60: 36665.104 | S60: =+(I60-R60)/R60 -> -1.1428248e-07
B61: 100516216 | C61: MILANESAS DE SOJA RELLENAS CON TOMATE Y QUESO | D61: 7790360967817 | E61: 7 | F61: 20 | G61: =+VLOOKUP(B61,$T$4:$U$106,2,FALSE) -> 36665.1 | I61: =+G61*(1-H61) -> 36665.1 | J61: =+I61/F61 -> 1833.255 | K61: =+J61*K$3 -> 384.98355 | L61: =+J61+K61 -> 2218.2385 | M61: =+L61*M$3 -> 665.47156 | N61: =+L61+M61 -> 2883.7101 | O61: =+N61*O$3 -> 1153.484 | P61: =+N61+O61 -> 4037.1941 | Q61: 0.05 | R61: 36665.104 | S61: =+(I61-R61)/R61 -> -1.1428248e-07 | T61: 100516217 | U61: 28398.276
J62: =+I62/F62 -> #DIV/0! | K62: 0.21 | M62: 0.3 | O62: 0.4 | S62: =+(I62-R62)/R62 -> #DIV/0! | T62: 100516214 | U62: 36665.1
B63: 100021704 | C63: BOCADITOS DE CARNE "SWIFT" - 12x380g | D63: 7790360023902 | E63: =12*0.38 -> 4.56 | F63: 12 | G63: =+VLOOKUP(B63,$T$4:$U$106,2,FALSE) -> 41455.299 | I63: =+G63*(1-H63) -> 41455.299 | J63: =+I63/F63 -> 3454.6083 | K63: =+J63*K$3 -> 725.46774 | L63: =+J63+K63 -> 4180.076 | M63: =+L63*M$3 -> 1254.0228 | N63: =+L63+M63 -> 5434.0988 | O63: =+N63*O$3 -> 2173.6395 | P63: =+N63+O63 -> 7607.7384 | R63: 41455.299 | S63: =+(I63-R63)/R63 -> 0 | T63: 100516215 | U63: 36665.1
B64: 100021705 | C64: BOCADITOS DE POLLO "SWIFT" - 12x380g | D64: 7790360024336 | E64: =12*0.38 -> 4.56 | F64: 12 | G64: =+VLOOKUP(B64,$T$4:$U$106,2,FALSE) -> 37683.832 | I64: =+G64*(1-H64) -> 37683.832 | J64: =+I64/F64 -> 3140.3193 | K64: =+J64*K$3 -> 659.46706 | L64: =+J64+K64 -> 3799.7864 | M64: =+L64*M$3 -> 1139.9359 | N64: =+L64+M64 -> 4939.7223 | O64: =+N64*O$3 -> 1975.8889 | P64: =+N64+O64 -> 6915.6112 | R64: 37683.832 | S64: =+(I64-R64)/R64 -> 0 | T64: 100516216 | U64: 36665.1
B65: 100021709 | C65: BOCADITOS DE POLLO "SWIFT" - 10x760g | D65: 7790360024701 | E65: 7.6 | F65: 10 | G65: =+VLOOKUP(B65,$T$4:$U$106,2,FALSE) -> 60469.387 | I65: =+G65*(1-H65) -> 60469.387 | J65: =+I65/F65 -> 6046.9387 | K65: =+J65*K$3 -> 1269.8571 | L65: =+J65+K65 -> 7316.7958 | M65: =+L65*M$3 -> 2195.0387 | N65: =+L65+M65 -> 9511.8345 | O65: =+N65*O$3 -> 3804.7338 | P65: =+N65+O65 -> 13316.568 | R65: 60469.387 | S65: =+(I65-R65)/R65 -> 0
B66: 100521357 | C66: CRUNCHIES DE POLLO "SWIFT" - 12x380g | E66: 4.56 | F66: 12 | G66: =+VLOOKUP(B66,$T$4:$U$106,2,FALSE) -> 48595.609 | H66: 0.33 | I66: =+G66*(1-H66) -> 32559.058 | J66: =+I66/F66 -> 2713.2548 | K66: =+J66*K$3 -> 569.78351 | L66: =+J66+K66 -> 3283.0383 | M66: =+L66*M$3 -> 984.9115 | N66: =+L66+M66 -> 4267.9498 | O66: =+N66*O$3 -> 1707.1799 | P66: =+N66+O66 -> 5975.1298 | Q66: 0.33 | R66: 32559.058 | S66: =+(I66-R66)/R66 -> 0 | T66: 100021704 | U66: 41455.299
B67: 100521358 | C67: CRUNCHIES DE POLLO "SWIFT" - 10x760g | D67: 7790360982025 | E67: 7.6 | F67: 10 | G67: =+VLOOKUP(B67,$T$4:$U$106,2,FALSE) -> 72893.413 | H67: 0.33 | I67: =+G67*(1-H67) -> 48838.587 | J67: =+I67/F67 -> 4883.8587 | K67: =+J67*K$3 -> 1025.6103 | L67: =+J67+K67 -> 5909.469 | M67: =+L67*M$3 -> 1772.8407 | N67: =+L67+M67 -> 7682.3097 | O67: =+N67*O$3 -> 3072.9239 | P67: =+N67+O67 -> 10755.234 | R67: 72893.413 | T67: 100021705 | U67: 37683.832
B68: 100522130 | C68: BOCADITOS DE POLLO "SWIFT KIDS" - 12x400g | E68: 4.8 | F68: 12 | G68: =+VLOOKUP(B68,$T$4:$U$106,2,FALSE) -> 40062.096 | I68: =+G68*(1-H68) -> 40062.096 | J68: =+I68/F68 -> 3338.508 | K68: =+J68*K$3 -> 701.08668 | L68: =+J68+K68 -> 4039.5947 | M68: =+L68*M$3 -> 1211.8784 | N68: =+L68+M68 -> 5251.4731 | O68: =+N68*O$3 -> 2100.5892 | P68: =+N68+O68 -> 7352.0623 | R68: 38154.377 | S68: =+(I68-R68)/R68 -> 0.05 | T68: 100021707 | U68: 0
B69: 100021725 | C69: BOCADITOS DE POLLO GASTRONOMICOS "LA BLANCA" - x6kg | D69: 7790360027009 | E69: 6 | F69: 4 | G69: =+VLOOKUP(B69,$T$4:$U$106,2,FALSE) -> 31255.57 | I69: =+G69*(1-H69) -> 31255.57 | J69: =+I69/F69 -> 7813.8925 | K69: =+J69*K$3 -> 1640.9174 | L69: =+J69+K69 -> 9454.8099 | M69: =+L69*M$3 -> 2836.443 | N69: =+L69+M69 -> 12291.253 | O69: =+N69*O$3 -> 4916.5011 | P69: =+N69+O69 -> 17207.754 | R69: 31255.57 | S69: =+(I69-R69)/R69 -> 0 | T69: 100021709 | U69: 60469.387
B70: 100517055 | C70: PALITO DE POLLO "SWIFT" 12 X 260 Grs. | D70: 7790360971135 | E70: 3.12 | F70: 12 | G70: =+VLOOKUP(B70,$T$4:$U$106,2,FALSE) -> 31213.609 | I70: =+G70*(1-H70) -> 31213.609 | J70: =+I70/F70 -> 2601.1341 | K70: =+J70*K$3 -> 546.23816 | L70: =+J70+K70 -> 3147.3722 | M70: =+L70*M$3 -> 944.21167 | N70: =+L70+M70 -> 4091.5839 | O70: =+N70*O$3 -> 1636.6336 | P70: =+N70+O70 -> 5728.2175 | R70: 31213.609 | S70: =+(I70-R70)/R70 -> 0 | T70: 100521357 | U70: 48595.609
B71: 100517186 | C71: PALITO DE POLLO "SWIFT" 8 X 1 Kg.. | D71: 7790360971395 | E71: 8 | F71: 8 | G71: =+VLOOKUP(B71,$T$4:$U$106,2,FALSE) -> 78871.462 | I71: =+G71*(1-H71) -> 78871.462 | J71: =+I71/F71 -> 9858.9327 | K71: =+J71*K$3 -> 2070.3759 | L71: =+J71+K71 -> 11929.309 | M71: =+L71*M$3 -> 3578.7926 | N71: =+L71+M71 -> 15508.101 | O71: =+N71*O$3 -> 6203.2405 | P71: =+N71+O71 -> 21711.342 | R71: 78871.462 | S71: =+(I71-R71)/R71 -> 0 | T71: 100521358 | U71: 72893.413
B72: 100521663 | C72: MILANESITAS DE CARNE "SWIFT" - 12x400g | E72: 4.8 | F72: 12 | G72: 41797.283 | H72: 0.33 | I72: =+G72*(1-H72) -> 28004.18 | J72: =+I72/F72 -> 2333.6816 | K72: =+J72*K$3 -> 490.07315 | L72: =+J72+K72 -> 2823.7548 | M72: =+L72*M$3 -> 847.12644 | N72: =+L72+M72 -> 3670.8812 | O72: =+N72*O$3 -> 1468.3525 | P72: =+N72+O72 -> 5139.2337 | Q72: 0.33 | R72: 28004.18 | S72: =+(I72-R72)/R72 -> 0 | T72: 100522130 | U72: 40062.096
B73: 100021728 | C73: MEDALLONES DE POLLO "SWIFT" - 12x4x80g | D73: 7790360967558 | E73: 3.84 | F73: 12 | G73: =+VLOOKUP(B73,$T$4:$U$106,2,FALSE) -> 39236.851 | I73: =+G73*(1-H73) -> 39236.851 | J73: =+I73/F73 -> 3269.7376 | K73: =+J73*K$3 -> 686.64489 | L73: =+J73+K73 -> 3956.3825 | M73: =+L73*M$3 -> 1186.9147 | N73: =+L73+M73 -> 5143.2972 | O73: =+N73*O$3 -> 2057.3189 | P73: =+N73+O73 -> 7200.6161 | R73: 39236.851 | S73: =+(I73-R73)/R73 -> 0 | T73: 100021725 | U73: 31255.57
B74: 100517679 | C74: MEDALLONES DE POLLO GASTRONÓMICO 8x12x80 Grs. | E74: 7.68 | F74: 8 | G74: =+VLOOKUP(B74,$T$4:$U$106,2,FALSE) -> 39413.592 | I74: =+G74*(1-H74) -> 39413.592 | J74: =+I74/F74 -> 4926.699 | K74: =+J74*K$3 -> 1034.6068 | L74: =+J74+K74 -> 5961.3058 | M74: =+L74*M$3 -> 1788.3918 | N74: =+L74+M74 -> 7749.6976 | O74: =+N74*O$3 -> 3099.879 | P74: =+N74+O74 -> 10849.577 | R74: 39413.592 | S74: =+(I74-R74)/R74 -> 0 | T74: 100517055 | U74: 31213.609
G75: #VALUE! | I75: =+G75*(1-H75) -> #VALUE! | J75: =+I75/F75 -> #VALUE! | K75: 0.21 | M75: 0.3 | O75: 0.4 | R75: #VALUE! | S75: =+(I75-R75)/R75 -> #VALUE! | T75: 100517186 | U75: 78871.462
B76: 100516219 | C76: PAPAS PREFRITAS SUPERCONGELADAS 25x400gr | D76: 7790360967770 | E76: 10 | F76: 25 | G76: 18259.4 | I76: =+G76*(1-H76) -> 18259.4 | J76: =+I76/F76 -> 730.376 | K76: =+J76*K$3 -> 153.37896 | L76: =+J76+K76 -> 883.75495 | M76: =+L76*M$3 -> 265.12649 | N76: =+L76+M76 -> 1148.8814 | O76: =+N76*O$3 -> 459.55258 | P76: =+N76+O76 -> 1608.434 | R76: 18259.4 | S76: =+(I76-R76)/R76 -> 0 | T76: 100521663 | U76: 41797.283
B77: 100516220 | C77: PAPAS PREFRITAS SUPERCONGELADAS 6x2000gr | D77: 7790360967787 | E77: 12 | F77: 6 | G77: 19613.922 | I77: =+G77*(1-H77) -> 19613.922 | J77: =+I77/F77 -> 3268.987 | K77: =+J77*K$3 -> 686.48726 | L77: =+J77+K77 -> 3955.4742 | M77: =+L77*M$3 -> 1186.6423 | N77: =+L77+M77 -> 5142.1165 | O77: =+N77*O$3 -> 2056.8466 | P77: =+N77+O77 -> 7198.9631 | R77: 19613.922 | S77: =+(I77-R77)/R77 -> 0 | T77: 100021728 | U77: 39236.851
G78: #VALUE! | I78: =+G78*(1-H78) -> #VALUE! | J78: =+I78/F78 -> #VALUE! | R78: #VALUE! | S78: =+(I78-R78)/R78 -> #VALUE! | T78: 100517679 | U78: 39413.592
B79: 100518158 | C79: MILANESA DE CARNE VACUNA CONGELADA 24un x 500grs | D79: 7790360974280 | E79: 12 | F79: 24 | G79: =+VLOOKUP(B79,$T$4:$U$106,2,FALSE) -> 75339.603 | I79: =+G79*(1-H79) -> 75339.603 | J79: =+I79/F79 -> 3139.1501 | K79: =+J79*K$3 -> 659.22153 | L79: =+J79+K79 -> 3798.3716 | M79: =+L79*M$3 -> 1139.5115 | N79: =+L79+M79 -> 4937.8831 | O79: =+N79*O$3 -> 1975.1533 | P79: =+N79+O79 -> 6913.0364 | R79: 75339.603 | S79: =+(I79-R79)/R79 -> 0 | U79: #VALUE!
B80: 100518160 | C80: MILANESA DE CARNE VACUNA CONGELADA 12un x 1000grs | D80: 7790360974686 | E80: 12 | F80: 12 | G80: =+VLOOKUP(B80,$T$4:$U$106,2,FALSE) -> 75339.603 | I80: =+G80*(1-H80) -> 75339.603 | J80: =+I80/F80 -> 6278.3002 | K80: =+J80*K$3 -> 1318.4431 | L80: =+J80+K80 -> 7596.7433 | M80: =+L80*M$3 -> 2279.023 | N80: =+L80+M80 -> 9875.7663 | O80: =+N80*O$3 -> 3950.3065 | P80: =+N80+O80 -> 13826.073 | R80: 75339.603 | S80: =+(I80-R80)/R80 -> 0 | T80: 100516219 | U80: 18259.4
B81: 100518463 | C81: MILANESAS DE CARNE VACUNA CONG GRANEL 5 kg (CAL GR) | E81: 5 | F81: 1 | G81: =+VLOOKUP(B81,$T$4:$U$106,2,FALSE) -> 36693.267 | I81: =+G81*(1-H81) -> 36693.267 | J81: =+I81/F81 -> 36693.267 | K81: =+J81*K$3 -> 7705.5861 | L81: =+J81+K81 -> 44398.853 | M81: =+L81*M$3 -> 13319.656 | N81: =+L81+M81 -> 57718.509 | O81: =+N81*O$3 -> 23087.404 | P81: =+N81+O81 -> 80805.913 | R81: 36693.267 | S81: =+(I81-R81)/R81 -> 0 | T81: 100516220 | U81: 19613.922
G82: #VALUE! | I82: =+G82*(1-H82) -> #VALUE! | J82: =+I82/F82 -> #VALUE! | M82: 0.2 | O82: 0.35 | R82: #VALUE! | S82: =+(I82-R82)/R82 -> #VALUE! | U82: #VALUE!
B83: 100518291 | C83: GRASA VACUNA REFINADA SWIFT 10 X 500 | D83: 7790360975195 | E83: 5 | F83: 10 | G83: =+VLOOKUP(B83,$T$4:$U$106,2,FALSE) -> 15651.493 | I83: =+G83*(1-H83) -> 15651.493 | J83: =+I83/F83 -> 1565.1493 | K83: =+J83*K$3 -> 328.68136 | L83: =+J83+K83 -> 1893.8307 | M83: =+L83*M$39 -> 378.76613 | N83: =+L83+M83 -> 2272.5968 | O83: =+N83*O$39 -> 795.40888 | P83: =+N83+O83 -> 3068.0057 | Q83: 0.15 | R83: 14906.184 | S83: =+(I83-R83)/R83 -> 0.05 | T83: 100518158 | U83: 75339.603
B84: 100518292 | C84: GRASA VACUNA REFINADA SWIFT 12x1Kg | D84: 7790360975201 | E84: 12 | F84: 12 | G84: =+VLOOKUP(B84,$T$4:$U$106,2,FALSE) -> 36931.939 | I84: =+G84*(1-H84) -> 36931.939 | J84: =+I84/F84 -> 3077.6616 | K84: =+J84*K$3 -> 646.30893 | L84: =+J84+K84 -> 3723.9705 | M84: =+L84*M$39 -> 744.7941 | N84: =+L84+M84 -> 4468.7646 | O84: =+N84*O$39 -> 1564.0676 | P84: =+N84+O84 -> 6032.8322 | Q84: 0.15 | R84: 35173.275 | S84: =+(I84-R84)/R84 -> 0.05 | T84: 100518160 | U84: 75339.603
G85: #VALUE! | I85: =+G85*(1-H85) -> #VALUE! | J85: =+I85/F85 -> #VALUE! | K85: 0.105 | M85: 0.3 | O85: 0.4 | R85: #VALUE! | S85: =+(I85-R85)/R85 -> #VALUE! | T85: 100518463 | U85: 36693.267
B86: 100517915 | C86: CARNE PICADA CONGELADA 36 UN X 500 g SWIFT | D86: 7790360974020 | E86: 18 | F86: 36 | G86: =+VLOOKUP(B86,$T$4:$U$106,2,FALSE) -> 160512.01 | I86: =+G86*(1-H86) -> 160512.01 | J86: =+I86/F86 -> 4458.667 | K86: =+J86*K$85 -> 468.16004 | L86: =+J86+K86 -> 4926.827 | M86: =+L86*M$85 -> 1478.0481 | N86: =+L86+M86 -> 6404.8752 | O86: =+N86*O$85 -> 2561.9501 | P86: =+N86+O86 -> 8966.8252 | R86: 160512.01 | S86: =+(I86-R86)/R86 -> 0 | U86: #VALUE!
B87: 100517914 | C87: CARNE PICADA CONGELADA 20 UN X 1 kg SWIFT | D87: 7790360974037 | E87: 20 | F87: 20 | G87: =+VLOOKUP(B87,$T$4:$U$106,2,FALSE) -> 175154.27 | I87: =+G87*(1-H87) -> 175154.27 | J87: =+I87/F87 -> 8757.7137 | K87: =+J87*K$85 -> 919.55994 | L87: =+J87+K87 -> 9677.2737 | M87: =+L87*M$85 -> 2903.1821 | N87: =+L87+M87 -> 12580.456 | O87: =+N87*O$85 -> 5032.1823 | P87: =+N87+O87 -> 17612.638 | R87: 175154.27 | S87: =+(I87-R87)/R87 -> 0 | T87: 100518291 | U87: 15651.493
G88: =+VLOOKUP(B88,$T$4:$U$106,2,FALSE) -> #N/A | I88: =+G88*(1-H88) -> #N/A | K88: 0.105 | M88: 0.3 | O88: 0.4 | R88: #N/A | S88: =+(I88-R88)/R88 -> #N/A | T88: 100518292 | U88: 36931.939
B89: 100010689 | C89: ENTRAÑA FINA ENF SWIFT | E89: 22 | F89: 1 | G89: =+VLOOKUP(B89,$T$4:$U$106,2,FALSE) -> 16500 | I89: =+G89*(1-H89) -> 16500 | J89: =+I89/F89 -> 16500 | K89: =+J89*K$88 -> 1732.5 | L89: =+J89+K89 -> 18232.5 | M89: =+L89*M$88 -> 5469.75 | N89: =+L89+M89 -> 23702.25 | O89: =+N89*O$88 -> 9480.9 | P89: =+N89+O89 -> 33183.15 | R89: 15714.286 | S89: =+(I89-R89)/R89 -> 0.05 | U89: #VALUE!
B90: 100518335 | C90: ROAST BEEF EN PORCIONES ENF SWIFT (L) | E90: 22.5 | F90: 1 | G90: =+VLOOKUP(B90,$T$4:$U$106,2,FALSE) -> 11785.714 | I90: =+G90*(1-H90) -> 11785.714 | J90: =+I90/F90 -> 11785.714 | K90: =+J90*K$88 -> 1237.5 | L90: =+J90+K90 -> 13023.214 | M90: =+L90*M$88 -> 3906.9643 | N90: =+L90+M90 -> 16930.179 | O90: =+N90*O$88 -> 6772.0714 | P90: =+N90+O90 -> 23702.25 | R90: 11224.49 | S90: =+(I90-R90)/R90 -> 0.05 | T90: 100517915 | U90: 160512.01
B91: 100518332 | C91: CARNAZA CUADRADA EN PORCIONES ENF SWIFT (L) | E91: 21.5 | F91: 1 | G91: =+VLOOKUP(B91,$T$4:$U$106,2,FALSE) -> 13553.571 | I91: =+G91*(1-H91) -> 13553.571 | J91: =+I91/F91 -> 13553.571 | K91: =+J91*K$88 -> 1423.125 | L91: =+J91+K91 -> 14976.696 | M91: =+L91*M$88 -> 4493.0089 | N91: =+L91+M91 -> 19469.705 | O91: =+N91*O$88 -> 7787.8821 | P91: =+N91+O91 -> 27257.588 | R91: 12908.163 | S91: =+(I91-R91)/R91 -> 0.05 | T91: 100517914 | U91: 175154.27
B92: 100518334 | C92: TAPA DE ASADO EN PORCIONES ENF SWIFT (L) | E92: 22.5 | F92: 1 | G92: =+VLOOKUP(B92,$T$4:$U$106,2,FALSE) -> 12021.429 | I92: =+G92*(1-H92) -> 12021.429 | J92: =+I92/F92 -> 12021.429 | K92: =+J92*K$88 -> 1262.25 | L92: =+J92+K92 -> 13283.679 | M92: =+L92*M$88 -> 3985.1036 | N92: =+L92+M92 -> 17268.782 | O92: =+N92*O$88 -> 6907.5129 | P92: =+N92+O92 -> 24176.295 | R92: 11448.98 | S92: =+(I92-R92)/R92 -> 0.05
B93: 100518227 | C93: VACIO EN PORCIONES NOV ENFRIADO PARA VENTA LOCAL (L) | E93: 22.5 | F93: 1 | G93: =+VLOOKUP(B93,$T$4:$U$106,2,FALSE) -> 14185.286 | I93: =+G93*(1-H93) -> 14185.286 | J93: =+I93/F93 -> 14185.286 | K93: =+J93*K$88 -> 1489.455 | L93: =+J93+K93 -> 15674.741 | M93: =+L93*M$88 -> 4702.4222 | N93: =+L93+M93 -> 20377.163 | O93: =+N93*O$88 -> 8150.8652 | P93: =+N93+O93 -> 28528.028 | R93: 13244.898 | S93: =+(I93-R93)/R93 -> 0.071 | T93: 100010689 | U93: 16500
B94: 100027726 | C94: BONDIOLA DE CERDO CONGELADA | D94: 22.5 | E94: 1 | F94: 1 | G94: =+VLOOKUP(B94,$T$4:$U$106,2,FALSE) -> 7155.225 | I94: =+G94*(1-H94) -> 7155.225 | J94: =+I94/F94 -> 7155.225 | K94: =+J94*K$88 -> 751.29863 | L94: =+J94+K94 -> 7906.5236 | M94: =+L94*M$88 -> 2371.9571 | N94: =+L94+M94 -> 10278.481 | O94: =+N94*O$88 -> 4111.3923 | P94: =+N94+O94 -> 14389.873 | R94: 6814.5 | T94: 100518335 | U94: 11785.714
G95: =+VLOOKUP(B95,$T$4:$U$106,2,FALSE) -> #N/A | I95: =+G95*(1-H95) -> #N/A | K95: 0.21 | M95: 0.3 | O95: 0.4 | R95: #N/A | S95: =+(I95-R95)/R95 -> #N/A | T95: 100518332 | U95: 13553.571
B96: 100520837 | C96: CHORIZOS FRESCOS DE CERDO LIBRE DE GLUTEN | D96: 7790360980625 | E96: 4.8 | F96: 12 | G96: =+VLOOKUP(B96,$T$4:$U$106,2,FALSE) -> 37186.423 | I96: =+G96*(1-H96) -> 37186.423 | J96: =+I96/F96 -> 3098.8685 | K96: =+J96*K$95 -> 650.76239 | L96: =+J96+K96 -> 3749.6309 | M96: =+L96*M$95 -> 1124.8893 | N96: =+L96+M96 -> 4874.5202 | O96: =+N96*O$95 -> 1949.8081 | P96: =+N96+O96 -> 6824.3283 | R96: 35756.176 | S96: =+(I96-R96)/R96 -> 0.04 | T96: 100518334 | U96: 12021.429
B97: 100522395 | C97: CHORIZOS FRESCOS DE CERDO CONGELADOS LIBRE DE GLUTEN 12u x 400g | D97: 7790360980625 | E97: 4.8 | F97: 12 | G97: =+VLOOKUP(B97,$T$4:$U$106,2,FALSE) -> 37930.144 | I97: =+G97*(1-H97) -> 37930.144 | J97: =+I97/F97 -> 3160.8453 | K97: =+J97*K$95 -> 663.77751 | L97: =+J97+K97 -> 3824.6228 | M97: =+L97*M$95 -> 1147.3868 | N97: =+L97+M97 -> 4972.0097 | O97: =+N97*O$95 -> 1988.8039 | P97: =+N97+O97 -> 6960.8135 | R97: 36471.292 | S97: =+(I97-R97)/R97 -> 0.04 | T97: 100518227 | U97: 14185.286
B98: 100522561 | C98: CHORIZOS CONGELADOS DE CERDO LIBRE DE GLUTEN SWIFT GRANEL | E98: 16 | F98: 8 | G98: =+VLOOKUP(B98,$T$4:$U$106,2,FALSE) -> 7507.0076 | I98: =+G98*(1-H98) -> 7507.0076 | J98: =+I98*2 -> 15014.015 | K98: =+J98*K$95 -> 3152.9432 | L98: =+J98+K98 -> 18166.958 | M98: =+L98*M$95 -> 5450.0875 | N98: =+L98+M98 -> 23617.046 | O98: =+N98*O$95 -> 9446.8184 | P98: =+N98+O98 -> 33063.864 | R98: #N/A | S98: =+(I98-R98)/R98 -> #N/A | T98: 100027726 | U98: 7155.225
G99: =+VLOOKUP(B99,$T$4:$U$106,2,FALSE) -> #N/A | I99: =+G99*(1-H99) -> #N/A | K99: 0.21 | M99: 0.3 | O99: 0.4 | R99: #N/A | S99: =+(I99-R99)/R99 -> #N/A
