Workbook

Sheet Litoral
A2: Código | B2: Descripción | C2: EAN | D2: Kg. x Caja | E2: Cant. X Caja | F2: Precio de Lista | G2: Dcto | H2: Precio de Factura | I2: Precio Neto estuche en factura | J2: IVA | K2: Px Unitario IVA Inc | L2: M-up Dx | M2: Px Unitario Minorista | N2: M-up Minorista | O2: Px Unitario Público | Q2: NOV | AF2: SEP | AG2: %
J3: 0.21 | L3: 0.35 | N3: 0.45
A4: 100021632 | B4: HAMBURGUESAS 30x160g CLASICA x2 SWIFT | C4: 7790360026606 | D4: 4.8 | E4: 30 | F4: =+VLOOKUP(A4,$AK$4:$AL$108,2,FALSE) -> 38344.554 | H4: =+F4*(1-G4) -> 38344.554 | I4: =+H4/E4 -> 1278.1518 | J4: =+I4*J$3 -> 268.41188 | K4: =+I4+J4 -> 1546.5637 | L4: =+K4*L$3 -> 541.29729 | M4: =+K4+L4 -> 2087.861 | N4: =+M4*N$3 -> 939.53744 | O4: =+M4+N4 -> 3027.3984 | P4: =H4/Q4-1 -> 0.08 | Q4: 35504.217 | AF4: 29534.055 | AG4: =+(H4-AF4)/AF4 -> 0.2983166 | AK4: 100021632 | AL4: 38344.554 | AN4: =+Q4/H4 -> 0.92592593
A5: 100021652 | B5: HAMBURGUESA 18X4X80G CLASICA SWIFT | C5: 7790360026576 | D5: 5.76 | E5: 18 | F5: =+VLOOKUP(A5,$AK$4:$AL$108,2,FALSE) -> 46159.859 | H5: =+F5*(1-G5) -> 46159.859 | I5: =+H5/E5 -> 2564.4366 | J5: =+I5*J$3 -> 538.53169 | K5: =+I5+J5 -> 3102.9683 | L5: =+K5*L$3 -> 1086.0389 | M5: =+K5+L5 -> 4189.0072 | N5: =+M5*N$3 -> 1885.0532 | O5: =+M5+N5 -> 6074.0605 | P5: =H5/Q5-1 -> 0.08 | Q5: 42740.61 | AF5: 38042.377 | AG5: =+(H5-AF5)/AF5 -> 0.21338 | AK5: 100021652 | AL5: 46159.859 | AN5: =+Q5/H5 -> 0.92592593
A6: 100021631 | B6: HAMBURGUESA 8X12X80G CLASICA SWIFT | C6: 7790360026590 | D6: 7.68 | E6: 8 | F6: =+VLOOKUP(A6,$AK$4:$AL$108,2,FALSE) -> 58510.949 | H6: =+F6*(1-G6) -> 58510.949 | I6: =+H6/E6 -> 7313.8687 | J6: =+I6*J$3 -> 1535.9124 | K6: =+I6+J6 -> 8849.7811 | L6: =+K6*L$3 -> 3097.4234 | M6: =+K6+L6 -> 11947.204 | N6: =+M6*N$3 -> 5376.242 | O6: =+M6+N6 -> 17323.447 | P6: =H6/Q6-1 -> 0.03 | Q6: 56806.747 | AF6: 63884.504 | AG6: =+(H6-AF6)/AF6 -> -0.084113578 | AK6: 100021631 | AL6: 58510.949 | AN6: =+Q6/H6 -> 0.97087379
A7: 100021630 | B7: HAMBURGUESA 6X20X80G CLASICA SWIFT | C7: 7790360026583 | D7: 9.6 | E7: 6 | F7: =+VLOOKUP(A7,$AK$4:$AL$108,2,FALSE) -> 71718.518 | H7: =+F7*(1-G7) -> 71718.518 | I7: =+H7/E7 -> 11953.086 | J7: =+I7*J$3 -> 2510.1481 | K7: =+I7+J7 -> 14463.234 | L7: =+K7*L$3 -> 5062.1321 | M7: =+K7+L7 -> 19525.367 | N7: =+M7*N$3 -> 8786.415 | O7: =+M7+N7 -> 28311.782 | P7: =H7/Q7-1 -> 0.01 | Q7: 71008.434 | AF7: 79885.735 | AG7: =+(H7-AF7)/AF7 -> -0.10223624 | AK7: 100021630 | AL7: 71718.518 | AN7: =+Q7/H7 -> 0.99009901
A8: 100021653 | B8: MEDALLON 18X4X80G PARRILLERO SWIFT | C8: 7790360026682 | D8: 5.76 | E8: 18 | F8: =+VLOOKUP(A8,$AK$4:$AL$108,2,FALSE) -> 50614.812 | H8: =+F8*(1-G8) -> 50614.812 | I8: =+H8/E8 -> 2811.934 | J8: =+I8*J$3 -> 590.50614 | K8: =+I8+J8 -> 3402.4401 | L8: =+K8*L$3 -> 1190.854 | M8: =+K8+L8 -> 4593.2942 | N8: =+M8*N$3 -> 2066.9824 | O8: =+M8+N8 -> 6660.2765 | P8: =H8/Q8-1 -> 0.08 | Q8: 46865.566 | AF8: 50298.202 | AG8: =+(H8-AF8)/AF8 -> 0.0062946466 | AK8: 100021653 | AL8: 50614.812 | AN8: =+Q8/H8 -> 0.92592593
A9: 100516169 | B9: MEDALLONES 18X4X80G SWIFT RECETA ESPECIAL | C9: 7790360967961 | D9: 5.76 | E9: 18 | F9: =+VLOOKUP(A9,$AK$4:$AL$108,2,FALSE) -> 46670.247 | H9: =+F9*(1-G9) -> 46670.247 | I9: =+H9/E9 -> 2592.7915 | J9: =+I9*J$3 -> 544.48622 | K9: =+I9+J9 -> 3137.2777 | L9: =+K9*L$3 -> 1098.0472 | M9: =+K9+L9 -> 4235.3249 | N9: =+M9*N$3 -> 1905.8962 | O9: =+M9+N9 -> 6141.2212 | P9: =H9/Q9-1 -> 0.08 | Q9: 43213.192 | AF9: 41155.421 | AG9: =+(H9-AF9)/AF9 -> 0.134 | AK9: 100516169 | AL9: 46670.247 | AN9: =+Q9/H9 -> 0.92592593
A10: 100520337 | B10: MEDALLON BURGER SWIFT MEGA 30 x 160 g | C10: 7790360977960 | D10: 4.8 | E10: 30 | F10: =+VLOOKUP(A10,$AK$4:$AL$108,2,FALSE) -> 27112.263 | H10: =+F10*(1-G10) -> 27112.263 | I10: =+H10/E10 -> 903.74209 | J10: =+I10*J$3 -> 189.78584 | K10: =+I10+J10 -> 1093.5279 | L10: =+K10*L$3 -> 382.73478 | M10: =+K10+L10 -> 1476.2627 | N10: =+M10*N$3 -> 664.31822 | O10: =+M10+N10 -> 2140.5809 | P10: =H10/Q10-1 -> 0.08 | Q10: 25103.947 | AF10: 25103.947 | AG10: =+(H10-AF10)/AF10 -> 0.08 | AK10: 100520337 | AL10: 27112.263 | AN10: =+Q10/H10 -> 0.92592593
A11: 100021503 | B11: Medallón CAJITA 12x4 69 grs | C11: 7790360966841 | D11: 3.312 | E11: 12 | F11: =+VLOOKUP(A11,$AK$4:$AL$108,2,FALSE) -> 20700.913 | G11: 0.0833 | H11: =+F11*(1-G11) -> 18976.527 | I11: =+H11/E11 -> 1581.3773 | J11: =+I11*J$3 -> 332.08922 | K11: =+I11+J11 -> 1913.4665 | L11: =+K11*L$3 -> 669.71327 | M11: =+K11+L11 -> 2583.1797 | N11: =+M11*N$3 -> 1162.4309 | O11: =+M11+N11 -> 3745.6106 | P11: =H11/Q11-1 -> 0.08 | Q11: 17570.858 | S11: Contra 11 estuches + 1 de regalo | AF11: 15081.22 | AG11: =+(H11-AF11)/AF11 -> 0.25828861 | AK11: 100021503 | AL11: 20700.913 | AN11: =+Q11/H11 -> 0.92592593
A12: 100516201 | B12: HAMBURGUESA 8X12X69G BURGER SWIFT | C12: 7790360968548 | D12: 6.624 | E12: 8 | F12: =+VLOOKUP(A12,$AK$4:$AL$108,2,FALSE) -> 45229.534 | H12: =+F12*(1-G12) -> 45229.534 | I12: =+H12/E12 -> 5653.6917 | J12: =+I12*J$3 -> 1187.2753 | K12: =+I12+J12 -> 6840.967 | L12: =+K12*L$3 -> 2394.3385 | M12: =+K12+L12 -> 9235.3055 | N12: =+M12*N$3 -> 4155.8875 | O12: =+M12+N12 -> 13391.193 | P12: =H12/Q12-1 -> 0.08 | Q12: 41879.198 | AF12: 37985.667 | AG12: =+(H12-AF12)/AF12 -> 0.1907 | AK12: 100516201 | AL12: 45229.534 | AN12: =+Q12/H12 -> 0.92592593
A13: 100021643 | B13: MEDALLON 42X112G DOBLE BURGER SWIFT | C13: 7790360966797 | D13: 4.704 | E13: 42 | F13: =+VLOOKUP(A13,$AK$4:$AL$108,2,FALSE) -> 27737.901 | H13: =+F13*(1-G13) -> 27737.901 | I13: =+H13/E13 -> 660.42622 | J13: =+I13*J$3 -> 138.68951 | K13: =+I13+J13 -> 799.11572 | L13: =+K13*L$3 -> 279.6905 | M13: =+K13+L13 -> 1078.8062 | N13: =+M13*N$3 -> 485.4628 | O13: =+M13+N13 -> 1564.269 | P13: =H13/Q13-1 -> 0.08 | Q13: 25683.242 | AF13: 23295.457 | AG13: =+(H13-AF13)/AF13 -> 0.1907 | AK13: 100021643 | AL13: 27737.901 | AN13: =+Q13/H13 -> 0.92592593
A14: 100516325 | B14: MEDALLON DOBLE BURGER 2X2 | C14: 7790360967763 | D14: 4.704 | E14: 21 | F14: =+VLOOKUP(A14,$AK$4:$AL$108,2,FALSE) -> 31195.33 | H14: =+F14*(1-G14) -> 31195.33 | I14: =+H14/E14 -> 1485.4919 | J14: =+I14*J$3 -> 311.9533 | K14: =+I14+J14 -> 1797.4452 | L14: =+K14*L$3 -> 629.10582 | M14: =+K14+L14 -> 2426.551 | N14: =+M14*N$3 -> 1091.948 | O14: =+M14+N14 -> 3518.499 | P14: =H14/Q14-1 -> 0.08 | Q14: 28884.565 | AF14: 27509.109 | AG14: =+(H14-AF14)/AF14 -> 0.134 | AK14: 100516325 | AL14: 31195.33 | AN14: =+Q14/H14 -> 0.92592593
A15: 100021676 | B15: HAMBURGUESA 30X250g CLASICA "XL" SWIFT | C15: 7790360967411 | D15: 7.5 | E15: 30 | F15: =+VLOOKUP(A15,$AK$4:$AL$108,2,FALSE) -> 60777.549 | G15: 0.0667 | H15: =+F15*(1-G15) -> 56723.687 | I15: =+H15/E15 -> 1890.7896 | J15: =+I15*J$3 -> 397.06581 | K15: =+I15+J15 -> 2287.8554 | L15: =+K15*L$3 -> 800.74938 | M15: =+K15+L15 -> 3088.6047 | N15: =+M15*N$3 -> 1389.8721 | O15: =+M15+N15 -> 4478.4769 | P15: =H15/Q15-1 -> 0.08 | Q15: 52521.932 | S15: Contra 14 flow + 1 de regalo | AF15: 53595.722 | AG15: =+(H15-AF15)/AF15 -> 0.0583622 | AK15: 100021676 | AL15: 60777.549 | AN15: =+Q15/H15 -> 0.92592593
A16: 100516008 | B16: HAMBURGUESA 24X2X120g CASERA SWIFT | C16: 7790360967701 | D16: 5.76 | E16: 24 | F16: =+VLOOKUP(A16,$AK$4:$AL$108,2,FALSE) -> 50957.087 | G16: 0.0909 | H16: =+F16*(1-G16) -> 46325.088 | I16: =+H16/E16 -> 1930.212 | J16: =+I16*J$3 -> 405.34452 | K16: =+I16+J16 -> 2335.5565 | L16: =+K16*L$3 -> 817.44477 | M16: =+K16+L16 -> 3153.0013 | N16: =+M16*N$3 -> 1418.8506 | O16: =+M16+N16 -> 4571.8518 | P16: =H16/Q16-1 -> 0.02 | Q16: 45416.753 | S16: OFERTA Compra 10 FLOW + 1 de regalo | AF16: 47578.979 | AG16: =+(H16-AF16)/AF16 -> -0.0263539 | AK16: 100516008 | AL16: 50957.087 | AN16: =+Q16/H16 -> 0.98039216
A17: 100520834 | B17: HAMBURGUESA X-TREMA 36 x 185 grs | C17: 7790360980618 | D17: 6.66 | E17: 36 | F17: =+VLOOKUP(A17,$AK$4:$AL$108,2,FALSE) -> 63095.588 | H17: =+F17*(1-G17) -> 63095.588 | I17: =+H17/E17 -> 1752.6552 | J17: =+I17*J$3 -> 368.0576 | K17: =+I17+J17 -> 2120.7128 | L17: =+K17*L$3 -> 742.24949 | M17: =+K17+L17 -> 2862.9623 | N17: =+M17*N$3 -> 1288.333 | O17: =+M17+N17 -> 4151.2954 | P17: =H17/Q17-1 -> 0.08 | Q17: 58421.841 | AF17: 55639.849 | AG17: =+(H17-AF17)/AF17 -> 0.134 | AK17: 100520834 | AL17: 63095.588 | AN17: =+Q17/H17 -> 0.92592593
A18: 100021680 | B18: HAMBURGUESAS 18X2X120g CLL BRA/ARG | C18: 7790360967688 | D18: 4.32 | E18: 18 | F18: =+VLOOKUP(A18,$AK$4:$AL$108,2,FALSE) -> 50536.767 | H18: =+F18*(1-G18) -> 50536.767 | I18: =+H18/E18 -> 2807.5981 | J18: =+I18*J$3 -> 589.59561 | K18: =+I18+J18 -> 3397.1938 | L18: =+K18*L$3 -> 1189.0178 | M18: =+K18+L18 -> 4586.2116 | N18: =+M18*N$3 -> 2063.7952 | O18: =+M18+N18 -> 6650.0068 | P18: =H18/Q18-1 -> 0.08 | Q18: 46793.302 | AF18: 44565.05 | AG18: =+(H18-AF18)/AF18 -> 0.134 | AK18: 100021680 | AL18: 50536.767 | AN18: =+Q18/H18 -> 0.92592593
A19: 100021644 | B19: MEDALLON 42X112G LA BLANCA | C19: 7790360008541 | D19: 4.704 | E19: 42 | F19: =+VLOOKUP(A19,$AK$4:$AL$108,2,FALSE) -> 19172.581 | H19: =+F19*(1-G19) -> 19172.581 | I19: =+H19/E19 -> 456.49003 | J19: =+I19*J$3 -> 95.862907 | K19: =+I19+J19 -> 552.35294 | L19: =+K19*0.3 -> 165.70588 | M19: =+K19+L19 -> 718.05882 | N19: =+M19*N$3 -> 323.12647 | O19: =+M19+N19 -> 1041.1853 | P19: =H19/Q19-1 -> 0.1 | Q19: 17429.619 | AF19: 14434.467 | AG19: =+(H19-AF19)/AF19 -> 0.32825 | AK19: 100021644 | AL19: 19172.581 | AN19: =+Q19/H19 -> 0.90909091
A20: 100021677 | B20: MEDALLON 12x4X69G LA BLANCA | C20: 7790360967404 | D20: 3.312 | E20: 12 | F20: =+VLOOKUP(A20,$AK$4:$AL$108,2,FALSE) -> 15215.664 | H20: =+F20*(1-G20) -> 15215.664 | I20: =+H20/E20 -> 1267.972 | J20: =+I20*J$3 -> 266.27413 | K20: =+I20+J20 -> 1534.2462 | L20: =+K20*0.3 -> 460.27385 | M20: =+K20+L20 -> 1994.52 | N20: =+M20*N$3 -> 897.53401 | O20: =+M20+N20 -> 2892.054 | P20: =H20/Q20-1 -> 0.1 | Q20: 13832.422 | AF20: 13173.735 | AG20: =+(H20-AF20)/AF20 -> 0.155 | AK20: 100021677 | AL20: 15215.664 | AN20: =+Q20/H20 -> 0.90909091
A21: 100021638 | B21: MEDALLONES 60X80g "SWIFT BURGER" PARRILLERAS FAMILY | C21: 7790360026699 | D21: 4.8 | E21: 60 | F21: =+VLOOKUP(A21,$AK$4:$AL$108,2,FALSE) -> 47532.849 | H21: =+F21*(1-G21) -> 47532.849 | I21: =+H21/E21 -> 792.21415 | J21: =+I21*J$3 -> 166.36497 | K21: =+I21+J21 -> 958.57912 | L21: =+K21*L$3 -> 335.50269 | M21: =+K21+L21 -> 1294.0818 | N21: =+M21*N$3 -> 582.33681 | O21: =+M21+N21 -> 1876.4186 | P21: =H21/Q21-1 -> 0.08 | Q21: 44011.897 | AF21: 41916.092 | AG21: =+(H21-AF21)/AF21 -> 0.134 | AK21: 100021638 | AL21: 47532.849 | AN21: =+Q21/H21 -> 0.92592593
A22: 100021575 | B22: MEDALLONES 60X69g "SWIFT BURGER"PARRILLERAS FAMILY | C22: 7790360007032 | D22: 4.14 | E22: 60 | F22: =+VLOOKUP(A22,$AK$4:$AL$108,2,FALSE) -> 38984.492 | H22: =+F22*(1-G22) -> 38984.492 | I22: =+H22/E22 -> 649.74153 | J22: =+I22*J$3 -> 136.44572 | K22: =+I22+J22 -> 786.18725 | L22: =+K22*L$3 -> 275.16554 | M22: =+K22+L22 -> 1061.3528 | N22: =+M22*N$3 -> 477.60875 | O22: =+M22+N22 -> 1538.9615 | P22: =H22/Q22-1 -> 0.08 | Q22: 36096.752 | AF22: 34377.859 | AG22: =+(H22-AF22)/AF22 -> 0.134 | AK22: 100021575 | AL22: 38984.492 | AN22: =+Q22/H22 -> 0.92592593
A23: 100021514 | B23: MEDALLON 60X69G CARNE VACUNA | C23: 7790360006943 | D23: 4.14 | E23: 60 | F23: =+VLOOKUP(A23,$AK$4:$AL$108,2,FALSE) -> 35475.666 | H23: =+F23*(1-G23) -> 35475.666 | I23: =+H23/E23 -> 591.26111 | J23: =+I23*J$3 -> 124.16483 | K23: =+I23+J23 -> 715.42594 | L23: =+K23*L$3 -> 250.39908 | M23: =+K23+L23 -> 965.82502 | N23: =+M23*N$3 -> 434.62126 | O23: =+M23+N23 -> 1400.4463 | P23: =H23/Q23-1 -> 0.08 | Q23: 32847.839 | AF23: 31283.656 | AG23: =+(H23-AF23)/AF23 -> 0.134 | AK23: 100021514 | AL23: 35475.666 | AN23: =+Q23/H23 -> 0.92592593
A24: 100516208 | B24: MEDALLON 60x80g PARRILLERO MC SWIFT | C24: 7790360968203 | D24: =60*0.08 -> 4.8 | E24: 60 | F24: =+VLOOKUP(A24,$AK$4:$AL$108,2,FALSE) -> 41131.229 | H24: =+F24*(1-G24) -> 41131.229 | I24: =+H24/E24 -> 685.52049 | J24: =+I24*J$3 -> 143.9593 | K24: =+I24+J24 -> 829.47979 | L24: =+K24*L$3 -> 290.31793 | M24: =+K24+L24 -> 1119.7977 | N24: =+M24*N$3 -> 503.90897 | O24: =+M24+N24 -> 1623.7067 | P24: =H24/Q24-1 -> 0.08 | Q24: 38084.471 | AF24: 36270.925 | AG24: =+(H24-AF24)/AF24 -> 0.134 | AK24: 100516208 | AL24: 41131.229 | AN24: =+Q24/H24 -> 0.92592593
A25: 100518346 | B25: MEDALLON 60X109G CARNE VACUNA PARRILLERO SWIFT | C25: 7790360975478 | D25: =60*0.109 -> 6.54 | E25: 60 | F25: =+VLOOKUP(A25,$AK$4:$AL$108,2,FALSE) -> 58788.442 | H25: =+F25*(1-G25) -> 58788.442 | I25: =+H25/E25 -> 979.80737 | J25: =I25*J3 -> 205.75955 | K25: =J25+I25 -> 1185.5669 | L25: =K25*L3 -> 414.94842 | M25: =L25+K25 -> 1600.5153 | N25: =M25*N3 -> 720.2319 | O25: =N25+M25 -> 2320.7472 | P25: =H25/Q25-1 -> 0.08 | Q25: 54433.743 | AF25: 51841.66 | AG25: =+(H25-AF25)/AF25 -> 0.134 | AK25: 100518346 | AL25: 58788.442 | AN25: =+Q25/H25 -> 0.92592593
A26: 100516259 | B26: MEDALLON GIGANTE 48x113.5g | C26: 7790360968340 | D26: 18.16 | E26: 48 | F26: =+VLOOKUP(A26,$AK$4:$AL$108,2,FALSE) -> 136018.21 | H26: =+F26*(1-G26) -> 136018.21 | I26: =+H26/E26 -> 2833.7127 | J26: =+I26*J$3 -> 595.07967 | K26: =+I26+J26 -> 3428.7924 | L26: =+K26*L$3 -> 1200.0773 | M26: =+K26+L26 -> 4628.8697 | N26: =+M26*N$3 -> 2082.9914 | O26: =+M26+N26 -> 6711.8611 | P26: =H26/Q26-1 -> 0.08 | Q26: 125942.79 | AF26: 119945.51 | AG26: =+(H26-AF26)/AF26 -> 0.134 | AK26: 100516259 | AL26: 136018.21 | AN26: =+Q26/H26 -> 0.92592593
A27: 100518095 | B27: HAMBURGUESA 36 X 185 GRS | C27: 7790360974785 | D27: 6.66 | E27: 36 | F27: =+VLOOKUP(A27,$AK$4:$AL$108,2,FALSE) -> 67770.616 | H27: =+F27*(1-G27) -> 67770.616 | I27: =+H27/E27 -> 1882.5171 | J27: =+I27*J$3 -> 395.32859 | K27: =+I27+J27 -> 2277.8457 | L27: =+K27*L$3 -> 797.24599 | M27: =+K27+L27 -> 3075.0917 | N27: =+M27*N$3 -> 1383.7913 | O27: =+M27+N27 -> 4458.883 | P27: =H27/Q27-1 -> 0.08 | Q27: 62750.57 | AF27: 59762.448 | AG27: =+(H27-AF27)/AF27 -> 0.134 | AK27: 100518095 | AL27: 67770.616 | AN27: =+Q27/H27 -> 0.92592593
A28: 100518223 | B28: HAMBURGUESA 30x2x106 GRS | C28: 7790360975065 | D28: =60*0.106 -> 6.36 | E28: 30 | F28: =+VLOOKUP(A28,$AK$4:$AL$108,2,FALSE) -> 52763.191 | H28: =+F28*(1-G28) -> 52763.191 | I28: =+H28/E28 -> 1758.773 | J28: =+I28*J$3 -> 369.34234 | K28: =+I28+J28 -> 2128.1154 | L28: =+K28*L$3 -> 744.84038 | M28: =+K28+L28 -> 2872.9557 | N28: =+M28*N$3 -> 1292.8301 | O28: =+M28+N28 -> 4165.7858 | P28: =H28/Q28-1 -> 0.08 | Q28: 48854.806 | AF28: 46528.387 | AG28: =+(H28-AF28)/AF28 -> 0.134 | AK28: 100518223 | AL28: 52763.191 | AN28: =+Q28/H28 -> 0.92592593
F29: =+VLOOKUP(A29,$AK$4:$AL$108,2,FALSE) -> #N/A | H29: =+F29*(1-G29) -> #N/A | I29: =+H29/E29 -> #N/A | P29: =H29/Q29-1 -> #N/A | Q29: #N/A | Y29: OCT | Z29: PATY VIENA | AA29: VIENISSIMA | AB29: PALADINI | AF29: #N/A | AG29: =+(H29-AF29)/AF29 -> #N/A | AN29: =+Q29/H29 -> #N/A
A30: 100022085 | B30: SALCHICHAS 24X6 SWIFT | C30: 7790360000132 | D30: 5.4 | E30: 24 | F30: =+VLOOKUP(A30,$AK$4:$AL$108,2,FALSE) -> 22291.884 | G30: =0.0833333333333333*100% -> 0.083333333 | H30: =+F30*(1-G30) -> 20434.227 | I30: =+H30/E30 -> 851.42614 | J30: =+I30*J$3 -> 178.79949 | K30: =+I30+J30 -> 1030.2256 | L30: =+K30*L$3 -> 360.57897 | M30: =+K30+L30 -> 1390.8046 | N30: =+M30*0.438 -> 609.17241 | O30: =+M30+N30 -> 1999.977 | P30: =H30/Q30-1 -> -5.2899972e-07 | Q30: 20434.238 | S30: Px LISTA: $2.200 + compra 11 estuches + 1 de regalo ----> OFERTA $2.000 público | Y30: 1900 | Z30: 2080 | AA30: 2435 | AB30: 2328 | AF30: 18238.814 | AG30: =+(H30-AF30)/AF30 -> 0.12037037 | AK30: 100022085 | AL30: 22291.884 | AN30: =+Q30/H30 -> 1.0000005
A31: 100522204 | B31: SALCHICHAS 24X6 SWIFT | C31: 7790360983947 | D31: 5.4 | E31: 24 | F31: =+VLOOKUP(A31,$AK$4:$AL$108,2,FALSE) -> 22291.884 | G31: =0.0833333333333333*100% -> 0.083333333 | H31: =+F31*(1-G31) -> 20434.227 | I31: =+H31/E31 -> 851.42614 | J31: =+I31*J$3 -> 178.79949 | K31: =+I31+J31 -> 1030.2256 | L31: =+K31*L$3 -> 360.57897 | M31: =+K31+L31 -> 1390.8046 | N31: =+M31*0.438 -> 609.17241 | O31: =+M31+N31 -> 1999.977 | P31: =H31/Q31-1 -> -5.2899972e-07 | Q31: 20434.238 | S31: Px LISTA: $2.200 + compra 11 estuches + 1 de regalo ----> OFERTA $2.000 público | AK31: 100522204 | AL31: 22291.884
A32: 100022072 | B32: SALCHICHAS 12X12 SWIFT | C32: 7790360024541 | D32: 5.4 | E32: 12 | F32: =+VLOOKUP(A32,$AK$4:$AL$108,2,FALSE) -> 21177.29 | G32: =0.0833333333333333*100% -> 0.083333333 | H32: =+F32*(1-G32) -> 19412.516 | I32: =+H32/E32 -> 1617.7097 | J32: =+I32*J$3 -> 339.71903 | K32: =+I32+J32 -> 1957.4287 | L32: =+K32*0.3388 -> 663.17684 | M32: =+K32+L32 -> 2620.6055 | N32: =+M32*N$3 -> 1179.2725 | O32: =+M32+N32 -> 3799.878 | P32: =H32/Q32-1 -> -3.6362314e-05 | Q32: 19413.222 | S32: Conveniencia vs 22085: Oferta $3.800 | Y32: 3600 | Z32: 4090 | AA32: 4495 | AB32: 4400 | AF32: 17225.547 | AG32: =+(H32-AF32)/AF32 -> 0.12696078 | AK32: 100022072 | AL32: 21177.29 | AN32: =+Q32/H32 -> 1.0000364
A33: 100522205 | B33: SALCHICHAS 12X12 SWIFT | C33: 7790360983954 | D33: 5.4 | E33: 12 | F33: =+VLOOKUP(A33,$AK$4:$AL$108,2,FALSE) -> 21177.29 | G33: =0.0833333333333333*100% -> 0.083333333 | H33: =+F33*(1-G33) -> 19412.516 | I33: =+H33/E33 -> 1617.7097 | J33: =+I33*J$3 -> 339.71903 | K33: =+I33+J33 -> 1957.4287 | L33: =+K33*0.3388 -> 663.17684 | M33: =+K33+L33 -> 2620.6055 | N33: =+M33*N$3 -> 1179.2725 | O33: =+M33+N33 -> 3799.878 | P33: =H33/Q33-1 -> -3.6362314e-05 | Q33: 19413.222 | S33: Conveniencia vs 22085: Oferta $3.800 | AK33: 100522205 | AL33: 21177.29
A34: 100516849 | B34: SALCHICHAS SIN PIEL 24X6 "SWIFT KIDS" X 190 g | C34: 7790360970053 | D34: 4.56 | E34: 24 | F34: =+VLOOKUP(A34,$AK$4:$AL$108,2,FALSE) -> 17165.375 | H34: =+F34*(1-G34) -> 17165.375 | I34: =+H34/E34 -> 715.22396 | J34: =+I34*J$3 -> 150.19703 | K34: =+I34+J34 -> 865.421 | L34: =+K34*0.339 -> 293.37772 | M34: =+K34+L34 -> 1158.7987 | N34: =+M34*0.424 -> 491.33065 | O34: =+M34+N34 -> 1650.1294 | P34: =H34/Q34-1 -> 0.05 | Q34: 16347.976 | S34: Oferta incluida en lista: $1.650 | Y34: 1650 | Z34: 1888 | AA34: PATY FUN | AF34: 15705.646 | AG34: =+(H34-AF34)/AF34 -> 0.092942968 | AK34: 100516849 | AL34: 17165.375 | AN34: =+Q34/H34 -> 0.95238095
A35: 100022039 | B35: SALCHICHAS LARGAS 10 x 12 SWIFT INSTITUCIONAL | C35: 7790360007063 | D35: 8.7 | E35: 10 | F35: =+VLOOKUP(A35,$AK$4:$AL$108,2,FALSE) -> 56041.789 | H35: =+F35*(1-G35) -> 56041.789 | I35: =+H35/E35 -> 5604.1789 | J35: =+I35*J$3 -> 1176.8776 | K35: =+I35+J35 -> 6781.0565 | L35: =+K35*L$3 -> 2373.3698 | M35: =+K35+L35 -> 9154.4263 | N35: =+M35*N$3 -> 4119.4918 | O35: =+M35+N35 -> 13273.918 | P35: =H35/Q35-1 -> 0 | Q35: 56041.789 | Z35: ICB | AA35: 66 | AB35: PANCHIN | AC35: fela | AF35: 44083.414 | AG35: =+(H35-AF35)/AF35 -> 0.271267 | AK35: 100022039 | AL35: 56041.789 | AN35: =+Q35/H35 -> 1
A36: 100522206 | B36: SALCHICHAS LARGAS 10 x 12 SWIFT INSTITUCIONAL | C36: 7790360983961 | D36: 8.7 | E36: 10 | F36: 56041.789 | H36: =+F36*(1-G36) -> 56041.789 | I36: =+H36/E36 -> 5604.1789 | J36: =+I36*J$3 -> 1176.8776 | K36: =+I36+J36 -> 6781.0565 | L36: =+K36*L$3 -> 2373.3698 | M36: =+K36+L36 -> 9154.4263 | N36: =+M36*N$3 -> 4119.4918 | O36: =+M36+N36 -> 13273.918 | Q36: 56041.789 | AK36: 100522206 | AL36: 56041.789
A37: 100022058 | B37: SALCHICHAS SIN PIEL "LA BLANCA" 24X6X190 Grs; | C37: 7790360026002 | D37: 4.56 | E37: 24 | F37: =+VLOOKUP(A37,$AK$4:$AL$108,2,FALSE) -> 15783.589 | H37: =+F37*(1-G37) -> 15783.589 | I37: =+H37/E37 -> 657.64956 | J37: =+I37*J$3 -> 138.10641 | K37: =+I37+J37 -> 795.75597 | L37: =+K37*0.3 -> 238.72679 | M37: =+K37+L37 -> 1034.4828 | N37: =+M37*N$3 -> 465.51724 | O37: =+M37+N37 -> 1500 | P37: =H37/Q37-1 -> -0.11598841 | Q37: 17854.505 | Y37: 1130 | Z37: 1190 | AA37: 1000 | AB37: 1198 | AC37: 1500 | AD37: MISMO PX MES ANT | AF37: 11449.922 | AG37: =+(H37-AF37)/AF37 -> 0.37848877 | AK37: 100022058 | AL37: 15783.589 | AN37: =+Q37/H37 -> 1.1312069
A38: 100518151 | B38: SALCHICHAS LARGAS 10 x 12 x 870g | C38: 7790360974990 | D38: 8.7 | E38: 10 | F38: =+VLOOKUP(A38,$AK$4:$AL$108,2,FALSE) -> 63845.74 | H38: =+F38*(1-G38) -> 63845.74 | I38: =+H38/E38 -> 6384.574 | J38: =+I38*J$3 -> 1340.7605 | K38: =+I38+J38 -> 7725.3345 | L38: =+K38*0.3 -> 2317.6003 | M38: =+K38+L38 -> 10042.935 | N38: =+M38*N$3 -> 4519.3207 | O38: =+M38+N38 -> 14562.256 | P38: =H38/Q38-1 -> 0 | Q38: 63845.74 | AF38: 50222.132 | AG38: =+(H38-AF38)/AF38 -> 0.271267 | AK38: 100518151 | AL38: 63845.74 | AN38: =+Q38/H38 -> 1
F39: =+VLOOKUP(A39,$AK$4:$AL$108,2,FALSE) -> #N/A | H39: =+F39*(1-G39) -> #N/A | I39: =+H39/E39 -> #N/A | J39: 0.21 | L39: 0.22 | N39: 0.35 | P39: =H39/Q39-1 -> #N/A | Q39: #N/A | Y39: =+Y37*24 -> 27120 | AF39: #N/A | AG39: =+(H39-AF39)/AF39 -> #N/A | AL39: 0 | AN39: =+Q39/H39 -> #N/A
A40: 100021000 | B40: PATE DE FOIE 24X90G SWIFT | C40: 7790360720382 | D40: 2.16 | E40: 24 | F40: =+VLOOKUP(A40,$AK$4:$AL$108,2,FALSE) -> 12345.023 | H40: =+F40*(1-G40) -> 12345.023 | I40: =+H40/E40 -> 514.37594 | J40: =+I40*J$3 -> 108.01895 | K40: =+I40+J40 -> 622.39489 | L40: =+K40*L$39 -> 136.92688 | M40: =+K40+L40 -> 759.32176 | N40: =+M40*N$39 -> 265.76262 | O40: =+M40+N40 -> 1025.0844 | P40: =H40/Q40-1 -> 0 | Q40: 12345.023 | Y40: =+Y39/1.21/1.35/1.45 -> 11449.922 | Z40: PX 22058 | AF40: 10353.088 | AG40: =+(H40-AF40)/AF40 -> 0.1924 | AK40: 100021000 | AL40: 12345.023 | AN40: =+Q40/H40 -> 1
A41: 100021001 | B41: PICADILLO DE CARNE 24X90G SWIFT | C41: 7790360720115 | D41: 2.16 | E41: 24 | F41: =+VLOOKUP(A41,$AK$4:$AL$108,2,FALSE) -> 12345.023 | H41: =+F41*(1-G41) -> 12345.023 | I41: =+H41/E41 -> 514.37594 | J41: =+I41*J$3 -> 108.01895 | K41: =+I41+J41 -> 622.39489 | L41: =+K41*L$39 -> 136.92688 | M41: =+K41+L41 -> 759.32176 | N41: =+M41*N$39 -> 265.76262 | O41: =+M41+N41 -> 1025.0844 | P41: =H41/Q41-1 -> 0 | Q41: 12345.023 | Y41: =+F37-Y40 -> 4333.667 | AF41: 10353.088 | AG41: =+(H41-AF41)/AF41 -> 0.1924 | AK41: 100021001 | AL41: 12345.023 | AN41: =+Q41/H41 -> 1
A42: 100522277 | B42: Picadillo de Carne Picante Chile Chipotle 24x90 g | D42: 2.16 | E42: 24 | F42: =+VLOOKUP(A42,$AK$4:$AL$108,2,FALSE) -> 12345.023 | H42: =+F42*(1-G42) -> 12345.023 | I42: =+H42/E42 -> 514.37594 | J42: =+I42*J$3 -> 108.01895 | K42: =+I42+J42 -> 622.39489 | L42: =+K42*L$39 -> 136.92688 | M42: =+K42+L42 -> 759.32176 | N42: =+M42*N$39 -> 265.76262 | O42: =+M42+N42 -> 1025.0844 | P42: =H42/Q42-1 -> 0 | Q42: 12345.023 | AK42: 100522277 | AL42: 12345.023 | AN42: =+Q42/H42 -> 1
A43: 100522333 | B43: Pate de Foie Jalapeño 24x90 Swift | D43: 2.16 | E43: 24 | F43: =+VLOOKUP(A43,$AK$4:$AL$108,2,FALSE) -> 12345.023 | H43: =+F43*(1-G43) -> 12345.023 | I43: =+H43/E43 -> 514.37594 | J43: =+I43*J$3 -> 108.01895 | K43: =+I43+J43 -> 622.39489 | L43: =+K43*L$39 -> 136.92688 | M43: =+K43+L43 -> 759.32176 | N43: =+M43*N$39 -> 265.76262 | O43: =+M43+N43 -> 1025.0844 | P43: =H43/Q43-1 -> 0 | Q43: 12345.023 | AK43: 100522333 | AL43: 12345.023 | AN43: =+Q43/H43 -> 1
A44: 100021045 | B44: PICADILLO DE CARNE PICANTE 24X90G SWIFT | C44: 7790360966582 | D44: 2.16 | E44: 24 | F44: =+VLOOKUP(A44,$AK$4:$AL$108,2,FALSE) -> 12345.023 | H44: =+F44*(1-G44) -> 12345.023 | I44: =+H44/E44 -> 514.37594 | J44: =+I44*J$3 -> 108.01895 | K44: =+I44+J44 -> 622.39489 | L44: =+K44*L$39 -> 136.92688 | M44: =+K44+L44 -> 759.32176 | N44: =+M44*N$39 -> 265.76262 | O44: =+M44+N44 -> 1025.0844 | P44: =H44/Q44-1 -> 0 | Q44: 12345.023 | Y44: =+Y41/F37 -> 0.2745679 | AF44: 10088.4 | AG44: =+(H44-AF44)/AF44 -> 0.22368488 | AK44: 100021045 | AL44: 12345.023 | AN44: =+Q44/H44 -> 1
A45: 100021004 | B45: PATE DE FOIE A LA CREMA 24X88G SWIFT | C45: 7790360964526 | D45: 2.112 | E45: 24 | F45: =+VLOOKUP(A45,$AK$4:$AL$108,2,FALSE) -> 12345.023 | H45: =+F45*(1-G45) -> 12345.023 | I45: =+H45/E45 -> 514.37594 | J45: =+I45*J$3 -> 108.01895 | K45: =+I45+J45 -> 622.39489 | L45: =+K45*L$39 -> 136.92688 | M45: =+K45+L45 -> 759.32176 | N45: =+M45*N$39 -> 265.76262 | O45: =+M45+N45 -> 1025.0844 | P45: =H45/Q45-1 -> 0 | Q45: 12345.023 | AF45: 10088.4 | AG45: =+(H45-AF45)/AF45 -> 0.22368488 | AK45: 100021004 | AL45: 12345.023 | AN45: =+Q45/H45 -> 1
A46: 100021006 | B46: JAMON DEL DIABLO 24X88G SWIFT | C46: 7790360964557 | D46: 2.112 | E46: 24 | F46: =+VLOOKUP(A46,$AK$4:$AL$108,2,FALSE) -> 12345.023 | H46: =+F46*(1-G46) -> 12345.023 | I46: =+H46/E46 -> 514.37594 | J46: =+I46*J$3 -> 108.01895 | K46: =+I46+J46 -> 622.39489 | L46: =+K46*L$39 -> 136.92688 | M46: =+K46+L46 -> 759.32176 | N46: =+M46*N$39 -> 265.76262 | O46: =+M46+N46 -> 1025.0844 | P46: =H46/Q46-1 -> 0 | Q46: 12345.023 | Y46: =+Y34*24 -> 39600 | AF46: 10088.4 | AG46: =+(H46-AF46)/AF46 -> 0.22368488 | AK46: 100021006 | AL46: 12345.023 | AN46: =+Q46/H46 -> 1
A47: 100021007 | B47: PATE DE FOIE DE POLLO 24X85G SWIFT | C47: 7790360964540 | D47: 2.04 | E47: 24 | F47: =+VLOOKUP(A47,$AK$4:$AL$108,2,FALSE) -> 14092.444 | H47: =+F47*(1-G47) -> 14092.444 | I47: =+H47/E47 -> 587.18516 | J47: =+I47*J$3 -> 123.30888 | K47: =+I47+J47 -> 710.49404 | L47: =+K47*L$39 -> 156.30869 | M47: =+K47+L47 -> 866.80273 | N47: =+M47*N$39 -> 303.38095 | O47: =+M47+N47 -> 1170.1837 | P47: =H47/Q47-1 -> 0 | Q47: 14092.444 | Y47: =+Y46/1.21/1.35/1.45 -> 16718.913 | AF47: 11917.5 | AG47: =+(H47-AF47)/AF47 -> 0.1825 | AK47: 100021007 | AL47: 14092.444 | AN47: =+Q47/H47 -> 1
A48: 100021013 | B48: PATE DE FOIE TIPO PROVENZAL 24X85G SWIFT GOURMET | C48: 7790360965714 | D48: 2.04 | E48: 24 | F48: =+VLOOKUP(A48,$AK$4:$AL$108,2,FALSE) -> 14092.444 | H48: =+F48*(1-G48) -> 14092.444 | I48: =+H48/E48 -> 587.18516 | J48: =+I48*J$3 -> 123.30888 | K48: =+I48+J48 -> 710.49404 | L48: =+K48*L$39 -> 156.30869 | M48: =+K48+L48 -> 866.80273 | N48: =+M48*N$39 -> 303.38095 | O48: =+M48+N48 -> 1170.1837 | P48: =H48/Q48-1 -> 0 | Q48: 14092.444 | Y48: =+F34-Y47 -> 446.46186 | AF48: 11917.5 | AG48: =+(H48-AF48)/AF48 -> 0.1825 | AK48: 100021013 | AL48: 14092.444 | AN48: =+Q48/H48 -> 1
A49: 100021014 | B49: PATE DE FOIE C/PIMIENTA VERDE 24X85G SWIFT GOURMET | C49: 7790360965721 | D49: 2.04 | E49: 24 | F49: =+VLOOKUP(A49,$AK$4:$AL$108,2,FALSE) -> 14092.444 | H49: =+F49*(1-G49) -> 14092.444 | I49: =+H49/E49 -> 587.18516 | J49: =+I49*J$3 -> 123.30888 | K49: =+I49+J49 -> 710.49404 | L49: =+K49*L$39 -> 156.30869 | M49: =+K49+L49 -> 866.80273 | N49: =+M49*N$39 -> 303.38095 | O49: =+M49+N49 -> 1170.1837 | P49: =H49/Q49-1 -> 0 | Q49: 14092.444 | Y49: =+Y48/F34 -> 0.026009444 | AF49: 11917.5 | AG49: =+(H49-AF49)/AF49 -> 0.1825 | AK49: 100021014 | AL49: 14092.444 | AN49: =+Q49/H49 -> 1
A50: 100021054 | B50: PATE JAMON AHUMADO 24X85G | C50: 7790360965707 | D50: 2.04 | E50: 24 | F50: =+VLOOKUP(A50,$AK$4:$AL$108,2,FALSE) -> 14092.444 | H50: =+F50*(1-G50) -> 14092.444 | I50: =+H50/E50 -> 587.18516 | J50: =+I50*J$3 -> 123.30888 | K50: =+I50+J50 -> 710.49404 | L50: =+K50*L$39 -> 156.30869 | M50: =+K50+L50 -> 866.80273 | N50: =+M50*N$39 -> 303.38095 | O50: =+M50+N50 -> 1170.1837 | P50: =H50/Q50-1 -> 0 | Q50: 14092.444 | AF50: 11917.5 | AG50: =+(H50-AF50)/AF50 -> 0.1825 | AK50: 100021054 | AL50: 14092.444 | AN50: =+Q50/H50 -> 1
A51: 100021055 | B51: PATE HONGOS 24X85G | C51: 7790360965189 | D51: 2.04 | E51: 24 | F51: =+VLOOKUP(A51,$AK$4:$AL$108,2,FALSE) -> 14092.444 | H51: =+F51*(1-G51) -> 14092.444 | I51: =+H51/E51 -> 587.18516 | J51: =+I51*J$3 -> 123.30888 | K51: =+I51+J51 -> 710.49404 | L51: =+K51*L$39 -> 156.30869 | M51: =+K51+L51 -> 866.80273 | N51: =+M51*N$39 -> 303.38095 | O51: =+M51+N51 -> 1170.1837 | P51: =H51/Q51-1 -> 0 | Q51: 14092.444 | AF51: 11917.5 | AG51: =+(H51-AF51)/AF51 -> 0.1825 | AK51: 100021055 | AL51: 14092.444 | AN51: =+Q51/H51 -> 1
A52: 100021015 | B52: PATE DE SALMON 24X85G SWIFT GOURMET | C52: 7790360965202 | D52: 2.04 | E52: 24 | F52: =+VLOOKUP(A52,$AK$4:$AL$108,2,FALSE) -> 14092.444 | H52: =+F52*(1-G52) -> 14092.444 | I52: =+H52/E52 -> 587.18516 | J52: =+I52*J$3 -> 123.30888 | K52: =+I52+J52 -> 710.49404 | L52: =+K52*L$39 -> 156.30869 | M52: =+K52+L52 -> 866.80273 | N52: =+M52*N$39 -> 303.38095 | O52: =+M52+N52 -> 1170.1837 | P52: =H52/Q52-1 -> 0 | Q52: 14092.444 | AF52: 11917.5 | AG52: =+(H52-AF52)/AF52 -> 0.1825 | AK52: 100021015 | AL52: 14092.444 | AN52: =+Q52/H52 -> 1
A53: 100021008 | B53: PICADILLO DE CARNE 24X90G LA BLANCA | C53: 7790360720122 | D53: 2.16 | E53: 24 | F53: =+VLOOKUP(A53,$AK$4:$AL$108,2,FALSE) -> 10448.578 | H53: =+F53*(1-G53) -> 10448.578 | I53: =+H53/E53 -> 435.35742 | J53: =+I53*J$3 -> 91.425058 | K53: =+I53+J53 -> 526.78248 | L53: =+K53*L$39 -> 115.89214 | M53: =+K53+L53 -> 642.67462 | N53: =+M53*N$39 -> 224.93612 | O53: =+M53+N53 -> 867.61074 | P53: =H53/Q53-1 -> 0 | Q53: 10448.578 | AF53: 9046.3879 | AG53: =+(H53-AF53)/AF53 -> 0.155 | AK53: 100021008 | AL53: 10448.578 | AN53: =+Q53/H53 -> 1
A54: 100021009 | B54: PATE DE FOIE 24X90G LA BLANCA | C54: 7790360965127 | D54: 2.16 | E54: 24 | F54: =+VLOOKUP(A54,$AK$4:$AL$108,2,FALSE) -> 10448.578 | H54: =+F54*(1-G54) -> 10448.578 | I54: =+H54/E54 -> 435.35742 | J54: =+I54*J$3 -> 91.425058 | K54: =+I54+J54 -> 526.78248 | L54: =+K54*L$39 -> 115.89214 | M54: =+K54+L54 -> 642.67462 | N54: =+M54*N$39 -> 224.93612 | O54: =+M54+N54 -> 867.61074 | P54: =H54/Q54-1 -> 0 | Q54: 10448.578 | AF54: 9046.3879 | AG54: =+(H54-AF54)/AF54 -> 0.155 | AK54: 100021009 | AL54: 10448.578 | AN54: =+Q54/H54 -> 1
A55: 100021010 | B55: PICADILLO DE CARNE 24X90G SAFRA | C55: 7790920008707 | D55: 2.16 | E55: 24 | F55: =+VLOOKUP(A55,$AK$4:$AL$108,2,FALSE) -> 10448.578 | H55: =+F55*(1-G55) -> 10448.578 | I55: =+H55/E55 -> 435.35742 | J55: =+I55*J$3 -> 91.425058 | K55: =+I55+J55 -> 526.78248 | L55: =+K55*L$39 -> 115.89214 | M55: =+K55+L55 -> 642.67462 | N55: =+M55*N$39 -> 224.93612 | O55: =+M55+N55 -> 867.61074 | P55: =H55/Q55-1 -> 0 | Q55: 10448.578 | AF55: 9046.3879 | AG55: =+(H55-AF55)/AF55 -> 0.155 | AK55: 100021010 | AL55: 10448.578 | AN55: =+Q55/H55 -> 1
A56: 100021011 | B56: PATE DE FOIE 24X90G SAFRA | C56: 7790920008714 | D56: 2.16 | E56: 24 | F56: =+VLOOKUP(A56,$AK$4:$AL$108,2,FALSE) -> 10448.578 | H56: =+F56*(1-G56) -> 10448.578 | I56: =+H56/E56 -> 435.35742 | J56: =+I56*J$3 -> 91.425058 | K56: =+I56+J56 -> 526.78248 | L56: =+K56*L$39 -> 115.89214 | M56: =+K56+L56 -> 642.67462 | N56: =+M56*N$39 -> 224.93612 | O56: =+M56+N56 -> 867.61074 | P56: =H56/Q56-1 -> 0 | Q56: 10448.578 | AF56: 9046.3879 | AG56: =+(H56-AF56)/AF56 -> 0.155 | AK56: 100021011 | AL56: 10448.578 | AN56: =+Q56/H56 -> 1
F57: =+VLOOKUP(A57,$AK$4:$AL$108,2,FALSE) -> #N/A | H57: =+F57*(1-G57) -> #N/A | I57: =+H57/E57 -> #N/A | P57: =H57/Q57-1 -> #N/A | Q57: #N/A | AF57: #N/A | AG57: =+(H57-AF57)/AF57 -> #N/A | AN57: =+Q57/H57 -> #N/A
A58: 100516217 | B58: MILANESAS DE SOJA CLASICAS PREFRITA | C58: 7790360967824 | D58: 5.8 | E58: 20 | F58: =+VLOOKUP(A58,$AK$4:$AL$108,2,FALSE) -> 25064.675 | H58: =+F58*(1-G58) -> 25064.675 | I58: =+H58/E58 -> 1253.2337 | J58: =+I58*J$3 -> 263.17908 | K58: =+I58+J58 -> 1516.4128 | L58: =+K58*L$3 -> 530.74449 | M58: =+K58+L58 -> 2047.1573 | N58: =+M58*N$3 -> 921.22079 | O58: =+M58+N58 -> 2968.3781 | P58: =H58/Q58-1 -> 0.03 | Q58: 24334.636 | AF58: 22937.728 | AG58: =+(H58-AF58)/AF58 -> 0.092727 | AK58: 100516217 | AL58: 25064.675 | AN58: =+Q58/H58 -> 0.97087379
A59: 100516214 | B59: MILANESAS DE SOJA RELLENAS CON JAMON Y QUESO | C59: 7790360967794 | D59: 7 | E59: 20 | F59: =+VLOOKUP(A59,$AK$4:$AL$108,2,FALSE) -> 35086.224 | G59: 0.05 | H59: =+F59*(1-G59) -> 33331.913 | I59: =+H59/E59 -> 1666.5956 | J59: =+I59*J$3 -> 349.98508 | K59: =+I59+J59 -> 2016.5807 | L59: =+K59*L$3 -> 705.80325 | M59: =+K59+L59 -> 2722.384 | N59: =+M59*N$3 -> 1225.0728 | O59: =+M59+N59 -> 3947.4568 | P59: =H59/Q59-1 -> 0 | Q59: 33331.913 | S59: 5% DCTO PARA OFERTA A PX EN FACTURA | AF59: 31418.525 | AG59: =+(H59-AF59)/AF59 -> 0.0609 | AK59: 100516214 | AL59: 35086.224 | AN59: =+Q59/H59 -> 1
A60: 100516215 | B60: MILANESAS DE SOJA RELLENAS CON ESPINACA Y QUESO | C60: 7790360967800 | D60: 7 | E60: 20 | F60: =+VLOOKUP(A60,$AK$4:$AL$108,2,FALSE) -> 35086.224 | G60: 0.05 | H60: =+F60*(1-G60) -> 33331.913 | I60: =+H60/E60 -> 1666.5956 | J60: =+I60*J$3 -> 349.98508 | K60: =+I60+J60 -> 2016.5807 | L60: =+K60*L$3 -> 705.80325 | M60: =+K60+L60 -> 2722.384 | N60: =+M60*N$3 -> 1225.0728 | O60: =+M60+N60 -> 3947.4568 | P60: =H60/Q60-1 -> 0 | Q60: 33331.913 | S60: 5% DCTO PARA OFERTA A PX EN FACTURA | AF60: 31418.525 | AG60: =+(H60-AF60)/AF60 -> 0.0609 | AK60: 100516215 | AL60: 35086.224 | AN60: =+Q60/H60 -> 1
A61: 100516216 | B61: MILANESAS DE SOJA RELLENAS CON TOMATE Y QUESO | C61: 7790360967817 | D61: 7 | E61: 20 | F61: =+VLOOKUP(A61,$AK$4:$AL$108,2,FALSE) -> 35086.224 | G61: 0.05 | H61: =+F61*(1-G61) -> 33331.913 | I61: =+H61/E61 -> 1666.5956 | J61: =+I61*J$3 -> 349.98508 | K61: =+I61+J61 -> 2016.5807 | L61: =+K61*L$3 -> 705.80325 | M61: =+K61+L61 -> 2722.384 | N61: =+M61*N$3 -> 1225.0728 | O61: =+M61+N61 -> 3947.4568 | P61: =H61/Q61-1 -> 0 | Q61: 33331.913 | S61: 5% DCTO PARA OFERTA A PX EN FACTURA | AF61: 31418.525 | AG61: =+(H61-AF61)/AF61 -> 0.0609 | AK61: 100516216 | AL61: 35086.224 | AN61: =+Q61/H61 -> 1
F62: =+VLOOKUP(A62,$AK$4:$AL$108,2,FALSE) -> #N/A | H62: =+F62*(1-G62) -> #N/A | I62: =+H62/E62 -> #N/A | P62: =H62/Q62-1 -> #N/A | Q62: #N/A | AF62: #N/A | AG62: =+(H62-AF62)/AF62 -> #N/A | AN62: =+Q62/H62 -> #N/A
A63: 100021704 | B63: BOCADITOS DE CARNE "SWIFT" - 12x380g | C63: 7790360023902 | D63: =12*0.38 -> 4.56 | E63: 12 | F63: =+VLOOKUP(A63,$AK$4:$AL$108,2,FALSE) -> 37686.636 | H63: =+F63*(1-G63) -> 37686.636 | I63: =+H63/E63 -> 3140.553 | J63: =+I63*J$3 -> 659.51613 | K63: =+I63+J63 -> 3800.0691 | L63: =+K63*L$3 -> 1330.0242 | M63: =+K63+L63 -> 5130.0933 | N63: =+M63*N$3 -> 2308.542 | O63: =+M63+N63 -> 7438.6353 | P63: =H63/Q63-1 -> 0 | Q63: 37686.636 | AF63: 35892.034 | AG63: =+(H63-AF63)/AF63 -> 0.05 | AK63: 100021704 | AL63: 37686.636 | AN63: =+Q63/H63 -> 1
A64: 100021705 | B64: BOCADITOS DE POLLO "SWIFT" - 12x380g | C64: 7790360024336 | D64: =12*0.38 -> 4.56 | E64: 12 | F64: =+VLOOKUP(A64,$AK$4:$AL$108,2,FALSE) -> 34258.029 | H64: =+F64*(1-G64) -> 34258.029 | I64: =+H64/E64 -> 2854.8357 | J64: =+I64*J$3 -> 599.51551 | K64: =+I64+J64 -> 3454.3513 | L64: =+K64*L$3 -> 1209.0229 | M64: =+K64+L64 -> 4663.3742 | N64: =+M64*N$3 -> 2098.5184 | O64: =+M64+N64 -> 6761.8926 | P64: =H64/Q64-1 -> 0 | Q64: 34258.029 | AF64: 32626.694 | AG64: =+(H64-AF64)/AF64 -> 0.05 | AK64: 100021705 | AL64: 34258.029 | AN64: =+Q64/H64 -> 1
A65: 100021709 | B65: BOCADITOS DE POLLO "SWIFT" - 10x760g | C65: 7790360024701 | D65: 7.6 | E65: 10 | F65: =+VLOOKUP(A65,$AK$4:$AL$108,2,FALSE) -> 54972.17 | H65: =+F65*(1-G65) -> 54972.17 | I65: =+H65/E65 -> 5497.217 | J65: =+I65*J$3 -> 1154.4156 | K65: =+I65+J65 -> 6651.6325 | L65: =+K65*L$3 -> 2328.0714 | M65: =+K65+L65 -> 8979.7039 | N65: =+M65*N$3 -> 4040.8668 | O65: =+M65+N65 -> 13020.571 | P65: =H65/Q65-1 -> 0 | Q65: 54972.17 | AF65: 43626.961 | AG65: =+(H65-AF65)/AF65 -> 0.2600504 | AK65: 100021709 | AL65: 54972.17 | AN65: =+Q65/H65 -> 1
A66: 100521357 | B66: CRUNCHIES DE POLLO "SWIFT" - 12x380g | C66: 7790360982018 | D66: 4.56 | E66: 12 | F66: =+VLOOKUP(A66,$AK$4:$AL$108,2,FALSE) -> 44177.826 | G66: 0.33 | H66: =+F66*(1-G66) -> 29599.143 | I66: =+H66/E66 -> 2466.5953 | J66: =+I66*J$3 -> 517.98501 | K66: =+I66+J66 -> 2984.5803 | L66: =+K66*L$3 -> 1044.6031 | M66: =+K66+L66 -> 4029.1834 | N66: =+M66*N$3 -> 1813.1325 | O66: =+M66+N66 -> 5842.3159 | P66: =H66/Q66-1 -> 0 | Q66: 29599.143 | S66: OFERTA INCORPORACION Compra 4 bolsa + 2 de regalo | AF66: 42074.12 | AG66: =+(H66-AF66)/AF66 -> -0.2965 | AK66: 100521357 | AL66: 44177.826 | AN66: =+Q66/H66 -> 1
A67: 100521358 | B67: CRUNCHIES DE POLLO "SWIFT" - 10x760g | C67: 7790360982025 | D67: 7.6 | E67: 10 | F67: =+VLOOKUP(A67,$AK$4:$AL$108,2,FALSE) -> 66266.739 | H67: =+F67*(1-G67) -> 66266.739 | I67: =+H67/E67 -> 6626.6739 | J67: =+I67*J$3 -> 1391.6015 | K67: =+I67+J67 -> 8018.2754 | L67: =+K67*L$3 -> 2806.3964 | M67: =+K67+L67 -> 10824.672 | N67: =+M67*N$3 -> 4871.1023 | O67: =+M67+N67 -> 15695.774 | P67: =H67/Q67-1 -> #N/A | Q67: #N/A | Y67: OCT | Z67: LUCHETTI | AA67: PATITAS | AF67: 63111.18 | AG67: =+(H67-AF67)/AF67 -> 0.05 | AK67: 100521358 | AL67: 66266.739 | AN67: =+Q67/H67 -> #N/A
A68: 100522130 | B68: BOCADITOS DE POLLO "SWIFT KIDS" - 12x400g | C68: 7790360982445 | D68: 4.8 | E68: 12 | F68: =+VLOOKUP(A68,$AK$4:$AL$108,2,FALSE) -> 34685.797 | H68: =+F68*(1-G68) -> 34685.797 | I68: =+H68/E68 -> 2890.4831 | J68: =+I68*J$3 -> 607.00145 | K68: =+I68+J68 -> 3497.4846 | L68: =+K68*L$3 -> 1224.1196 | M68: =+K68+L68 -> 4721.6042 | N68: =+M68*N$3 -> 2124.7219 | O68: =+M68+N68 -> 6846.326 | P68: =H68/Q68-1 -> 0.05 | Q68: 33034.093 | Y68: 5250 | Z68: 5560 | AA68: 7192 | AF68: 25331.687 | AG68: =+(H68-AF68)/AF68 -> 0.3692652 | AK68: 100522130 | AL68: 34685.797 | AN68: =+Q68/H68 -> 0.95238095
A69: 100021725 | B69: BOCADITOS DE POLLO GASTRONOMICOS "LA BLANCA" - x6kg | C69: 7790360027009 | D69: 6 | E69: 4 | F69: =+VLOOKUP(A69,$AK$4:$AL$108,2,FALSE) -> 28414.154 | H69: =+F69*(1-G69) -> 28414.154 | I69: =+H69/E69 -> 7103.5386 | J69: =+I69*J$3 -> 1491.7431 | K69: =+I69+J69 -> 8595.2817 | L69: =+K69*L$3 -> 3008.3486 | M69: =+K69+L69 -> 11603.63 | N69: =+M69*N$3 -> 5221.6336 | O69: =+M69+N69 -> 16825.264 | P69: =H69/Q69-1 -> 0 | Q69: 28414.154 | AF69: 27061.099 | AG69: =+(H69-AF69)/AF69 -> 0.05 | AK69: 100021725 | AL69: 28414.154 | AN69: =+Q69/H69 -> 1
A70: 100517055 | B70: PALITO DE POLLO "SWIFT" 12 X 260 Grs. | C70: 7790360971135 | D70: 3.12 | E70: 12 | F70: =+VLOOKUP(A70,$AK$4:$AL$108,2,FALSE) -> 28376.008 | H70: =+F70*(1-G70) -> 28376.008 | I70: =+H70/E70 -> 2364.6673 | J70: =+I70*J$3 -> 496.58014 | K70: =+I70+J70 -> 2861.2475 | L70: =+K70*L$3 -> 1001.4366 | M70: =+K70+L70 -> 3862.6841 | N70: =+M70*N$3 -> 1738.2079 | O70: =+M70+N70 -> 5600.892 | P70: =H70/Q70-1 -> 0 | Q70: 28376.008 | AF70: 27024.77 | AG70: =+(H70-AF70)/AF70 -> 0.05 | AK70: 100517055 | AL70: 28376.008 | AN70: =+Q70/H70 -> 1
A71: 100517186 | B71: PALITO DE POLLO "SWIFT" 8 X 1 Kg.. | C71: 7790360971395 | D71: 8 | E71: 8 | F71: =+VLOOKUP(A71,$AK$4:$AL$108,2,FALSE) -> 71701.329 | H71: =+F71*(1-G71) -> 71701.329 | I71: =+H71/E71 -> 8962.6661 | J71: =+I71*J$3 -> 1882.1599 | K71: =+I71+J71 -> 10844.826 | L71: =+K71*L$3 -> 3795.6891 | M71: =+K71+L71 -> 14640.515 | N71: =+M71*N$3 -> 6588.2318 | O71: =+M71+N71 -> 21228.747 | P71: =H71/Q71-1 -> 0 | Q71: 71701.329 | AF71: 68286.98 | AG71: =+(H71-AF71)/AF71 -> 0.05 | AK71: 100517186 | AL71: 71701.329 | AN71: =+Q71/H71 -> 1
A72: 100521663 | B72: MILANESITAS DE CARNE "SWIFT" - 12x400g | C72: 7790360982537 | D72: 4.8 | E72: 12 | F72: 37997.53 | G72: 0.33 | H72: =+F72*(1-G72) -> 25458.345 | I72: =+H72/E72 -> 2121.5288 | J72: =+I72*J$3 -> 445.52104 | K72: =+I72+J72 -> 2567.0498 | L72: =+K72*0.343 -> 880.49808 | M72: =+K72+L72 -> 3447.5479 | N72: =+M72*N$3 -> 1551.3965 | O72: =+M72+N72 -> 4998.9444 | P72: =H72/Q72-1 -> 0 | Q72: 25458.345 | S72: OFERTA INCORPORACION Compra 4 bolsa + 2 de regalo | AF72: 42746.88 | AK72: 100521663 | AL72: 37997.53 | AN72: =+Q72/H72 -> 1
A73: 100021728 | B73: MEDALLONES DE POLLO "SWIFT" - 12x4x80g | C73: 7790360967558 | D73: 3.84 | E73: 12 | F73: =+VLOOKUP(A73,$AK$4:$AL$108,2,FALSE) -> 35669.865 | H73: =+F73*(1-G73) -> 35669.865 | I73: =+H73/E73 -> 2972.4887 | J73: =+I73*J$3 -> 624.22263 | K73: =+I73+J73 -> 3596.7114 | L73: =+K73*L$3 -> 1258.849 | M73: =+K73+L73 -> 4855.5603 | N73: =+M73*N$3 -> 2185.0021 | O73: =+M73+N73 -> 7040.5625 | P73: =H73/Q73-1 -> 0 | Q73: 35669.865 | AF73: 33971.3 | AG73: =+(H73-AF73)/AF73 -> 0.05 | AK73: 100021728 | AL73: 35669.865 | AN73: =+Q73/H73 -> 1
A74: 100517679 | B74: MEDALLONES DE POLLO GASTRONÓMICO 8x12x80 Grs. | C74: 7790360973498 | D74: 7.68 | E74: 8 | F74: =+VLOOKUP(A74,$AK$4:$AL$108,2,FALSE) -> 35830.538 | H74: =+F74*(1-G74) -> 35830.538 | I74: =+H74/E74 -> 4478.8173 | J74: =+I74*J$3 -> 940.55163 | K74: =+I74+J74 -> 5419.3689 | L74: =+K74*L$3 -> 1896.7791 | M74: =+K74+L74 -> 7316.1481 | N74: =+M74*N$3 -> 3292.2666 | O74: =+M74+N74 -> 10608.415 | P74: =H74/Q74-1 -> 0 | Q74: 35830.538 | AF74: 34124.322 | AG74: =+(H74-AF74)/AF74 -> 0.05 | AK74: 100517679 | AL74: 35830.538 | AN74: =+Q74/H74 -> 1
F75: =+VLOOKUP(A75,$AK$4:$AL$108,2,FALSE) -> #N/A | H75: =+F75*(1-G75) -> #N/A | I75: =+H75/E75 -> #N/A | P75: =H75/Q75-1 -> #N/A | Q75: #N/A | AF75: #N/A | AG75: =+(H75-AF75)/AF75 -> #N/A | AN75: =+Q75/H75 -> #N/A
A76: 100516219 | B76: PAPAS PREFRITAS SUPERCONGELADAS 25x400gr | C76: 7790360967770 | D76: 10 | E76: 25 | F76: =+VLOOKUP(A76,$AK$4:$AL$108,2,FALSE) -> 16599.454 | H76: =+F76*(1-G76) -> 16599.454 | I76: =+H76/E76 -> 663.97818 | J76: =+I76*J$3 -> 139.43542 | K76: =+I76+J76 -> 803.4136 | L76: =+K76*L$3 -> 281.19476 | M76: =+K76+L76 -> 1084.6084 | N76: =+M76*N$3 -> 488.07376 | O76: =+M76+N76 -> 1572.6821 | P76: =H76/Q76-1 -> 0 | Q76: 16599.454 | AF76: 16599.454 | AG76: =+(H76-AF76)/AF76 -> 0 | AK76: 100516219 | AL76: 16599.454 | AN76: =+Q76/H76 -> 1
A77: 100516220 | B77: PAPAS PREFRITAS SUPERCONGELADAS 6x2000gr | C77: 7790360967787 | D77: 12 | E77: 6 | F77: =+VLOOKUP(A77,$AK$4:$AL$108,2,FALSE) -> 17830.838 | H77: =+F77*(1-G77) -> 17830.838 | I77: =+H77/E77 -> 2971.8063 | J77: =+I77*J$3 -> 624.07933 | K77: =+I77+J77 -> 3595.8857 | L77: =+K77*L$3 -> 1258.56 | M77: =+K77+L77 -> 4854.4457 | N77: =+M77*N$3 -> 2184.5005 | O77: =+M77+N77 -> 7038.9462 | P77: =H77/Q77-1 -> 0 | Q77: 17830.838 | AF77: 17830.838 | AG77: =+(H77-AF77)/AF77 -> 0 | AK77: 100516220 | AL77: 17830.838 | AN77: =+Q77/H77 -> 1
F78: =+VLOOKUP(A78,$AK$4:$AL$108,2,FALSE) -> #N/A | H78: =+F78*(1-G78) -> #N/A | I78: =+H78/E78 -> #N/A | P78: =H78/Q78-1 -> #N/A | Q78: #N/A | AF78: #N/A | AG78: =+(H78-AF78)/AF78 -> #N/A | AL78: 0 | AN78: =+Q78/H78 -> #N/A
A79: 100518158 | B79: MILANESA DE CARNE VACUNA CONGELADA 24un x 500grs | C79: 7790360974280 | D79: 12 | E79: 24 | F79: =+VLOOKUP(A79,$AK$4:$AL$108,2,FALSE) -> 68490.548 | H79: =+F79*(1-G79) -> 68490.548 | I79: =+H79/E79 -> 2853.7728 | J79: =+I79*J$3 -> 599.2923 | K79: =+I79+J79 -> 3453.0651 | L79: =+K79*L$3 -> 1208.5728 | M79: =+K79+L79 -> 4661.6379 | N79: =+M79*N$3 -> 2097.7371 | O79: =+M79+N79 -> 6759.375 | P79: =H79/Q79-1 -> #N/A | Q79: #N/A | AF79: 68490.548 | AG79: =+(H79-AF79)/AF79 -> 0 | AK79: 100518158 | AL79: 68490.548 | AN79: =+Q79/H79 -> #N/A
A80: 100518160 | B80: MILANESA DE CARNE VACUNA CONGELADA 12un x 1000grs | C80: 7790360974686 | D80: 12 | E80: 12 | F80: =+VLOOKUP(A80,$AK$4:$AL$108,2,FALSE) -> 68490.548 | H80: =+F80*(1-G80) -> 68490.548 | I80: =+H80/E80 -> 5707.5457 | J80: =+I80*J$3 -> 1198.5846 | K80: =+I80+J80 -> 6906.1303 | L80: =+K80*L$3 -> 2417.1456 | M80: =+K80+L80 -> 9323.2759 | N80: =+M80*N$3 -> 4195.4741 | O80: =+M80+N80 -> 13518.75 | P80: =H80/Q80-1 -> #N/A | Q80: #N/A | AF80: 68490.548 | AG80: =+(H80-AF80)/AF80 -> 0 | AK80: 100518160 | AL80: 68490.548 | AN80: =+Q80/H80 -> #N/A
A81: 100518463 | B81: MILANESAS DE CARNE VACUNA CONG GRANEL 5 kg | C81: 7790360975188 | D81: 5 | E81: 1 | F81: =+VLOOKUP(A81,$AK$4:$AL$108,2,FALSE) -> 33357.516 | H81: =+F81*(1-G81) -> 33357.516 | I81: =+H81/E81 -> 33357.516 | J81: =+I81*J$3 -> 7005.0783 | K81: =+I81+J81 -> 40362.594 | L81: =+K81*L$3 -> 14126.908 | M81: =+K81+L81 -> 54489.502 | N81: =+M81*N$3 -> 24520.276 | O81: =+M81+N81 -> 79009.778 | P81: =H81/Q81-1 -> #N/A | Q81: #N/A | AF81: 33357.516 | AG81: =+(H81-AF81)/AF81 -> 0 | AK81: 100518463 | AL81: 33357.516 | AN81: =+Q81/H81 -> #N/A
F82: =+VLOOKUP(A82,$AK$4:$AL$108,2,FALSE) -> #N/A | H82: =+F82*(1-G82) -> #N/A | I82: =+H82/E82 -> #N/A | P82: =H82/Q82-1 -> #N/A | Q82: #N/A | AF82: #N/A | AG82: =+(H82-AF82)/AF82 -> #N/A | AN82: =+Q82/H82 -> #N/A
A83: 100518291 | B83: GRASA VACUNA REFINADA SWIFT 10 X 500 | C83: 7790360975195 | D83: 5 | E83: 10 | F83: =+VLOOKUP(A83,$AK$4:$AL$108,2,FALSE) -> 15942.443 | G83: 0.15 | H83: =+F83*(1-G83) -> 13551.076 | I83: =+H83/E83 -> 1355.1076 | J83: =+I83*J$3 -> 284.5726 | K83: =+I83+J83 -> 1639.6802 | L83: =+K83*L$39 -> 360.72965 | M83: =+K83+L83 -> 2000.4099 | N83: =+M83*N$39 -> 700.14346 | O83: =+M83+N83 -> 2700.5533 | P83: =H83/Q83-1 -> 0 | Q83: 13551.076 | S83: Oferta a px en factura para $2.700 público | AF83: 13551.076 | AG83: =+(H83-AF83)/AF83 -> 0 | AK83: 100518291 | AL83: 15942.443 | AN83: =+Q83/H83 -> 1
A84: 100518292 | B84: GRASA VACUNA REFINADA SWIFT 12x1Kg | C84: 7790360975201 | D84: 12 | E84: 12 | F84: =+VLOOKUP(A84,$AK$4:$AL$108,2,FALSE) -> 37618.476 | G84: 0.15 | H84: =+F84*(1-G84) -> 31975.705 | I84: =+H84/E84 -> 2664.6421 | J84: =+I84*J$3 -> 559.57483 | K84: =+I84+J84 -> 3224.2169 | L84: =+K84*L$39 -> 709.32772 | M84: =+K84+L84 -> 3933.5446 | N84: =+M84*N$39 -> 1376.7406 | O84: =+M84+N84 -> 5310.2852 | P84: =H84/Q84-1 -> 0 | Q84: 31975.705 | S84: Oferta a px en factura para $5.300 público | AF84: 31975.705 | AG84: =+(H84-AF84)/AF84 -> 0 | AK84: 100518292 | AL84: 37618.476 | AN84: =+Q84/H84 -> 1
F85: =+VLOOKUP(A85,$AK$4:$AL$108,2,FALSE) -> #N/A | H85: =+F85*(1-G85) -> #N/A | I85: =+H85/E85 -> #N/A | J85: 0.105 | L85: 0.3 | N85: 0.4 | P85: =H85/Q85-1 -> #N/A | Q85: #N/A | AF85: #N/A | AG85: =+(H85-AF85)/AF85 -> #N/A | AN85: =+Q85/H85 -> #N/A
A86: 100517915 | B86: CARNE PICADA CONGELADA 36 UN X 500 g SWIFT | C86: 7790360974020 | D86: 18 | E86: 36 | F86: =+VLOOKUP(A86,$AK$4:$AL$108,2,FALSE) -> 145920.01 | H86: =+F86*(1-G86) -> 145920.01 | I86: =+H86/E86 -> 4053.3336 | J86: =+I86*J$85 -> 425.60003 | K86: =+I86+J86 -> 4478.9337 | L86: =+K86*L$85 -> 1343.6801 | M86: =+K86+L86 -> 5822.6138 | N86: =+M86*N$85 -> 2329.0455 | O86: =+M86+N86 -> 8151.6593 | P86: =H86/Q86-1 -> 0.04 | Q86: 140307.7 | AF86: 126062.63 | AG86: =+(H86-AF86)/AF86 -> 0.15752 | AK86: 100517915 | AL86: 145920.01 | AN86: =+Q86/H86 -> 0.96153846
A87: 100517914 | B87: CARNE PICADA CONGELADA 20 UN X 1 kg SWIFT | C87: 7790360974037 | D87: 20 | E87: 20 | F87: =+VLOOKUP(A87,$AK$4:$AL$108,2,FALSE) -> 159231.16 | H87: =+F87*(1-G87) -> 159231.16 | I87: =+H87/E87 -> 7961.5579 | J87: =+I87*J$85 -> 835.96358 | K87: =+I87+J87 -> 8797.5215 | L87: =+K87*L$85 -> 2639.2565 | M87: =+K87+L87 -> 11436.778 | N87: =+M87*N$85 -> 4574.7112 | O87: =+M87+N87 -> 16011.489 | P87: =H87/Q87-1 -> 0.04 | Q87: 153106.88 | AF87: 137562.34 | AG87: =+(H87-AF87)/AF87 -> 0.15752 | AK87: 100517914 | AL87: 159231.16 | AN87: =+Q87/H87 -> 0.96153846
F88: =+VLOOKUP(A88,$AK$4:$AL$108,2,FALSE) -> #N/A | H88: =+F88*(1-G88) -> #N/A | J88: 0.105 | L88: 0.3 | N88: 0.4 | P88: =H88/Q88-1 -> #N/A | Q88: #N/A | AF88: #N/A | AG88: =+(H88-AF88)/AF88 -> #N/A | AN88: =+Q88/H88 -> #N/A
A89: 100010689 | B89: ENTRAÑA FINA ENF SWIFT | D89: 22 | E89: 1 | F89: =+VLOOKUP(A89,$AK$4:$AL$108,2,FALSE) -> 14285.714 | H89: =+F89*(1-G89) -> 14285.714 | I89: =+H89/E89 -> 14285.714 | J89: =+I89*J$88 -> 1500 | K89: =+I89+J89 -> 15785.714 | L89: =+K89*L$88 -> 4735.7143 | M89: =+K89+L89 -> 20521.429 | N89: =+M89*N$88 -> 8208.5714 | O89: =+M89+N89 -> 28730 | P89: =H89/Q89-1 -> -0.045573849 | Q89: 14967.857 | AF89: 14255.102 | AG89: =+(H89-AF89)/AF89 -> 0.0021474588 | AK89: 100010689 | AL89: 14285.714 | AN89: =+Q89/H89 -> 1.04775
A90: 100518335 | B90: ROAST BEEF EN PORCIONES ENF SWIFT (L) | D90: 22.5 | E90: 1 | F90: =+VLOOKUP(A90,$AK$4:$AL$108,2,FALSE) -> 10204.082 | H90: =+F90*(1-G90) -> 10204.082 | I90: =+H90/E90 -> 10204.082 | J90: =+I90*J$88 -> 1071.4286 | K90: =+I90+J90 -> 11275.51 | L90: =+K90*L$88 -> 3382.6531 | M90: =+K90+L90 -> 14658.163 | N90: =+M90*N$88 -> 5863.2653 | O90: =+M90+N90 -> 20521.429 | P90: =H90/Q90-1 -> 0.07625828 | Q90: 9481.0714 | AF90: 9029.5918 | AG90: =+(H90-AF90)/AF90 -> 0.13007119 | AK90: 100518335 | AL90: 10204.082 | AN90: =+Q90/H90 -> 0.929145
A91: 100518332 | B91: CARNAZA CUADRADA EN PORCIONES ENF SWIFT (L) | D91: 21.5 | E91: 1 | F91: =+VLOOKUP(A91,$AK$4:$AL$108,2,FALSE) -> 11734.694 | H91: =+F91*(1-G91) -> 11734.694 | I91: =+H91/E91 -> 11734.694 | J91: =+I91*J$88 -> 1232.1429 | K91: =+I91+J91 -> 12966.837 | L91: =+K91*L$88 -> 3890.051 | M91: =+K91+L91 -> 16856.888 | N91: =+M91*N$88 -> 6742.7551 | O91: =+M91+N91 -> 23599.643 | P91: =H91/Q91-1 -> 0.15009776 | Q91: 10203.214 | Y91: =+R99*72+R4*144 -> 0 | AF91: 9717.3469 | AG91: =+(H91-AF91)/AF91 -> 0.20760265 | AK91: 100518332 | AL91: 11734.694 | AN91: =+Q91/H91 -> 0.8694913
A92: 100518334 | B92: TAPA DE ASADO EN PORCIONES ENF SWIFT (L) | D92: 22.5 | E92: 1 | F92: =+VLOOKUP(A92,$AK$4:$AL$108,2,FALSE) -> 10408.163 | H92: =+F92*(1-G92) -> 10408.163 | I92: =+H92/E92 -> 10408.163 | J92: =+I92*J$88 -> 1092.8571 | K92: =+I92+J92 -> 11501.02 | L92: =+K92*L$88 -> 3450.3061 | M92: =+K92+L92 -> 14951.327 | N92: =+M92*N$88 -> 5980.5306 | O92: =+M92+N92 -> 20931.857 | P92: =H92/Q92-1 -> 0.23938322 | Q92: 8397.8571 | Y92: =+R96*24+R4*144 -> 0 | AF92: 7997.9592 | AG92: =+(H92-AF92)/AF92 -> 0.30135239 | AK92: 100518334 | AL92: 10408.163 | AN92: =+Q92/H92 -> 0.80685294
A93: 100518227 | B93: VACIO EN PORCIONES NOV ENFRIADO PARA VENTA LOCAL (L) | D93: 22.5 | E93: 1 | F93: =+VLOOKUP(A93,$AK$4:$AL$108,2,FALSE) -> 12040.816 | H93: =+F93*(1-G93) -> 12040.816 | I93: =+H93/E93 -> 12040.816 | J93: =+I93*J$88 -> 1264.2857 | K93: =+I93+J93 -> 13305.102 | L93: =+K93*L$88 -> 3991.5306 | M93: =+K93+L93 -> 17296.633 | N93: =+M93*N$88 -> 6918.6531 | O93: =+M93+N93 -> 24215.286 | P93: =H93/Q93-1 -> 0.43379628 | Q93: 8397.8571 | AF93: 7997.9592 | AG93: =+(H93-AF93)/AF93 -> 0.50548609 | AK93: 100518227 | AL93: 12040.816 | AN93: =+Q93/H93 -> 0.69744915
A94: 100027726 | B94: BONDIOLA DE CERDO CONGELADA | D94: 22.5 | E94: 1 | F94: =+VLOOKUP(A94,$AK$4:$AL$108,2,FALSE) -> 6195 | H94: =+F94*(1-G94) -> 6195 | I94: =+H94/E94 -> 6195 | J94: =+I94*J$88 -> 650.475 | K94: =+I94+J94 -> 6845.475 | L94: =+K94*L$88 -> 2053.6425 | M94: =+K94+L94 -> 8899.1175 | N94: =+M94*N$88 -> 3559.647 | O94: =+M94+N94 -> 12458.765 | P94: =H94/Q94-1 -> 0 | Q94: 6195 | AK94: 100027726 | AL94: 6195 | AN94: =+Q94/H94 -> 1
F95: =+VLOOKUP(A95,$AK$4:$AL$108,2,FALSE) -> #N/A | H95: =+F95*(1-G95) -> #N/A | J95: 0.21 | L95: 0.3 | N95: 0.4 | P95: =H95/Q95-1 -> #N/A | Q95: #N/A | AF95: #N/A | AG95: =+(H95-AF95)/AF95 -> #N/A | AN95: =+Q95/H95 -> #N/A
A96: 100520837 | B96: CHORIZOS FRESCOS DE CERDO LIBRE DE GLUTEN | C96: 7790360980625 | D96: 4.8 | E96: 12 | F96: =+VLOOKUP(A96,$AK$4:$AL$108,2,FALSE) -> 32505.614 | H96: =+F96*(1-G96) -> 32505.614 | I96: =+H96/E96 -> 2708.8012 | J96: =+I96*J$95 -> 568.84825 | K96: =+I96+J96 -> 3277.6494 | L96: =+K96*L$95 -> 983.29483 | M96: =+K96+L96 -> 4260.9443 | N96: =+M96*N$95 -> 1704.3777 | O96: =+M96+N96 -> 5965.322 | P96: =H96/Q96-1 -> 0 | Q96: 32505.614 | Y96: 0.1 | Z96: =+H96*(1-Y96) -> 29255.053 | AA96: =+Z96/E96 -> 2437.9211 | AB96: =+AA96*1.21*1.3*1.4 -> 5368.7898 | AC96: VER CUPOS | AD96: Con la compra de 1 caja de 21632 + 2 unidades de Chorizos --> 10% de dcto en ambos SKU | AF96: 30957.728 | AG96: =+(H96-AF96)/AF96 -> 0.05 | AK96: 100520837 | AL96: 32505.614 | AN96: =+Q96/H96 -> 1
A97: 100522395 | B97: CHORIZOS FRESCOS DE CERDO CONGELADOS LIBRE DE GLUTEN 12u x 400g | C97: 7790360980625 | D97: 4.8 | E97: 12 | F97: =+VLOOKUP(A97,$AK$4:$AL$108,2,FALSE) -> 33155.72 | H97: =+F97*(1-G97) -> 33155.72 | I97: =+H97/E97 -> 2762.9767 | J97: =+I97*J$95 -> 580.2251 | K97: =+I97+J97 -> 3343.2018 | L97: =+K97*L$95 -> 1002.9605 | M97: =+K97+L97 -> 4346.1623 | N97: =+M97*N$95 -> 1738.4649 | O97: =+M97+N97 -> 6084.6272 | Q97: 33155.72 | S97: Dinámica 2+1. Compra 2, recibe 3 ----> oferta $4.100 (para distribuidores estratégios, según objetivo asignado) | AK97: 100522395 | AL97: 33155.72
F98: =+VLOOKUP(A98,$AK$4:$AL$108,2,FALSE) -> #N/A | H98: =+F98*(1-G98) -> #N/A | J98: 0.21 | L98: 0.35 | N98: 0.45 | P98: =H98/Q98-1 -> #N/A | Q98: #N/A | AF98: #N/A | AG98: =+(H98-AF98)/AF98 -> #N/A | AN98: =+Q98/H98 -> #N/A
A99: 100520902 | B99: PAPAS PRE COCIDAS SUPERCONGELADAS LIBRES DE GLUTEN 700G | C99: 7790360981042 | D99: 9.8 | E99: 14 | F99: =+VLOOKUP(A99,$AK$4:$AL$108,2,FALSE) -> 29405.275 | G99: 0.125 | H99: =+F99*(1-G99) -> 25729.616 | I99: =+H99/E99 -> 1837.8297 | J99: =+I99*J$98 -> 385.94424 | K99: =+I99+J99 -> 2223.7739 | L99: =+K99*L$98 -> 778.32088 | M99: =+K99+L99 -> 3002.0948 | N99: =+M99*N$98 -> 1350.9427 | O99: =+M99+N99 -> 4353.0375 | P99: =H99/Q99-1 -> 0.020833333 | Q99: 25204.522 | S99: OFERTA compra 6 bolsas + 1 de regalo | Y99: 0.1 | Z99: =+H99*(1-Y99) -> 23156.654 | AA99: =+Z99/E99 -> 1654.0467 | AB99: =+AA99*1.21*1.3*1.4 -> 3642.5417 | AC99: VER CUPOS | AD99: Con la compra de 1 caja de 21632 + 7 unidades de PAPAS --> 10% de dcto en ambos SKU | AF99: 25729.616 | AG99: =+(H99-AF99)/AF99 -> 0 | AK99: 100520902 | AL99: 29405.275 | AN99: =+Q99/H99 -> 0.97959184
F100: =+VLOOKUP(A100,$AK$4:$AL$108,2,FALSE) -> #N/A | J100: 0.21 | L100: 0.35 | N100: 0.45 | P100: =H100/Q100-1 -> #DIV/0! | AN100: =+Q100/H100 -> #DIV/0!
A101: 100521457 | B101: NUGGETS DE ESPINACA 300GR | C101: 7790360982254 | D101: 4.8 | E101: 16 | F101: =+VLOOKUP(A101,$AK$4:$AL$108,2,FALSE) -> 32843.545 | G101: 0.075 | H101: =+F101*(1-G101) -> 30380.279 | I101: =+H101/E101 -> 1898.7675 | J101: =+I101*J$100 -> 398.74117 | K101: =+I101+J101 -> 2297.5086 | L101: =+K101*L$100 -> 804.12802 | M101: =+K101+L101 -> 3101.6366 | N101: =+M101*N$100 -> 1395.7365 | O101: =+M101+N101 -> 4497.3731 | P101: =H101/Q101-1 -> 0 | Q101: 30380.279 | S101: Oferta a px en factura para $4.500 público | Y101: 0.15 | Z101: =+H101*(1-Y101) -> 25823.237 | AA101: =+Z101/E101 -> 1613.9523 | AB101: =+AA101*1.21*1.3*1.4 -> 3554.2458 | AC101: VER CUPOS | AD101: Con la compra de 1 caja de 21632 + 1 unidades de cada veggie --> 10% de dcto en 21632 Y 15% de dcto en veggies | AF101: 28151.61 | AG101: =+(H101-AF101)/AF101 -> 0.079166667 | AK101: 100521457 | AL101: 32843.545 | AN101: =+Q101/H101 -> 1
...

Sheet Sub Litoral
B2: Código | C2: Descripción | D2: EAN | E2: Kg. x Caja | F2: Cant. X Caja | G2: Precio de Lista | H2: Dcto | I2: Precio de factura | J2: Precio Neto estuche en factura | K2: IVA | L2: Px Unitario IVA Inc | M2: M-up Dx | N2: Px Unitario Minorista | O2: M-up Minorista | P2: Px Unitario Público | R2: PX MAYO
K3: 0.21 | M3: 0.3 | O3: 0.4
B4: 100021632 | C4: HAMBURGUESAS 30x160g CLASICA x2 SWIFT | D4: 7790360026606 | E4: 4.8 | F4: 30 | G4: =+VLOOKUP(B4,$T$4:$U$104,2,FALSE) -> 39054.639 | I4: =+G4*(1-H4) -> 39054.639 | J4: =+I4/F4 -> 1301.8213 | K4: =+J4*K$3 -> 273.38247 | L4: =+J4+K4 -> 1575.2038 | M4: =+L4*M$3 -> 472.56113 | N4: =+L4+M4 -> 2047.7649 | O4: =+N4*O$3 -> 819.10595 | P4: =+N4+O4 -> 2866.8708 | R4: 34111.834 | S4: =+(I4-R4)/R4 -> 0.1449 | T4: 100021632 | U4: 39054.639
B5: 100021652 | C5: HAMBURGUESA 18X4X80G CLASICA SWIFT | D5: 7790360026576 | E5: 5.76 | F5: 18 | G5: =+VLOOKUP(B5,$T$4:$U$104,2,FALSE) -> 47014.671 | I5: =+G5*(1-H5) -> 47014.671 | J5: =+I5/F5 -> 2611.9262 | K5: =+J5*K$3 -> 548.5045 | L5: =+J5+K5 -> 3160.4307 | M5: =+L5*M$3 -> 948.1292 | N5: =+L5+M5 -> 4108.5599 | O5: =+N5*O$3 -> 1643.424 | P5: =+N5+O5 -> 5751.9838 | R5: 43938.945 | S5: =+(I5-R5)/R5 -> 0.07 | T5: 100021652 | U5: 47014.671
B6: 100021631 | C6: HAMBURGUESA 8X12X80G CLASICA SWIFT | D6: 7790360026590 | E6: 7.68 | F6: 8 | G6: =+VLOOKUP(B6,$T$4:$U$104,2,FALSE) -> 62487.422 | I6: =+G6*(1-H6) -> 62487.422 | J6: =+I6/F6 -> 7810.9277 | K6: =+J6*K$3 -> 1640.2948 | L6: =+J6+K6 -> 9451.2225 | M6: =+L6*M$3 -> 2835.3668 | N6: =+L6+M6 -> 12286.589 | O6: =+N6*O$3 -> 4914.6357 | P6: =+N6+O6 -> 17201.225 | R6: 73786.602 | S6: =+(I6-R6)/R6 -> -0.15313322 | T6: 100021631 | U6: 62487.422
B7: 100021630 | C7: HAMBURGUESA 6X20X80G CLASICA SWIFT | D7: 7790360026583 | E7: 9.6 | F7: 6 | G7: =+VLOOKUP(B7,$T$4:$U$104,2,FALSE) -> 78109.277 | I7: =+G7*(1-H7) -> 78109.277 | J7: =+I7/F7 -> 13018.213 | K7: =+J7*K$3 -> 2733.8247 | L7: =+J7+K7 -> 15752.038 | M7: =+L7*M$3 -> 4725.6113 | N7: =+L7+M7 -> 20477.649 | O7: =+N7*O$3 -> 8191.0595 | P7: =+N7+O7 -> 28668.708 | R7: 92268.024 | S7: =+(I7-R7)/R7 -> -0.15345237 | T7: 100021630 | U7: 78109.277
B8: 100021653 | C8: MEDALLON 18X4X80G PARRILLERO SWIFT | D8: 7790360026682 | E8: 5.76 | F8: 18 | G8: =+VLOOKUP(B8,$T$4:$U$104,2,FALSE) -> 51552.123 | I8: =+G8*(1-H8) -> 51552.123 | J8: =+I8/F8 -> 2864.0068 | K8: =+J8*K$3 -> 601.44143 | L8: =+J8+K8 -> 3465.4483 | M8: =+L8*M$3 -> 1039.6345 | N8: =+L8+M8 -> 4505.0827 | O8: =+N8*O$3 -> 1802.0331 | P8: =+N8+O8 -> 6307.1158 | R8: 58094.424 | S8: =+(I8-R8)/R8 -> -0.11261495 | T8: 100021653 | U8: 51552.123
B9: 100516169 | C9: MEDALLONES 18X4X80G SWIFT RECETA ESPECIAL | D9: 7790360967961 | E9: 5.76 | F9: 18 | G9: =+VLOOKUP(B9,$T$4:$U$104,2,FALSE) -> 47534.511 | I9: =+G9*(1-H9) -> 47534.511 | J9: =+I9/F9 -> 2640.8062 | K9: =+J9*K$3 -> 554.5693 | L9: =+J9+K9 -> 3195.3755 | M9: =+L9*M$3 -> 958.61264 | N9: =+L9+M9 -> 4153.9881 | O9: =+N9*O$3 -> 1661.5952 | P9: =+N9+O9 -> 5815.5834 | R9: 47534.511 | S9: =+(I9-R9)/R9 -> 0 | T9: 100516169 | U9: 47534.511
B10: 100520337 | C10: MEDALLON BURGER SWIFT MEGA 30 x 160 g | D10: 7790360977960 | E10: 4.8 | F10: 30 | G10: =+VLOOKUP(B10,$T$4:$U$104,2,FALSE) -> 27614.342 | I10: =+G10*(1-H10) -> 27614.342 | J10: =+I10/F10 -> 920.47806 | K10: =+J10*K$3 -> 193.30039 | L10: =+J10+K10 -> 1113.7784 | M10: =+L10*M$3 -> 334.13353 | N10: =+L10+M10 -> 1447.912 | O10: =+N10*O$3 -> 579.16479 | P10: =+N10+O10 -> 2027.0768 | R10: 27614.342 | S10: =+(I10-R10)/R10 -> 0 | T10: 100520337 | U10: 27614.342
B11: 100021503 | C11: Medallón CAJITA 12x4 69 grs | D11: 7790360966841 | E11: 3.312 | F11: 12 | G11: =+VLOOKUP(B11,$T$4:$U$104,2,FALSE) -> 21084.263 | H11: 0.0833 | I11: =+G11*(1-H11) -> 19327.944 | J11: =+I11/F11 -> 1610.662 | K11: =+J11*K$3 -> 338.23902 | L11: =+J11+K11 -> 1948.901 | M11: =+L11*M$3 -> 584.67031 | N11: =+L11+M11 -> 2533.5714 | O11: =+N11*O$3 -> 1013.4285 | P11: =+N11+O11 -> 3546.9999 | R11: 17418.809 | S11: =+(I11-R11)/R11 -> 0.10960195 | T11: 100021503 | U11: 21084.263
B12: 100516201 | C12: HAMBURGUESA 8X12X69G BURGER SWIFT | D12: 7790360968548 | E12: 6.624 | F12: 8 | G12: =+VLOOKUP(B12,$T$4:$U$104,2,FALSE) -> 46067.118 | I12: =+G12*(1-H12) -> 46067.118 | J12: =+I12/F12 -> 5758.3897 | K12: =+J12*K$3 -> 1209.2618 | L12: =+J12+K12 -> 6967.6516 | M12: =+L12*M$3 -> 2090.2955 | N12: =+L12+M12 -> 9057.947 | O12: =+N12*O$3 -> 3623.1788 | P12: =+N12+O12 -> 12681.126 | R12: 43873.446 | S12: =+(I12-R12)/R12 -> 0.05 | T12: 100516201 | U12: 46067.118
B13: 100021643 | C13: MEDALLON 42X112G DOBLE BURGER SWIFT | D13: 7790360966797 | E13: 4.704 | F13: 42 | G13: =+VLOOKUP(B13,$T$4:$U$104,2,FALSE) -> 28251.566 | I13: =+G13*(1-H13) -> 28251.566 | J13: =+I13/F13 -> 672.65633 | K13: =+J13*K$3 -> 141.25783 | L13: =+J13+K13 -> 813.91416 | M13: =+L13*M$3 -> 244.17425 | N13: =+L13+M13 -> 1058.0884 | O13: =+N13*O$3 -> 423.23536 | P13: =+N13+O13 -> 1481.3238 | R13: 26906.253 | S13: =+(I13-R13)/R13 -> 0.05 | T13: 100021643 | U13: 28251.566
B14: 100516325 | C14: MEDALLON DOBLE BURGER 2X2 | D14: 7790360967763 | E14: 4.704 | F14: 21 | G14: =+VLOOKUP(B14,$T$4:$U$104,2,FALSE) -> 31773.021 | I14: =+G14*(1-H14) -> 31773.021 | J14: =+I14/F14 -> 1513.001 | K14: =+J14*K$3 -> 317.73021 | L14: =+J14+K14 -> 1830.7312 | M14: =+L14*M$3 -> 549.21937 | N14: =+L14+M14 -> 2379.9506 | O14: =+N14*O$3 -> 951.98024 | P14: =+N14+O14 -> 3331.9309 | R14: 31773.021 | S14: =+(I14-R14)/R14 -> 0 | T14: 100516325 | U14: 31773.021
B15: 100021676 | C15: HAMBURGUESA 30X250g CLASICA "XL" SWIFT | D15: 7790360967411 | E15: 7.5 | F15: 30 | G15: =+VLOOKUP(B15,$T$4:$U$104,2,FALSE) -> 61903.059 | H15: 0.0667 | I15: =+G15*(1-H15) -> 57774.125 | J15: =+I15/F15 -> 1925.8042 | K15: =+J15*K$3 -> 404.41888 | L15: =+J15+K15 -> 2330.2231 | M15: =+L15*M$3 -> 699.06692 | N15: =+L15+M15 -> 3029.29 | O15: =+N15*O$3 -> 1211.716 | P15: =+N15+O15 -> 4241.006 | R15: 61903.059 | S15: =+(I15-R15)/R15 -> -0.0667 | T15: 100021676 | U15: 61903.059
B16: 100516008 | C16: HAMBURGUESA 24X2X120g CASERA SWIFT | D16: 7790360967701 | E16: 5.76 | F16: 24 | G16: =+VLOOKUP(B16,$T$4:$U$104,2,FALSE) -> 54953.721 | H16: 0.0909 | I16: =+G16*(1-H16) -> 49958.428 | J16: =+I16/F16 -> 2081.6012 | K16: =+J16*K$3 -> 437.13624 | L16: =+J16+K16 -> 2518.7374 | M16: =+L16*M$3 -> 755.62122 | N16: =+L16+M16 -> 3274.3586 | O16: =+N16*O$3 -> 1309.7434 | P16: =+N16+O16 -> 4584.1021 | R16: 54953.721 | S16: =+(I16-R16)/R16 -> -0.0909 | T16: 100516008 | U16: 54953.721
B17: 100520834 | C17: HAMBURGUESA X-TREMA 36 x 185 grs | D17: 7790360980618 | E17: 6.66 | F17: 36 | G17: =+VLOOKUP(B17,$T$4:$U$104,2,FALSE) -> 64264.025 | I17: =+G17*(1-H17) -> 64264.025 | J17: =+I17/F17 -> 1785.1118 | K17: =+J17*K$3 -> 374.87348 | L17: =+J17+K17 -> 2159.9853 | M17: =+L17*M$3 -> 647.99559 | N17: =+L17+M17 -> 2807.9809 | O17: =+N17*O$3 -> 1123.1924 | P17: =+N17+O17 -> 3931.1732 | R17: 64264.025 | S17: =+(I17-R17)/R17 -> 0 | T17: 100520834 | U17: 64264.025
B18: 100021680 | C18: HAMBURGUESAS 18X2X120g CLL BRA/ARG | D18: 7790360967688 | E18: 4.32 | F18: 18 | G18: =+VLOOKUP(B18,$T$4:$U$104,2,FALSE) -> 51472.633 | I18: =+G18*(1-H18) -> 51472.633 | J18: =+I18/F18 -> 2859.5907 | K18: =+J18*K$3 -> 600.51405 | L18: =+J18+K18 -> 3460.1048 | M18: =+L18*M$3 -> 1038.0314 | N18: =+L18+M18 -> 4498.1362 | O18: =+N18*O$3 -> 1799.2545 | P18: =+N18+O18 -> 6297.3907 | R18: 51472.633 | S18: =+(I18-R18)/R18 -> 0 | T18: 100021680 | U18: 51472.633
B19: 100021644 | C19: MEDALLON 42X112G LA BLANCA | D19: 7790360008541 | E19: 4.704 | F19: 42 | G19: =+VLOOKUP(B19,$T$4:$U$104,2,FALSE) -> 19172.581 | I19: =+G19*(1-H19) -> 19172.581 | J19: =+I19/F19 -> 456.49003 | K19: =+J19*K$3 -> 95.862907 | L19: =+J19+K19 -> 552.35294 | M19: =+L19*0.33 -> 182.27647 | N19: =+L19+M19 -> 734.62941 | O19: =+N19*O$3 -> 293.85176 | P19: =+N19+O19 -> 1028.4812 | R19: 16671.81 | S19: =+(I19-R19)/R19 -> 0.15 | T19: 100021644 | U19: 19172.581
B20: 100021677 | C20: MEDALLON 12x4X69G LA BLANCA | D20: 7790360967404 | E20: 3.312 | F20: 12 | G20: =+VLOOKUP(B20,$T$4:$U$104,2,FALSE) -> 15215.664 | I20: =+G20*(1-H20) -> 15215.664 | J20: =+I20/F20 -> 1267.972 | K20: =+J20*K$3 -> 266.27413 | L20: =+J20+K20 -> 1534.2462 | M20: =+L20*0.33 -> 506.30123 | N20: =+L20+M20 -> 2040.5474 | O20: =+N20*O$3 -> 816.21896 | P20: =+N20+O20 -> 2856.7664 | R20: 15215.664 | S20: =+(I20-R20)/R20 -> 0 | T20: 100021677 | U20: 15215.664
B21: 100021638 | C21: MEDALLONES 60X80g "SWIFT BURGER" PARRILLERAS FAMILY | D21: 7790360026699 | E21: 4.8 | F21: 60 | G21: =+VLOOKUP(B21,$T$4:$U$104,2,FALSE) -> 48413.087 | I21: =+G21*(1-H21) -> 48413.087 | J21: =+I21/F21 -> 806.88478 | K21: =+J21*K$3 -> 169.4458 | L21: =+J21+K21 -> 976.33058 | M21: =+L21*M$3 -> 292.89917 | N21: =+L21+M21 -> 1269.2298 | O21: =+N21*O$3 -> 507.6919 | P21: =+N21+O21 -> 1776.9217 | R21: 48413.087 | S21: =+(I21-R21)/R21 -> 0 | T21: 100021638 | U21: 48413.087
B22: 100021575 | C22: MEDALLONES 60X69g "SWIFT BURGER"PARRILLERAS FAMILY | D22: 7790360007032 | E22: 4.14 | F22: 60 | G22: =+VLOOKUP(B22,$T$4:$U$104,2,FALSE) -> 39706.427 | I22: =+G22*(1-H22) -> 39706.427 | J22: =+I22/F22 -> 661.77378 | K22: =+J22*K$3 -> 138.97249 | L22: =+J22+K22 -> 800.74627 | M22: =+L22*M$3 -> 240.22388 | N22: =+L22+M22 -> 1040.9702 | O22: =+N22*O$3 -> 416.38806 | P22: =+N22+O22 -> 1457.3582 | R22: 39706.427 | S22: =+(I22-R22)/R22 -> 0 | T22: 100021575 | U22: 39706.427
B23: 100021514 | C23: MEDALLON 60X69G CARNE VACUNA | D23: 7790360006943 | E23: 4.14 | F23: 60 | G23: =+VLOOKUP(B23,$T$4:$U$104,2,FALSE) -> 36132.623 | I23: =+G23*(1-H23) -> 36132.623 | J23: =+I23/F23 -> 602.21039 | K23: =+J23*K$3 -> 126.46418 | L23: =+J23+K23 -> 728.67457 | M23: =+L23*M$3 -> 218.60237 | N23: =+L23+M23 -> 947.27694 | O23: =+N23*O$3 -> 378.91078 | P23: =+N23+O23 -> 1326.1877 | R23: 36132.623 | S23: =+(I23-R23)/R23 -> 0 | T23: 100021514 | U23: 36132.623
B24: 100516208 | C24: MEDALLON 60x80g PARRILLERO MC SWIFT | D24: 7790360968203 | E24: =60*0.08 -> 4.8 | F24: 60 | G24: =+VLOOKUP(B24,$T$4:$U$104,2,FALSE) -> 41892.919 | I24: =+G24*(1-H24) -> 41892.919 | J24: =+I24/F24 -> 698.21531 | K24: =+J24*K$3 -> 146.62521 | L24: =+J24+K24 -> 844.84052 | M24: =+L24*M$3 -> 253.45216 | N24: =+L24+M24 -> 1098.2927 | O24: =+N24*O$3 -> 439.31707 | P24: =+N24+O24 -> 1537.6098 | R24: 41892.919 | S24: =+(I24-R24)/R24 -> 0 | T24: 100516208 | U24: 41892.919
B25: 100518346 | C25: MEDALLON 60X109G CARNE VACUNA PARRILLERO SWIFT | E25: 6.54 | F25: 60 | G25: =+VLOOKUP(B25,$T$4:$U$104,2,FALSE) -> 59877.117 | I25: =+G25*(1-H25) -> 59877.117 | J25: =+I25/F25 -> 997.95195 | K25: =+J25*K$3 -> 209.56991 | L25: =+J25+K25 -> 1207.5219 | M25: =+L25*M$3 -> 362.25656 | N25: =+L25+M25 -> 1569.7784 | O25: =+N25*O$3 -> 627.91136 | P25: =+N25+O25 -> 2197.6898 | R25: 59877.117 | S25: =+(I25-R25)/R25 -> 0 | T25: 100518346 | U25: 59877.117
B26: 100516259 | C26: MEDALLON GIGANTE 48x113.5g | D26: 7790360968340 | E26: 18.16 | F26: 48 | G26: =+VLOOKUP(B26,$T$4:$U$104,2,FALSE) -> 138537.07 | I26: =+G26*(1-H26) -> 138537.07 | J26: =+I26/F26 -> 2886.1889 | K26: =+J26*K$3 -> 606.09967 | L26: =+J26+K26 -> 3492.2885 | M26: =+L26*M$3 -> 1047.6866 | N26: =+L26+M26 -> 4539.9751 | O26: =+N26*O$3 -> 1815.99 | P26: =+N26+O26 -> 6355.9652 | R26: 138537.07 | S26: =+(I26-R26)/R26 -> 0 | T26: 100516259 | U26: 138537.07
B27: 100518095 | C27: HAMBURGUESA 36 X 185 GRS | D27: 7790360974785 | E27: 6.66 | F27: 36 | G27: =+VLOOKUP(B27,$T$4:$U$104,2,FALSE) -> 69025.627 | I27: =+G27*(1-H27) -> 69025.627 | J27: =+I27/F27 -> 1917.3785 | K27: =+J27*K$3 -> 402.64949 | L27: =+J27+K27 -> 2320.028 | M27: =+L27*M$3 -> 696.00841 | N27: =+L27+M27 -> 3016.0364 | O27: =+N27*O$3 -> 1206.4146 | P27: =+N27+O27 -> 4222.451 | R27: 69025.627 | S27: =+(I27-R27)/R27 -> 0 | T27: 100518095 | U27: 69025.627
B28: 100518223 | C28: HAMBURGUESA 30x2x106 GRS | D28: 7790360975065 | E28: =60*0.106 -> 6.36 | F28: 30 | G28: =+VLOOKUP(B28,$T$4:$U$104,2,FALSE) -> 53740.287 | I28: =+G28*(1-H28) -> 53740.287 | J28: =+I28/F28 -> 1791.3429 | K28: =+J28*K$3 -> 376.18201 | L28: =+J28+K28 -> 2167.5249 | M28: =+L28*M$3 -> 650.25747 | N28: =+L28+M28 -> 2817.7824 | O28: =+N28*O$3 -> 1127.113 | P28: =+N28+O28 -> 3944.8953 | R28: 53740.287 | S28: =+(I28-R28)/R28 -> 0 | T28: 100518223 | U28: 53740.287
J29: =+I29/F29 -> #DIV/0! | K29: 0.21 | M29: 0.3 | O29: 0.4 | S29: =+(I29-R29)/R29 -> #DIV/0!
B30: 100022085 | C30: SALCHICHAS 24X6 SWIFT | D30: 7790360000132 | E30: 5.4 | F30: 24 | G30: =+Litoral!H30*1.1 -> 22477.65 | I30: =+G30*(1-H30) -> 22477.65 | J30: =+I30/F30 -> 936.56875 | K30: =+J30*K$3 -> 196.67944 | L30: =+J30+K30 -> 1133.2482 | M30: =+L30*M$3 -> 339.97446 | N30: =+L30+M30 -> 1473.2226 | O30: =+N30*O$3 -> 589.28906 | P30: =+N30+O30 -> 2062.5117 | R30: 21177.281 | S30: =+(I30-R30)/R30 -> 0.061403979 | T30: 100022085 | U30: 35527.915
B31: 100522204 | C31: SALCHICHAS 24X6 SWIFT | D31: 7790360983947 | E31: 5.4 | F31: 24 | G31: =+Litoral!H31*1.1 -> 22477.65 | I31: =+G31*(1-H31) -> 22477.65 | J31: =+I31/F31 -> 936.56875 | K31: =+J31*K$3 -> 196.67944 | L31: =+J31+K31 -> 1133.2482 | M31: =+L31*M$3 -> 339.97446 | N31: =+L31+M31 -> 1473.2226 | O31: =+N31*O$3 -> 589.28906 | P31: =+N31+O31 -> 2062.5117 | T31: 100522204 | U31: 35527.915
B32: 100022072 | C32: SALCHICHAS 12X12 SWIFT | D32: 7790360024541 | E32: 5.4 | F32: 12 | G32: =+Litoral!H32*1.1 -> 21353.768 | I32: =+G32*(1-H32) -> 21353.768 | J32: =+I32/F32 -> 1779.4806 | K32: =+J32*K$3 -> 373.69093 | L32: =+J32+K32 -> 2153.1716 | M32: =+L32*M$3 -> 645.95147 | N32: =+L32+M32 -> 2799.123 | O32: =+N32*O$3 -> 1119.6492 | P32: =+N32+O32 -> 3918.7722 | R32: 20062.698 | S32: =+(I32-R32)/R32 -> 0.064351759 | T32: 100022072 | U32: 35441.013
B33: 100522205 | C33: SALCHICHAS 12X12 SWIFT | D33: 7790360983954 | E33: 5.4 | F33: 12 | G33: =+Litoral!H33*1.1 -> 21353.768 | I33: =+G33*(1-H33) -> 21353.768 | J33: =+I33/F33 -> 1779.4806 | K33: =+J33*K$3 -> 373.69093 | L33: =+J33+K33 -> 2153.1716 | M33: =+L33*M$3 -> 645.95147 | N33: =+L33+M33 -> 2799.123 | O33: =+N33*O$3 -> 1119.6492 | P33: =+N33+O33 -> 3918.7722 | T33: 100522205 | U33: 35441.013
B34: 100516849 | C34: SALCHICHAS SIN PIEL 24X6 "SWIFT KIDS" X 190 g | D34: 7790360970053 | E34: 4.56 | F34: 24 | G34: =+Litoral!H34*1.1 -> 18881.913 | I34: =+G34*(1-H34) -> 18881.913 | J34: =+I34/F34 -> 786.74636 | K34: =+J34*K$3 -> 165.21674 | L34: =+J34+K34 -> 951.9631 | M34: =+L34*M$3 -> 285.58893 | N34: =+L34+M34 -> 1237.552 | O34: =+N34*O$3 -> 495.02081 | P34: =+N34+O34 -> 1732.5728 | R34: 18390.839 | S34: =+(I34-R34)/R34 -> 0.026702084 | T34: 100516849 | U34: 34489.699
B35: 100022039 | C35: SALCHICHAS LARGAS 10 x 12 SWIFT INSTITUCIONAL | D35: 7790360007063 | E35: 8.7 | F35: 10 | G35: =+VLOOKUP(B35,$T$4:$U$104,2,FALSE) -> 61645.968 | I35: =+G35*(1-H35) -> 61645.968 | J35: =+I35/F35 -> 6164.5968 | K35: =+J35*K$3 -> 1294.5653 | L35: =+J35+K35 -> 7459.1622 | M35: =+L35*M$3 -> 2237.7487 | N35: =+L35+M35 -> 9696.9108 | O35: =+N35*O$3 -> 3878.7643 | P35: =+N35+O35 -> 13575.675 | R35: 51886.178 | S35: =+(I35-R35)/R35 -> 0.1881 | T35: 100022039 | U35: 61645.968
B36: 100522206 | C36: SALCHICHAS LARGAS 10 x 12 SWIFT INSTITUCIONAL | D36: 7790360983961 | E36: 8.7 | F36: 10 | G36: =+VLOOKUP(B36,$T$4:$U$104,2,FALSE) -> 61645.968 | I36: =+G36*(1-H36) -> 61645.968 | J36: =+I36/F36 -> 6164.5968 | K36: =+J36*K$3 -> 1294.5653 | L36: =+J36+K36 -> 7459.1622 | M36: =+L36*M$3 -> 2237.7487 | N36: =+L36+M36 -> 9696.9108 | O36: =+N36*O$3 -> 3878.7643 | P36: =+N36+O36 -> 13575.675 | T36: 100522206 | U36: 61645.968
B37: 100022058 | C37: SALCHICHAS SIN PIEL "LA BLANCA" 24X6X190 Grs; | D37: 7790360026002 | E37: 4.56 | F37: 24 | G37: =+VLOOKUP(B37,$T$4:$U$104,2,FALSE) -> 19639.956 | I37: =+G37*(1-H37) -> 19639.956 | J37: =+I37/F37 -> 818.33148 | K37: =+J37*K$3 -> 171.84961 | L37: =+J37+K37 -> 990.1811 | M37: =+L37*0.33 -> 326.75976 | N37: =+L37+M37 -> 1316.9409 | O37: =+N37*O$3 -> 526.77634 | P37: =+N37+O37 -> 1843.7172 | R37: 12594.915 | S37: =+(I37-R37)/R37 -> 0.55935599 | T37: 100022058 | U37: 19639.956 | X37: Ver posicionamiento por verba según necesidad de la zona
B38: 100518151 | C38: SALCHICHAS LARGAS 10 x 12 x 870g | D38: 7790360974990 | E38: 8.7 | F38: 10 | G38: =+VLOOKUP(B38,$T$4:$U$104,2,FALSE) -> 70230.314 | I38: =+G38*(1-H38) -> 70230.314 | J38: =+I38/F38 -> 7023.0314 | K38: =+J38*K$3 -> 1474.8366 | L38: =+J38+K38 -> 8497.8679 | M38: =+L38*0.33 -> 2804.2964 | N38: =+L38+M38 -> 11302.164 | O38: =+N38*O$3 -> 4520.8657 | P38: =+N38+O38 -> 15823.03 | R38: 59111.45 | S38: =+(I38-R38)/R38 -> 0.1881 | T38: 100518151 | U38: 70230.314
J39: =+I39/F39 -> #DIV/0! | K39: 0.21 | M39: 0.2 | O39: 0.35 | S39: =+(I39-R39)/R39 -> #DIV/0!
B40: 100021000 | C40: PATE DE FOIE 24X90G SWIFT | D40: 7790360720382 | E40: 2.16 | F40: 24 | G40: =+VLOOKUP(B40,$T$4:$U$104,2,FALSE) -> 13579.525 | I40: =+G40*(1-H40) -> 13579.525 | J40: =+I40/F40 -> 565.81353 | K40: =+J40*K$3 -> 118.82084 | L40: =+J40+K40 -> 684.63438 | M40: =+L40*M$39 -> 136.92688 | N40: =+L40+M40 -> 821.56125 | O40: =+N40*O$39 -> 287.54644 | P40: =+N40+O40 -> 1109.1077 | Q40: DCTO VIA NC - SUJETO A LA COMPRA DE 5 CAJAS DE C/U GOURMET | R40: 12345.023 | S40: =+(I40-R40)/R40 -> 0.1 | T40: 100021000 | U40: 13579.525
B41: 100021001 | C41: PICADILLO DE CARNE 24X90G SWIFT | D41: 7790360720115 | E41: 2.16 | F41: 24 | G41: =+VLOOKUP(B41,$T$4:$U$104,2,FALSE) -> 13579.525 | I41: =+G41*(1-H41) -> 13579.525 | J41: =+I41/F41 -> 565.81353 | K41: =+J41*K$3 -> 118.82084 | L41: =+J41+K41 -> 684.63438 | M41: =+L41*M$39 -> 136.92688 | N41: =+L41+M41 -> 821.56125 | O41: =+N41*O$39 -> 287.54644 | P41: =+N41+O41 -> 1109.1077 | Q41: DCTO VIA NC - SUJETO A LA COMPRA DE 5 CAJAS DE C/U GOURMET | R41: 12345.023 | S41: =+(I41-R41)/R41 -> 0.1 | T41: 100021001 | U41: 13579.525
B42: 100522277 | C42: Picadillo de Carne Picante Chile Chipotle 24x90 g | E42: 2.16 | F42: 24 | G42: =+VLOOKUP(B42,$T$4:$U$104,2,FALSE) -> 13579.525 | I42: =+G42*(1-H42) -> 13579.525 | J42: =+I42/F42 -> 565.81353 | K42: =+J42*K$3 -> 118.82084 | L42: =+J42+K42 -> 684.63438 | M42: =+L42*M$39 -> 136.92688 | N42: =+L42+M42 -> 821.56125 | O42: =+N42*O$39 -> 287.54644 | P42: =+N42+O42 -> 1109.1077 | R42: 12345.023 | T42: 100522277 | U42: 13579.525
B43: 100522333 | C43: Pate de Foie Jalapeño 24x90 Swift | E43: 2.16 | F43: 24 | G43: =+VLOOKUP(B43,$T$4:$U$104,2,FALSE) -> 13579.525 | I43: =+G43*(1-H43) -> 13579.525 | J43: =+I43/F43 -> 565.81353 | K43: =+J43*K$3 -> 118.82084 | L43: =+J43+K43 -> 684.63438 | M43: =+L43*M$39 -> 136.92688 | N43: =+L43+M43 -> 821.56125 | O43: =+N43*O$39 -> 287.54644 | P43: =+N43+O43 -> 1109.1077 | R43: 12345.023 | T43: 100522333 | U43: 13579.525
B44: 100021045 | C44: PICADILLO DE CARNE PICANTE 24X90G SWIFT | D44: 7790360966582 | E44: 2.16 | F44: 24 | G44: =+VLOOKUP(B44,$T$4:$U$104,2,FALSE) -> 13579.525 | I44: =+G44*(1-H44) -> 13579.525 | J44: =+I44/F44 -> 565.81353 | K44: =+J44*K$3 -> 118.82084 | L44: =+J44+K44 -> 684.63438 | M44: =+L44*M$39 -> 136.92688 | N44: =+L44+M44 -> 821.56125 | O44: =+N44*O$39 -> 287.54644 | P44: =+N44+O44 -> 1109.1077 | R44: 12029.408 | S44: =+(I44-R44)/R44 -> 0.12886059 | T44: 100021045 | U44: 13579.525
B45: 100021004 | C45: PATE DE FOIE A LA CREMA 24X88G SWIFT | D45: 7790360964526 | E45: 2.112 | F45: 24 | G45: =+VLOOKUP(B45,$T$4:$U$104,2,FALSE) -> 13579.525 | I45: =+G45*(1-H45) -> 13579.525 | J45: =+I45/F45 -> 565.81353 | K45: =+J45*K$3 -> 118.82084 | L45: =+J45+K45 -> 684.63438 | M45: =+L45*M$39 -> 136.92688 | N45: =+L45+M45 -> 821.56125 | O45: =+N45*O$39 -> 287.54644 | P45: =+N45+O45 -> 1109.1077 | R45: 12029.408 | S45: =+(I45-R45)/R45 -> 0.12886059 | T45: 100021004 | U45: 13579.525
B46: 100021006 | C46: JAMON DEL DIABLO 24X88G SWIFT | D46: 7790360964557 | E46: 2.112 | F46: 24 | G46: =+VLOOKUP(B46,$T$4:$U$104,2,FALSE) -> 13579.525 | I46: =+G46*(1-H46) -> 13579.525 | J46: =+I46/F46 -> 565.81353 | K46: =+J46*K$3 -> 118.82084 | L46: =+J46+K46 -> 684.63438 | M46: =+L46*M$39 -> 136.92688 | N46: =+L46+M46 -> 821.56125 | O46: =+N46*O$39 -> 287.54644 | P46: =+N46+O46 -> 1109.1077 | R46: 12029.408 | S46: =+(I46-R46)/R46 -> 0.12886059 | T46: 100021006 | U46: 13579.525
B47: 100021007 | C47: PATE DE FOIE DE POLLO 24X85G SWIFT | D47: 7790360964540 | E47: 2.04 | F47: 24 | G47: =+VLOOKUP(B47,$T$4:$U$104,2,FALSE) -> 15501.688 | I47: =+G47*(1-H47) -> 15501.688 | J47: =+I47/F47 -> 645.90367 | K47: =+J47*K$3 -> 135.63977 | L47: =+J47+K47 -> 781.54344 | M47: =+L47*M$39 -> 156.30869 | N47: =+L47+M47 -> 937.85213 | O47: =+N47*O$39 -> 328.24825 | P47: =+N47+O47 -> 1266.1004 | R47: 14092.444 | S47: =+(I47-R47)/R47 -> 0.1 | T47: 100021007 | U47: 15501.688
B48: 100021013 | C48: PATE DE FOIE TIPO PROVENZAL 24X85G SWIFT GOURMET | D48: 7790360965714 | E48: 2.04 | F48: 24 | G48: =+VLOOKUP(B48,$T$4:$U$104,2,FALSE) -> 15501.688 | I48: =+G48*(1-H48) -> 15501.688 | J48: =+I48/F48 -> 645.90367 | K48: =+J48*K$3 -> 135.63977 | L48: =+J48+K48 -> 781.54344 | M48: =+L48*M$39 -> 156.30869 | N48: =+L48+M48 -> 937.85213 | O48: =+N48*O$39 -> 328.24825 | P48: =+N48+O48 -> 1266.1004 | R48: 14092.444 | S48: =+(I48-R48)/R48 -> 0.1 | T48: 100021013 | U48: 15501.688
B49: 100021014 | C49: PATE DE FOIE C/PIMIENTA VERDE 24X85G SWIFT GOURMET | D49: 7790360965721 | E49: 2.04 | F49: 24 | G49: =+VLOOKUP(B49,$T$4:$U$104,2,FALSE) -> 15501.688 | I49: =+G49*(1-H49) -> 15501.688 | J49: =+I49/F49 -> 645.90367 | K49: =+J49*K$3 -> 135.63977 | L49: =+J49+K49 -> 781.54344 | M49: =+L49*M$39 -> 156.30869 | N49: =+L49+M49 -> 937.85213 | O49: =+N49*O$39 -> 328.24825 | P49: =+N49+O49 -> 1266.1004 | R49: 14092.444 | S49: =+(I49-R49)/R49 -> 0.1 | T49: 100021014 | U49: 15501.688
B50: 100021054 | C50: PATE JAMON AHUMADO 24X85G | D50: 7790360965707 | E50: 2.04 | F50: 24 | G50: =+VLOOKUP(B50,$T$4:$U$104,2,FALSE) -> 15501.688 | I50: =+G50*(1-H50) -> 15501.688 | J50: =+I50/F50 -> 645.90367 | K50: =+J50*K$3 -> 135.63977 | L50: =+J50+K50 -> 781.54344 | M50: =+L50*M$39 -> 156.30869 | N50: =+L50+M50 -> 937.85213 | O50: =+N50*O$39 -> 328.24825 | P50: =+N50+O50 -> 1266.1004 | R50: 14092.444 | S50: =+(I50-R50)/R50 -> 0.1 | T50: 100021054 | U50: 15501.688
B51: 100021055 | C51: PATE HONGOS 24X85G | D51: 7790360965189 | E51: 2.04 | F51: 24 | G51: =+VLOOKUP(B51,$T$4:$U$104,2,FALSE) -> 15501.688 | I51: =+G51*(1-H51) -> 15501.688 | J51: =+I51/F51 -> 645.90367 | K51: =+J51*K$3 -> 135.63977 | L51: =+J51+K51 -> 781.54344 | M51: =+L51*M$39 -> 156.30869 | N51: =+L51+M51 -> 937.85213 | O51: =+N51*O$39 -> 328.24825 | P51: =+N51+O51 -> 1266.1004 | R51: 14092.444 | S51: =+(I51-R51)/R51 -> 0.1 | T51: 100021055 | U51: 15501.688
B52: 100021015 | C52: PATE DE SALMON 24X85G SWIFT GOURMET | D52: 7790360965202 | E52: 2.04 | F52: 24 | G52: =+VLOOKUP(B52,$T$4:$U$104,2,FALSE) -> 15501.688 | I52: =+G52*(1-H52) -> 15501.688 | J52: =+I52/F52 -> 645.90367 | K52: =+J52*K$3 -> 135.63977 | L52: =+J52+K52 -> 781.54344 | M52: =+L52*M$39 -> 156.30869 | N52: =+L52+M52 -> 937.85213 | O52: =+N52*O$39 -> 328.24825 | P52: =+N52+O52 -> 1266.1004 | R52: 14092.444 | S52: =+(I52-R52)/R52 -> 0.1 | T52: 100021015 | U52: 15501.688
B53: 100021008 | C53: PICADILLO DE CARNE 24X90G LA BLANCA | D53: 7790360720122 | E53: 2.16 | F53: 24 | G53: =+VLOOKUP(B53,$T$4:$U$104,2,FALSE) -> 11493.436 | I53: =+G53*(1-H53) -> 11493.436 | J53: =+I53/F53 -> 478.89316 | K53: =+J53*K$3 -> 100.56756 | L53: =+J53+K53 -> 579.46072 | M53: =+L53*M$39 -> 115.89214 | N53: =+L53+M53 -> 695.35287 | O53: =+N53*O$39 -> 243.3735 | P53: =+N53+O53 -> 938.72637 | R53: 10448.578 | S53: =+(I53-R53)/R53 -> 0.1 | T53: 100021008 | U53: 11493.436
B54: 100021009 | C54: PATE DE FOIE 24X90G LA BLANCA | D54: 7790360965127 | E54: 2.16 | F54: 24 | G54: =+VLOOKUP(B54,$T$4:$U$104,2,FALSE) -> 11493.436 | I54: =+G54*(1-H54) -> 11493.436 | J54: =+I54/F54 -> 478.89316 | K54: =+J54*K$3 -> 100.56756 | L54: =+J54+K54 -> 579.46072 | M54: =+L54*M$39 -> 115.89214 | N54: =+L54+M54 -> 695.35287 | O54: =+N54*O$39 -> 243.3735 | P54: =+N54+O54 -> 938.72637 | R54: 10448.578 | S54: =+(I54-R54)/R54 -> 0.1 | T54: 100021009 | U54: 11493.436
B55: 100021010 | C55: PICADILLO DE CARNE 24X90G SAFRA | D55: 7790920008707 | E55: 2.16 | F55: 24 | G55: =+VLOOKUP(B55,$T$4:$U$104,2,FALSE) -> 11493.436 | I55: =+G55*(1-H55) -> 11493.436 | J55: =+I55/F55 -> 478.89316 | K55: =+J55*K$3 -> 100.56756 | L55: =+J55+K55 -> 579.46072 | M55: =+L55*M$39 -> 115.89214 | N55: =+L55+M55 -> 695.35287 | O55: =+N55*O$39 -> 243.3735 | P55: =+N55+O55 -> 938.72637 | R55: 10448.578 | S55: =+(I55-R55)/R55 -> 0.1 | T55: 100021010 | U55: 11493.436
B56: 100021011 | C56: PATE DE FOIE 24X90G SAFRA | D56: 7790920008714 | E56: 2.16 | F56: 24 | G56: =+VLOOKUP(B56,$T$4:$U$104,2,FALSE) -> 11493.436 | I56: =+G56*(1-H56) -> 11493.436 | J56: =+I56/F56 -> 478.89316 | K56: =+J56*K$3 -> 100.56756 | L56: =+J56+K56 -> 579.46072 | M56: =+L56*M$39 -> 115.89214 | N56: =+L56+M56 -> 695.35287 | O56: =+N56*O$39 -> 243.3735 | P56: =+N56+O56 -> 938.72637 | R56: 10448.578 | S56: =+(I56-R56)/R56 -> 0.1 | T56: 100021011 | U56: 11493.436
J57: =+I57/F57 -> #DIV/0! | K57: 0.21 | M57: 0.3 | O57: 0.4 | S57: =+(I57-R57)/R57 -> #DIV/0!
B58: 100516217 | C58: MILANESAS DE SOJA CLASICAS PREFRITA | D58: 7790360967824 | E58: 5.8 | F58: 20 | G58: =+VLOOKUP(B58,$T$4:$U$104,2,FALSE) -> 26768.099 | I58: =+G58*(1-H58) -> 26768.099 | J58: =+I58/F58 -> 1338.405 | K58: =+J58*K$3 -> 281.06504 | L58: =+J58+K58 -> 1619.47 | M58: =+L58*M$3 -> 485.841 | N58: =+L58+M58 -> 2105.311 | O58: =+N58*O$3 -> 842.1244 | P58: =+N58+O58 -> 2947.4354 | R58: 25988.446 | S58: =+(I58-R58)/R58 -> 0.03 | T58: 100516217 | U58: 26768.099
B59: 100516214 | C59: MILANESAS DE SOJA RELLENAS CON JAMON Y QUESO | D59: 7790360967794 | E59: 7 | F59: 20 | G59: =+VLOOKUP(B59,$T$4:$U$104,2,FALSE) -> 38594.846 | H59: 0.05 | I59: =+G59*(1-H59) -> 36665.104 | J59: =+I59/F59 -> 1833.2552 | K59: =+J59*K$3 -> 384.98359 | L59: =+J59+K59 -> 2218.2388 | M59: =+L59*M$3 -> 665.47164 | N59: =+L59+M59 -> 2883.7104 | O59: =+N59*O$3 -> 1153.4842 | P59: =+N59+O59 -> 4037.1946 | R59: 35597.188 | S59: =+(I59-R59)/R59 -> 0.03 | T59: 100516214 | U59: 38594.846
B60: 100516215 | C60: MILANESAS DE SOJA RELLENAS CON ESPINACA Y QUESO | D60: 7790360967800 | E60: 7 | F60: 20 | G60: =+VLOOKUP(B60,$T$4:$U$104,2,FALSE) -> 38594.846 | H60: 0.05 | I60: =+G60*(1-H60) -> 36665.104 | J60: =+I60/F60 -> 1833.2552 | K60: =+J60*K$3 -> 384.98359 | L60: =+J60+K60 -> 2218.2388 | M60: =+L60*M$3 -> 665.47164 | N60: =+L60+M60 -> 2883.7104 | O60: =+N60*O$3 -> 1153.4842 | P60: =+N60+O60 -> 4037.1946 | R60: 35597.188 | S60: =+(I60-R60)/R60 -> 0.03 | T60: 100516215 | U60: 38594.846
B61: 100516216 | C61: MILANESAS DE SOJA RELLENAS CON TOMATE Y QUESO | D61: 7790360967817 | E61: 7 | F61: 20 | G61: =+VLOOKUP(B61,$T$4:$U$104,2,FALSE) -> 38594.846 | H61: 0.05 | I61: =+G61*(1-H61) -> 36665.104 | J61: =+I61/F61 -> 1833.2552 | K61: =+J61*K$3 -> 384.98359 | L61: =+J61+K61 -> 2218.2388 | M61: =+L61*M$3 -> 665.47164 | N61: =+L61+M61 -> 2883.7104 | O61: =+N61*O$3 -> 1153.4842 | P61: =+N61+O61 -> 4037.1946 | R61: 35597.188 | S61: =+(I61-R61)/R61 -> 0.03 | T61: 100516216 | U61: 38594.846
J62: =+I62/F62 -> #DIV/0! | K62: 0.21 | M62: 0.3 | O62: 0.4 | S62: =+(I62-R62)/R62 -> #DIV/0!
B63: 100021704 | C63: BOCADITOS DE CARNE "SWIFT" - 12x380g | D63: 7790360023902 | E63: =12*0.38 -> 4.56 | F63: 12 | G63: =+VLOOKUP(B63,$T$4:$U$104,2,FALSE) -> 41455.299 | I63: =+G63*(1-H63) -> 41455.299 | J63: =+I63/F63 -> 3454.6083 | K63: =+J63*K$3 -> 725.46774 | L63: =+J63+K63 -> 4180.076 | M63: =+L63*M$3 -> 1254.0228 | N63: =+L63+M63 -> 5434.0988 | O63: =+N63*O$3 -> 2173.6395 | P63: =+N63+O63 -> 7607.7384 | R63: 39481.237 | S63: =+(I63-R63)/R63 -> 0.05 | T63: 100021704 | U63: 41455.299
B64: 100021705 | C64: BOCADITOS DE POLLO "SWIFT" - 12x380g | D64: 7790360024336 | E64: =12*0.38 -> 4.56 | F64: 12 | G64: =+VLOOKUP(B64,$T$4:$U$104,2,FALSE) -> 37683.832 | I64: =+G64*(1-H64) -> 37683.832 | J64: =+I64/F64 -> 3140.3193 | K64: =+J64*K$3 -> 659.46706 | L64: =+J64+K64 -> 3799.7864 | M64: =+L64*M$3 -> 1139.9359 | N64: =+L64+M64 -> 4939.7223 | O64: =+N64*O$3 -> 1975.8889 | P64: =+N64+O64 -> 6915.6112 | R64: 35889.364 | S64: =+(I64-R64)/R64 -> 0.05 | T64: 100021705 | U64: 37683.832
B65: 100021709 | C65: BOCADITOS DE POLLO "SWIFT" - 10x760g | D65: 7790360024701 | E65: 7.6 | F65: 10 | G65: =+VLOOKUP(B65,$T$4:$U$104,2,FALSE) -> 60469.387 | I65: =+G65*(1-H65) -> 60469.387 | J65: =+I65/F65 -> 6046.9387 | K65: =+J65*K$3 -> 1269.8571 | L65: =+J65+K65 -> 7316.7958 | M65: =+L65*M$3 -> 2195.0387 | N65: =+L65+M65 -> 9511.8345 | O65: =+N65*O$3 -> 3804.7338 | P65: =+N65+O65 -> 13316.568 | R65: 47989.657 | S65: =+(I65-R65)/R65 -> 0.2600504 | T65: 100021709 | U65: 60469.387
B66: 100521357 | C66: CRUNCHIES DE POLLO "SWIFT" - 12x380g | E66: 4.56 | F66: 12 | G66: =+VLOOKUP(B66,$T$4:$U$104,2,FALSE) -> 48595.609 | H66: 0.33 | I66: =+G66*(1-H66) -> 32559.058 | J66: =+I66/F66 -> 2713.2548 | K66: =+J66*K$3 -> 569.78351 | L66: =+J66+K66 -> 3283.0383 | M66: =+L66*M$3 -> 984.9115 | N66: =+L66+M66 -> 4267.9498 | O66: =+N66*O$3 -> 1707.1799 | P66: =+N66+O66 -> 5975.1298 | R66: 46281.532 | S66: =+(I66-R66)/R66 -> -0.2965 | T66: 100521357 | U66: 48595.609
B67: 100521358 | C67: CRUNCHIES DE POLLO "SWIFT" - 10x760g | D67: 7790360982025 | E67: 7.6 | F67: 10 | G67: =+VLOOKUP(B67,$T$4:$U$104,2,FALSE) -> 72893.413 | I67: =+G67*(1-H67) -> 72893.413 | J67: =+I67/F67 -> 7289.3413 | K67: =+J67*K$3 -> 1530.7617 | L67: =+J67+K67 -> 8820.103 | M67: =+L67*M$3 -> 2646.0309 | N67: =+L67+M67 -> 11466.134 | O67: =+N67*O$3 -> 4586.4535 | P67: =+N67+O67 -> 16052.587 | R67: 69422.298 | T67: 100521358 | U67: 72893.413
B68: 100522130 | C68: BOCADITOS DE POLLO "SWIFT KIDS" - 12x400g | E68: 4.8 | F68: 12 | G68: =+VLOOKUP(B68,$T$4:$U$104,2,FALSE) -> 36337.502 | I68: =+G68*(1-H68) -> 36337.502 | J68: =+I68/F68 -> 3028.1252 | K68: =+J68*K$3 -> 635.90628 | L68: =+J68+K68 -> 3664.0314 | M68: =+L68*M$3 -> 1099.2094 | N68: =+L68+M68 -> 4763.2409 | O68: =+N68*O$3 -> 1905.2963 | P68: =+N68+O68 -> 6668.5372 | R68: 29258.098 | S68: =+(I68-R68)/R68 -> 0.2419639 | T68: 100522130 | U68: 36337.502
B69: 100021725 | C69: BOCADITOS DE POLLO GASTRONOMICOS "LA BLANCA" - x6kg | D69: 7790360027009 | E69: 6 | F69: 4 | G69: =+VLOOKUP(B69,$T$4:$U$104,2,FALSE) -> 31255.57 | I69: =+G69*(1-H69) -> 31255.57 | J69: =+I69/F69 -> 7813.8925 | K69: =+J69*K$3 -> 1640.9174 | L69: =+J69+K69 -> 9454.8099 | M69: =+L69*M$3 -> 2836.443 | N69: =+L69+M69 -> 12291.253 | O69: =+N69*O$3 -> 4916.5011 | P69: =+N69+O69 -> 17207.754 | R69: 29767.209 | S69: =+(I69-R69)/R69 -> 0.05 | T69: 100021725 | U69: 31255.57
B70: 100517055 | C70: PALITO DE POLLO "SWIFT" 12 X 260 Grs. | D70: 7790360971135 | E70: 3.12 | F70: 12 | G70: =+VLOOKUP(B70,$T$4:$U$104,2,FALSE) -> 31213.609 | I70: =+G70*(1-H70) -> 31213.609 | J70: =+I70/F70 -> 2601.1341 | K70: =+J70*K$3 -> 546.23816 | L70: =+J70+K70 -> 3147.3722 | M70: =+L70*M$3 -> 944.21167 | N70: =+L70+M70 -> 4091.5839 | O70: =+N70*O$3 -> 1636.6336 | P70: =+N70+O70 -> 5728.2175 | R70: 29727.247 | S70: =+(I70-R70)/R70 -> 0.05 | T70: 100517055 | U70: 31213.609
B71: 100517186 | C71: PALITO DE POLLO "SWIFT" 8 X 1 Kg.. | D71: 7790360971395 | E71: 8 | F71: 8 | G71: =+VLOOKUP(B71,$T$4:$U$104,2,FALSE) -> 78871.462 | I71: =+G71*(1-H71) -> 78871.462 | J71: =+I71/F71 -> 9858.9327 | K71: =+J71*K$3 -> 2070.3759 | L71: =+J71+K71 -> 11929.309 | M71: =+L71*M$3 -> 3578.7926 | N71: =+L71+M71 -> 15508.101 | O71: =+N71*O$3 -> 6203.2405 | P71: =+N71+O71 -> 21711.342 | R71: 75115.678 | S71: =+(I71-R71)/R71 -> 0.05 | T71: 100517186 | U71: 78871.462
B72: 100521663 | C72: MILANESITAS DE CARNE "SWIFT" - 12x400g | E72: 4.8 | F72: 12 | G72: 41797.283 | H72: 0.33 | I72: =+G72*(1-H72) -> 28004.18 | J72: =+I72/F72 -> 2333.6816 | K72: =+J72*K$3 -> 490.07315 | L72: =+J72+K72 -> 2823.7548 | M72: =+L72*M$3 -> 847.12644 | N72: =+L72+M72 -> 3670.8812 | O72: =+N72*O$3 -> 1468.3525 | P72: =+N72+O72 -> 5139.2337 | R72: 47021.568 | S72: =+(I72-R72)/R72 -> -0.40443969 | T72: 100521663 | U72: 49372.646
B73: 100021728 | C73: MEDALLONES DE POLLO "SWIFT" - 12x4x80g | D73: 7790360967558 | E73: 3.84 | F73: 12 | G73: =+VLOOKUP(B73,$T$4:$U$104,2,FALSE) -> 39236.851 | I73: =+G73*(1-H73) -> 39236.851 | J73: =+I73/F73 -> 3269.7376 | K73: =+J73*K$3 -> 686.64489 | L73: =+J73+K73 -> 3956.3825 | M73: =+L73*M$3 -> 1186.9147 | N73: =+L73+M73 -> 5143.2972 | O73: =+N73*O$3 -> 2057.3189 | P73: =+N73+O73 -> 7200.6161 | R73: 37368.43 | S73: =+(I73-R73)/R73 -> 0.05 | T73: 100021728 | U73: 39236.851
B74: 100517679 | C74: MEDALLONES DE POLLO GASTRONÓMICO 8x12x80 Grs. | E74: 7.68 | F74: 8 | G74: =+VLOOKUP(B74,$T$4:$U$104,2,FALSE) -> 39413.592 | I74: =+G74*(1-H74) -> 39413.592 | J74: =+I74/F74 -> 4926.699 | K74: =+J74*K$3 -> 1034.6068 | L74: =+J74+K74 -> 5961.3058 | M74: =+L74*M$3 -> 1788.3918 | N74: =+L74+M74 -> 7749.6976 | O74: =+N74*O$3 -> 3099.879 | P74: =+N74+O74 -> 10849.577 | R74: 37536.755 | S74: =+(I74-R74)/R74 -> 0.05 | T74: 100517679 | U74: 39413.592
G75: #VALUE! | I75: =+G75*(1-H75) -> #VALUE! | J75: =+I75/F75 -> #VALUE! | K75: 0.21 | M75: 0.3 | O75: 0.4 | R75: #VALUE! | S75: =+(I75-R75)/R75 -> #VALUE! | U75: #VALUE!
B76: 100516219 | C76: PAPAS PREFRITAS SUPERCONGELADAS 25x400gr | D76: 7790360967770 | E76: 10 | F76: 25 | G76: 18259.4 | I76: =+G76*(1-H76) -> 18259.4 | J76: =+I76/F76 -> 730.376 | K76: =+J76*K$3 -> 153.37896 | L76: =+J76+K76 -> 883.75495 | M76: =+L76*M$3 -> 265.12649 | N76: =+L76+M76 -> 1148.8814 | O76: =+N76*O$3 -> 459.55258 | P76: =+N76+O76 -> 1608.434 | R76: 18259.4 | S76: =+(I76-R76)/R76 -> 0 | T76: 100516219 | U76: 18259.4
B77: 100516220 | C77: PAPAS PREFRITAS SUPERCONGELADAS 6x2000gr | D77: 7790360967787 | E77: 12 | F77: 6 | G77: 19613.922 | I77: =+G77*(1-H77) -> 19613.922 | J77: =+I77/F77 -> 3268.987 | K77: =+J77*K$3 -> 686.48726 | L77: =+J77+K77 -> 3955.4742 | M77: =+L77*M$3 -> 1186.6423 | N77: =+L77+M77 -> 5142.1165 | O77: =+N77*O$3 -> 2056.8466 | P77: =+N77+O77 -> 7198.9631 | R77: 19613.922 | S77: =+(I77-R77)/R77 -> 0 | T77: 100516220 | U77: 19613.922
G78: #VALUE! | I78: =+G78*(1-H78) -> #VALUE! | J78: =+I78/F78 -> #VALUE! | R78: #VALUE! | S78: =+(I78-R78)/R78 -> #VALUE! | U78: #VALUE!
B79: 100518158 | C79: MILANESA DE CARNE VACUNA CONGELADA 24un x 500grs | D79: 7790360974280 | E79: 12 | F79: 24 | G79: =+VLOOKUP(B79,$T$4:$U$104,2,FALSE) -> 75339.603 | I79: =+G79*(1-H79) -> 75339.603 | J79: =+I79/F79 -> 3139.1501 | K79: =+J79*K$3 -> 659.22153 | L79: =+J79+K79 -> 3798.3716 | M79: =+L79*M$3 -> 1139.5115 | N79: =+L79+M79 -> 4937.8831 | O79: =+N79*O$3 -> 1975.1533 | P79: =+N79+O79 -> 6913.0364 | R79: 75339.603 | S79: =+(I79-R79)/R79 -> 0 | T79: 100518158 | U79: 75339.603
B80: 100518160 | C80: MILANESA DE CARNE VACUNA CONGELADA 12un x 1000grs | D80: 7790360974686 | E80: 12 | F80: 12 | G80: =+VLOOKUP(B80,$T$4:$U$104,2,FALSE) -> 75339.603 | I80: =+G80*(1-H80) -> 75339.603 | J80: =+I80/F80 -> 6278.3002 | K80: =+J80*K$3 -> 1318.4431 | L80: =+J80+K80 -> 7596.7433 | M80: =+L80*M$3 -> 2279.023 | N80: =+L80+M80 -> 9875.7663 | O80: =+N80*O$3 -> 3950.3065 | P80: =+N80+O80 -> 13826.073 | R80: 75339.603 | S80: =+(I80-R80)/R80 -> 0 | T80: 100518160 | U80: 75339.603
B81: 100518463 | C81: MILANESAS DE CARNE VACUNA CONG GRANEL 5 kg (CAL GR) | E81: 5 | F81: 1 | G81: =+VLOOKUP(B81,$T$4:$U$104,2,FALSE) -> 36693.267 | I81: =+G81*(1-H81) -> 36693.267 | J81: =+I81/F81 -> 36693.267 | K81: =+J81*K$3 -> 7705.5861 | L81: =+J81+K81 -> 44398.853 | M81: =+L81*M$3 -> 13319.656 | N81: =+L81+M81 -> 57718.509 | O81: =+N81*O$3 -> 23087.404 | P81: =+N81+O81 -> 80805.913 | R81: 36693.267 | S81: =+(I81-R81)/R81 -> 0 | T81: 100518463 | U81: 36693.267
G82: #VALUE! | I82: =+G82*(1-H82) -> #VALUE! | J82: =+I82/F82 -> #VALUE! | M82: 0.2 | O82: 0.35 | R82: #VALUE! | S82: =+(I82-R82)/R82 -> #VALUE! | U82: #VALUE!
B83: 100518291 | C83: GRASA VACUNA REFINADA SWIFT 10 X 500 | D83: 7790360975195 | E83: 5 | F83: 10 | G83: =+VLOOKUP(B83,$T$4:$U$104,2,FALSE) -> 17536.687 | H83: 0.15 | I83: =+G83*(1-H83) -> 14906.184 | J83: =+I83/F83 -> 1490.6184 | K83: =+J83*K$3 -> 313.02986 | L83: =+J83+K83 -> 1803.6483 | M83: =+L83*M$39 -> 360.72965 | N83: =+L83+M83 -> 2164.3779 | O83: =+N83*O$39 -> 757.53227 | P83: =+N83+O83 -> 2921.9102 | R83: 14906.184 | S83: =+(I83-R83)/R83 -> 0 | T83: 100518291 | U83: 17536.687
B84: 100518292 | C84: GRASA VACUNA REFINADA SWIFT 12x1Kg | D84: 7790360975201 | E84: 12 | F84: 12 | G84: =+VLOOKUP(B84,$T$4:$U$104,2,FALSE) -> 41380.324 | H84: 0.15 | I84: =+G84*(1-H84) -> 35173.275 | J84: =+I84/F84 -> 2931.1063 | K84: =+J84*K$3 -> 615.53232 | L84: =+J84+K84 -> 3546.6386 | M84: =+L84*M$39 -> 709.32772 | N84: =+L84+M84 -> 4255.9663 | O84: =+N84*O$39 -> 1489.5882 | P84: =+N84+O84 -> 5745.5545 | R84: 35173.275 | S84: =+(I84-R84)/R84 -> 0 | T84: 100518292 | U84: 41380.324
G85: #VALUE! | I85: =+G85*(1-H85) -> #VALUE! | J85: =+I85/F85 -> #VALUE! | K85: 0.105 | M85: 0.3 | O85: 0.4 | R85: #VALUE! | S85: =+(I85-R85)/R85 -> #VALUE! | U85: #VALUE!
B86: 100517915 | C86: CARNE PICADA CONGELADA 36 UN X 500 g SWIFT | D86: 7790360974020 | E86: 18 | F86: 36 | G86: =+VLOOKUP(B86,$T$4:$U$104,2,FALSE) -> 154338.47 | I86: =+G86*(1-H86) -> 154338.47 | J86: =+I86/F86 -> 4287.1798 | K86: =+J86*K$85 -> 450.15388 | L86: =+J86+K86 -> 4737.3337 | M86: =+L86*M$85 -> 1421.2001 | N86: =+L86+M86 -> 6158.5338 | O86: =+N86*O$85 -> 2463.4135 | P86: =+N86+O86 -> 8621.9473 | R86: 145602.33 | S86: =+(I86-R86)/R86 -> 0.06 | T86: 100517915 | U86: 154338.47
B87: 100517914 | C87: CARNE PICADA CONGELADA 20 UN X 1 kg SWIFT | D87: 7790360974037 | E87: 20 | F87: 20 | G87: =+VLOOKUP(B87,$T$4:$U$104,2,FALSE) -> 168417.57 | I87: =+G87*(1-H87) -> 168417.57 | J87: =+I87/F87 -> 8420.8786 | K87: =+J87*K$85 -> 884.19225 | L87: =+J87+K87 -> 9305.0708 | M87: =+L87*M$85 -> 2791.5213 | N87: =+L87+M87 -> 12096.592 | O87: =+N87*O$85 -> 4838.6368 | P87: =+N87+O87 -> 16935.229 | R87: 158884.5 | S87: =+(I87-R87)/R87 -> 0.06 | T87: 100517914 | U87: 168417.57
G88: =+VLOOKUP(B88,$T$4:$U$104,2,FALSE) -> #N/A | I88: =+G88*(1-H88) -> #N/A | K88: 0.105 | M88: 0.3 | O88: 0.4 | R88: #N/A | S88: =+(I88-R88)/R88 -> #N/A
B89: 100010689 | C89: ENTRAÑA FINA ENF SWIFT | E89: 22 | F89: 1 | G89: =+VLOOKUP(B89,$T$4:$U$104,2,FALSE) -> 16464.643 | I89: =+G89*(1-H89) -> 16464.643 | J89: =+I89/F89 -> 16464.643 | K89: =+J89*K$88 -> 1728.7875 | L89: =+J89+K89 -> 18193.43 | M89: =+L89*M$88 -> 5458.0291 | N89: =+L89+M89 -> 23651.459 | O89: =+N89*O$88 -> 9460.5838 | P89: =+N89+O89 -> 33112.043 | R89: 16464.643 | S89: =+(I89-R89)/R89 -> 0 | T89: 100010689 | U89: 16464.643
B90: 100518335 | C90: ROAST BEEF EN PORCIONES ENF SWIFT (L) | E90: 22.5 | F90: 1 | G90: =+VLOOKUP(B90,$T$4:$U$104,2,FALSE) -> 10429.179 | I90: =+G90*(1-H90) -> 10429.179 | J90: =+I90/F90 -> 10429.179 | K90: =+J90*K$88 -> 1095.0638 | L90: =+J90+K90 -> 11524.242 | M90: =+L90*M$88 -> 3457.2727 | N90: =+L90+M90 -> 14981.515 | O90: =+N90*O$88 -> 5992.606 | P90: =+N90+O90 -> 20974.121 | R90: 10429.179 | S90: =+(I90-R90)/R90 -> 0 | T90: 100518335 | U90: 10429.179
B91: 100518332 | C91: CARNAZA CUADRADA EN PORCIONES ENF SWIFT (L) | E91: 21.5 | F91: 1 | G91: =+VLOOKUP(B91,$T$4:$U$104,2,FALSE) -> 11223.536 | I91: =+G91*(1-H91) -> 11223.536 | J91: =+I91/F91 -> 11223.536 | K91: =+J91*K$88 -> 1178.4713 | L91: =+J91+K91 -> 12402.007 | M91: =+L91*M$88 -> 3720.6021 | N91: =+L91+M91 -> 16122.609 | O91: =+N91*O$88 -> 6449.0436 | P91: =+N91+O91 -> 22571.653 | R91: 11223.536 | S91: =+(I91-R91)/R91 -> 0 | T91: 100518332 | U91: 11223.536
B92: 100518334 | C92: TAPA DE ASADO EN PORCIONES ENF SWIFT (L) | E92: 22.5 | F92: 1 | G92: =+VLOOKUP(B92,$T$4:$U$104,2,FALSE) -> 9237.6429 | I92: =+G92*(1-H92) -> 9237.6429 | J92: =+I92/F92 -> 9237.6429 | K92: =+J92*K$88 -> 969.9525 | L92: =+J92+K92 -> 10207.595 | M92: =+L92*M$88 -> 3062.2786 | N92: =+L92+M92 -> 13269.874 | O92: =+N92*O$88 -> 5307.9496 | P92: =+N92+O92 -> 18577.824 | R92: 9237.6429 | S92: =+(I92-R92)/R92 -> 0 | T92: 100518334 | U92: 9237.6429
B93: 100518227 | C93: VACIO EN PORCIONES NOV ENFRIADO PARA VENTA LOCAL (L) | E93: 22.5 | F93: 1 | G93: =+VLOOKUP(B93,$T$4:$U$104,2,FALSE) -> 9237.6429 | I93: =+G93*(1-H93) -> 9237.6429 | J93: =+I93/F93 -> 9237.6429 | K93: =+J93*K$88 -> 969.9525 | L93: =+J93+K93 -> 10207.595 | M93: =+L93*M$88 -> 3062.2786 | N93: =+L93+M93 -> 13269.874 | O93: =+N93*O$88 -> 5307.9496 | P93: =+N93+O93 -> 18577.824 | R93: 9237.6429 | S93: =+(I93-R93)/R93 -> 0 | T93: 100518227 | U93: 9237.6429
B94: 100027726 | C94: BONDIOLA DE CERDO CONGELADA | D94: 22.5 | E94: 1 | F94: 1 | G94: =+VLOOKUP(B94,$T$4:$U$104,2,FALSE) -> 6814.5 | I94: =+G94*(1-H94) -> 6814.5 | J94: =+I94/F94 -> 6814.5 | K94: =+J94*K$88 -> 715.5225 | L94: =+J94+K94 -> 7530.0225 | M94: =+L94*M$88 -> 2259.0068 | N94: =+L94+M94 -> 9789.0293 | O94: =+N94*O$88 -> 3915.6117 | P94: =+N94+O94 -> 13704.641 | R94: #N/A | T94: 100027726 | U94: 6814.5
G95: =+VLOOKUP(B95,$T$4:$U$104,2,FALSE) -> #N/A | I95: =+G95*(1-H95) -> #N/A | K95: 0.21 | M95: 0.3 | O95: 0.4 | R95: #N/A | S95: =+(I95-R95)/R95 -> #N/A
B96: 100520837 | C96: CHORIZOS FRESCOS DE CERDO LIBRE DE GLUTEN | D96: 7790360980625 | E96: 4.8 | F96: 12 | G96: =+VLOOKUP(B96,$T$4:$U$104,2,FALSE) -> 35756.176 | I96: =+G96*(1-H96) -> 35756.176 | J96: =+I96/F96 -> 2979.6813 | K96: =+J96*K$95 -> 625.73307 | L96: =+J96+K96 -> 3605.4144 | M96: =+L96*M$95 -> 1081.6243 | N96: =+L96+M96 -> 4687.0387 | O96: =+N96*O$95 -> 1874.8155 | P96: =+N96+O96 -> 6561.8541 | R96: 35756.176 | S96: =+(I96-R96)/R96 -> 0 | T96: 100520837 | U96: 35756.176
B97: 100522395 | C97: CHORIZOS FRESCOS DE CERDO CONGELADOS LIBRE DE GLUTEN 12u x 400g | D97: 7790360980625 | E97: 4.8 | F97: 12 | G97: =+VLOOKUP(B97,$T$4:$U$104,2,FALSE) -> 36471.292 | I97: =+G97*(1-H97) -> 36471.292 | J97: =+I97/F97 -> 3039.2743 | K97: =+J97*K$95 -> 638.24761 | L97: =+J97+K97 -> 3677.5219 | M97: =+L97*M$95 -> 1103.2566 | N97: =+L97+M97 -> 4780.7785 | O97: =+N97*O$95 -> 1912.3114 | P97: =+N97+O97 -> 6693.0899 | T97: 100522395 | U97: 36471.292
G98: =+VLOOKUP(B98,$T$4:$U$104,2,FALSE) -> #N/A | I98: =+G98*(1-H98) -> #N/A | K98: 0.21 | M98: 0.3 | O98: 0.4 | R98: #N/A | S98: =+(I98-R98)/R98 -> #N/A
B99: 100520902 | C99: PAPAS PRE COCIDAS SUPERCONGELADAS LIBRES DE GLUTEN 700G | D99: 7790360981042 | E99: 9.8 | F99: 14 | G99: =+VLOOKUP(B99,$T$4:$U$104,2,FALSE) -> 32345.803 | H99: =0.142857142857143*100% -> 0.14285714 | I99: =+G99*(1-H99) -> 27724.974 | J99: =+I99/F99 -> 1980.3553 | K99: =+J99*K$98 -> 415.87461 | L99: =+J99+K99 -> 2396.2299 | M99: =+L99*M$98 -> 718.86897 | N99: =+L99+M99 -> 3115.0989 | O99: =+N99*O$98 -> 1246.0395 | P99: =+N99+O99 -> 4361.1384 | R99: 28302.577 | S99: =+(I99-R99)/R99 -> -0.020408163 | T99: 100520902 | U99: 32345.803
G100: =+VLOOKUP(B100,$T$4:$U$104,2,FALSE) -> #N/A | I100: =+G100*(1-H100) -> #N/A | K100: 0.21 | M100: 0.3 | O100: 0.4 | R100: #N/A
B101: 100521457 | C101: NUGGETS DE ESPINACA 300GR | D101: 7790360982254 | E101: 4.8 | F101: 16 | G101: =+VLOOKUP(B101,$T$4:$U$104,2,FALSE) -> 36127.9 | H101: 0.075 | I101: =+G101*(1-H101) -> 33418.307 | J101: =+I101/F101 -> 2088.6442 | K101: =+J101*K$100 -> 438.61528 | L101: =+J101+K101 -> 2527.2595 | M101: =+L101*M$100 -> 758.17784 | N101: =+L101+M101 -> 3285.4373 | O101: =+N101*O$100 -> 1314.1749 | P101: =+N101+O101 -> 4599.6123 | R101: 31826.959 | S101: =+(I101-R101)/R101 -> 0.05 | T101: 100521457 | U101: 36127.9
...

Sheet Sub NEA
B2: Código | C2: Descripción | D2: EAN | E2: Kg. x Caja | F2: Cant. X Caja | G2: Precio de Lista | H2: dcto | I2: Precio de Factura | J2: Precio Neto estuche en factura | K2: IVA | L2: Px Unitario IVA Inc | M2: M-up Dx | N2: Px Unitario Minorista | O2: M-up Minorista | P2: Px Unitario Público | R2: PX ABRIL
K3: 0.21 | M3: 0.3 | O3: 0.4
B4: 100021632 | C4: HAMBURGUESAS 30x160g CLASICA x2 SWIFT | D4: 7790360026606 | E4: 4.8 | F4: 30 | G4: =+VLOOKUP(B4,$U$4:$V$104,2,FALSE) -> 44187.112 | I4: =+G4*(1-H4) -> 44187.112 | J4: =+I4/F4 -> 1472.9037 | K4: =+J4*K$3 -> 309.30978 | L4: =+J4+K4 -> 1782.2135 | M4: =+L4*M$3 -> 534.66406 | N4: =+L4+M4 -> 2316.8776 | O4: =+N4*O$3 -> 926.75103 | P4: =+N4+O4 -> 3243.6286 | R4: 42082.964 | S4: =+(I4-R4)/R4 -> 0.05 | U4: 100021632 | V4: 44187.112
B5: 100021652 | C5: HAMBURGUESA 18X4X80G CLASICA SWIFT | D5: 7790360026576 | E5: 5.76 | F5: 18 | G5: =+VLOOKUP(B5,$U$4:$V$104,2,FALSE) -> 57541.051 | I5: =+G5*(1-H5) -> 57541.051 | J5: =+I5/F5 -> 3196.7251 | K5: =+J5*K$3 -> 671.31226 | L5: =+J5+K5 -> 3868.0373 | M5: =+L5*M$3 -> 1160.4112 | N5: =+L5+M5 -> 5028.4485 | O5: =+N5*O$3 -> 2011.3794 | P5: =+N5+O5 -> 7039.8279 | R5: 54801.001 | S5: =+(I5-R5)/R5 -> 0.05 | U5: 100021652 | V5: 57541.051
B6: 100021631 | C6: HAMBURGUESA 8X12X80G CLASICA SWIFT | D6: 7790360026590 | E6: 7.68 | F6: 8 | G6: =+VLOOKUP(B6,$U$4:$V$104,2,FALSE) -> 67164.41 | I6: =+G6*(1-H6) -> 67164.41 | J6: =+I6/F6 -> 8395.5513 | K6: =+J6*K$3 -> 1763.0658 | L6: =+J6+K6 -> 10158.617 | M6: =+L6*M$3 -> 3047.5851 | N6: =+L6+M6 -> 13206.202 | O6: =+N6*O$3 -> 5282.4809 | P6: =+N6+O6 -> 18488.683 | R6: 80712.772 | S6: =+(I6-R6)/R6 -> -0.16785896 | U6: 100021631 | V6: 67164.41
B7: 100021630 | C7: HAMBURGUESA 6X20X80G CLASICA SWIFT | D7: 7790360026583 | E7: 9.6 | F7: 6 | G7: =+VLOOKUP(B7,$U$4:$V$104,2,FALSE) -> 82188.028 | I7: =+G7*(1-H7) -> 82188.028 | J7: =+I7/F7 -> 13698.005 | K7: =+J7*K$3 -> 2876.581 | L7: =+J7+K7 -> 16574.586 | M7: =+L7*M$3 -> 4972.3757 | N7: =+L7+M7 -> 21546.961 | O7: =+N7*O$3 -> 8618.7846 | P7: =+N7+O7 -> 30165.746 | R7: 100890.96 | S7: =+(I7-R7)/R7 -> -0.18537772 | U7: 100021630 | V7: 82188.028
B8: 100021653 | C8: MEDALLON 18X4X80G PARRILLERO SWIFT | D8: 7790360026682 | E8: 5.76 | F8: 18 | G8: =+VLOOKUP(B8,$U$4:$V$104,2,FALSE) -> 58326.988 | I8: =+G8*(1-H8) -> 58326.988 | J8: =+I8/F8 -> 3240.3882 | K8: =+J8*K$3 -> 680.48152 | L8: =+J8+K8 -> 3920.8697 | M8: =+L8*M$3 -> 1176.2609 | N8: =+L8+M8 -> 5097.1307 | O8: =+N8*O$3 -> 2038.8523 | P8: =+N8+O8 -> 7135.9829 | R8: 60814.954 | S8: =+(I8-R8)/R8 -> -0.040910438 | U8: 100021653 | V8: 58326.988
B9: 100516169 | C9: MEDALLONES 18X4X80G SWIFT RECETA ESPECIAL | D9: 7790360967961 | E9: 5.76 | F9: 18 | G9: =+VLOOKUP(B9,$U$4:$V$104,2,FALSE) -> 47534.511 | I9: =+G9*(1-H9) -> 47534.511 | J9: =+I9/F9 -> 2640.8062 | K9: =+J9*K$3 -> 554.5693 | L9: =+J9+K9 -> 3195.3755 | M9: =+L9*M$3 -> 958.61264 | N9: =+L9+M9 -> 4153.9881 | O9: =+N9*O$3 -> 1661.5952 | P9: =+N9+O9 -> 5815.5834 | R9: 47534.511 | S9: =+(I9-R9)/R9 -> 0 | U9: 100516169 | V9: 47534.511
B10: 100520337 | C10: MEDALLON BURGER SWIFT MEGA 30 x 160 g | D10: 7790360977960 | E10: 4.8 | F10: 30 | G10: =+VLOOKUP(B10,$U$4:$V$104,2,FALSE) -> 29765.977 | H10: 0.0666 | I10: =+G10*(1-H10) -> 27783.563 | J10: =+I10/F10 -> 926.11878 | K10: =+J10*K$3 -> 194.48494 | L10: =+J10+K10 -> 1120.6037 | M10: =+L10*M$3 -> 336.18112 | N10: =+L10+M10 -> 1456.7848 | O10: =+N10*O$3 -> 582.71394 | P10: =+N10+O10 -> 2039.4988 | R10: 29765.977 | S10: =+(I10-R10)/R10 -> -0.0666 | U10: 100520337 | V10: 29765.977
B11: 100021503 | C11: Medallón CAJITA 12x4 69 grs | D11: 7790360966841 | E11: 3.312 | F11: 12 | G11: =+VLOOKUP(B11,$U$4:$V$104,2,FALSE) -> 25165.542 | H11: 0.167 | I11: =+G11*(1-H11) -> 20962.897 | J11: =+I11/F11 -> 1746.9081 | K11: =+J11*K$3 -> 366.85069 | L11: =+J11+K11 -> 2113.7587 | M11: =+L11*M$3 -> 634.12762 | N11: =+L11+M11 -> 2747.8864 | O11: =+N11*O$3 -> 1099.1545 | P11: =+N11+O11 -> 3847.0409 | R11: 25165.542 | S11: =+(I11-R11)/R11 -> -0.167 | U11: 100021503 | V11: 25165.542
B12: 100516201 | C12: HAMBURGUESA 8X12X69G BURGER SWIFT | D12: 7790360968548 | E12: 6.624 | F12: 8 | G12: =+VLOOKUP(B12,$U$4:$V$104,2,FALSE) -> 49695.701 | I12: =+G12*(1-H12) -> 49695.701 | J12: =+I12/F12 -> 6211.9627 | K12: =+J12*K$3 -> 1304.5122 | L12: =+J12+K12 -> 7516.4748 | M12: =+L12*M$3 -> 2254.9425 | N12: =+L12+M12 -> 9771.4173 | O12: =+N12*O$3 -> 3908.5669 | P12: =+N12+O12 -> 13679.984 | R12: 49695.701 | S12: =+(I12-R12)/R12 -> 0 | U12: 100516201 | V12: 49695.701
B13: 100021643 | C13: MEDALLON 42X112G DOBLE BURGER SWIFT | D13: 7790360966797 | E13: 4.704 | F13: 42 | G13: =+VLOOKUP(B13,$U$4:$V$104,2,FALSE) -> 24868.421 | I13: =+G13*(1-H13) -> 24868.421 | J13: =+I13/F13 -> 592.10526 | K13: =+J13*K$3 -> 124.34211 | L13: =+J13+K13 -> 716.44737 | M13: =+L13*M$3 -> 214.93421 | N13: =+L13+M13 -> 931.38158 | O13: =+N13*O$3 -> 372.55263 | P13: =+N13+O13 -> 1303.9342 | R13: 22607.656 | S13: =+(I13-R13)/R13 -> 0.1 | U13: 100021643 | V13: 24868.421
B14: 100516325 | C14: MEDALLON DOBLE BURGER 2X2 | D14: 7790360967763 | E14: 4.704 | F14: 21 | G14: =+VLOOKUP(B14,$U$4:$V$104,2,FALSE) -> 29947.062 | I14: =+G14*(1-H14) -> 29947.062 | J14: =+I14/F14 -> 1426.0506 | K14: =+J14*K$3 -> 299.47062 | L14: =+J14+K14 -> 1725.5212 | M14: =+L14*M$3 -> 517.65635 | N14: =+L14+M14 -> 2243.1775 | O14: =+N14*O$3 -> 897.27101 | P14: =+N14+O14 -> 3140.4485 | R14: 29947.062 | S14: =+(I14-R14)/R14 -> 0 | U14: 100516325 | V14: 29947.062
B15: 100021676 | C15: HAMBURGUESA 30X250g CLASICA "XL" SWIFT | D15: 7790360967411 | E15: 7.5 | F15: 30 | G15: =+VLOOKUP(B15,$U$4:$V$104,2,FALSE) -> 70541.904 | I15: =+G15*(1-H15) -> 70541.904 | J15: =+I15/F15 -> 2351.3968 | K15: =+J15*K$3 -> 493.79333 | L15: =+J15+K15 -> 2845.1901 | M15: =+L15*M$3 -> 853.55704 | N15: =+L15+M15 -> 3698.7472 | O15: =+N15*O$3 -> 1479.4989 | P15: =+N15+O15 -> 5178.2461 | R15: 70541.904 | S15: =+(I15-R15)/R15 -> 0 | U15: 100021676 | V15: 70541.904
B16: 100516008 | C16: HAMBURGUESA 24X2X120g CASERA SWIFT | D16: 7790360967701 | E16: 5.76 | F16: 24 | G16: =+VLOOKUP(B16,$U$4:$V$104,2,FALSE) -> 68994.307 | H16: 0.0909 | I16: =+G16*(1-H16) -> 62722.725 | J16: =+I16/F16 -> 2613.4469 | K16: =+J16*K$3 -> 548.82384 | L16: =+J16+K16 -> 3162.2707 | M16: =+L16*M$3 -> 948.68121 | N16: =+L16+M16 -> 4110.9519 | O16: =+N16*O$3 -> 1644.3808 | P16: =+N16+O16 -> 5755.3327 | R16: 68994.307 | S16: =+(I16-R16)/R16 -> -0.0909 | U16: 100516008 | V16: 68994.307
B17: 100520834 | C17: HAMBURGUESA X-TREMA 36 x 185 grs | D17: 7790360980618 | E17: 6.66 | F17: 36 | G17: =+VLOOKUP(B17,$U$4:$V$104,2,FALSE) -> 67560.059 | I17: =+G17*(1-H17) -> 67560.059 | J17: =+I17/F17 -> 1876.6683 | K17: =+J17*K$3 -> 394.10034 | L17: =+J17+K17 -> 2270.7686 | M17: =+L17*M$3 -> 681.23059 | N17: =+L17+M17 -> 2951.9992 | O17: =+N17*O$3 -> 1180.7997 | P17: =+N17+O17 -> 4132.7989 | R17: 67560.059 | S17: =+(I17-R17)/R17 -> 0 | U17: 100520834 | V17: 67560.059
B18: 100021680 | C18: HAMBURGUESAS 18X2X120g CLL BRA/ARG | D18: 7790360967688 | E18: 4.32 | F18: 18 | G18: =+VLOOKUP(B18,$U$4:$V$104,2,FALSE) -> 52915.791 | I18: =+G18*(1-H18) -> 52915.791 | J18: =+I18/F18 -> 2939.7661 | K18: =+J18*K$3 -> 617.35089 | L18: =+J18+K18 -> 3557.117 | M18: =+L18*M$3 -> 1067.1351 | N18: =+L18+M18 -> 4624.2522 | O18: =+N18*O$3 -> 1849.7009 | P18: =+N18+O18 -> 6473.953 | R18: 52915.791 | S18: =+(I18-R18)/R18 -> 0 | U18: 100021680 | V18: 52915.791
B19: 100021644 | C19: MEDALLON 42X112G LA BLANCA | D19: 7790360008541 | E19: 4.704 | F19: 42 | G19: =+VLOOKUP(B19,$U$4:$V$104,2,FALSE) -> 21066.231 | H19: 0.054 | I19: =+G19*(1-H19) -> 19928.654 | J19: =+I19/F19 -> 474.49177 | K19: =+J19*K$3 -> 99.643272 | L19: =+J19+K19 -> 574.13504 | M19: =+L19*0.33 -> 189.46456 | N19: =+L19+M19 -> 763.5996 | O19: =+N19*O$3 -> 305.43984 | P19: =+N19+O19 -> 1069.0394 | R19: 19151.119 | S19: =+(I19-R19)/R19 -> 0.0406 | U19: 100021644 | V19: 21066.231
B20: 100021677 | C20: MEDALLON 12x4X69G LA BLANCA | D20: 7790360967404 | E20: 3.312 | F20: 12 | G20: =+VLOOKUP(B20,$U$4:$V$104,2,FALSE) -> 15913.331 | I20: =+G20*(1-H20) -> 15913.331 | J20: =+I20/F20 -> 1326.1109 | K20: =+J20*K$3 -> 278.48329 | L20: =+J20+K20 -> 1604.5942 | M20: =+L20*0.33 -> 529.51608 | N20: =+L20+M20 -> 2134.1103 | O20: =+N20*O$3 -> 853.64411 | P20: =+N20+O20 -> 2987.7544 | R20: 15913.331 | S20: =+(I20-R20)/R20 -> 0 | U20: 100021677 | V20: 15913.331
B21: 100021638 | C21: MEDALLONES 60X80g "SWIFT BURGER" PARRILLERAS FAMILY | D21: 7790360026699 | E21: 4.8 | F21: 60 | G21: =+VLOOKUP(B21,$U$4:$V$104,2,FALSE) -> 53909.27 | I21: =+G21*(1-H21) -> 53909.27 | J21: =+I21/F21 -> 898.48783 | K21: =+J21*K$3 -> 188.68244 | L21: =+J21+K21 -> 1087.1703 | M21: =+L21*M$3 -> 326.15108 | N21: =+L21+M21 -> 1413.3214 | O21: =+N21*O$3 -> 565.32854 | P21: =+N21+O21 -> 1978.6499 | R21: 53909.27 | S21: =+(I21-R21)/R21 -> 0 | U21: 100021638 | V21: 53909.27
B22: 100021575 | C22: MEDALLONES 60X69g "SWIFT BURGER"PARRILLERAS FAMILY | D22: 7790360007032 | E22: 4.14 | F22: 60 | G22: =+VLOOKUP(B22,$U$4:$V$104,2,FALSE) -> 43782.411 | I22: =+G22*(1-H22) -> 43782.411 | J22: =+I22/F22 -> 729.70684 | K22: =+J22*K$3 -> 153.23844 | L22: =+J22+K22 -> 882.94528 | M22: =+L22*M$3 -> 264.88358 | N22: =+L22+M22 -> 1147.8289 | O22: =+N22*O$3 -> 459.13155 | P22: =+N22+O22 -> 1606.9604 | R22: 43782.411 | S22: =+(I22-R22)/R22 -> 0 | U22: 100021575 | V22: 43782.411
B23: 100021514 | C23: MEDALLON 60X69G CARNE VACUNA | D23: 7790360006943 | E23: 4.14 | F23: 60 | G23: =+VLOOKUP(B23,$U$4:$V$104,2,FALSE) -> 40234.645 | I23: =+G23*(1-H23) -> 40234.645 | J23: =+I23/F23 -> 670.57741 | K23: =+J23*K$3 -> 140.82126 | L23: =+J23+K23 -> 811.39867 | M23: =+L23*M$3 -> 243.4196 | N23: =+L23+M23 -> 1054.8183 | O23: =+N23*O$3 -> 421.92731 | P23: =+N23+O23 -> 1476.7456 | R23: 40234.645 | S23: =+(I23-R23)/R23 -> 0 | U23: 100021514 | V23: 40234.645
B24: 100516208 | C24: MEDALLON 60x80g PARRILLERO MC SWIFT | D24: 7790360968203 | E24: =60*0.08 -> 4.8 | F24: 60 | G24: =+VLOOKUP(B24,$U$4:$V$104,2,FALSE) -> 46172.879 | I24: =+G24*(1-H24) -> 46172.879 | J24: =+I24/F24 -> 769.54798 | K24: =+J24*K$3 -> 161.60508 | L24: =+J24+K24 -> 931.15306 | M24: =+L24*M$3 -> 279.34592 | N24: =+L24+M24 -> 1210.499 | O24: =+N24*O$3 -> 484.19959 | P24: =+N24+O24 -> 1694.6986 | R24: 46172.879 | S24: =+(I24-R24)/R24 -> 0 | U24: 100516208 | V24: 46172.879
B25: 100518346 | C25: MEDALLON 60X109G CARNE VACUNA PARRILLERO SWIFT | E25: 6.54 | F25: 60 | G25: =+VLOOKUP(B25,$U$4:$V$104,2,FALSE) -> 63499.785 | I25: =+G25*(1-H25) -> 63499.785 | J25: =+I25/F25 -> 1058.3298 | K25: =+J25*K$3 -> 222.24925 | L25: =+J25+K25 -> 1280.579 | M25: =+L25*M$3 -> 384.1737 | N25: =+L25+M25 -> 1664.7527 | O25: =+N25*O$3 -> 665.90108 | P25: =+N25+O25 -> 2330.6538 | R25: 63499.785 | S25: =+(I25-R25)/R25 -> 0 | U25: 100518346 | V25: 63499.785
B26: 100516259 | C26: MEDALLON GIGANTE 48x113.5g | D26: 7790360968340 | E26: 18.16 | F26: 48 | G26: =+VLOOKUP(B26,$U$4:$V$104,2,FALSE) -> 149542.39 | I26: =+G26*(1-H26) -> 149542.39 | J26: =+I26/F26 -> 3115.4665 | K26: =+J26*K$3 -> 654.24798 | L26: =+J26+K26 -> 3769.7145 | M26: =+L26*M$3 -> 1130.9144 | N26: =+L26+M26 -> 4900.6289 | O26: =+N26*O$3 -> 1960.2516 | P26: =+N26+O26 -> 6860.8804 | R26: 149542.39 | S26: =+(I26-R26)/R26 -> 0 | U26: 100516259 | V26: 149542.39
B27: 100518095 | C27: HAMBURGUESA 36 X 185 GRS | D27: 7790360974785 | E27: 6.66 | F27: 36 | G27: =+VLOOKUP(B27,$U$4:$V$104,2,FALSE) -> 70960.925 | I27: =+G27*(1-H27) -> 70960.925 | J27: =+I27/F27 -> 1971.1368 | K27: =+J27*K$3 -> 413.93873 | L27: =+J27+K27 -> 2385.0755 | M27: =+L27*M$3 -> 715.52266 | N27: =+L27+M27 -> 3100.5982 | O27: =+N27*O$3 -> 1240.2393 | P27: =+N27+O27 -> 4340.8375 | R27: 70960.925 | S27: =+(I27-R27)/R27 -> 0 | U27: 100518095 | V27: 70960.925
B28: 100518223 | C28: HAMBURGUESA 30x2x106 GRS | D28: 7790360975065 | E28: =60*0.106 -> 6.36 | F28: 30 | G28: =+VLOOKUP(B28,$U$4:$V$104,2,FALSE) -> 55247.024 | I28: =+G28*(1-H28) -> 55247.024 | J28: =+I28/F28 -> 1841.5675 | K28: =+J28*K$3 -> 386.72917 | L28: =+J28+K28 -> 2228.2966 | M28: =+L28*M$3 -> 668.48899 | N28: =+L28+M28 -> 2896.7856 | O28: =+N28*O$3 -> 1158.7142 | P28: =+N28+O28 -> 4055.4999 | R28: 55247.024 | S28: =+(I28-R28)/R28 -> 0 | U28: 100518223 | V28: 55247.024
G29: =+VLOOKUP(B29,$U$4:$V$104,2,FALSE) -> #N/A | I29: =+G29*(1-H29) -> #N/A | J29: =+I29/F29 -> #N/A | K29: 0.21 | M29: 0.3 | O29: 0.4 | R29: #N/A | S29: =+(I29-R29)/R29 -> #N/A | V29: #VALUE!
B30: 100022085 | C30: SALCHICHAS 24X6 SWIFT | D30: 7790360000132 | E30: 5.4 | F30: 24 | G30: =+VLOOKUP(B30,$U$4:$V$104,2,FALSE) -> 26853.823 | I30: =+G30*(1-H30) -> 26853.823 | J30: =+I30/F30 -> 1118.9093 | K30: =+J30*K$3 -> 234.97095 | L30: =+J30+K30 -> 1353.8802 | M30: =+L30*M$3 -> 406.16407 | N30: =+L30+M30 -> 1760.0443 | O30: =+N30*O$3 -> 704.01772 | P30: =+N30+O30 -> 2464.062 | R30: 23435.086 | S30: =+(I30-R30)/R30 -> 0.14588115 | U30: 100022085 | V30: 26853.823
B31: 100522204 | C31: SALCHICHAS 24X6 SWIFT | D31: 7790360983947 | E31: 5.4 | F31: 24 | G31: =+VLOOKUP(B31,$U$4:$V$104,2,FALSE) -> 26853.823 | I31: =+G31*(1-H31) -> 26853.823 | J31: =+I31/F31 -> 1118.9093 | K31: =+J31*K$3 -> 234.97095 | L31: =+J31+K31 -> 1353.8802 | M31: =+L31*M$3 -> 406.16407 | N31: =+L31+M31 -> 1760.0443 | O31: =+N31*O$3 -> 704.01772 | P31: =+N31+O31 -> 2464.062 | R31: 0 | U31: 100522204 | V31: 26853.823
B32: 100022072 | C32: SALCHICHAS 12X12 SWIFT | D32: 7790360024541 | E32: 5.4 | F32: 12 | G32: =+VLOOKUP(B32,$U$4:$V$104,2,FALSE) -> 25511.132 | I32: =+G32*(1-H32) -> 25511.132 | J32: =+I32/F32 -> 2125.9276 | K32: =+J32*K$3 -> 446.44481 | L32: =+J32+K32 -> 2572.3724 | M32: =+L32*M$3 -> 771.71173 | N32: =+L32+M32 -> 3344.0842 | O32: =+N32*O$3 -> 1337.6337 | P32: =+N32+O32 -> 4681.7179 | R32: 21677.574 | S32: =+(I32-R32)/R32 -> 0.1768444 | U32: 100022072 | V32: 25511.132
B33: 100522205 | C33: SALCHICHAS 12X12 SWIFT | D33: 7790360983954 | E33: 5.4 | F33: 12 | G33: =+VLOOKUP(B33,$U$4:$V$104,2,FALSE) -> 25511.132 | I33: =+G33*(1-H33) -> 25511.132 | J33: =+I33/F33 -> 2125.9276 | K33: =+J33*K$3 -> 446.44481 | L33: =+J33+K33 -> 2572.3724 | M33: =+L33*M$3 -> 771.71173 | N33: =+L33+M33 -> 3344.0842 | O33: =+N33*O$3 -> 1337.6337 | P33: =+N33+O33 -> 4681.7179 | R33: 0 | U33: 100522205 | V33: 25511.132
B34: 100516849 | C34: SALCHICHAS SIN PIEL 24X6 "SWIFT KIDS" X 190 g | D34: 7790360970053 | E34: 4.56 | F34: 24 | G34: =+VLOOKUP(B34,$U$4:$V$104,2,FALSE) -> 21483.058 | I34: =+G34*(1-H34) -> 21483.058 | J34: =+I34/F34 -> 895.12743 | K34: =+J34*K$3 -> 187.97676 | L34: =+J34+K34 -> 1083.1042 | M34: =+L34*M$3 -> 324.93126 | N34: =+L34+M34 -> 1408.0354 | O34: =+N34*O$3 -> 563.21418 | P34: =+N34+O34 -> 1971.2496 | R34: 19919.988 | S34: =+(I34-R34)/R34 -> 0.078467421 | U34: 100516849 | V34: 21483.058
B35: 100022039 | C35: SALCHICHAS LARGAS 10 x 12 SWIFT INSTITUCIONAL | D35: 7790360007063 | E35: 8.7 | F35: 10 | G35: =+VLOOKUP(B35,$U$4:$V$104,2,FALSE) -> 66403.468 | I35: =+G35*(1-H35) -> 66403.468 | J35: =+I35/F35 -> 6640.3468 | K35: =+J35*K$3 -> 1394.4728 | L35: =+J35+K35 -> 8034.8197 | M35: =+L35*M$3 -> 2410.4459 | N35: =+L35+M35 -> 10445.266 | O35: =+N35*O$3 -> 4178.1062 | P35: =+N35+O35 -> 14623.372 | R35: 60366.789 | S35: =+(I35-R35)/R35 -> 0.1 | U35: 100022039 | V35: 66403.468
B36: 100522206 | C36: SALCHICHAS LARGAS 10 x 12 SWIFT INSTITUCIONAL | D36: 7790360983961 | E36: 8.7 | F36: 10 | G36: =+VLOOKUP(B36,$U$4:$V$104,2,FALSE) -> 66403.468 | I36: =+G36*(1-H36) -> 66403.468 | J36: =+I36/F36 -> 6640.3468 | K36: =+J36*K$3 -> 1394.4728 | L36: =+J36+K36 -> 8034.8197 | M36: =+L36*M$3 -> 2410.4459 | N36: =+L36+M36 -> 10445.266 | O36: =+N36*O$3 -> 4178.1062 | P36: =+N36+O36 -> 14623.372 | R36: 0 | U36: 100522206 | V36: 66403.468
B37: 100022058 | C37: SALCHICHAS SIN PIEL "LA BLANCA" 24X6X190 Grs; | D37: 7790360026002 | E37: 4.56 | F37: 24 | G37: =+VLOOKUP(B37,$U$4:$V$104,2,FALSE) -> 18273.698 | I37: =+G37*(1-H37) -> 18273.698 | J37: =+I37/F37 -> 761.40408 | K37: =+J37*K$3 -> 159.89486 | L37: =+J37+K37 -> 921.29893 | M37: =+L37*0.33 -> 304.02865 | N37: =+L37+M37 -> 1225.3276 | O37: =+N37*O$3 -> 490.13103 | P37: =+N37+O37 -> 1715.4586 | R37: 12772.19 | S37: =+(I37-R37)/R37 -> 0.43074113 | U37: 100022058 | V37: 18273.698 | X37: Ver posicionamiento por verba según necesidad de la zona
B38: 100518151 | C38: SALCHICHAS LARGAS 10 x 12 x 870g | D38: 7790360974990 | E38: 8.7 | F38: 10 | G38: =+VLOOKUP(B38,$U$4:$V$104,2,FALSE) -> 76363.989 | I38: =+G38*(1-H38) -> 76363.989 | J38: =+I38/F38 -> 7636.3989 | K38: =+J38*K$3 -> 1603.6438 | L38: =+J38+K38 -> 9240.0426 | M38: =+L38*0.33 -> 3049.2141 | N38: =+L38+M38 -> 12289.257 | O38: =+N38*O$3 -> 4915.7027 | P38: =+N38+O38 -> 17204.959 | R38: 69421.808 | S38: =+(I38-R38)/R38 -> 0.1 | U38: 100518151 | V38: 76363.989
G39: =+VLOOKUP(B39,$U$4:$V$104,2,FALSE) -> #N/A | I39: =+G39*(1-H39) -> #N/A | J39: =+I39/F39 -> #N/A | K39: 0.21 | M39: 0.2 | O39: 0.35 | R39: #N/A | S39: =+(I39-R39)/R39 -> #N/A | V39: #VALUE!
B40: 100021000 | C40: PATE DE FOIE 24X90G SWIFT | D40: 7790360720382 | E40: 2.16 | F40: 24 | G40: =+VLOOKUP(B40,$U$4:$V$104,2,FALSE) -> 13579.525 | I40: =+G40*(1-H40) -> 13579.525 | J40: =+I40/F40 -> 565.81353 | K40: =+J40*K$3 -> 118.82084 | L40: =+J40+K40 -> 684.63438 | M40: =+L40*M$39 -> 136.92688 | N40: =+L40+M40 -> 821.56125 | O40: =+N40*O$39 -> 287.54644 | P40: =+N40+O40 -> 1109.1077 | Q40: DCTO VIA NC - SUJETO A LA COMPRA DE 5 CAJAS DE C/U GOURMET | R40: 13579.525 | S40: =+(I40-R40)/R40 -> 0 | U40: 100021000 | V40: 13579.525
B41: 100021001 | C41: PICADILLO DE CARNE 24X90G SWIFT | D41: 7790360720115 | E41: 2.16 | F41: 24 | G41: =+VLOOKUP(B41,$U$4:$V$104,2,FALSE) -> 13579.525 | I41: =+G41*(1-H41) -> 13579.525 | J41: =+I41/F41 -> 565.81353 | K41: =+J41*K$3 -> 118.82084 | L41: =+J41+K41 -> 684.63438 | M41: =+L41*M$39 -> 136.92688 | N41: =+L41+M41 -> 821.56125 | O41: =+N41*O$39 -> 287.54644 | P41: =+N41+O41 -> 1109.1077 | Q41: DCTO VIA NC - SUJETO A LA COMPRA DE 5 CAJAS DE C/U GOURMET | R41: 13579.525 | S41: =+(I41-R41)/R41 -> 0 | U41: 100021001 | V41: 13579.525
B42: 100522277 | C42: Picadillo de Carne Picante Chile Chipotle 24x90 g | E42: 2.16 | F42: 24 | G42: =+VLOOKUP(B42,$U$4:$V$104,2,FALSE) -> 13579.525 | I42: =+G42*(1-H42) -> 13579.525 | J42: =+I42/F42 -> 565.81353 | K42: =+J42*K$3 -> 118.82084 | L42: =+J42+K42 -> 684.63438 | M42: =+L42*M$39 -> 136.92688 | N42: =+L42+M42 -> 821.56125 | O42: =+N42*O$39 -> 287.54644 | P42: =+N42+O42 -> 1109.1077 | R42: 13579.525 | U42: 100522277 | V42: 13579.525
B43: 100522333 | C43: Pate de Foie Jalapeño 24x90 Swift | E43: 2.16 | F43: 24 | G43: =+VLOOKUP(B43,$U$4:$V$104,2,FALSE) -> 13579.525 | I43: =+G43*(1-H43) -> 13579.525 | J43: =+I43/F43 -> 565.81353 | K43: =+J43*K$3 -> 118.82084 | L43: =+J43+K43 -> 684.63438 | M43: =+L43*M$39 -> 136.92688 | N43: =+L43+M43 -> 821.56125 | O43: =+N43*O$39 -> 287.54644 | P43: =+N43+O43 -> 1109.1077 | R43: 13579.525 | U43: 100522333 | V43: 13579.525
B44: 100021045 | C44: PICADILLO DE CARNE PICANTE 24X90G SWIFT | D44: 7790360966582 | E44: 2.16 | F44: 24 | G44: =+G45 -> 13579.525 | I44: =+G44*(1-H44) -> 13579.525 | J44: =+I44/F44 -> 565.81353 | K44: =+J44*K$3 -> 118.82084 | L44: =+J44+K44 -> 684.63438 | M44: =+L44*M$39 -> 136.92688 | N44: =+L44+M44 -> 821.56125 | O44: =+N44*O$39 -> 287.54644 | P44: =+N44+O44 -> 1109.1077 | R44: 13579.525 | S44: =+(I44-R44)/R44 -> 0 | U44: 100021045 | V44: 13579.525
B45: 100021004 | C45: PATE DE FOIE A LA CREMA 24X88G SWIFT | D45: 7790360964526 | E45: 2.112 | F45: 24 | G45: =+G46 -> 13579.525 | I45: =+G45*(1-H45) -> 13579.525 | J45: =+I45/F45 -> 565.81353 | K45: =+J45*K$3 -> 118.82084 | L45: =+J45+K45 -> 684.63438 | M45: =+L45*M$39 -> 136.92688 | N45: =+L45+M45 -> 821.56125 | O45: =+N45*O$39 -> 287.54644 | P45: =+N45+O45 -> 1109.1077 | R45: 13579.525 | S45: =+(I45-R45)/R45 -> 0 | U45: 100021006 | V45: 13579.525
B46: 100021006 | C46: JAMON DEL DIABLO 24X88G SWIFT | D46: 7790360964557 | E46: 2.112 | F46: 24 | G46: =+VLOOKUP(B46,$U$4:$V$104,2,FALSE) -> 13579.525 | I46: =+G46*(1-H46) -> 13579.525 | J46: =+I46/F46 -> 565.81353 | K46: =+J46*K$3 -> 118.82084 | L46: =+J46+K46 -> 684.63438 | M46: =+L46*M$39 -> 136.92688 | N46: =+L46+M46 -> 821.56125 | O46: =+N46*O$39 -> 287.54644 | P46: =+N46+O46 -> 1109.1077 | R46: 13579.525 | S46: =+(I46-R46)/R46 -> 0 | U46: 100021007 | V46: 15501.688
B47: 100021007 | C47: PATE DE FOIE DE POLLO 24X85G SWIFT | D47: 7790360964540 | E47: 2.04 | F47: 24 | G47: =+VLOOKUP(B47,$U$4:$V$104,2,FALSE) -> 15501.688 | I47: =+G47*(1-H47) -> 15501.688 | J47: =+I47/F47 -> 645.90367 | K47: =+J47*K$3 -> 135.63977 | L47: =+J47+K47 -> 781.54344 | M47: =+L47*M$39 -> 156.30869 | N47: =+L47+M47 -> 937.85213 | O47: =+N47*O$39 -> 328.24825 | P47: =+N47+O47 -> 1266.1004 | R47: 15501.688 | S47: =+(I47-R47)/R47 -> 0 | U47: 100021013 | V47: 15501.688
B48: 100021013 | C48: PATE DE FOIE TIPO PROVENZAL 24X85G SWIFT GOURMET | D48: 7790360965714 | E48: 2.04 | F48: 24 | G48: =+VLOOKUP(B48,$U$4:$V$104,2,FALSE) -> 15501.688 | I48: =+G48*(1-H48) -> 15501.688 | J48: =+I48/F48 -> 645.90367 | K48: =+J48*K$3 -> 135.63977 | L48: =+J48+K48 -> 781.54344 | M48: =+L48*M$39 -> 156.30869 | N48: =+L48+M48 -> 937.85213 | O48: =+N48*O$39 -> 328.24825 | P48: =+N48+O48 -> 1266.1004 | R48: 15501.688 | S48: =+(I48-R48)/R48 -> 0 | U48: 100021014 | V48: 15501.688
B49: 100021014 | C49: PATE DE FOIE C/PIMIENTA VERDE 24X85G SWIFT GOURMET | D49: 7790360965721 | E49: 2.04 | F49: 24 | G49: =+VLOOKUP(B49,$U$4:$V$104,2,FALSE) -> 15501.688 | I49: =+G49*(1-H49) -> 15501.688 | J49: =+I49/F49 -> 645.90367 | K49: =+J49*K$3 -> 135.63977 | L49: =+J49+K49 -> 781.54344 | M49: =+L49*M$39 -> 156.30869 | N49: =+L49+M49 -> 937.85213 | O49: =+N49*O$39 -> 328.24825 | P49: =+N49+O49 -> 1266.1004 | R49: 15501.688 | S49: =+(I49-R49)/R49 -> 0 | U49: 100021054 | V49: 15501.688
B50: 100021054 | C50: PATE JAMON AHUMADO 24X85G | D50: 7790360965707 | E50: 2.04 | F50: 24 | G50: =+VLOOKUP(B50,$U$4:$V$104,2,FALSE) -> 15501.688 | I50: =+G50*(1-H50) -> 15501.688 | J50: =+I50/F50 -> 645.90367 | K50: =+J50*K$3 -> 135.63977 | L50: =+J50+K50 -> 781.54344 | M50: =+L50*M$39 -> 156.30869 | N50: =+L50+M50 -> 937.85213 | O50: =+N50*O$39 -> 328.24825 | P50: =+N50+O50 -> 1266.1004 | R50: 15501.688 | S50: =+(I50-R50)/R50 -> 0 | U50: 100021055 | V50: 15501.688
B51: 100021055 | C51: PATE HONGOS 24X85G | D51: 7790360965189 | E51: 2.04 | F51: 24 | G51: =+VLOOKUP(B51,$U$4:$V$104,2,FALSE) -> 15501.688 | I51: =+G51*(1-H51) -> 15501.688 | J51: =+I51/F51 -> 645.90367 | K51: =+J51*K$3 -> 135.63977 | L51: =+J51+K51 -> 781.54344 | M51: =+L51*M$39 -> 156.30869 | N51: =+L51+M51 -> 937.85213 | O51: =+N51*O$39 -> 328.24825 | P51: =+N51+O51 -> 1266.1004 | R51: 15501.688 | S51: =+(I51-R51)/R51 -> 0 | U51: 100021015 | V51: 15501.688
B52: 100021015 | C52: PATE DE SALMON 24X85G SWIFT GOURMET | D52: 7790360965202 | E52: 2.04 | F52: 24 | G52: =+VLOOKUP(B52,$U$4:$V$104,2,FALSE) -> 15501.688 | I52: =+G52*(1-H52) -> 15501.688 | J52: =+I52/F52 -> 645.90367 | K52: =+J52*K$3 -> 135.63977 | L52: =+J52+K52 -> 781.54344 | M52: =+L52*M$39 -> 156.30869 | N52: =+L52+M52 -> 937.85213 | O52: =+N52*O$39 -> 328.24825 | P52: =+N52+O52 -> 1266.1004 | R52: 15501.688 | S52: =+(I52-R52)/R52 -> 0 | U52: 100021008 | V52: 11493.436
B53: 100021008 | C53: PICADILLO DE CARNE 24X90G LA BLANCA | D53: 7790360720122 | E53: 2.16 | F53: 24 | G53: =+VLOOKUP(B53,$U$4:$V$104,2,FALSE) -> 11493.436 | I53: =+G53*(1-H53) -> 11493.436 | J53: =+I53/F53 -> 478.89316 | K53: =+J53*K$3 -> 100.56756 | L53: =+J53+K53 -> 579.46072 | M53: =+L53*M$39 -> 115.89214 | N53: =+L53+M53 -> 695.35287 | O53: =+N53*O$39 -> 243.3735 | P53: =+N53+O53 -> 938.72637 | R53: 11493.436 | S53: =+(I53-R53)/R53 -> 0 | U53: 100021009 | V53: 11493.436
B54: 100021009 | C54: PATE DE FOIE 24X90G LA BLANCA | D54: 7790360965127 | E54: 2.16 | F54: 24 | G54: =+VLOOKUP(B54,$U$4:$V$104,2,FALSE) -> 11493.436 | I54: =+G54*(1-H54) -> 11493.436 | J54: =+I54/F54 -> 478.89316 | K54: =+J54*K$3 -> 100.56756 | L54: =+J54+K54 -> 579.46072 | M54: =+L54*M$39 -> 115.89214 | N54: =+L54+M54 -> 695.35287 | O54: =+N54*O$39 -> 243.3735 | P54: =+N54+O54 -> 938.72637 | R54: 11493.436 | S54: =+(I54-R54)/R54 -> 0 | U54: 100021010 | V54: 11493.436
B55: 100021010 | C55: PICADILLO DE CARNE 24X90G SAFRA | D55: 7790920008707 | E55: 2.16 | F55: 24 | G55: =+VLOOKUP(B55,$U$4:$V$104,2,FALSE) -> 11493.436 | I55: =+G55*(1-H55) -> 11493.436 | J55: =+I55/F55 -> 478.89316 | K55: =+J55*K$3 -> 100.56756 | L55: =+J55+K55 -> 579.46072 | M55: =+L55*M$39 -> 115.89214 | N55: =+L55+M55 -> 695.35287 | O55: =+N55*O$39 -> 243.3735 | P55: =+N55+O55 -> 938.72637 | R55: 11493.436 | S55: =+(I55-R55)/R55 -> 0 | U55: 100021011 | V55: 11493.436
B56: 100021011 | C56: PATE DE FOIE 24X90G SAFRA | D56: 7790920008714 | E56: 2.16 | F56: 24 | G56: =+VLOOKUP(B56,$U$4:$V$104,2,FALSE) -> 11493.436 | I56: =+G56*(1-H56) -> 11493.436 | J56: =+I56/F56 -> 478.89316 | K56: =+J56*K$3 -> 100.56756 | L56: =+J56+K56 -> 579.46072 | M56: =+L56*M$39 -> 115.89214 | N56: =+L56+M56 -> 695.35287 | O56: =+N56*O$39 -> 243.3735 | P56: =+N56+O56 -> 938.72637 | R56: 11493.436 | S56: =+(I56-R56)/R56 -> 0 | V56: #VALUE!
G57: =+VLOOKUP(B57,$U$4:$V$104,2,FALSE) -> #N/A | I57: =+G57*(1-H57) -> #N/A | J57: =+I57/F57 -> #N/A | K57: 0.21 | M57: 0.3 | O57: 0.4 | R57: #N/A | S57: =+(I57-R57)/R57 -> #N/A | U57: 100516217 | V57: 26798.761
B58: 100516217 | C58: MILANESAS DE SOJA CLASICAS PREFRITA | D58: 7790360967824 | E58: 5.8 | F58: 20 | G58: =+VLOOKUP(B58,$U$4:$V$104,2,FALSE) -> 26798.761 | I58: =+G58*(1-H58) -> 26798.761 | J58: =+I58/F58 -> 1339.9381 | K58: =+J58*K$3 -> 281.38699 | L58: =+J58+K58 -> 1621.3251 | M58: =+L58*M$3 -> 486.39752 | N58: =+L58+M58 -> 2107.7226 | O58: =+N58*O$3 -> 843.08903 | P58: =+N58+O58 -> 2950.8116 | R58: 26018.215 | S58: =+(I58-R58)/R58 -> 0.03 | U58: 100516214 | V58: 38777.328
B59: 100516214 | C59: MILANESAS DE SOJA RELLENAS CON JAMON Y QUESO | D59: 7790360967794 | E59: 7 | F59: 20 | G59: =+VLOOKUP(B59,$U$4:$V$104,2,FALSE) -> 38777.328 | H59: 0.05 | I59: =+G59*(1-H59) -> 36838.462 | J59: =+I59/F59 -> 1841.9231 | K59: =+J59*K$3 -> 386.80385 | L59: =+J59+K59 -> 2228.7269 | M59: =+L59*M$3 -> 668.61808 | N59: =+L59+M59 -> 2897.345 | O59: =+N59*O$3 -> 1158.938 | P59: =+N59+O59 -> 4056.283 | R59: 35765.497 | S59: =+(I59-R59)/R59 -> 0.03 | U59: 100516215 | V59: 38777.328
B60: 100516215 | C60: MILANESAS DE SOJA RELLENAS CON ESPINACA Y QUESO | D60: 7790360967800 | E60: 7 | F60: 20 | G60: =+VLOOKUP(B60,$U$4:$V$104,2,FALSE) -> 38777.328 | H60: 0.05 | I60: =+G60*(1-H60) -> 36838.462 | J60: =+I60/F60 -> 1841.9231 | K60: =+J60*K$3 -> 386.80385 | L60: =+J60+K60 -> 2228.7269 | M60: =+L60*M$3 -> 668.61808 | N60: =+L60+M60 -> 2897.345 | O60: =+N60*O$3 -> 1158.938 | P60: =+N60+O60 -> 4056.283 | R60: 35765.497 | S60: =+(I60-R60)/R60 -> 0.03 | U60: 100516216 | V60: 38777.328
B61: 100516216 | C61: MILANESAS DE SOJA RELLENAS CON TOMATE Y QUESO | D61: 7790360967817 | E61: 7 | F61: 20 | G61: =+VLOOKUP(B61,$U$4:$V$104,2,FALSE) -> 38777.328 | H61: 0.05 | I61: =+G61*(1-H61) -> 36838.462 | J61: =+I61/F61 -> 1841.9231 | K61: =+J61*K$3 -> 386.80385 | L61: =+J61+K61 -> 2228.7269 | M61: =+L61*M$3 -> 668.61808 | N61: =+L61+M61 -> 2897.345 | O61: =+N61*O$3 -> 1158.938 | P61: =+N61+O61 -> 4056.283 | R61: 35765.497 | S61: =+(I61-R61)/R61 -> 0.03 | V61: #VALUE!
G62: =+VLOOKUP(B62,$U$4:$V$104,2,FALSE) -> #N/A | I62: =+G62*(1-H62) -> #N/A | J62: =+I62/F62 -> #N/A | K62: 0.21 | M62: 0.3 | O62: 0.4 | R62: #N/A | S62: =+(I62-R62)/R62 -> #N/A | U62: 100021704 | V62: 36137.296
B63: 100021704 | C63: BOCADITOS DE CARNE "SWIFT" - 12x380g | D63: 7790360023902 | E63: =12*0.38 -> 4.56 | F63: 12 | G63: =+VLOOKUP(B63,$U$4:$V$104,2,FALSE) -> 36137.296 | I63: =+G63*(1-H63) -> 36137.296 | J63: =+I63/F63 -> 3011.4414 | K63: =+J63*K$3 -> 632.40269 | L63: =+J63+K63 -> 3643.844 | M63: =+L63*M$3 -> 1093.1532 | N63: =+L63+M63 -> 4736.9973 | O63: =+N63*O$3 -> 1894.7989 | P63: =+N63+O63 -> 6631.7962 | R63: 36137.296 | S63: =+(I63-R63)/R63 -> 0 | U63: 100021705 | V63: 32860.301
B64: 100021705 | C64: BOCADITOS DE POLLO "SWIFT" - 12x380g | D64: 7790360024336 | E64: =12*0.38 -> 4.56 | F64: 12 | G64: =+VLOOKUP(B64,$U$4:$V$104,2,FALSE) -> 32860.301 | I64: =+G64*(1-H64) -> 32860.301 | J64: =+I64/F64 -> 2738.3584 | K64: =+J64*K$3 -> 575.05527 | L64: =+J64+K64 -> 3313.4137 | M64: =+L64*M$3 -> 994.02412 | N64: =+L64+M64 -> 4307.4378 | O64: =+N64*O$3 -> 1722.9751 | P64: =+N64+O64 -> 6030.413 | R64: 32860.301 | S64: =+(I64-R64)/R64 -> 0 | U64: 100021709 | V64: 62208.541
B65: 100021709 | C65: BOCADITOS DE POLLO "SWIFT" - 10x760g | D65: 7790360024701 | E65: 7.6 | F65: 10 | G65: =+'Sub NOA'!G65 -> 60214.277 | I65: =+G65*(1-H65) -> 60214.277 | J65: =+I65/F65 -> 6021.4277 | K65: =+J65*K$3 -> 1264.4998 | L65: =+J65+K65 -> 7285.9275 | M65: =+L65*M$3 -> 2185.7783 | N65: =+L65+M65 -> 9471.7058 | O65: =+N65*O$3 -> 3788.6823 | P65: =+N65+O65 -> 13260.388 | R65: 60214.277 | S65: =+(I65-R65)/R65 -> 0 | U65: 100521357 | V65: 48595.609
B66: 100521357 | C66: CRUNCHIES DE POLLO "SWIFT" - 12x380g | E66: 4.56 | F66: 12 | G66: =+VLOOKUP(B66,$U$4:$V$104,2,FALSE) -> 48595.609 | H66: 0.33 | I66: =+G66*(1-H66) -> 32559.058 | J66: =+I66/F66 -> 2713.2548 | K66: =+J66*K$3 -> 569.78351 | L66: =+J66+K66 -> 3283.0383 | M66: =+L66*M$3 -> 984.9115 | N66: =+L66+M66 -> 4267.9498 | O66: =+N66*O$3 -> 1707.1799 | P66: =+N66+O66 -> 5975.1298 | R66: 40494.721 | U66: 100521358 | V66: 72893.413
B67: 100521358 | C67: CRUNCHIES DE POLLO "SWIFT" - 10x760g | D67: 7790360982025 | E67: 7.6 | F67: 10 | G67: =+VLOOKUP(B67,$U$4:$V$104,2,FALSE) -> 72893.413 | I67: =+G67*(1-H67) -> 72893.413 | J67: =+I67/F67 -> 7289.3413 | K67: =+J67*K$3 -> 1530.7617 | L67: =+J67+K67 -> 8820.103 | M67: =+L67*M$3 -> 2646.0309 | N67: =+L67+M67 -> 11466.134 | O67: =+N67*O$3 -> 4586.4535 | P67: =+N67+O67 -> 16052.587 | R67: 72893.413 | U67: 100522130 | V67: 36337.502
B68: 100522130 | C68: BOCADITOS DE POLLO "SWIFT KIDS" - 12x400g | E68: 4.8 | F68: 12 | G68: =+VLOOKUP(B68,$U$4:$V$104,2,FALSE) -> 36337.502 | I68: =+G68*(1-H68) -> 36337.502 | J68: =+I68/F68 -> 3028.1252 | K68: =+J68*K$3 -> 635.90628 | L68: =+J68+K68 -> 3664.0314 | M68: =+L68*M$3 -> 1099.2094 | N68: =+L68+M68 -> 4763.2409 | O68: =+N68*O$3 -> 1905.2963 | P68: =+N68+O68 -> 6668.5372 | R68: 26950.435 | U68: 100021725 | V68: 31749.879
B69: 100021725 | C69: BOCADITOS DE POLLO GASTRONOMICOS "LA BLANCA" - x6kg | D69: 7790360027009 | E69: 6 | F69: 4 | G69: =+VLOOKUP(B69,$U$4:$V$104,2,FALSE) -> 31749.879 | I69: =+G69*(1-H69) -> 31749.879 | J69: =+I69/F69 -> 7937.4699 | K69: =+J69*K$3 -> 1666.8687 | L69: =+J69+K69 -> 9604.3385 | M69: =+L69*M$3 -> 2881.3016 | N69: =+L69+M69 -> 12485.64 | O69: =+N69*O$3 -> 4994.256 | P69: =+N69+O69 -> 17479.896 | R69: 31749.879 | S69: =+(I69-R69)/R69 -> 0 | U69: 100517055 | V69: 27152.795
B70: 100517055 | C70: PALITO DE POLLO "SWIFT" 12 X 260 Grs. | D70: 7790360971135 | E70: 3.12 | F70: 12 | G70: =+VLOOKUP(B70,$U$4:$V$104,2,FALSE) -> 27152.795 | I70: =+G70*(1-H70) -> 27152.795 | J70: =+I70/F70 -> 2262.7329 | K70: =+J70*K$3 -> 475.17391 | L70: =+J70+K70 -> 2737.9068 | M70: =+L70*M$3 -> 821.37204 | N70: =+L70+M70 -> 3559.2789 | O70: =+N70*O$3 -> 1423.7115 | P70: =+N70+O70 -> 4982.9904 | R70: 27152.795 | S70: =+(I70-R70)/R70 -> 0 | U70: 100517186 | V70: 68590.402
B71: 100517186 | C71: PALITO DE POLLO "SWIFT" 8 X 1 Kg.. | D71: 7790360971395 | E71: 8 | F71: 8 | G71: =+VLOOKUP(B71,$U$4:$V$104,2,FALSE) -> 68590.402 | I71: =+G71*(1-H71) -> 68590.402 | J71: =+I71/F71 -> 8573.8003 | K71: =+J71*K$3 -> 1800.4981 | L71: =+J71+K71 -> 10374.298 | M71: =+L71*M$3 -> 3112.2895 | N71: =+L71+M71 -> 13486.588 | O71: =+N71*O$3 -> 5394.6351 | P71: =+N71+O71 -> 18881.223 | R71: 68590.402 | S71: =+(I71-R71)/R71 -> 0 | U71: 100521663 | V71: 49372.646
B72: 100521663 | C72: MILANESITAS DE CARNE "SWIFT" - 12x400g | E72: 4.8 | F72: 12 | G72: 43941.021 | H72: 0.33 | I72: =+G72*(1-H72) -> 29440.484 | J72: =+I72/F72 -> 2453.3737 | K72: =+J72*K$3 -> 515.20848 | L72: =+J72+K72 -> 2968.5822 | M72: =+L72*M$3 -> 890.57465 | N72: =+L72+M72 -> 3859.1568 | O72: =+N72*O$3 -> 1543.6627 | P72: =+N72+O72 -> 5402.8195 | R72: 49372.646 | U72: 100021728 | V72: 41610.877
B73: 100021728 | C73: MEDALLONES DE POLLO "SWIFT" - 12x4x80g | D73: 7790360967558 | E73: 3.84 | F73: 12 | G73: =+VLOOKUP(B73,$U$4:$V$104,2,FALSE) -> 41610.877 | I73: =+G73*(1-H73) -> 41610.877 | J73: =+I73/F73 -> 3467.5731 | K73: =+J73*K$3 -> 728.19036 | L73: =+J73+K73 -> 4195.7635 | M73: =+L73*M$3 -> 1258.729 | N73: =+L73+M73 -> 5454.4925 | O73: =+N73*O$3 -> 2181.797 | P73: =+N73+O73 -> 7636.2895 | R73: 41610.877 | S73: =+(I73-R73)/R73 -> 0 | U73: 100517679 | V73: 39413.592
B74: 100517679 | C74: MEDALLONES DE POLLO GASTRONÓMICO 8x12x80 Grs. | E74: 7.68 | F74: 8 | G74: =+VLOOKUP(B74,$U$4:$V$104,2,FALSE) -> 39413.592 | I74: =+G74*(1-H74) -> 39413.592 | J74: =+I74/F74 -> 4926.699 | K74: =+J74*K$3 -> 1034.6068 | L74: =+J74+K74 -> 5961.3058 | M74: =+L74*M$3 -> 1788.3918 | N74: =+L74+M74 -> 7749.6976 | O74: =+N74*O$3 -> 3099.879 | P74: =+N74+O74 -> 10849.577 | R74: 39413.592 | S74: =+(I74-R74)/R74 -> 0 | V74: #VALUE!
G75: =+VLOOKUP(B75,$U$4:$V$104,2,FALSE) -> #N/A | I75: =+G75*(1-H75) -> #N/A | J75: =+I75/F75 -> #N/A | K75: 0.21 | M75: 0.3 | O75: 0.4 | R75: #N/A | S75: =+(I75-R75)/R75 -> #N/A | U75: 100516219 | V75: 18259.4
B76: 100516219 | C76: PAPAS PREFRITAS SUPERCONGELADAS 25x400gr | D76: 7790360967770 | E76: 10 | F76: 25 | G76: =+VLOOKUP(B76,$U$4:$V$104,2,FALSE) -> 18259.4 | I76: =+G76*(1-H76) -> 18259.4 | J76: =+I76/F76 -> 730.376 | K76: =+J76*K$3 -> 153.37896 | L76: =+J76+K76 -> 883.75495 | M76: =+L76*M$3 -> 265.12649 | N76: =+L76+M76 -> 1148.8814 | O76: =+N76*O$3 -> 459.55258 | P76: =+N76+O76 -> 1608.434 | R76: 18259.4 | S76: =+(I76-R76)/R76 -> 0 | U76: 100516220 | V76: 19613.922
B77: 100516220 | C77: PAPAS PREFRITAS SUPERCONGELADAS 6x2000gr | D77: 7790360967787 | E77: 12 | F77: 6 | G77: =+VLOOKUP(B77,$U$4:$V$104,2,FALSE) -> 19613.922 | I77: =+G77*(1-H77) -> 19613.922 | J77: =+I77/F77 -> 3268.987 | K77: =+J77*K$3 -> 686.48726 | L77: =+J77+K77 -> 3955.4742 | M77: =+L77*M$3 -> 1186.6423 | N77: =+L77+M77 -> 5142.1165 | O77: =+N77*O$3 -> 2056.8466 | P77: =+N77+O77 -> 7198.9631 | R77: 19613.922 | S77: =+(I77-R77)/R77 -> 0 | V77: #VALUE!
G78: =+VLOOKUP(B78,$U$4:$V$104,2,FALSE) -> #N/A | I78: =+G78*(1-H78) -> #N/A | J78: =+I78/F78 -> #N/A | R78: #N/A | S78: =+(I78-R78)/R78 -> #N/A | U78: 100518158 | V78: 79203.691
B79: 100518158 | C79: MILANESA DE CARNE VACUNA CONGELADA 24un x 500grs | D79: 7790360974280 | E79: 12 | F79: 24 | G79: =+VLOOKUP(B79,$U$4:$V$104,2,FALSE) -> 79203.691 | I79: =+G79*(1-H79) -> 79203.691 | J79: =+I79/F79 -> 3300.1538 | K79: =+J79*K$3 -> 693.0323 | L79: =+J79+K79 -> 3993.1861 | M79: =+L79*M$3 -> 1197.9558 | N79: =+L79+M79 -> 5191.1419 | O79: =+N79*O$3 -> 2076.4568 | P79: =+N79+O79 -> 7267.5987 | R79: 79203.691 | S79: =+(I79-R79)/R79 -> 0 | U79: 100518160 | V79: 79203.691
B80: 100518160 | C80: MILANESA DE CARNE VACUNA CONGELADA 12un x 1000grs | D80: 7790360974686 | E80: 12 | F80: 12 | G80: =+VLOOKUP(B80,$U$4:$V$104,2,FALSE) -> 79203.691 | I80: =+G80*(1-H80) -> 79203.691 | J80: =+I80/F80 -> 6600.3076 | K80: =+J80*K$3 -> 1386.0646 | L80: =+J80+K80 -> 7986.3722 | M80: =+L80*M$3 -> 2395.9117 | N80: =+L80+M80 -> 10382.284 | O80: =+N80*O$3 -> 4152.9135 | P80: =+N80+O80 -> 14535.197 | R80: 79203.691 | S80: =+(I80-R80)/R80 -> 0 | U80: 100518463 | V80: 36649.894
B81: 100518463 | C81: MILANESAS DE CARNE VACUNA CONG GRANEL 5 kg (CAL GR) | E81: 5 | F81: 1 | G81: =+VLOOKUP(B81,$U$4:$V$104,2,FALSE) -> 36649.894 | I81: =+G81*(1-H81) -> 36649.894 | J81: =+I81/F81 -> 36649.894 | K81: =+J81*K$3 -> 7696.4777 | L81: =+J81+K81 -> 44346.372 | M81: =+L81*M$3 -> 13303.912 | N81: =+L81+M81 -> 57650.283 | O81: =+N81*O$3 -> 23060.113 | P81: =+N81+O81 -> 80710.397 | R81: 36649.894 | S81: =+(I81-R81)/R81 -> 0 | V81: #VALUE!
G82: =+VLOOKUP(B82,$U$4:$V$104,2,FALSE) -> #N/A | I82: =+G82*(1-H82) -> #N/A | J82: =+I82/F82 -> #N/A | R82: #N/A | S82: =+(I82-R82)/R82 -> #N/A | U82: 100518291 | V82: 17536.687
B83: 100518291 | C83: GRASA VACUNA REFINADA SWIFT 10 X 500 | D83: 7790360975195 | E83: 5 | F83: 10 | G83: =+VLOOKUP(B83,$U$4:$V$104,2,FALSE) -> 17536.687 | H83: 0.15 | I83: =+G83*(1-H83) -> 14906.184 | J83: =+I83/F83 -> 1490.6184 | K83: =+J83*K$3 -> 313.02986 | L83: =+J83+K83 -> 1803.6483 | M83: =+L83*M$39 -> 360.72965 | N83: =+L83+M83 -> 2164.3779 | O83: =+N83*O$39 -> 757.53227 | P83: =+N83+O83 -> 2921.9102 | R83: 14906.184 | S83: =+(I83-R83)/R83 -> 0 | U83: 100518292 | V83: 41380.324
B84: 100518292 | C84: GRASA VACUNA REFINADA SWIFT 12x1Kg | D84: 7790360975201 | E84: 12 | F84: 12 | G84: =+VLOOKUP(B84,$U$4:$V$104,2,FALSE) -> 41380.324 | H84: 0.15 | I84: =+G84*(1-H84) -> 35173.275 | J84: =+I84/F84 -> 2931.1063 | K84: =+J84*K$3 -> 615.53232 | L84: =+J84+K84 -> 3546.6386 | M84: =+L84*M$39 -> 709.32772 | N84: =+L84+M84 -> 4255.9663 | O84: =+N84*O$39 -> 1489.5882 | P84: =+N84+O84 -> 5745.5545 | R84: 35173.275 | S84: =+(I84-R84)/R84 -> 0 | V84: #VALUE!
G85: =+VLOOKUP(B85,$U$4:$V$104,2,FALSE) -> #N/A | I85: =+G85*(1-H85) -> #N/A | J85: =+I85/F85 -> #N/A | K85: 0.105 | M85: 0.2 | O85: 0.35 | R85: #N/A | S85: =+(I85-R85)/R85 -> #N/A | U85: 100517915 | V85: 154338.47
B86: 100517915 | C86: CARNE PICADA CONGELADA 36 UN X 500 g SWIFT | D86: 7790360974020 | E86: 18 | F86: 36 | G86: =+VLOOKUP(B86,$U$4:$V$104,2,FALSE) -> 154338.47 | I86: =+G86*(1-H86) -> 154338.47 | J86: =+I86/F86 -> 4287.1798 | K86: =+J86*K$85 -> 450.15388 | L86: =+J86+K86 -> 4737.3337 | M86: =+L86*M$85 -> 947.46674 | N86: =+L86+M86 -> 5684.8004 | O86: =+N86*O$85 -> 1989.6802 | P86: =+N86+O86 -> 7674.4806 | R86: 145602.33 | S86: =+(I86-R86)/R86 -> 0.06 | U86: 100517914 | V86: 168417.57
B87: 100517914 | C87: CARNE PICADA CONGELADA 20 UN X 1 kg SWIFT | D87: 7790360974037 | E87: 20 | F87: 20 | G87: =+VLOOKUP(B87,$U$4:$V$104,2,FALSE) -> 168417.57 | I87: =+G87*(1-H87) -> 168417.57 | J87: =+I87/F87 -> 8420.8786 | K87: =+J87*K$85 -> 884.19225 | L87: =+J87+K87 -> 9305.0708 | M87: =+L87*M$85 -> 1861.0142 | N87: =+L87+M87 -> 11166.085 | O87: =+N87*O$85 -> 3908.1298 | P87: =+N87+O87 -> 15074.215 | R87: 158884.5 | S87: =+(I87-R87)/R87 -> 0.06
G88: =+VLOOKUP(B88,$U$4:$V$104,2,FALSE) -> #N/A | I88: =+G88*(1-H88) -> #N/A | K88: 0.105 | M88: 0.3 | O88: 0.4 | R88: #N/A | S88: =+(I88-R88)/R88 -> #N/A | U88: 100010689 | V88: 16464.643
B89: 100010689 | C89: ENTRAÑA FINA ENF SWIFT | E89: 22 | F89: 1 | G89: =+VLOOKUP(B89,$U$4:$V$104,2,FALSE) -> 16464.643 | I89: =+G89*(1-H89) -> 16464.643 | J89: =+I89/F89 -> 16464.643 | K89: =+J89*K$88 -> 1728.7875 | L89: =+J89+K89 -> 18193.43 | M89: =+L89*M$88 -> 5458.0291 | N89: =+L89+M89 -> 23651.459 | O89: =+N89*O$88 -> 9460.5838 | P89: =+N89+O89 -> 33112.043 | R89: 16464.643 | S89: =+(I89-R89)/R89 -> 0 | U89: 100518335 | V89: 10429.179
B90: 100518335 | C90: ROAST BEEF EN PORCIONES ENF SWIFT (L) | E90: 22.5 | F90: 1 | G90: =+VLOOKUP(B90,$U$4:$V$104,2,FALSE) -> 10429.179 | I90: =+G90*(1-H90) -> 10429.179 | J90: =+I90/F90 -> 10429.179 | K90: =+J90*K$88 -> 1095.0638 | L90: =+J90+K90 -> 11524.242 | M90: =+L90*M$88 -> 3457.2727 | N90: =+L90+M90 -> 14981.515 | O90: =+N90*O$88 -> 5992.606 | P90: =+N90+O90 -> 20974.121 | R90: 10429.179 | S90: =+(I90-R90)/R90 -> 0 | U90: 100518332 | V90: 11223.536
B91: 100518332 | C91: CARNAZA CUADRADA EN PORCIONES ENF SWIFT (L) | E91: 21.5 | F91: 1 | G91: =+VLOOKUP(B91,$U$4:$V$104,2,FALSE) -> 11223.536 | I91: =+G91*(1-H91) -> 11223.536 | J91: =+I91/F91 -> 11223.536 | K91: =+J91*K$88 -> 1178.4713 | L91: =+J91+K91 -> 12402.007 | M91: =+L91*M$88 -> 3720.6021 | N91: =+L91+M91 -> 16122.609 | O91: =+N91*O$88 -> 6449.0436 | P91: =+N91+O91 -> 22571.653 | R91: 11223.536 | S91: =+(I91-R91)/R91 -> 0 | U91: 100518334 | V91: 9237.6429
B92: 100518334 | C92: TAPA DE ASADO EN PORCIONES ENF SWIFT (L) | E92: 22.5 | F92: 1 | G92: =+VLOOKUP(B92,$U$4:$V$104,2,FALSE) -> 9237.6429 | I92: =+G92*(1-H92) -> 9237.6429 | J92: =+I92/F92 -> 9237.6429 | K92: =+J92*K$88 -> 969.9525 | L92: =+J92+K92 -> 10207.595 | M92: =+L92*M$88 -> 3062.2786 | N92: =+L92+M92 -> 13269.874 | O92: =+N92*O$88 -> 5307.9496 | P92: =+N92+O92 -> 18577.824 | R92: 9237.6429 | S92: =+(I92-R92)/R92 -> 0 | U92: 100518227 | V92: 9237.6429
B93: 100518227 | C93: VACIO EN PORCIONES NOV ENFRIADO PARA VENTA LOCAL (L) | E93: 22.5 | F93: 1 | G93: =+VLOOKUP(B93,$U$4:$V$104,2,FALSE) -> 9237.6429 | I93: =+G93*(1-H93) -> 9237.6429 | J93: =+I93/F93 -> 9237.6429 | K93: =+J93*K$88 -> 969.9525 | L93: =+J93+K93 -> 10207.595 | M93: =+L93*M$88 -> 3062.2786 | N93: =+L93+M93 -> 13269.874 | O93: =+N93*O$88 -> 5307.9496 | P93: =+N93+O93 -> 18577.824 | R93: 9237.6429 | S93: =+(I93-R93)/R93 -> 0 | U93: 100027726 | V93: 6814.5
B94: 100027726 | C94: BONDIOLA DE CERDO CONGELADA | D94: 22.5 | E94: 1 | F94: 1 | G94: =+VLOOKUP(B94,$U$4:$V$104,2,FALSE) -> 6814.5 | I94: =+G94*(1-H94) -> 6814.5 | J94: =+I94/F94 -> 6814.5 | K94: =+J94*K$88 -> 715.5225 | L94: =+J94+K94 -> 7530.0225 | M94: =+L94*M$88 -> 2259.0068 | N94: =+L94+M94 -> 9789.0293 | O94: =+N94*O$88 -> 3915.6117 | P94: =+N94+O94 -> 13704.641 | R94: 6814.5
G95: =+VLOOKUP(B95,$U$4:$V$104,2,FALSE) -> #N/A | I95: =+G95*(1-H95) -> #N/A | K95: 0.21 | M95: 0.3 | O95: 0.4 | R95: #N/A | S95: =+(I95-R95)/R95 -> #N/A | U95: 100520837 | V95: 35756.176
B96: 100520837 | C96: CHORIZOS FRESCOS DE CERDO LIBRE DE GLUTEN | D96: 7790360980625 | E96: 4.8 | F96: 12 | G96: =+VLOOKUP(B96,$U$4:$V$104,2,FALSE) -> 35756.176 | I96: =+G96*(1-H96) -> 35756.176 | J96: =+I96/F96 -> 2979.6813 | K96: =+J96*K$95 -> 625.73307 | L96: =+J96+K96 -> 3605.4144 | M96: =+L96*M$95 -> 1081.6243 | N96: =+L96+M96 -> 4687.0387 | O96: =+N96*O$95 -> 1874.8155 | P96: =+N96+O96 -> 6561.8541 | R96: 35756.176 | S96: =+(I96-R96)/R96 -> 0 | U96: 100522395 | V96: 36471.292
A97: 100522395 | B97: 100522395 | C97: CHORIZOS FRESCOS DE CERDO CONGELADOS LIBRE DE GLUTEN 12u x 400g | D97: 7790360980625 | E97: 4.8 | F97: 12 | G97: =+VLOOKUP(B97,$U$4:$V$104,2,FALSE) -> 36471.292 | I97: =+G97*(1-H97) -> 36471.292 | J97: =+I97/F97 -> 3039.2743 | K97: =+J97*K$95 -> 638.24761 | L97: =+J97+K97 -> 3677.5219 | M97: =+L97*M$95 -> 1103.2566 | N97: =+L97+M97 -> 4780.7785 | O97: =+N97*O$95 -> 1912.3114 | P97: =+N97+O97 -> 6693.0899 | R97: 0
G98: =+VLOOKUP(B98,$U$4:$V$104,2,FALSE) -> #N/A | I98: =+G98*(1-H98) -> #N/A | K98: 0.21 | M98: 0.3 | O98: 0.4 | R98: #N/A | S98: =+(I98-R98)/R98 -> #N/A | U98: 100520902 | V98: 32345.803
B99: 100520902 | C99: PAPAS PRE COCIDAS SUPERCONGELADAS LIBRES DE GLUTEN 700G | D99: 7790360981042 | E99: 9.8 | F99: 14 | G99: =+VLOOKUP(B99,$U$4:$V$104,2,FALSE) -> 32345.803 | H99: =0.142857142857143*100% -> 0.14285714 | I99: =+G99*(1-H99) -> 27724.974 | J99: =+I99/F99 -> 1980.3553 | K99: =+J99*K$98 -> 415.87461 | L99: =+J99+K99 -> 2396.2299 | M99: =+L99*M$98 -> 718.86897 | N99: =+L99+M99 -> 3115.0989 | O99: =+N99*O$98 -> 1246.0395 | P99: =+N99+O99 -> 4361.1384 | R99: 28302.577 | S99: =+(I99-R99)/R99 -> -0.020408163
K100: 0.21 | M100: 0.3 | O100: 0.4 | U100: 100521457 | V100: 36127.9
B101: 100521457 | C101: NUGGETS DE ESPINACA 300GR | D101: 7790360982254 | E101: 4.8 | F101: 16 | G101: =+VLOOKUP(B101,$U$4:$V$104,2,FALSE) -> 36127.9 | H101: 0.075 | I101: =+G101*(1-H101) -> 33418.307 | J101: =+I101/F101 -> 2088.6442 | K101: =+J101*K$100 -> 438.61528 | L101: =+J101+K101 -> 2527.2595 | M101: =+L101*M$100 -> 758.17784 | N101: =+L101+M101 -> 3285.4373 | O101: =+N101*O$100 -> 1314.1749 | P101: =+N101+O101 -> 4599.6123 | R101: 31826.959 | S101: =+(I101-R101)/R101 -> 0.05 | U101: 100521455 | V101: 36127.9
...

Sheet Sub NOA
B2: Código | C2: Descripción | D2: EAN | E2: Kg. x Caja | F2: Cant. X Caja | G2: Precio de Lista | H2: Dcto | I2: Precio de Factura | J2: Precio Neto estuche en factura | K2: IVA | L2: Px Unitario IVA Inc | M2: M-up Dx | N2: Px Unitario Minorista | O2: M-up Minorista | P2: Px Unitario Público | R2: PX ABR
K3: 0.21 | M3: 0.3 | O3: 0.4
B4: 100021632 | C4: HAMBURGUESAS 30x160g CLASICA x2 SWIFT | D4: 7790360026606 | E4: 4.8 | F4: 30 | G4: =+VLOOKUP(B4,$U$4:$V$104,2,FALSE) -> 36141.234 | I4: =+G4*(1-H4) -> 36141.234 | J4: =+I4/F4 -> 1204.7078 | K4: =+J4*K$3 -> 252.98864 | L4: =+J4+K4 -> 1457.6965 | M4: =+L4*M$3 -> 437.30894 | N4: =+L4+M4 -> 1895.0054 | O4: =+N4*O$3 -> 758.00216 | P4: =+N4+O4 -> 2653.0076 | R4: 33114.563 | S4: =+(I4-R4)/R4 -> 0.0914 | U4: 100021632 | V4: 36141.234
B5: 100021652 | C5: HAMBURGUESA 18X4X80G CLASICA SWIFT | D5: 7790360026576 | E5: 5.76 | F5: 18 | G5: =+VLOOKUP(B5,$U$4:$V$104,2,FALSE) -> 51551.959 | I5: =+G5*(1-H5) -> 51551.959 | J5: =+I5/F5 -> 2863.9977 | K5: =+J5*K$3 -> 601.43952 | L5: =+J5+K5 -> 3465.4372 | M5: =+L5*M$3 -> 1039.6312 | N5: =+L5+M5 -> 4505.0684 | O5: =+N5*O$3 -> 1802.0274 | P5: =+N5+O5 -> 6307.0958 | R5: 48179.401 | S5: =+(I5-R5)/R5 -> 0.07 | U5: 100021652 | V5: 51551.959
B6: 100021631 | C6: HAMBURGUESA 8X12X80G CLASICA SWIFT | D6: 7790360026590 | E6: 7.68 | F6: 8 | G6: =+VLOOKUP(B6,$U$4:$V$104,2,FALSE) -> 63608.573 | I6: =+G6*(1-H6) -> 63608.573 | J6: =+I6/F6 -> 7951.0716 | K6: =+J6*K$3 -> 1669.725 | L6: =+J6+K6 -> 9620.7966 | M6: =+L6*M$3 -> 2886.239 | N6: =+L6+M6 -> 12507.036 | O6: =+N6*O$3 -> 5002.8142 | P6: =+N6+O6 -> 17509.85 | R6: 70485.893 | S6: =+(I6-R6)/R6 -> -0.097570167 | U6: 100021631 | V6: 63608.573
B7: 100021630 | C7: HAMBURGUESA 6X20X80G CLASICA SWIFT | D7: 7790360026583 | E7: 9.6 | F7: 6 | G7: =+VLOOKUP(B7,$U$4:$V$104,2,FALSE) -> 79510.716 | I7: =+G7*(1-H7) -> 79510.716 | J7: =+I7/F7 -> 13251.786 | K7: =+J7*K$3 -> 2782.8751 | L7: =+J7+K7 -> 16034.661 | M7: =+L7*M$3 -> 4810.3983 | N7: =+L7+M7 -> 20845.059 | O7: =+N7*O$3 -> 8338.0237 | P7: =+N7+O7 -> 29183.083 | R7: 88089.919 | S7: =+(I7-R7)/R7 -> -0.097391432 | U7: 100021630 | V7: 79510.716
B8: 100021653 | C8: MEDALLON 18X4X80G PARRILLERO SWIFT | D8: 7790360026682 | E8: 5.76 | F8: 18 | G8: =+VLOOKUP(B8,$U$4:$V$104,2,FALSE) -> 51551.959 | I8: =+G8*(1-H8) -> 51551.959 | J8: =+I8/F8 -> 2863.9977 | K8: =+J8*K$3 -> 601.43952 | L8: =+J8+K8 -> 3465.4372 | M8: =+L8*M$3 -> 1039.6312 | N8: =+L8+M8 -> 4505.0684 | O8: =+N8*O$3 -> 1802.0274 | P8: =+N8+O8 -> 6307.0958 | R8: 56884.18 | S8: =+(I8-R8)/R8 -> -0.093738215 | U8: 100021653 | V8: 51551.959
B9: 100516169 | C9: MEDALLONES 18X4X80G SWIFT RECETA ESPECIAL | D9: 7790360967961 | E9: 5.76 | F9: 18 | G9: =+VLOOKUP(B9,$U$4:$V$104,2,FALSE) -> 47534.511 | I9: =+G9*(1-H9) -> 47534.511 | J9: =+I9/F9 -> 2640.8062 | K9: =+J9*K$3 -> 554.5693 | L9: =+J9+K9 -> 3195.3755 | M9: =+L9*M$3 -> 958.61264 | N9: =+L9+M9 -> 4153.9881 | O9: =+N9*O$3 -> 1661.5952 | P9: =+N9+O9 -> 5815.5834 | R9: 47534.511 | S9: =+(I9-R9)/R9 -> 0 | U9: 100516169 | V9: 47534.511
B10: 100520337 | C10: MEDALLON BURGER SWIFT MEGA 30 x 160 g | D10: 7790360977960 | E10: 4.8 | F10: 30 | G10: =+VLOOKUP(B10,$U$4:$V$104,2,FALSE) -> 28147.379 | I10: =+G10*(1-H10) -> 28147.379 | J10: =+I10/F10 -> 938.24596 | K10: =+J10*K$3 -> 197.03165 | L10: =+J10+K10 -> 1135.2776 | M10: =+L10*M$3 -> 340.58328 | N10: =+L10+M10 -> 1475.8609 | O10: =+N10*O$3 -> 590.34436 | P10: =+N10+O10 -> 2066.2053 | R10: 28147.379 | S10: =+(I10-R10)/R10 -> 0 | U10: 100520337 | V10: 28147.379
B11: 100021503 | C11: Medallón CAJITA 12x4 69 grs | D11: 7790360966841 | E11: 3.312 | F11: 12 | G11: =+VLOOKUP(B11,$U$4:$V$104,2,FALSE) -> 20900.325 | H11: 0.1666 | I11: =+G11*(1-H11) -> 17418.331 | J11: =+I11/F11 -> 1451.5276 | K11: =+J11*K$3 -> 304.8208 | L11: =+J11+K11 -> 1756.3484 | M11: =+L11*M$3 -> 526.90452 | N11: =+L11+M11 -> 2283.2529 | O11: =+N11*O$3 -> 913.30116 | P11: =+N11+O11 -> 3196.5541 | R11: 19533.014 | S11: =+(I11-R11)/R11 -> -0.108262 | U11: 100021503 | V11: 20900.325
B12: 100516201 | C12: HAMBURGUESA 8X12X69G BURGER SWIFT | D12: 7790360968548 | E12: 6.624 | F12: 8 | G12: =+VLOOKUP(B12,$U$4:$V$104,2,FALSE) -> 39472.683 | I12: =+G12*(1-H12) -> 39472.683 | J12: =+I12/F12 -> 4934.0853 | K12: =+J12*K$3 -> 1036.1579 | L12: =+J12+K12 -> 5970.2432 | M12: =+L12*M$3 -> 1791.073 | N12: =+L12+M12 -> 7761.3162 | O12: =+N12*O$3 -> 3104.5265 | P12: =+N12+O12 -> 10865.843 | R12: 39472.683 | S12: =+(I12-R12)/R12 -> 0 | U12: 100516201 | V12: 39472.683
B13: 100021643 | C13: MEDALLON 42X112G DOBLE BURGER SWIFT | D13: 7790360966797 | E13: 4.704 | F13: 42 | G13: =+VLOOKUP(B13,$U$4:$V$104,2,FALSE) -> 28485.646 | I13: =+G13*(1-H13) -> 28485.646 | J13: =+I13/F13 -> 678.22967 | K13: =+J13*K$3 -> 142.42823 | L13: =+J13+K13 -> 820.65789 | M13: =+L13*M$3 -> 246.19737 | N13: =+L13+M13 -> 1066.8553 | O13: =+N13*O$3 -> 426.74211 | P13: =+N13+O13 -> 1493.5974 | R13: 28485.646 | S13: =+(I13-R13)/R13 -> 0 | U13: 100021643 | V13: 28485.646
B14: 100516325 | C14: MEDALLON DOBLE BURGER 2X2 | D14: 7790360967763 | E14: 4.704 | F14: 21 | G14: =+VLOOKUP(B14,$U$4:$V$104,2,FALSE) -> 27704.096 | I14: =+G14*(1-H14) -> 27704.096 | J14: =+I14/F14 -> 1319.2426 | K14: =+J14*K$3 -> 277.04096 | L14: =+J14+K14 -> 1596.2836 | M14: =+L14*M$3 -> 478.88508 | N14: =+L14+M14 -> 2075.1687 | O14: =+N14*O$3 -> 830.06747 | P14: =+N14+O14 -> 2905.2362 | R14: 27704.096 | S14: =+(I14-R14)/R14 -> 0 | U14: 100516325 | V14: 27704.096
B15: 100021676 | C15: HAMBURGUESA 30X250g CLASICA "XL" SWIFT | D15: 7790360967411 | E15: 7.5 | F15: 30 | G15: =+VLOOKUP(B15,$U$4:$V$104,2,FALSE) -> 61188.927 | H15: 0.04 | I15: =+G15*(1-H15) -> 58741.37 | J15: =+I15/F15 -> 1958.0457 | K15: =+J15*K$3 -> 411.18959 | L15: =+J15+K15 -> 2369.2353 | M15: =+L15*M$3 -> 710.77058 | N15: =+L15+M15 -> 3080.0058 | O15: =+N15*O$3 -> 1232.0023 | P15: =+N15+O15 -> 4312.0082 | R15: 52977.426 | S15: =+(I15-R15)/R15 -> 0.1088 | U15: 100021676 | V15: 61188.927
B16: 100516008 | C16: HAMBURGUESA 24X2X120g CASERA SWIFT | D16: 7790360967701 | E16: 5.76 | F16: 24 | G16: =+VLOOKUP(B16,$U$4:$V$104,2,FALSE) -> 60720.964 | H16: 0.0909 | I16: =+G16*(1-H16) -> 55201.428 | J16: =+I16/F16 -> 2300.0595 | K16: =+J16*K$3 -> 483.0125 | L16: =+J16+K16 -> 2783.072 | M16: =+L16*M$3 -> 834.9216 | N16: =+L16+M16 -> 3617.9936 | O16: =+N16*O$3 -> 1447.1974 | P16: =+N16+O16 -> 5065.1911 | R16: 57829.49 | S16: =+(I16-R16)/R16 -> -0.045445 | U16: 100516008 | V16: 60720.964
B17: 100520834 | C17: HAMBURGUESA X-TREMA 36 x 185 grs | D17: 7790360980618 | E17: 6.66 | F17: 36 | G17: =+VLOOKUP(B17,$U$4:$V$104,2,FALSE) -> 70938.062 | I17: =+G17*(1-H17) -> 70938.062 | J17: =+I17/F17 -> 1970.5017 | K17: =+J17*K$3 -> 413.80536 | L17: =+J17+K17 -> 2384.3071 | M17: =+L17*M$3 -> 715.29212 | N17: =+L17+M17 -> 3099.5992 | O17: =+N17*O$3 -> 1239.8397 | P17: =+N17+O17 -> 4339.4389 | R17: 67560.059 | S17: =+(I17-R17)/R17 -> 0.05 | U17: 100520834 | V17: 70938.062
B18: 100021680 | C18: HAMBURGUESAS 18X2X120g CLL BRA/ARG | D18: 7790360967688 | E18: 4.32 | F18: 18 | G18: =+VLOOKUP(B18,$U$4:$V$104,2,FALSE) -> 54046.264 | I18: =+G18*(1-H18) -> 54046.264 | J18: =+I18/F18 -> 3002.5702 | K18: =+J18*K$3 -> 630.53975 | L18: =+J18+K18 -> 3633.11 | M18: =+L18*M$3 -> 1089.933 | N18: =+L18+M18 -> 4723.043 | O18: =+N18*O$3 -> 1889.2172 | P18: =+N18+O18 -> 6612.2602 | R18: 51472.633 | S18: =+(I18-R18)/R18 -> 0.05 | U18: 100021680 | V18: 54046.264
B19: 100021644 | C19: MEDALLON 42X112G LA BLANCA | D19: 7790360008541 | E19: 4.704 | F19: 42 | G19: =+VLOOKUP(B19,$U$4:$V$104,2,FALSE) -> 18822.252 | I19: =+G19*(1-H19) -> 18822.252 | J19: =+I19/F19 -> 448.14887 | K19: =+J19*K$3 -> 94.111262 | L19: =+J19+K19 -> 542.26013 | M19: =+L19*0.33 -> 178.94584 | N19: =+L19+M19 -> 721.20597 | O19: =+N19*O$3 -> 288.48239 | P19: =+N19+O19 -> 1009.6884 | R19: 17925.955 | S19: =+(I19-R19)/R19 -> 0.05 | U19: 100021644 | V19: 18822.252
B20: 100021677 | C20: MEDALLON 12x4X69G LA BLANCA | D20: 7790360967404 | E20: 3.312 | F20: 12 | G20: =+VLOOKUP(B20,$U$4:$V$104,2,FALSE) -> 17616.948 | I20: =+G20*(1-H20) -> 17616.948 | J20: =+I20/F20 -> 1468.079 | K20: =+J20*K$3 -> 308.29659 | L20: =+J20+K20 -> 1776.3756 | M20: =+L20*0.33 -> 586.20394 | N20: =+L20+M20 -> 2362.5795 | O20: =+N20*O$3 -> 945.0318 | P20: =+N20+O20 -> 3307.6113 | R20: 16778.045 | S20: =+(I20-R20)/R20 -> 0.05 | U20: 100021677 | V20: 17616.948
B21: 100021638 | C21: MEDALLONES 60X80g "SWIFT BURGER" PARRILLERAS FAMILY | D21: 7790360026699 | E21: 4.8 | F21: 60 | G21: =+VLOOKUP(B21,$U$4:$V$104,2,FALSE) -> 50422.132 | I21: =+G21*(1-H21) -> 50422.132 | J21: =+I21/F21 -> 840.36886 | K21: =+J21*K$3 -> 176.47746 | L21: =+J21+K21 -> 1016.8463 | M21: =+L21*M$3 -> 305.0539 | N21: =+L21+M21 -> 1321.9002 | O21: =+N21*O$3 -> 528.76009 | P21: =+N21+O21 -> 1850.6603 | R21: 48021.078 | S21: =+(I21-R21)/R21 -> 0.05 | U21: 100021638 | V21: 50422.132
B22: 100021575 | C22: MEDALLONES 60X69g "SWIFT BURGER"PARRILLERAS FAMILY | D22: 7790360007032 | E22: 4.14 | F22: 60 | G22: =+VLOOKUP(B22,$U$4:$V$104,2,FALSE) -> 42588.345 | I22: =+G22*(1-H22) -> 42588.345 | J22: =+I22/F22 -> 709.80575 | K22: =+J22*K$3 -> 149.05921 | L22: =+J22+K22 -> 858.86495 | M22: =+L22*M$3 -> 257.65949 | N22: =+L22+M22 -> 1116.5244 | O22: =+N22*O$3 -> 446.60978 | P22: =+N22+O22 -> 1563.1342 | R22: 40560.328 | S22: =+(I22-R22)/R22 -> 0.05 | U22: 100021575 | V22: 42588.345
B23: 100021514 | C23: MEDALLON 60X69G CARNE VACUNA | D23: 7790360006943 | E23: 4.14 | F23: 60 | G23: =+VLOOKUP(B23,$U$4:$V$104,2,FALSE) -> 39137.336 | I23: =+G23*(1-H23) -> 39137.336 | J23: =+I23/F23 -> 652.28893 | K23: =+J23*K$3 -> 136.98068 | L23: =+J23+K23 -> 789.26961 | M23: =+L23*M$3 -> 236.78088 | N23: =+L23+M23 -> 1026.0505 | O23: =+N23*O$3 -> 410.4202 | P23: =+N23+O23 -> 1436.4707 | R23: 37273.653 | S23: =+(I23-R23)/R23 -> 0.05 | U23: 100021514 | V23: 39137.336
B24: 100516208 | C24: MEDALLON 60x80g PARRILLERO MC SWIFT | D24: 7790360968203 | E24: =60*0.08 -> 4.8 | F24: 60 | G24: =+VLOOKUP(B24,$U$4:$V$104,2,FALSE) -> 44913.618 | I24: =+G24*(1-H24) -> 44913.618 | J24: =+I24/F24 -> 748.56031 | K24: =+J24*K$3 -> 157.19766 | L24: =+J24+K24 -> 905.75797 | M24: =+L24*M$3 -> 271.72739 | N24: =+L24+M24 -> 1177.4854 | O24: =+N24*O$3 -> 470.99415 | P24: =+N24+O24 -> 1648.4795 | R24: 42774.875 | S24: =+(I24-R24)/R24 -> 0.05 | U24: 100516208 | V24: 44913.618
B25: 100518346 | C25: MEDALLON 60X109G CARNE VACUNA PARRILLERO SWIFT | E25: 6.54 | F25: 60 | G25: =+VLOOKUP(B25,$U$4:$V$104,2,FALSE) -> 64856.372 | I25: =+G25*(1-H25) -> 64856.372 | J25: =+I25/F25 -> 1080.9395 | K25: =+J25*K$3 -> 226.9973 | L25: =+J25+K25 -> 1307.9368 | M25: =+L25*M$3 -> 392.38105 | N25: =+L25+M25 -> 1700.3179 | O25: =+N25*O$3 -> 680.12715 | P25: =+N25+O25 -> 2380.445 | R25: 61767.973 | S25: =+(I25-R25)/R25 -> 0.05 | U25: 100518346 | V25: 64856.372
B26: 100516259 | C26: MEDALLON GIGANTE 48x113.5g | D26: 7790360968340 | E26: 18.16 | F26: 48 | G26: =+VLOOKUP(B26,$U$4:$V$104,2,FALSE) -> 145463.97 | I26: =+G26*(1-H26) -> 145463.97 | J26: =+I26/F26 -> 3030.4993 | K26: =+J26*K$3 -> 636.40485 | L26: =+J26+K26 -> 3666.9041 | M26: =+L26*M$3 -> 1100.0712 | N26: =+L26+M26 -> 4766.9754 | O26: =+N26*O$3 -> 1906.7901 | P26: =+N26+O26 -> 6673.7655 | R26: 138537.11 | S26: =+(I26-R26)/R26 -> 0.05 | U26: 100516259 | V26: 145463.97
B27: 100518095 | C27: HAMBURGUESA 36 X 185 GRS | D27: 7790360974785 | E27: 6.66 | F27: 36 | G27: =+VLOOKUP(B27,$U$4:$V$104,2,FALSE) -> 72476.909 | I27: =+G27*(1-H27) -> 72476.909 | J27: =+I27/F27 -> 2013.2475 | K27: =+J27*K$3 -> 422.78197 | L27: =+J27+K27 -> 2436.0294 | M27: =+L27*M$3 -> 730.80883 | N27: =+L27+M27 -> 3166.8383 | O27: =+N27*O$3 -> 1266.7353 | P27: =+N27+O27 -> 4433.5736 | R27: 69025.627 | S27: =+(I27-R27)/R27 -> 0.05 | U27: 100518095 | V27: 72476.909
B28: 100518223 | C28: HAMBURGUESA 30x2x106 GRS | D28: 7790360975065 | E28: =60*0.106 -> 6.36 | F28: 30 | G28: =+VLOOKUP(B28,$U$4:$V$104,2,FALSE) -> 56427.301 | I28: =+G28*(1-H28) -> 56427.301 | J28: =+I28/F28 -> 1880.91 | K28: =+J28*K$3 -> 394.99111 | L28: =+J28+K28 -> 2275.9011 | M28: =+L28*M$3 -> 682.77034 | N28: =+L28+M28 -> 2958.6715 | O28: =+N28*O$3 -> 1183.4686 | P28: =+N28+O28 -> 4142.1401 | R28: 53740.287 | S28: =+(I28-R28)/R28 -> 0.05 | U28: 100518223 | V28: 56427.301
G29: =+VLOOKUP(B29,$U$4:$V$104,2,FALSE) -> #N/A | I29: =+G29*(1-H29) -> #N/A | J29: =+I29/F29 -> #N/A | K29: 0.21 | M29: 0.3 | O29: 0.4 | R29: #N/A | S29: =+(I29-R29)/R29 -> #N/A | V29: #VALUE!
B30: 100022085 | C30: SALCHICHAS 24X6 SWIFT | D30: 7790360000132 | E30: 5.4 | F30: 24 | G30: =+VLOOKUP(B30,$U$4:$V$104,2,FALSE) -> 21970.511 | I30: =+G30*(1-H30) -> 21970.511 | J30: =+I30/F30 -> 915.43795 | K30: =+J30*K$3 -> 192.24197 | L30: =+J30+K30 -> 1107.6799 | M30: =+L30*M$3 -> 332.30397 | N30: =+L30+M30 -> 1439.9839 | O30: =+N30*O$3 -> 575.99356 | P30: =+N30+O30 -> 2015.9774 | R30: 20505.727 | S30: =+(I30-R30)/R30 -> 0.071432922 | U30: 100022085 | V30: 21970.511
B31: 100522204 | C31: SALCHICHAS 24X6 SWIFT | D31: 7790360983947 | E31: 5.4 | F31: 24 | G31: =+VLOOKUP(B31,$U$4:$V$104,2,FALSE) -> 21970.511 | I31: =+G31*(1-H31) -> 21970.511 | J31: =+I31/F31 -> 915.43795 | K31: =+J31*K$3 -> 192.24197 | L31: =+J31+K31 -> 1107.6799 | M31: =+L31*M$3 -> 332.30397 | N31: =+L31+M31 -> 1439.9839 | O31: =+N31*O$3 -> 575.99356 | P31: =+N31+O31 -> 2015.9774 | U31: 100522204 | V31: 21970.511
B32: 100022072 | C32: SALCHICHAS 12X12 SWIFT | D32: 7790360024541 | E32: 5.4 | F32: 12 | G32: =+VLOOKUP(B32,$U$4:$V$104,2,FALSE) -> 20871.985 | I32: =+G32*(1-H32) -> 20871.985 | J32: =+I32/F32 -> 1739.3321 | K32: =+J32*K$3 -> 365.25974 | L32: =+J32+K32 -> 2104.5918 | M32: =+L32*M$3 -> 631.37755 | N32: =+L32+M32 -> 2735.9694 | O32: =+N32*O$3 -> 1094.3878 | P32: =+N32+O32 -> 3830.3571 | R32: 19626.928 | S32: =+(I32-R32)/R32 -> 0.063436191 | U32: 100022072 | V32: 20871.985
B33: 100522205 | C33: SALCHICHAS 12X12 SWIFT | D33: 7790360983954 | E33: 5.4 | F33: 12 | G33: =+VLOOKUP(B33,$U$4:$V$104,2,FALSE) -> 20871.985 | I33: =+G33*(1-H33) -> 20871.985 | J33: =+I33/F33 -> 1739.3321 | K33: =+J33*K$3 -> 365.25974 | L33: =+J33+K33 -> 2104.5918 | M33: =+L33*M$3 -> 631.37755 | N33: =+L33+M33 -> 2735.9694 | O33: =+N33*O$3 -> 1094.3878 | P33: =+N33+O33 -> 3830.3571 | U33: 100522205 | V33: 20871.985
B34: 100516849 | C34: SALCHICHAS SIN PIEL 24X6 "SWIFT KIDS" X 190 g | D34: 7790360970053 | E34: 4.56 | F34: 24 | G34: =+VLOOKUP(B34,$U$4:$V$104,2,FALSE) -> 17576.409 | I34: =+G34*(1-H34) -> 17576.409 | J34: =+I34/F34 -> 732.35036 | K34: =+J34*K$3 -> 153.79357 | L34: =+J34+K34 -> 886.14393 | M34: =+L34*M$3 -> 265.84318 | N34: =+L34+M34 -> 1151.9871 | O34: =+N34*O$3 -> 460.79484 | P34: =+N34+O34 -> 1612.782 | R34: 17576.45 | S34: =+(I34-R34)/R34 -> -2.3642784e-06 | U34: 100516849 | V34: 17576.409
B35: 100022039 | C35: SALCHICHAS LARGAS 10 x 12 SWIFT INSTITUCIONAL | D35: 7790360007063 | E35: 8.7 | F35: 10 | G35: =+VLOOKUP(B35,$U$4:$V$104,2,FALSE) -> 52385.6 | I35: =+G35*(1-H35) -> 52385.6 | J35: =+I35/F35 -> 5238.56 | K35: =+J35*K$3 -> 1100.0976 | L35: =+J35+K35 -> 6338.6576 | M35: =+L35*M$3 -> 1901.5973 | N35: =+L35+M35 -> 8240.2549 | O35: =+N35*O$3 -> 3296.102 | P35: =+N35+O35 -> 11536.357 | R35: 47092.413 | S35: =+(I35-R35)/R35 -> 0.1124 | U35: 100022039 | V35: 52385.6
B36: 100522206 | C36: SALCHICHAS LARGAS 10 x 12 SWIFT INSTITUCIONAL | D36: 7790360983961 | E36: 8.7 | F36: 10 | G36: =+VLOOKUP(B36,$U$4:$V$104,2,FALSE) -> 52385.6 | I36: =+G36*(1-H36) -> 52385.6 | J36: =+I36/F36 -> 5238.56 | K36: =+J36*K$3 -> 1100.0976 | L36: =+J36+K36 -> 6338.6576 | M36: =+L36*M$3 -> 1901.5973 | N36: =+L36+M36 -> 8240.2549 | O36: =+N36*O$3 -> 3296.102 | P36: =+N36+O36 -> 11536.357 | U36: 100522206 | V36: 52385.6
B37: 100022058 | C37: SALCHICHAS SIN PIEL "LA BLANCA" 24X6X190 Grs; | D37: 7790360026002 | E37: 4.56 | F37: 24 | G37: =+VLOOKUP(B37,$U$4:$V$104,2,FALSE) -> 17603.103 | I37: =+G37*(1-H37) -> 17603.103 | J37: =+I37/F37 -> 733.46264 | K37: =+J37*K$3 -> 154.02715 | L37: =+J37+K37 -> 887.4898 | M37: =+L37*0.33 -> 292.87163 | N37: =+L37+M37 -> 1180.3614 | O37: =+N37*O$3 -> 472.14457 | P37: =+N37+O37 -> 1652.506 | R37: 11483.254 | S37: =+(I37-R37)/R37 -> 0.53293692 | U37: 100022058 | V37: 17603.103 | X37: Ver posicionamiento por verba según necesidad de la zona
B38: 100518151 | C38: SALCHICHAS LARGAS 10 x 12 x 870g | D38: 7790360974990 | E38: 8.7 | F38: 10 | G38: =+VLOOKUP(B38,$U$4:$V$104,2,FALSE) -> 63817.204 | I38: =+G38*(1-H38) -> 63817.204 | J38: =+I38/F38 -> 6381.7204 | K38: =+J38*K$3 -> 1340.1613 | L38: =+J38+K38 -> 7721.8817 | M38: =+L38*0.33 -> 2548.2209 | N38: =+L38+M38 -> 10270.103 | O38: =+N38*O$3 -> 4108.041 | P38: =+N38+O38 -> 14378.144 | R38: 57368.935 | S38: =+(I38-R38)/R38 -> 0.1124 | U38: 100518151 | V38: 63817.204
G39: =+VLOOKUP(B39,$U$4:$V$104,2,FALSE) -> #N/A | I39: =+G39*(1-H39) -> #N/A | J39: =+I39/F39 -> #N/A | K39: 0.21 | M39: 0.2 | O39: 0.35 | R39: #N/A | S39: =+(I39-R39)/R39 -> #N/A | V39: #VALUE!
B40: 100021000 | C40: PATE DE FOIE 24X90G SWIFT | D40: 7790360720382 | E40: 2.16 | F40: 24 | G40: =+VLOOKUP(B40,$U$4:$V$104,2,FALSE) -> 13579.525 | I40: =+G40*(1-H40) -> 13579.525 | J40: =+I40/F40 -> 565.81353 | K40: =+J40*K$3 -> 118.82084 | L40: =+J40+K40 -> 684.63438 | M40: =+L40*M$39 -> 136.92688 | N40: =+L40+M40 -> 821.56125 | O40: =+N40*O$39 -> 287.54644 | P40: =+N40+O40 -> 1109.1077 | Q40: DCTO VIA NC - SUJETO A LA COMPRA DE 5 CAJAS DE C/U GOURMET | R40: 12345.023 | S40: =+(I40-R40)/R40 -> 0.1 | U40: 100021000 | V40: 13579.525
B41: 100021001 | C41: PICADILLO DE CARNE 24X90G SWIFT | D41: 7790360720115 | E41: 2.16 | F41: 24 | G41: =+VLOOKUP(B41,$U$4:$V$104,2,FALSE) -> 13579.525 | I41: =+G41*(1-H41) -> 13579.525 | J41: =+I41/F41 -> 565.81353 | K41: =+J41*K$3 -> 118.82084 | L41: =+J41+K41 -> 684.63438 | M41: =+L41*M$39 -> 136.92688 | N41: =+L41+M41 -> 821.56125 | O41: =+N41*O$39 -> 287.54644 | P41: =+N41+O41 -> 1109.1077 | Q41: DCTO VIA NC - SUJETO A LA COMPRA DE 5 CAJAS DE C/U GOURMET | R41: 12345.023 | S41: =+(I41-R41)/R41 -> 0.1 | U41: 100021001 | V41: 13579.525
B42: 100522277 | C42: Picadillo de Carne Picante Chile Chipotle 24x90 g | E42: 2.16 | F42: 24 | G42: =+VLOOKUP(B42,$U$4:$V$104,2,FALSE) -> 13579.525 | I42: =+G42*(1-H42) -> 13579.525 | J42: =+I42/F42 -> 565.81353 | K42: =+J42*K$3 -> 118.82084 | L42: =+J42+K42 -> 684.63438 | M42: =+L42*M$39 -> 136.92688 | N42: =+L42+M42 -> 821.56125 | O42: =+N42*O$39 -> 287.54644 | P42: =+N42+O42 -> 1109.1077 | R42: 12345.023 | U42: 100522277 | V42: 13579.525
B43: 100522333 | C43: Pate de Foie Jalapeño 24x90 Swift | E43: 2.16 | F43: 24 | G43: =+VLOOKUP(B43,$U$4:$V$104,2,FALSE) -> 13579.525 | I43: =+G43*(1-H43) -> 13579.525 | J43: =+I43/F43 -> 565.81353 | K43: =+J43*K$3 -> 118.82084 | L43: =+J43+K43 -> 684.63438 | M43: =+L43*M$39 -> 136.92688 | N43: =+L43+M43 -> 821.56125 | O43: =+N43*O$39 -> 287.54644 | P43: =+N43+O43 -> 1109.1077 | R43: 12345.023 | U43: 100522333 | V43: 13579.525
B44: 100021045 | C44: PICADILLO DE CARNE PICANTE 24X90G SWIFT | D44: 7790360966582 | E44: 2.16 | F44: 24 | G44: =+VLOOKUP(B44,$U$4:$V$104,2,FALSE) -> 13579.525 | I44: =+G44*(1-H44) -> 13579.525 | J44: =+I44/F44 -> 565.81353 | K44: =+J44*K$3 -> 118.82084 | L44: =+J44+K44 -> 684.63438 | M44: =+L44*M$39 -> 136.92688 | N44: =+L44+M44 -> 821.56125 | O44: =+N44*O$39 -> 287.54644 | P44: =+N44+O44 -> 1109.1077 | R44: 12029.408 | S44: =+(I44-R44)/R44 -> 0.12886059 | U44: 100021045 | V44: 13579.525
B45: 100021004 | C45: PATE DE FOIE A LA CREMA 24X88G SWIFT | D45: 7790360964526 | E45: 2.112 | F45: 24 | G45: =+VLOOKUP(B45,$U$4:$V$104,2,FALSE) -> 13579.525 | I45: =+G45*(1-H45) -> 13579.525 | J45: =+I45/F45 -> 565.81353 | K45: =+J45*K$3 -> 118.82084 | L45: =+J45+K45 -> 684.63438 | M45: =+L45*M$39 -> 136.92688 | N45: =+L45+M45 -> 821.56125 | O45: =+N45*O$39 -> 287.54644 | P45: =+N45+O45 -> 1109.1077 | R45: 12029.408 | S45: =+(I45-R45)/R45 -> 0.12886059 | U45: 100021004 | V45: 13579.525
B46: 100021006 | C46: JAMON DEL DIABLO 24X88G SWIFT | D46: 7790360964557 | E46: 2.112 | F46: 24 | G46: =+VLOOKUP(B46,$U$4:$V$104,2,FALSE) -> 13579.525 | I46: =+G46*(1-H46) -> 13579.525 | J46: =+I46/F46 -> 565.81353 | K46: =+J46*K$3 -> 118.82084 | L46: =+J46+K46 -> 684.63438 | M46: =+L46*M$39 -> 136.92688 | N46: =+L46+M46 -> 821.56125 | O46: =+N46*O$39 -> 287.54644 | P46: =+N46+O46 -> 1109.1077 | R46: 12029.408 | S46: =+(I46-R46)/R46 -> 0.12886059 | U46: 100021006 | V46: 13579.525
B47: 100021007 | C47: PATE DE FOIE DE POLLO 24X85G SWIFT | D47: 7790360964540 | E47: 2.04 | F47: 24 | G47: =+VLOOKUP(B47,$U$4:$V$104,2,FALSE) -> 15501.688 | I47: =+G47*(1-H47) -> 15501.688 | J47: =+I47/F47 -> 645.90367 | K47: =+J47*K$3 -> 135.63977 | L47: =+J47+K47 -> 781.54344 | M47: =+L47*M$39 -> 156.30869 | N47: =+L47+M47 -> 937.85213 | O47: =+N47*O$39 -> 328.24825 | P47: =+N47+O47 -> 1266.1004 | R47: 14092.444 | S47: =+(I47-R47)/R47 -> 0.1 | U47: 100021007 | V47: 15501.688
B48: 100021013 | C48: PATE DE FOIE TIPO PROVENZAL 24X85G SWIFT GOURMET | D48: 7790360965714 | E48: 2.04 | F48: 24 | G48: =+VLOOKUP(B48,$U$4:$V$104,2,FALSE) -> 15501.688 | I48: =+G48*(1-H48) -> 15501.688 | J48: =+I48/F48 -> 645.90367 | K48: =+J48*K$3 -> 135.63977 | L48: =+J48+K48 -> 781.54344 | M48: =+L48*M$39 -> 156.30869 | N48: =+L48+M48 -> 937.85213 | O48: =+N48*O$39 -> 328.24825 | P48: =+N48+O48 -> 1266.1004 | R48: 14092.444 | S48: =+(I48-R48)/R48 -> 0.1 | U48: 100021013 | V48: 15501.688
B49: 100021014 | C49: PATE DE FOIE C/PIMIENTA VERDE 24X85G SWIFT GOURMET | D49: 7790360965721 | E49: 2.04 | F49: 24 | G49: =+VLOOKUP(B49,$U$4:$V$104,2,FALSE) -> 15501.688 | I49: =+G49*(1-H49) -> 15501.688 | J49: =+I49/F49 -> 645.90367 | K49: =+J49*K$3 -> 135.63977 | L49: =+J49+K49 -> 781.54344 | M49: =+L49*M$39 -> 156.30869 | N49: =+L49+M49 -> 937.85213 | O49: =+N49*O$39 -> 328.24825 | P49: =+N49+O49 -> 1266.1004 | R49: 14092.444 | S49: =+(I49-R49)/R49 -> 0.1 | U49: 100021014 | V49: 15501.688
B50: 100021054 | C50: PATE JAMON AHUMADO 24X85G | D50: 7790360965707 | E50: 2.04 | F50: 24 | G50: =+VLOOKUP(B50,$U$4:$V$104,2,FALSE) -> 15501.688 | I50: =+G50*(1-H50) -> 15501.688 | J50: =+I50/F50 -> 645.90367 | K50: =+J50*K$3 -> 135.63977 | L50: =+J50+K50 -> 781.54344 | M50: =+L50*M$39 -> 156.30869 | N50: =+L50+M50 -> 937.85213 | O50: =+N50*O$39 -> 328.24825 | P50: =+N50+O50 -> 1266.1004 | R50: 14092.444 | S50: =+(I50-R50)/R50 -> 0.1 | U50: 100021054 | V50: 15501.688
B51: 100021055 | C51: PATE HONGOS 24X85G | D51: 7790360965189 | E51: 2.04 | F51: 24 | G51: =+VLOOKUP(B51,$U$4:$V$104,2,FALSE) -> 15501.688 | I51: =+G51*(1-H51) -> 15501.688 | J51: =+I51/F51 -> 645.90367 | K51: =+J51*K$3 -> 135.63977 | L51: =+J51+K51 -> 781.54344 | M51: =+L51*M$39 -> 156.30869 | N51: =+L51+M51 -> 937.85213 | O51: =+N51*O$39 -> 328.24825 | P51: =+N51+O51 -> 1266.1004 | R51: 14092.444 | S51: =+(I51-R51)/R51 -> 0.1 | U51: 100021055 | V51: 15501.688
B52: 100021015 | C52: PATE DE SALMON 24X85G SWIFT GOURMET | D52: 7790360965202 | E52: 2.04 | F52: 24 | G52: =+VLOOKUP(B52,$U$4:$V$104,2,FALSE) -> 15501.688 | I52: =+G52*(1-H52) -> 15501.688 | J52: =+I52/F52 -> 645.90367 | K52: =+J52*K$3 -> 135.63977 | L52: =+J52+K52 -> 781.54344 | M52: =+L52*M$39 -> 156.30869 | N52: =+L52+M52 -> 937.85213 | O52: =+N52*O$39 -> 328.24825 | P52: =+N52+O52 -> 1266.1004 | R52: 14092.444 | S52: =+(I52-R52)/R52 -> 0.1 | U52: 100021015 | V52: 15501.688
B53: 100021008 | C53: PICADILLO DE CARNE 24X90G LA BLANCA | D53: 7790360720122 | E53: 2.16 | F53: 24 | G53: =+VLOOKUP(B53,$U$4:$V$104,2,FALSE) -> 11493.436 | I53: =+G53*(1-H53) -> 11493.436 | J53: =+I53/F53 -> 478.89316 | K53: =+J53*K$3 -> 100.56756 | L53: =+J53+K53 -> 579.46072 | M53: =+L53*M$39 -> 115.89214 | N53: =+L53+M53 -> 695.35287 | O53: =+N53*O$39 -> 243.3735 | P53: =+N53+O53 -> 938.72637 | R53: 10448.578 | S53: =+(I53-R53)/R53 -> 0.1 | U53: 100021008 | V53: 11493.436
B54: 100021009 | C54: PATE DE FOIE 24X90G LA BLANCA | D54: 7790360965127 | E54: 2.16 | F54: 24 | G54: =+VLOOKUP(B54,$U$4:$V$104,2,FALSE) -> 11493.436 | I54: =+G54*(1-H54) -> 11493.436 | J54: =+I54/F54 -> 478.89316 | K54: =+J54*K$3 -> 100.56756 | L54: =+J54+K54 -> 579.46072 | M54: =+L54*M$39 -> 115.89214 | N54: =+L54+M54 -> 695.35287 | O54: =+N54*O$39 -> 243.3735 | P54: =+N54+O54 -> 938.72637 | R54: 10448.578 | S54: =+(I54-R54)/R54 -> 0.1 | U54: 100021009 | V54: 11493.436
B55: 100021010 | C55: PICADILLO DE CARNE 24X90G SAFRA | D55: 7790920008707 | E55: 2.16 | F55: 24 | G55: =+VLOOKUP(B55,$U$4:$V$104,2,FALSE) -> 11493.436 | I55: =+G55*(1-H55) -> 11493.436 | J55: =+I55/F55 -> 478.89316 | K55: =+J55*K$3 -> 100.56756 | L55: =+J55+K55 -> 579.46072 | M55: =+L55*M$39 -> 115.89214 | N55: =+L55+M55 -> 695.35287 | O55: =+N55*O$39 -> 243.3735 | P55: =+N55+O55 -> 938.72637 | R55: 10448.578 | S55: =+(I55-R55)/R55 -> 0.1 | U55: 100021010 | V55: 11493.436
B56: 100021011 | C56: PATE DE FOIE 24X90G SAFRA | D56: 7790920008714 | E56: 2.16 | F56: 24 | G56: =+VLOOKUP(B56,$U$4:$V$104,2,FALSE) -> 11493.436 | I56: =+G56*(1-H56) -> 11493.436 | J56: =+I56/F56 -> 478.89316 | K56: =+J56*K$3 -> 100.56756 | L56: =+J56+K56 -> 579.46072 | M56: =+L56*M$39 -> 115.89214 | N56: =+L56+M56 -> 695.35287 | O56: =+N56*O$39 -> 243.3735 | P56: =+N56+O56 -> 938.72637 | R56: 10448.578 | S56: =+(I56-R56)/R56 -> 0.1 | U56: 100021011 | V56: 11493.436
G57: =+VLOOKUP(B57,$U$4:$V$104,2,FALSE) -> #N/A | I57: =+G57*(1-H57) -> #N/A | J57: =+I57/F57 -> #N/A | K57: 0.21 | M57: 0.3 | O57: 0.4 | R57: #N/A | S57: =+(I57-R57)/R57 -> #N/A | V57: #VALUE!
B58: 100516217 | C58: MILANESAS DE SOJA CLASICAS PREFRITA | D58: 7790360967824 | E58: 5.8 | F58: 20 | G58: =+VLOOKUP(B58,$U$4:$V$104,2,FALSE) -> 28055.911 | I58: =+G58*(1-H58) -> 28055.911 | J58: =+I58/F58 -> 1402.7956 | K58: =+J58*K$3 -> 294.58707 | L58: =+J58+K58 -> 1697.3826 | M58: =+L58*M$3 -> 509.21479 | N58: =+L58+M58 -> 2206.5974 | O58: =+N58*O$3 -> 882.63898 | P58: =+N58+O58 -> 3089.2364 | R58: 27238.749 | S58: =+(I58-R58)/R58 -> 0.03 | U58: 100516217 | V58: 28055.911
B59: 100516214 | C59: MILANESAS DE SOJA RELLENAS CON JAMON Y QUESO | D59: 7790360967794 | E59: 7 | F59: 20 | G59: =+VLOOKUP(B59,$U$4:$V$104,2,FALSE) -> 42153.237 | H59: 0.05 | I59: =+G59*(1-H59) -> 40045.575 | J59: =+I59/F59 -> 2002.2787 | K59: =+J59*K$3 -> 420.47853 | L59: =+J59+K59 -> 2422.7573 | M59: =+L59*M$3 -> 726.82718 | N59: =+L59+M59 -> 3149.5844 | O59: =+N59*O$3 -> 1259.8338 | P59: =+N59+O59 -> 4409.4182 | R59: 38879.199 | S59: =+(I59-R59)/R59 -> 0.03 | U59: 100516214 | V59: 42153.237
B60: 100516215 | C60: MILANESAS DE SOJA RELLENAS CON ESPINACA Y QUESO | D60: 7790360967800 | E60: 7 | F60: 20 | G60: =+VLOOKUP(B60,$U$4:$V$104,2,FALSE) -> 42153.237 | H60: 0.05 | I60: =+G60*(1-H60) -> 40045.575 | J60: =+I60/F60 -> 2002.2787 | K60: =+J60*K$3 -> 420.47853 | L60: =+J60+K60 -> 2422.7573 | M60: =+L60*M$3 -> 726.82718 | N60: =+L60+M60 -> 3149.5844 | O60: =+N60*O$3 -> 1259.8338 | P60: =+N60+O60 -> 4409.4182 | R60: 38879.199 | S60: =+(I60-R60)/R60 -> 0.03 | U60: 100516215 | V60: 42153.237
B61: 100516216 | C61: MILANESAS DE SOJA RELLENAS CON TOMATE Y QUESO | D61: 7790360967817 | E61: 7 | F61: 20 | G61: =+VLOOKUP(B61,$U$4:$V$104,2,FALSE) -> 42153.237 | H61: 0.05 | I61: =+G61*(1-H61) -> 40045.575 | J61: =+I61/F61 -> 2002.2787 | K61: =+J61*K$3 -> 420.47853 | L61: =+J61+K61 -> 2422.7573 | M61: =+L61*M$3 -> 726.82718 | N61: =+L61+M61 -> 3149.5844 | O61: =+N61*O$3 -> 1259.8338 | P61: =+N61+O61 -> 4409.4182 | R61: 38879.199 | S61: =+(I61-R61)/R61 -> 0.03 | U61: 100516216 | V61: 42153.237
G62: =+VLOOKUP(B62,$U$4:$V$104,2,FALSE) -> #N/A | I62: =+G62*(1-H62) -> #N/A | J62: =+I62/F62 -> #N/A | K62: 0.21 | M62: 0.3 | O62: 0.4 | R62: #N/A | S62: =+(I62-R62)/R62 -> #N/A | V62: #VALUE!
B63: 100021704 | C63: BOCADITOS DE CARNE "SWIFT" - 12x380g | D63: 7790360023902 | E63: =12*0.38 -> 4.56 | F63: 12 | G63: =+VLOOKUP(B63,$U$4:$V$104,2,FALSE) -> 39692.434 | I63: =+G63*(1-H63) -> 39692.434 | J63: =+I63/F63 -> 3307.7029 | K63: =+J63*K$3 -> 694.6176 | L63: =+J63+K63 -> 4002.3205 | M63: =+L63*M$3 -> 1200.6961 | N63: =+L63+M63 -> 5203.0166 | O63: =+N63*O$3 -> 2081.2066 | P63: =+N63+O63 -> 7284.2232 | R63: 37802.318 | S63: =+(I63-R63)/R63 -> 0.05 | U63: 100021704 | V63: 39692.434
B64: 100021705 | C64: BOCADITOS DE POLLO "SWIFT" - 12x380g | D64: 7790360024336 | E64: =12*0.38 -> 4.56 | F64: 12 | G64: =+VLOOKUP(B64,$U$4:$V$104,2,FALSE) -> 35720.533 | I64: =+G64*(1-H64) -> 35720.533 | J64: =+I64/F64 -> 2976.7111 | K64: =+J64*K$3 -> 625.10933 | L64: =+J64+K64 -> 3601.8204 | M64: =+L64*M$3 -> 1080.5461 | N64: =+L64+M64 -> 4682.3665 | O64: =+N64*O$3 -> 1872.9466 | P64: =+N64+O64 -> 6555.3131 | R64: 34019.555 | S64: =+(I64-R64)/R64 -> 0.05 | U64: 100021705 | V64: 35720.533
B65: 100021709 | C65: BOCADITOS DE POLLO "SWIFT" - 10x760g | D65: 7790360024701 | E65: 7.6 | F65: 10 | G65: =+VLOOKUP(B65,$U$4:$V$104,2,FALSE) -> 60214.277 | I65: =+G65*(1-H65) -> 60214.277 | J65: =+I65/F65 -> 6021.4277 | K65: =+J65*K$3 -> 1264.4998 | L65: =+J65+K65 -> 7285.9275 | M65: =+L65*M$3 -> 2185.7783 | N65: =+L65+M65 -> 9471.7058 | O65: =+N65*O$3 -> 3788.6823 | P65: =+N65+O65 -> 13260.388 | R65: 47787.197 | S65: =+(I65-R65)/R65 -> 0.2600504 | U65: 100021709 | V65: 60214.277
B66: 100521357 | C66: CRUNCHIES DE POLLO "SWIFT" - 12x380g | E66: 4.56 | F66: 12 | G66: =+VLOOKUP(B66,$U$4:$V$104,2,FALSE) -> 48595.609 | H66: 0.33 | I66: =+G66*(1-H66) -> 32559.058 | J66: =+I66/F66 -> 2713.2548 | K66: =+J66*K$3 -> 569.78351 | L66: =+J66+K66 -> 3283.0383 | M66: =+L66*M$3 -> 984.9115 | N66: =+L66+M66 -> 4267.9498 | O66: =+N66*O$3 -> 1707.1799 | P66: =+N66+O66 -> 5975.1298 | R66: 46281.532 | U66: 100521357 | V66: 48595.609
B67: 100521358 | C67: CRUNCHIES DE POLLO "SWIFT" - 10x760g | D67: 7790360982025 | E67: 7.6 | F67: 10 | G67: =+VLOOKUP(B67,$U$4:$V$104,2,FALSE) -> 72893.413 | I67: =+G67*(1-H67) -> 72893.413 | J67: =+I67/F67 -> 7289.3413 | K67: =+J67*K$3 -> 1530.7617 | L67: =+J67+K67 -> 8820.103 | M67: =+L67*M$3 -> 2646.0309 | N67: =+L67+M67 -> 11466.134 | O67: =+N67*O$3 -> 4586.4535 | P67: =+N67+O67 -> 16052.587 | R67: 69422.298 | U67: 100521358 | V67: 72893.413
B68: 100522130 | C68: BOCADITOS DE POLLO "SWIFT KIDS" - 12x400g | E68: 4.8 | F68: 12 | G68: =+VLOOKUP(B68,$U$4:$V$104,2,FALSE) -> 36337.502 | I68: =+G68*(1-H68) -> 36337.502 | J68: =+I68/F68 -> 3028.1252 | K68: =+J68*K$3 -> 635.90628 | L68: =+J68+K68 -> 3664.0314 | M68: =+L68*M$3 -> 1099.2094 | N68: =+L68+M68 -> 4763.2409 | O68: =+N68*O$3 -> 1905.2963 | P68: =+N68+O68 -> 6668.5372 | R68: 24606.972 | U68: 100522130 | V68: 36337.502
B69: 100021725 | C69: BOCADITOS DE POLLO GASTRONOMICOS "LA BLANCA" - x6kg | D69: 7790360027009 | E69: 6 | F69: 4 | G69: =+VLOOKUP(B69,$U$4:$V$104,2,FALSE) -> 30046.413 | I69: =+G69*(1-H69) -> 30046.413 | J69: =+I69/F69 -> 7511.6032 | K69: =+J69*K$3 -> 1577.4367 | L69: =+J69+K69 -> 9089.0399 | M69: =+L69*M$3 -> 2726.712 | N69: =+L69+M69 -> 11815.752 | O69: =+N69*O$3 -> 4726.3007 | P69: =+N69+O69 -> 16542.053 | R69: 28615.631 | S69: =+(I69-R69)/R69 -> 0.05 | U69: 100021725 | V69: 30046.413
B70: 100517055 | C70: PALITO DE POLLO "SWIFT" 12 X 260 Grs. | D70: 7790360971135 | E70: 3.12 | F70: 12 | G70: =+VLOOKUP(B70,$U$4:$V$104,2,FALSE) -> 29936.929 | I70: =+G70*(1-H70) -> 29936.929 | J70: =+I70/F70 -> 2494.7441 | K70: =+J70*K$3 -> 523.89626 | L70: =+J70+K70 -> 3018.6404 | M70: =+L70*M$3 -> 905.59211 | N70: =+L70+M70 -> 3924.2325 | O70: =+N70*O$3 -> 1569.693 | P70: =+N70+O70 -> 5493.9255 | R70: 28511.361 | S70: =+(I70-R70)/R70 -> 0.05 | U70: 100517055 | V70: 29936.929
B71: 100517186 | C71: PALITO DE POLLO "SWIFT" 8 X 1 Kg.. | D71: 7790360971395 | E71: 8 | F71: 8 | G71: =+VLOOKUP(B71,$U$4:$V$104,2,FALSE) -> 76027.74 | I71: =+G71*(1-H71) -> 76027.74 | J71: =+I71/F71 -> 9503.4675 | K71: =+J71*K$3 -> 1995.7282 | L71: =+J71+K71 -> 11499.196 | M71: =+L71*M$3 -> 3449.7587 | N71: =+L71+M71 -> 14948.954 | O71: =+N71*O$3 -> 5979.5817 | P71: =+N71+O71 -> 20928.536 | R71: 72407.371 | S71: =+(I71-R71)/R71 -> 0.05 | U71: 100517186 | V71: 76027.74
B72: 100521663 | C72: MILANESITAS DE CARNE "SWIFT" - 12x400g | E72: 4.8 | F72: 12 | G72: 43941.021 | H72: 0.33 | I72: =+G72*(1-H72) -> 29440.484 | J72: =+I72/F72 -> 2453.3737 | K72: =+J72*K$3 -> 515.20848 | L72: =+J72+K72 -> 2968.5822 | M72: =+L72*M$3 -> 890.57465 | N72: =+L72+M72 -> 3859.1568 | O72: =+N72*O$3 -> 1543.6627 | P72: =+N72+O72 -> 5402.8195 | R72: 47021.568 | U72: 100521663 | V72: 49372.646
B73: 100021728 | C73: MEDALLONES DE POLLO "SWIFT" - 12x4x80g | D73: 7790360967558 | E73: 3.84 | F73: 12 | G73: =+VLOOKUP(B73,$U$4:$V$104,2,FALSE) -> 41631.804 | I73: =+G73*(1-H73) -> 41631.804 | J73: =+I73/F73 -> 3469.317 | K73: =+J73*K$3 -> 728.55657 | L73: =+J73+K73 -> 4197.8736 | M73: =+L73*M$3 -> 1259.3621 | N73: =+L73+M73 -> 5457.2356 | O73: =+N73*O$3 -> 2182.8943 | P73: =+N73+O73 -> 7640.1299 | R73: 39649.337 | S73: =+(I73-R73)/R73 -> 0.05 | U73: 100021728 | V73: 41631.804
B74: 100517679 | C74: MEDALLONES DE POLLO GASTRONÓMICO 8x12x80 Grs. | E74: 7.68 | F74: 8 | G74: =+VLOOKUP(B74,$U$4:$V$104,2,FALSE) -> 39413.592 | I74: =+G74*(1-H74) -> 39413.592 | J74: =+I74/F74 -> 4926.699 | K74: =+J74*K$3 -> 1034.6068 | L74: =+J74+K74 -> 5961.3058 | M74: =+L74*M$3 -> 1788.3918 | N74: =+L74+M74 -> 7749.6976 | O74: =+N74*O$3 -> 3099.879 | P74: =+N74+O74 -> 10849.577 | R74: 37536.755 | S74: =+(I74-R74)/R74 -> 0.05 | U74: 100517679 | V74: 39413.592
G75: =+VLOOKUP(B75,$U$4:$V$104,2,FALSE) -> #N/A | I75: =+G75*(1-H75) -> #N/A | J75: =+I75/F75 -> #N/A | K75: 0.21 | M75: 0.3 | O75: 0.4 | R75: #N/A | S75: =+(I75-R75)/R75 -> #N/A | V75: #VALUE!
B76: 100516219 | C76: PAPAS PREFRITAS SUPERCONGELADAS 25x400gr | D76: 7790360967770 | E76: 10 | F76: 25 | G76: =+VLOOKUP(B76,$U$4:$V$104,2,FALSE) -> 18259.4 | I76: =+G76*(1-H76) -> 18259.4 | J76: =+I76/F76 -> 730.376 | K76: =+J76*K$3 -> 153.37896 | L76: =+J76+K76 -> 883.75495 | M76: =+L76*M$3 -> 265.12649 | N76: =+L76+M76 -> 1148.8814 | O76: =+N76*O$3 -> 459.55258 | P76: =+N76+O76 -> 1608.434 | R76: 18259.4 | S76: =+(I76-R76)/R76 -> 0 | U76: 100516219 | V76: 18259.4
B77: 100516220 | C77: PAPAS PREFRITAS SUPERCONGELADAS 6x2000gr | D77: 7790360967787 | E77: 12 | F77: 6 | G77: =+VLOOKUP(B77,$U$4:$V$104,2,FALSE) -> 19613.922 | I77: =+G77*(1-H77) -> 19613.922 | J77: =+I77/F77 -> 3268.987 | K77: =+J77*K$3 -> 686.48726 | L77: =+J77+K77 -> 3955.4742 | M77: =+L77*M$3 -> 1186.6423 | N77: =+L77+M77 -> 5142.1165 | O77: =+N77*O$3 -> 2056.8466 | P77: =+N77+O77 -> 7198.9631 | R77: 19613.922 | S77: =+(I77-R77)/R77 -> 0 | U77: 100516220 | V77: 19613.922
G78: =+VLOOKUP(B78,$U$4:$V$104,2,FALSE) -> #N/A | I78: =+G78*(1-H78) -> #N/A | J78: =+I78/F78 -> #N/A | R78: #N/A | S78: =+(I78-R78)/R78 -> #N/A | V78: #VALUE!
B79: 100518158 | C79: MILANESA DE CARNE VACUNA CONGELADA 24un x 500grs | D79: 7790360974280 | E79: 12 | F79: 24 | G79: =+VLOOKUP(B79,$U$4:$V$104,2,FALSE) -> 79203.691 | I79: =+G79*(1-H79) -> 79203.691 | J79: =+I79/F79 -> 3300.1538 | K79: =+J79*K$3 -> 693.0323 | L79: =+J79+K79 -> 3993.1861 | M79: =+L79*M$3 -> 1197.9558 | N79: =+L79+M79 -> 5191.1419 | O79: =+N79*O$3 -> 2076.4568 | P79: =+N79+O79 -> 7267.5987 | R79: 79203.691 | S79: =+(I79-R79)/R79 -> 0 | U79: 100518158 | V79: 79203.691
B80: 100518160 | C80: MILANESA DE CARNE VACUNA CONGELADA 12un x 1000grs | D80: 7790360974686 | E80: 12 | F80: 12 | G80: =+VLOOKUP(B80,$U$4:$V$104,2,FALSE) -> 79203.691 | I80: =+G80*(1-H80) -> 79203.691 | J80: =+I80/F80 -> 6600.3076 | K80: =+J80*K$3 -> 1386.0646 | L80: =+J80+K80 -> 7986.3722 | M80: =+L80*M$3 -> 2395.9117 | N80: =+L80+M80 -> 10382.284 | O80: =+N80*O$3 -> 4152.9135 | P80: =+N80+O80 -> 14535.197 | R80: 79203.691 | S80: =+(I80-R80)/R80 -> 0 | U80: 100518160 | V80: 79203.691
B81: 100518463 | C81: MILANESAS DE CARNE VACUNA CONG GRANEL 5 kg (CAL GR) | E81: 5 | F81: 1 | G81: =+VLOOKUP(B81,$U$4:$V$104,2,FALSE) -> 36693.267 | I81: =+G81*(1-H81) -> 36693.267 | J81: =+I81/F81 -> 36693.267 | K81: =+J81*K$3 -> 7705.5861 | L81: =+J81+K81 -> 44398.853 | M81: =+L81*M$3 -> 13319.656 | N81: =+L81+M81 -> 57718.509 | O81: =+N81*O$3 -> 23087.404 | P81: =+N81+O81 -> 80805.913 | R81: 36693.267 | S81: =+(I81-R81)/R81 -> 0 | U81: 100518463 | V81: 36693.267
G82: =+VLOOKUP(B82,$U$4:$V$104,2,FALSE) -> #N/A | I82: =+G82*(1-H82) -> #N/A | J82: =+I82/F82 -> #N/A | R82: #N/A | S82: =+(I82-R82)/R82 -> #N/A | V82: #VALUE!
B83: 100518291 | C83: GRASA VACUNA REFINADA SWIFT 10 X 500 | D83: 7790360975195 | E83: 5 | F83: 10 | G83: =+VLOOKUP(B83,$U$4:$V$104,2,FALSE) -> 17536.687 | H83: 0.15 | I83: =+G83*(1-H83) -> 14906.184 | J83: =+I83/F83 -> 1490.6184 | K83: =+J83*K$3 -> 313.02986 | L83: =+J83+K83 -> 1803.6483 | M83: =+L83*M$39 -> 360.72965 | N83: =+L83+M83 -> 2164.3779 | O83: =+N83*O$39 -> 757.53227 | P83: =+N83+O83 -> 2921.9102 | R83: 14906.184 | S83: =+(I83-R83)/R83 -> 0 | U83: 100518291 | V83: 17536.687
B84: 100518292 | C84: GRASA VACUNA REFINADA SWIFT 12x1Kg | D84: 7790360975201 | E84: 12 | F84: 12 | G84: =+VLOOKUP(B84,$U$4:$V$104,2,FALSE) -> 41380.324 | H84: 0.15 | I84: =+G84*(1-H84) -> 35173.275 | J84: =+I84/F84 -> 2931.1063 | K84: =+J84*K$3 -> 615.53232 | L84: =+J84+K84 -> 3546.6386 | M84: =+L84*M$39 -> 709.32772 | N84: =+L84+M84 -> 4255.9663 | O84: =+N84*O$39 -> 1489.5882 | P84: =+N84+O84 -> 5745.5545 | R84: 35173.275 | S84: =+(I84-R84)/R84 -> 0 | U84: 100518292 | V84: 41380.324
G85: =+VLOOKUP(B85,$U$4:$V$104,2,FALSE) -> #N/A | I85: =+G85*(1-H85) -> #N/A | J85: =+I85/F85 -> #N/A | K85: 0.105 | M85: 0.3 | O85: 0.4 | R85: #N/A | S85: =+(I85-R85)/R85 -> #N/A | V85: #VALUE!
B86: 100517915 | C86: CARNE PICADA CONGELADA 36 UN X 500 g SWIFT | D86: 7790360974020 | E86: 18 | F86: 36 | G86: =+VLOOKUP(B86,$U$4:$V$104,2,FALSE) -> 154338.47 | I86: =+G86*(1-H86) -> 154338.47 | J86: =+I86/F86 -> 4287.1798 | K86: =+J86*K$85 -> 450.15388 | L86: =+J86+K86 -> 4737.3337 | M86: =+L86*M$85 -> 1421.2001 | N86: =+L86+M86 -> 6158.5338 | O86: =+N86*O$85 -> 2463.4135 | P86: =+N86+O86 -> 8621.9473 | R86: 145602.33 | S86: =+(I86-R86)/R86 -> 0.06 | U86: 100517915 | V86: 154338.47
B87: 100517914 | C87: CARNE PICADA CONGELADA 20 UN X 1 kg SWIFT | D87: 7790360974037 | E87: 20 | F87: 20 | G87: =+VLOOKUP(B87,$U$4:$V$104,2,FALSE) -> 168417.57 | I87: =+G87*(1-H87) -> 168417.57 | J87: =+I87/F87 -> 8420.8786 | K87: =+J87*K$85 -> 884.19225 | L87: =+J87+K87 -> 9305.0708 | M87: =+L87*M$85 -> 2791.5213 | N87: =+L87+M87 -> 12096.592 | O87: =+N87*O$85 -> 4838.6368 | P87: =+N87+O87 -> 16935.229 | R87: 158884.5 | S87: =+(I87-R87)/R87 -> 0.06 | U87: 100517914 | V87: 168417.57
G88: =+VLOOKUP(B88,$U$4:$V$104,2,FALSE) -> #N/A | I88: =+G88*(1-H88) -> #N/A | K88: 0.105 | M88: 0.3 | O88: 0.4 | R88: #N/A | S88: =+(I88-R88)/R88 -> #N/A
B89: 100010689 | C89: ENTRAÑA FINA ENF SWIFT | E89: 22 | F89: 1 | G89: =+VLOOKUP(B89,$U$4:$V$104,2,FALSE) -> 16464.643 | I89: =+G89*(1-H89) -> 16464.643 | J89: =+I89/F89 -> 16464.643 | K89: =+J89*K$88 -> 1728.7875 | L89: =+J89+K89 -> 18193.43 | M89: =+L89*M$88 -> 5458.0291 | N89: =+L89+M89 -> 23651.459 | O89: =+N89*O$88 -> 9460.5838 | P89: =+N89+O89 -> 33112.043 | R89: 16464.643 | S89: =+(I89-R89)/R89 -> 0 | U89: 100010689 | V89: 16464.643
B90: 100518335 | C90: ROAST BEEF EN PORCIONES ENF SWIFT (L) | E90: 22.5 | F90: 1 | G90: =+VLOOKUP(B90,$U$4:$V$104,2,FALSE) -> 10429.179 | I90: =+G90*(1-H90) -> 10429.179 | J90: =+I90/F90 -> 10429.179 | K90: =+J90*K$88 -> 1095.0638 | L90: =+J90+K90 -> 11524.242 | M90: =+L90*M$88 -> 3457.2727 | N90: =+L90+M90 -> 14981.515 | O90: =+N90*O$88 -> 5992.606 | P90: =+N90+O90 -> 20974.121 | R90: 10429.179 | S90: =+(I90-R90)/R90 -> 0 | U90: 100518335 | V90: 10429.179
B91: 100518332 | C91: CARNAZA CUADRADA EN PORCIONES ENF SWIFT (L) | E91: 21.5 | F91: 1 | G91: =+VLOOKUP(B91,$U$4:$V$104,2,FALSE) -> 11223.536 | I91: =+G91*(1-H91) -> 11223.536 | J91: =+I91/F91 -> 11223.536 | K91: =+J91*K$88 -> 1178.4713 | L91: =+J91+K91 -> 12402.007 | M91: =+L91*M$88 -> 3720.6021 | N91: =+L91+M91 -> 16122.609 | O91: =+N91*O$88 -> 6449.0436 | P91: =+N91+O91 -> 22571.653 | R91: 11223.536 | S91: =+(I91-R91)/R91 -> 0 | U91: 100518332 | V91: 11223.536
B92: 100518334 | C92: TAPA DE ASADO EN PORCIONES ENF SWIFT (L) | E92: 22.5 | F92: 1 | G92: =+VLOOKUP(B92,$U$4:$V$104,2,FALSE) -> 9237.6429 | I92: =+G92*(1-H92) -> 9237.6429 | J92: =+I92/F92 -> 9237.6429 | K92: =+J92*K$88 -> 969.9525 | L92: =+J92+K92 -> 10207.595 | M92: =+L92*M$88 -> 3062.2786 | N92: =+L92+M92 -> 13269.874 | O92: =+N92*O$88 -> 5307.9496 | P92: =+N92+O92 -> 18577.824 | R92: 9237.6429 | S92: =+(I92-R92)/R92 -> 0 | U92: 100518334 | V92: 9237.6429
B93: 100518227 | C93: VACIO EN PORCIONES NOV ENFRIADO PARA VENTA LOCAL (L) | E93: 22.5 | F93: 1 | G93: =+VLOOKUP(B93,$U$4:$V$104,2,FALSE) -> 9237.6429 | I93: =+G93*(1-H93) -> 9237.6429 | J93: =+I93/F93 -> 9237.6429 | K93: =+J93*K$88 -> 969.9525 | L93: =+J93+K93 -> 10207.595 | M93: =+L93*M$88 -> 3062.2786 | N93: =+L93+M93 -> 13269.874 | O93: =+N93*O$88 -> 5307.9496 | P93: =+N93+O93 -> 18577.824 | R93: 9237.6429 | S93: =+(I93-R93)/R93 -> 0 | U93: 100518227 | V93: 9237.6429
B94: 100027726 | C94: BONDIOLA DE CERDO CONGELADA | E94: 22.5 | F94: 1 | G94: =+VLOOKUP(B94,$U$4:$V$104,2,FALSE) -> 6814.5 | I94: =+G94*(1-H94) -> 6814.5 | J94: =+I94/F94 -> 6814.5 | K94: =+J94*K$88 -> 715.5225 | L94: =+J94+K94 -> 7530.0225 | M94: =+L94*M$88 -> 2259.0068 | N94: =+L94+M94 -> 9789.0293 | O94: =+N94*O$88 -> 3915.6117 | P94: =+N94+O94 -> 13704.641 | R94: 6814.5 | U94: 100027726 | V94: 6814.5
G95: =+VLOOKUP(B95,$U$4:$V$104,2,FALSE) -> #N/A | I95: =+G95*(1-H95) -> #N/A | K95: 0.21 | M95: 0.3 | O95: 0.4 | R95: #N/A | S95: =+(I95-R95)/R95 -> #N/A
B96: 100520837 | C96: CHORIZOS FRESCOS DE CERDO LIBRE DE GLUTEN | D96: 7790360980625 | E96: 4.8 | F96: 12 | G96: =+VLOOKUP(B96,$U$4:$V$104,2,FALSE) -> 35756.176 | I96: =+G96*(1-H96) -> 35756.176 | J96: =+I96/F96 -> 2979.6813 | K96: =+J96*K$95 -> 625.73307 | L96: =+J96+K96 -> 3605.4144 | M96: =+L96*M$95 -> 1081.6243 | N96: =+L96+M96 -> 4687.0387 | O96: =+N96*O$95 -> 1874.8155 | P96: =+N96+O96 -> 6561.8541 | R96: 35756.176 | S96: =+(I96-R96)/R96 -> 0 | U96: 100520837 | V96: 35756.176
B97: 100522395 | C97: CHORIZOS FRESCOS DE CERDO CONGELADOS LIBRE DE GLUTEN 12u x 400g | D97: 7790360980625 | E97: 4.8 | F97: 12 | G97: =+VLOOKUP(B97,$U$4:$V$104,2,FALSE) -> 36471.292 | I97: =+G97*(1-H97) -> 36471.292 | J97: =+I97/F97 -> 3039.2743 | K97: =+J97*K$95 -> 638.24761 | L97: =+J97+K97 -> 3677.5219 | M97: =+L97*M$95 -> 1103.2566 | N97: =+L97+M97 -> 4780.7785 | O97: =+N97*O$95 -> 1912.3114 | P97: =+N97+O97 -> 6693.0899 | U97: 100522395 | V97: 36471.292
G98: =+VLOOKUP(B98,$U$4:$V$104,2,FALSE) -> #N/A | I98: =+G98*(1-H98) -> #N/A | K98: 0.21 | M98: 0.3 | O98: 0.4 | R98: #N/A | S98: =+(I98-R98)/R98 -> #N/A
B99: 100520902 | C99: PAPAS PRE COCIDAS SUPERCONGELADAS LIBRES DE GLUTEN 700G | D99: 7790360981042 | E99: 9.8 | F99: 14 | G99: =+VLOOKUP(B99,$U$4:$V$104,2,FALSE) -> 32345.803 | H99: =0.142857142857143*100% -> 0.14285714 | I99: =+G99*(1-H99) -> 27724.974 | J99: =+I99/F99 -> 1980.3553 | K99: =+J99*K$98 -> 415.87461 | L99: =+J99+K99 -> 2396.2299 | M99: =+L99*M$98 -> 718.86897 | N99: =+L99+M99 -> 3115.0989 | O99: =+N99*O$98 -> 1246.0395 | P99: =+N99+O99 -> 4361.1384 | R99: 28302.577 | S99: =+(I99-R99)/R99 -> -0.020408163 | U99: 100520902 | V99: 32345.803
K100: 0.21 | M100: 0.3 | O100: 0.4
B101: 100521457 | C101: NUGGETS DE ESPINACA 300GR | D101: 7790360982254 | E101: 4.8 | F101: 16 | G101: =+VLOOKUP(B101,$U$4:$V$104,2,FALSE) -> 36127.9 | H101: 0.075 | I101: =+G101*(1-H101) -> 33418.307 | J101: =+G101/F101 -> 2257.9937 | K101: =+J101*K$100 -> 474.17868 | L101: =+J101+K101 -> 2732.1724 | M101: =+L101*M$100 -> 819.65172 | N101: =+L101+M101 -> 3551.8241 | O101: =+N101*O$100 -> 1420.7297 | P101: =+N101+O101 -> 4972.5538 | R101: 31826.959 | S101: =+(I101-R101)/R101 -> 0.05 | U101: 100521457 | V101: 36127.9
...
